Workbook

Sheet Scoring Matrix
A1: Category | B1: Metric | C1: Weight (%) | D1: 0 | E1: 1 | F1: 2 | G1: 3 (Contributor) | H1: 4 (High) | I1: 5 (STAR)
A2: Sales | B2: Sales vs Budget (%) | C2: 5 | D2: <90% | E2: 90-94.9% | F2: 95–98.9% | G2: 99–101.9% | H2: 102–104.9% | I2: >105% | J2: 5.9 | K2: 6
A3: Sales | B3: Sales vs Prior Year (%) | C3: 5 | D3: <-5% | E3: -5-0% | F3: 0.1-4.9% | G3: 5-7.4% | H3: 7.5-14.9% | I3: ≥15% | J3: 5.9 | K3: 6
A4: EBITDA | B4: EBITDA vs Budget (%) | C4: 15 | D4: <75% | E4: 75-84.9% | F4: 85–94.9% | G4: 95–100.9% | H4: 101–104.9% | I4: ≥105%
A5: Prime Cost | B5: Labor vs Budget Variance (pts) | C5: 12.5 | D5: ≥+3.0 | E5: +2.0–2.99 | F5: +1.0–1.99 | G5: 0.0–0.99 | H5: -0.5– -0.99 | I5: ≤-1.0 | J5: 14.7 | K5: 14.5 | L5: /** * Automatically triggers whenever a cell is edited in the spreadsheet. */ function onEdit(e) { // If the edit is not valid, stop here if (!e) return; // Only run if the edit happened on the Scorecards sheet const activeSheetName = e.source.getActiveSheet().getName(); if (activeSheetName === "Weekly Store Scorecards ") { syncCrossSheetColors(); } } function syncCrossSheetColors() { const ss = SpreadsheetApp.getActiveSpreadsheet(); const sourceSheet = ss.getSheetByName("Weekly Store Scorecards "); const targetSheet = ss.getSheetByName("Weekly Area Leader Dashboard"); if (!sourceSheet || !targetSheet) return; // 1. Force Google to finish the formula calculation SpreadsheetApp.flush(); // 2. Add a tiny delay (200ms) to let the Color Scale "paint" itself Utilities.sleep(200); const startRowSource = 3; const startRowTarget = 2; const numRows = 6; const mapping = [ [3, 4], [6, 5], [12, 6], [15, 7], [18, 8], [21, 10], [24, 11], [27, 9]]; mapping.forEach(pair => { try { const sourceCol = pair[0]; const targetCol = pair[1]; // Grab the NEW colors from Column C (Source) const colors = sourceSheet.getRange(startRowSource, sourceCol, numRows).getBackgrounds(); // Update the "Input" column on the same scorecard sheet (SourceCol - 1) sourceSheet.getRange(startRowSource, sourceCol - 1, numRows).setBackgrounds(colors); // Syncing the Dashboard targetSheet.getRange(startRowTarget, targetCol, numRows).setBackgrounds(colors); } catch (err) { Logger.log("Error: " + err.message); } }); }
A6: Prime Cost | B6: COGS vs Budget Variance (pts) | C6: 12.5 | D6: ≥+3.0 | E6: +2.0–2.99 | F6: +1.0–1.99 | G6: 0.0–0.99 | H6: -0.5–-0.99 | I6: ≤-1.0 | J6: 14.7 | K6: 14.5
A7: Operational | B7: Google Rating | C7: 17.5 | D7: <3.8 | E7: <4.0 | F7: 4.0–4.29 | G7: 4.3–4.49 | H7: 4.5–4.69 | I7: ≥4.7 | J7: 20.6 | K7: 20.5
A8: Operational | B8: Yelp Rating | C8: 7.5 | D8: <3.8 | E8: <4.0 | F8: 4.0–4.29 | G8: 4.3–4.49 | H8: 4.5–4.69 | I8: ≥4.7 | J8: 8.8 | K8: 8.5
A9: Operational | B9: 3P Error Rate (%) | C9: 10 | D9: >6% | E9: 4.01–6% | F9: 2.01–4% | G9: 1.51–2% | H9: 1.01–1.5% | I9: ≤1% | J9: 11.8 | K9: 12
A10: Operational | B10: Avoidable Wait (mins) | C10: 7.5 | D10: >8 | E10: >5–8 | F10: >2–5 | G10: ≤2 & >1.5 | H10: ≤1.5 & >1 | I10: ≤1 | J10: 8.8 | K10: 9
A11: Operational | B11: 3P Rating | C11: 7.5 | D11: <3.8 | E11: <4.0 | F11: 4.0–4.29 | G11: 4.3–4.49 | H11: 4.5–4.69 | I11: ≥4.7 | J11: 8.8 | K11: 9
A12: Operational | B12: Full Audit Score | C12: 12.5 | D12: <70 | E12: 70–74 | F12: 75–82 | G12: 83–88 | H12: 89–93 | I12: ≥94
A13: Operational | B13: Culinary Audit Score | C13: 6.25 | D13: <70 | E13: 70–74 | F13: 75–82 | G13: 83–88 | H13: 89–93 | I13: ≥94
A14: Eligibility | B14: Training Completion % (Gate) | C14: 0 | E14: <87% | G14: ≥87%
A18: RASA · Store Scoring Matrix - Weekly | K18: Performance Rating Key
A19: Category | B19: Metric | C19: Weight (%) | D19: 0 | E19: 1 | F19: 2 | G19: 3 (Contributor) | H19: 4 (High) | I19: 5 (STAR) | K19: Performance | L19: Score | M19: Colour
A20: Sales | B20: Sales vs Budget (%) | C20: 0.06 | D20: <90% | E20: 90–94.9% | F20: 95–98.9% | G20: 99–101.9% | H20: 102–104.9% | I20: ≥105% | K20: STAR | L20: 4.7 - 5.0
B21: Interpolated score range | D21: — | E21: 1.0 – 1.9 | F21: 2.0 – 2.9 | G21: 3.0 – 3.9 | H21: 4.0 – 4.9 | I21: 5 | K21: HIGH | L21: 3.7 - 4.7
B22: Sales vs Prior Year (%) | C22: 0.06 | D22: <−5% | E22: −5% to 0% | F22: 0.1–4.9% | G22: 5–7.4% | H22: 7.5–14.9% | I22: ≥15% | K22: CONTRIBUTOR | L22: 2.7 - 3.7
B23: Interpolated score range | D23: — | E23: 1.0 – 1.9 | F23: 2.0 – 2.9 | G23: 3.0 – 3.9 | H23: 4.0 – 4.9 | I23: 5 | K23: LOW | L23: 1.7 - 2.7
A24: Prime Cost | B24: Labor vs Budget Variance (pts) | C24: 0.145 | D24: ≥+3.0 | E24: 2.0 to 2.99 | F24: 1.0 to +1.99 | G24: 0.01 to 0.99 | H24: 0.0 to -0.99 | I24: ≤−1.0 | K24: NON | L24: 0.0 - 1.7
B25: Interpolated score range | D25: — | E25: 1.0 – 1.9 | F25: 2.0 – 2.9 | G25: 3.0 – 3.9 | H25: 4.0 – 4.9 | I25: 5
B26: COGS vs Budget Variance (pts) | C26: 0.145 | D26: ≥+3.0 | E26: 2.0 to +2.99 | F26: 1.0 to +1.99 | G26: 0.01 to 0.99 | H26: 0.0 to -0.99 | I26: ≤−1.0
B27: Interpolated score range | D27: — | E27: 1.0 – 1.9 | F27: 2.0 – 2.9 | G27: 3.0 – 3.9 | H27: 4.0 – 4.9 | I27: 5
A28: Operational | B28: Google Rating | C28: 0.29 | D28: <3.8 | E28: 3.8–3.99 | F28: 4.0–4.29 | G28: 4.3–4.49 | H28: 4.5–4.69 | I28: ≥4.7
B29: Interpolated score range | D29: — | E29: 1.0 – 1.9 | F29: 2.0 – 2.9 | G29: 3.0 – 3.9 | H29: 4.0 – 4.9 | I29: 5
B30: 3P Error Rate (%) | C30: 0.12 | D30: >6% | E30: 4.01–6% | F30: 2.01–4% | G30: 1.51–2% | H30: 1.01–1.5% | I30: ≤1%
B31: Interpolated score range | D31: — | E31: 1.0 – 1.9 | F31: 2.0 – 2.9 | G31: 3.0 – 3.9 | H31: 4.0 – 4.9 | I31: 5
B32: Avoidable Wait (mins) | C32: 0.09 | D32: >8 | E32: >5 to 8 | F32: >2 to 5 | G32: >1.5 to 2 | H32: >1 to 1.5 | I32: ≤1
B33: Interpolated score range | D33: — | E33: 1.0 – 1.9 | F33: 2.0 – 2.9 | G33: 3.0 – 3.9 | H33: 4.0 – 4.9 | I33: 5
B34: 3P Rating | C34: 0.09 | D34: <3.8 | E34: 3.8–3.99 | F34: 4.0–4.29 | G34: 4.3–4.49 | H34: 4.5–4.69 | I34: ≥4.7
B35: Interpolated score range | D35: — | E35: 1.0 – 1.9 | F35: 2.0 – 2.9 | G35: 3.0 – 3.9 | H35: 4.0 – 4.9 | I35: 5
A36: Total Weight (scored metrics only) | C36: =SUM(C20:C34) -> 1
A40: RASA · Period Scoring Matrix
A41: Category | B41: Metric | C41: Weight (%) | D41: 0 | E41: 1 | F41: 2 | G41: 3 (Contributor) | H41: 4 (High) | I41: 5 (STAR)
A42: Sales | B42: Sales vs Budget (%) | C42: 0.04 | D42: <90% | E42: 90–94.9% | F42: 95–98.9% | G42: 99–101.9% | H42: 102–104.9% | I42: ≥105%
B43: Interpolated score range | D43: — | E43: 1.0 – 1.9 | F43: 2.0 – 2.9 | G43: 3.0 – 3.9 | H43: 4.0 – 4.9 | I43: 5
B44: Sales vs Prior Year (%) | C44: 0.04 | D44: <−5% | E44: −5% to 0% | F44: 0.1–4.9% | G44: 5–7.4% | H44: 7.5–14.9% | I44: ≥15%
B45: Interpolated score range | D45: — | E45: 1.0 – 1.9 | F45: 2.0 – 2.9 | G45: 3.0 – 3.9 | H45: 4.0 – 4.9 | I45: 5
A46: EBITDA | B46: EBITDA vs Budget (%) | C46: 0.125 | D46: <75% | E46: 75–84% | F46: 85–94% | G46: 95–100% | H46: 101–105% | I46: >105%
B47: Interpolated score range | D47: — | E47: 1.0 – 1.9 | F47: 2.0 – 2.9 | G47: 3.0 – 3.9 | H47: 4.0 – 4.9 | I47: 5
A48: Prime Cost | B48: Labor vs Budget Variance (pts) | C48: 0.105 | D48: ≥+3.0 | E48: 2.0 to 2.99 | F48: 1.0 to +1.99 | G48: 0.01 to 0.99 | H48: 0.0 to -0.99 | I48: ≤−1.0
B49: Interpolated score range | D49: — | E49: 1.0 – 1.9 | F49: 2.0 – 2.9 | G49: 3.0 – 3.9 | H49: 4.0 – 4.9 | I49: 5
B50: COGS vs Budget Variance (pts) | C50: 0.105 | D50: ≥+3.0 | E50: 2.0 to +2.99 | F50: 1.0 to +1.99 | G50: 0.01 to 0.99 | H50: 0.0 to -0.99 | I50: ≤−1.0
B51: Interpolated score range | D51: — | E51: 1.0 – 1.9 | F51: 2.0 – 2.9 | G51: 3.0 – 3.9 | H51: 4.0 – 4.9 | I51: 5
A52: Operational | B52: Google Rating | C52: 0.21 | D52: <3.8 | E52: 3.8–3.99 | F52: 4.0–4.29 | G52: 4.3–4.49 | H52: 4.5–4.69 | I52: ≥4.7
B53: Interpolated score range | D53: — | E53: 1.0 – 1.9 | F53: 2.0 – 2.9 | G53: 3.0 – 3.9 | H53: 4.0 – 4.9 | I53: 5
B54: 3P Error Rate (%) | C54: 0.085 | D54: >6% | E54: 4.01–6% | F54: 2.01–4% | G54: 1.51–2% | H54: 1.01–1.5% | I54: ≤1%
B55: Interpolated score range | D55: — | E55: 1.0 – 1.9 | F55: 2.0 – 2.9 | G55: 3.0 – 3.9 | H55: 4.0 – 4.9 | I55: 5
B56: Avoidable Wait (mins) | C56: 0.065 | D56: >8 | E56: >5 to 8 | F56: >2 to 5 | G56: >1.5 to 2 | H56: >1 to 1.5 | I56: ≤1
B57: Interpolated score range | D57: — | E57: 1.0 – 1.9 | F57: 2.0 – 2.9 | G57: 3.0 – 3.9 | H57: 4.0 – 4.9 | I57: 5
B58: 3P Rating | C58: 0.065 | D58: <3.8 | E58: 3.8–3.99 | F58: 4.0–4.29 | G58: 4.3–4.49 | H58: 4.5–4.69 | I58: ≥4.7
B59: Interpolated score range | D59: — | E59: 1.0 – 1.9 | F59: 2.0 – 2.9 | G59: 3.0 – 3.9 | H59: 4.0 – 4.9 | I59: 5
B60: Full Audit Score | C60: 0.105 | D60: <70 | E60: 70–74 | F60: 75–82 | G60: 83–88 | H60: 89–93 | I60: ≥94
B61: Interpolated score range | D61: — | E61: 1.0 – 1.9 | F61: 2.0 – 2.9 | G61: 3.0 – 3.9 | H61: 4.0 – 4.9 | I61: 5
B62: Culinary Audit Score | C62: 0.055 | D62: <70 | E62: 70–74 | F62: 75–82 | G62: 83–88 | H62: 89–93 | I62: ≥94
B63: Interpolated score range | D63: — | E63: 1.0 – 1.9 | F63: 2.0 – 2.9 | G63: 3.0 – 3.9 | H63: 4.0 – 4.9 | I63: 5
A64: Eligibility | B64: Training Completion % (Gate) | C64: — | E64: <87% = Ineligible | G64: ≥87% = Eligible
B65: Interpolated score range
A66: Total Weight (scored metrics only) | C66: =SUM(C42:C64) -> 1
A70: RASA · Quaterly Scoring Matrix
A71: Category | B71: Metric | C71: Weight (%) | D71: 0 | E71: 1 | F71: 2 | G71: 3 (Contributor) | H71: 4 (High) | I71: 5 (STAR)
A72: Sales | B72: Sales vs Budget (%) | C72: 0.04 | D72: <90% | E72: 90–94.9% | F72: 95–98.9% | G72: 99–101.9% | H72: 102–104.9% | I72: ≥105%
B73: Interpolated score range | D73: — | E73: 1.0 – 1.9 | F73: 2.0 – 2.9 | G73: 3.0 – 3.9 | H73: 4.0 – 4.9 | I73: 5
B74: Sales vs Prior Year (%) | C74: 0.04 | D74: <−5% | E74: −5% to 0% | F74: 0.1–4.9% | G74: 5–7.4% | H74: 7.5–14.9% | I74: ≥15%
B75: Interpolated score range | D75: — | E75: 1.0 – 1.9 | F75: 2.0 – 2.9 | G75: 3.0 – 3.9 | H75: 4.0 – 4.9 | I75: 5
A76: EBITDA | B76: EBITDA vs Budget (%) | C76: 0.125 | D76: <75% | E76: 75–84% | F76: 85–94% | G76: 95–100% | H76: 101–105% | I76: >105%
B77: Interpolated score range | D77: — | E77: 1.0 – 1.9 | F77: 2.0 – 2.9 | G77: 3.0 – 3.9 | H77: 4.0 – 4.9 | I77: 5
A78: Prime Cost | B78: Labor vs Budget Variance (pts) | C78: 0.105 | D78: ≥+3.0 | E78: 2.0 to 2.99 | F78: 1.0 to +1.99 | G78: 0.01 to 0.99 | H78: 0.0 to -0.99 | I78: ≤−1.0
B79: Interpolated score range | D79: — | E79: 1.0 – 1.9 | F79: 2.0 – 2.9 | G79: 3.0 – 3.9 | H79: 4.0 – 4.9 | I79: 5
B80: COGS vs Budget Variance (pts) | C80: 0.105 | D80: ≥+3.0 | E80: 2.0 to +2.99 | F80: 1.0 to +1.99 | G80: 0.01 to 0.99 | H80: 0.0 to -0.99 | I80: ≤−1.0
B81: Interpolated score range | D81: — | E81: 1.0 – 1.9 | F81: 2.0 – 2.9 | G81: 3.0 – 3.9 | H81: 4.0 – 4.9 | I81: 5
A82: Operational | B82: Google Rating | C82: 0.21 | D82: <3.8 | E82: 3.8–3.99 | F82: 4.0–4.29 | G82: 4.3–4.49 | H82: 4.5–4.69 | I82: ≥4.7
B83: Interpolated score range | D83: — | E83: 1.0 – 1.9 | F83: 2.0 – 2.9 | G83: 3.0 – 3.9 | H83: 4.0 – 4.9 | I83: 5
B84: 3P Error Rate (%) | C84: 0.085 | D84: >6% | E84: 4.01–6% | F84: 2.01–4% | G84: 1.51–2% | H84: 1.01–1.5% | I84: ≤1%
B85: Interpolated score range | D85: — | E85: 1.0 – 1.9 | F85: 2.0 – 2.9 | G85: 3.0 – 3.9 | H85: 4.0 – 4.9 | I85: 5
B86: Avoidable Wait (mins) | C86: 0.065 | D86: >8 | E86: >5 to 8 | F86: >2 to 5 | G86: >1.5 to 2 | H86: >1 to 1.5 | I86: ≤1
B87: Interpolated score range | D87: — | E87: 1.0 – 1.9 | F87: 2.0 – 2.9 | G87: 3.0 – 3.9 | H87: 4.0 – 4.9 | I87: 5
B88: 3P Rating | C88: 0.065 | D88: <3.8 | E88: 3.8–3.99 | F88: 4.0–4.29 | G88: 4.3–4.49 | H88: 4.5–4.69 | I88: ≥4.7
B89: Interpolated score range | D89: — | E89: 1.0 – 1.9 | F89: 2.0 – 2.9 | G89: 3.0 – 3.9 | H89: 4.0 – 4.9 | I89: 5
B90: Full Audit Score | C90: 0.105 | D90: <70 | E90: 70–74 | F90: 75–82 | G90: 83–88 | H90: 89–93 | I90: ≥94
B91: Interpolated score range | D91: — | E91: 1.0 – 1.9 | F91: 2.0 – 2.9 | G91: 3.0 – 3.9 | H91: 4.0 – 4.9 | I91: 5
B92: Culinary Audit Score | C92: 0.055 | D92: <70 | E92: 70–74 | F92: 75–82 | G92: 83–88 | H92: 89–93 | I92: ≥94
B93: Interpolated score range | D93: — | E93: 1.0 – 1.9 | F93: 2.0 – 2.9 | G93: 3.0 – 3.9 | H93: 4.0 – 4.9 | I93: 5
A94: Eligibility | B94: Training Completion % (Gate) | C94: — | E94: <87% = Ineligible | G94: ≥87% = Eligible
B95: Interpolated score range
A96: Total Weight (scored metrics only) | C96: =SUM(C72:C94) -> 1

Sheet WEEKLY>>>

Sheet Weekly Store Scorecards 
A1: Location | B1: Sales vs Budget (%) | E1: Sales vs Prior Year (%) | K1: Labor vs Budget Variance (pts) | N1: COGS vs Budget Variance (pts) | Q1: In-Store Rating | T1: 3P Error Rate (%) | W1: Avoidable Wait (mins) | Z1: 3P Rating | AC1: Composite Score (0–5)
B2: Input | C2: Score | D2: Weighted | E2: Input | F2: Score | G2: Weighted | K2: Input | L2: Score | M2: Weighted | N2: Input | O2: Score | P2: Weighted | Q2: Input | R2: Score | S2: Weighted | T2: Input | U2: Score | V2: Weighted | W2: Input | X2: Score | Y2: Weighted | Z2: Input | AA2: Score | AB2: Weighted
A3: Mosaic | B3: =100%+'Weekly Tables'!I3 -> 0.94670671 | C3: =IFERROR(ROUND(ifs(B3="","",B3>=1.05,5,B3>=1.02,4+(B3-1.02)/0.03,B3>=0.99,3+(B3-0.99)/0.03,B3>=0.95,2+(B3-0.95)/0.04,B3>=0.9,1+(B3-0.9)/0.05,TRUE(),0),1),"") -> 1.9 | D3: =IF(C3="","",C3*C$8) -> 0.114 | E3: =100%+'Weekly Tables'!F3 -> 1.0965152 | F3: =IFERROR(ROUND(ifs(E3="","",E3>=1.15,5,E3>=1.075,4+(E3-1.075)/0.075,E3>=1.05,3+(E3-1.05)/0.025,E3>=1,2+(E3-1)/0.05,E3>=0.95,1+(E3-0.95)/0.05,TRUE(),0),1),"") -> 4.3 | G3: =IF(F3="","",F3*F$8) -> 0.258 | K3: ='Weekly Tables'!L3*100 -> -2.7 | L3: =IFERROR(ROUND(IFS(K3="","",K3>=3,0,K3>=2,1+(3-K3)/1,K3>=1,2+(2-K3)/1,K3>0,3+(1-K3)/1,K3>=-1,4+(0-K3)/1,TRUE,5),1),"") -> 5 | M3: =IF(L3="","",L3*L$8) -> 0.725 | N3: ='Weekly Tables'!O3*100 -> -3.4 | O3: =IFERROR(ROUND(IFS(N3="","",N3>=3,0,N3>=2,1+(3-N3)/1,N3>=1,2+(2-N3)/1,N3>0,3+(1-N3)/1,N3>=-1,4+(0-N3)/1,TRUE,5),1),"") -> 5 | P3: =IF(O3="","",O3*O$8) -> 0.725 | Q3: ='Weekly Tables'!E14 -> 3.33 | R3: =IFERROR(ROUND(ifs(Q3="","",Value(Q3)="NA","" ,Q3>=4.7,5,Q3>=4.5,4+(Q3-4.5)/0.2,Q3>=4.3,3+(Q3-4.3)/0.2,Q3>=4,2+(Q3-4)/0.3,Q3>=3.8,1+(Q3-3.8)/0.2,TRUE(),0),1),"") -> 0 | S3: =IF(R3="","",R3*R$8) -> 0 | T3: ='Weekly Tables'!N21 -> 0.0372 | U3: =IFERROR(ROUND(ifs(T3="","",T3<=0.01,5,T3<=0.015,4+(0.015-T3)/0.005,T3<=0.02,3+(0.02-T3)/0.005,T3<=0.04,2+(0.04-T3)/0.02,T3<=0.06,1+(0.06-T3)/0.02,TRUE(),0),1),"") -> 2.1 | V3: =IF(U3="","",U3*U$8) -> 0.252 | W3: {=XLOOKUP(A3,'Weekly Tables'!$B$30:$B$34,'Weekly Tables'!$H$30:$H$34)} -> 1.6 | X3: =IFERROR(ROUND(ifs(W3="","",W3<=1,5,W3<=1.5,4+(1.5-W3)/0.5,W3<=2,3+(2-W3)/0.5,W3<=5,2+(5-W3)/3,W3<=8,1+(8-W3)/3,TRUE(),0),1),"") -> 3.8 | Y3: =IF(X3="","",X3*X$8) -> 0.342 | Z3: ='Weekly Tables'!E21 -> 4.3 | AA3: =IFERROR(ROUND(ifs(Z3="","",Z3>=4.7,5,Z3>=4.5,4+(Z3-4.5)/0.2,Z3>=4.3,3+(Z3-4.3)/0.2,Z3>=4,2+(Z3-4)/0.3,Z3>=3.8,1+(Z3-3.8)/0.2,TRUE(),0),1),"") -> 3 | AB3: =IF(AA3="","",AA3*AA$8) -> 0.27 | AC3: =SUM(D3,G3,J3,M3,P3,S3,V3,Y3,AB3) -> 2.686
A4: MVT | B4: =100%+'Weekly Tables'!I4 -> 1.0190662 | C4: =IFERROR(ROUND(ifs(B4="","",B4>=1.05,5,B4>=1.02,4+(B4-1.02)/0.03,B4>=0.99,3+(B4-0.99)/0.03,B4>=0.95,2+(B4-0.95)/0.04,B4>=0.9,1+(B4-0.9)/0.05,TRUE(),0),1),"") -> 4 | D4: =IF(C4="","",C4*C$8) -> 0.24 | E4: =100%+'Weekly Tables'!F4 -> 1.3761061 | F4: =IFERROR(ROUND(ifs(E4="","",E4>=1.15,5,E4>=1.075,4+(E4-1.075)/0.075,E4>=1.05,3+(E4-1.05)/0.025,E4>=1,2+(E4-1)/0.05,E4>=0.95,1+(E4-0.95)/0.05,TRUE(),0),1),"") -> 5 | G4: =IF(F4="","",F4*F$8) -> 0.3 | K4: ='Weekly Tables'!L4*100 -> 2.4 | L4: =IFERROR(ROUND(IFS(K4="","",K4>=3,0,K4>=2,1+(3-K4)/1,K4>=1,2+(2-K4)/1,K4>0,3+(1-K4)/1,K4>=-1,4+(0-K4)/1,TRUE,5),1),"") -> 1.6 | M4: =IF(L4="","",L4*L$8) -> 0.232 | N4: ='Weekly Tables'!O4*100 -> 1.1 | O4: =IFERROR(ROUND(IFS(N4="","",N4>=3,0,N4>=2,1+(3-N4)/1,N4>=1,2+(2-N4)/1,N4>0,3+(1-N4)/1,N4>=-1,4+(0-N4)/1,TRUE,5),1),"") -> 2.9 | P4: =IF(O4="","",O4*O$8) -> 0.4205 | Q4: ='Weekly Tables'!E12 -> NA | R4: =IFERROR(ROUND(ifs(Q4="","",Value(Q4)="NA","" ,Q4>=4.7,5,Q4>=4.5,4+(Q4-4.5)/0.2,Q4>=4.3,3+(Q4-4.3)/0.2,Q4>=4,2+(Q4-4)/0.3,Q4>=3.8,1+(Q4-3.8)/0.2,TRUE(),0),1),"") | S4: =IF(R4="","",R4*R$8) | T4: ='Weekly Tables'!N19 -> 0.0209 | U4: =IFERROR(ROUND(ifs(T4="","",T4<=0.01,5,T4<=0.015,4+(0.015-T4)/0.005,T4<=0.02,3+(0.02-T4)/0.005,T4<=0.04,2+(0.04-T4)/0.02,T4<=0.06,1+(0.06-T4)/0.02,TRUE(),0),1),"") -> 3 | V4: =IF(U4="","",U4*U$8) -> 0.36 | W4: {=XLOOKUP(A4,'Weekly Tables'!$B$30:$B$34,'Weekly Tables'!$H$30:$H$34)} -> 1.02 | X4: =IFERROR(ROUND(ifs(W4="","",W4<=1,5,W4<=1.5,4+(1.5-W4)/0.5,W4<=2,3+(2-W4)/0.5,W4<=5,2+(5-W4)/3,W4<=8,1+(8-W4)/3,TRUE(),0),1),"") -> 5 | Y4: =IF(X4="","",X4*X$8) -> 0.45 | Z4: ='Weekly Tables'!E19 -> 4.5 | AA4: =IFERROR(ROUND(ifs(Z4="","",Z4>=4.7,5,Z4>=4.5,4+(Z4-4.5)/0.2,Z4>=4.3,3+(Z4-4.3)/0.2,Z4>=4,2+(Z4-4)/0.3,Z4>=3.8,1+(Z4-3.8)/0.2,TRUE(),0),1),"") -> 4 | AB4: =IF(AA4="","",AA4*AA$8) -> 0.36 | AC4: =SUM(D4,G4,J4,M4,P4,S4,V4,Y4,AB4) -> 2.3625
A5: National Landing | B5: =100%+'Weekly Tables'!I5 -> 1.2172449 | C5: =IFERROR(ROUND(ifs(B5="","",B5>=1.05,5,B5>=1.02,4+(B5-1.02)/0.03,B5>=0.99,3+(B5-0.99)/0.03,B5>=0.95,2+(B5-0.95)/0.04,B5>=0.9,1+(B5-0.9)/0.05,TRUE(),0),1),"") -> 5 | D5: =IF(C5="","",C5*C$8) -> 0.3 | E5: =100%+'Weekly Tables'!F5 -> 1.4285788 | F5: =IFERROR(ROUND(ifs(E5="","",E5>=1.15,5,E5>=1.075,4+(E5-1.075)/0.075,E5>=1.05,3+(E5-1.05)/0.025,E5>=1,2+(E5-1)/0.05,E5>=0.95,1+(E5-0.95)/0.05,TRUE(),0),1),"") -> 5 | G5: =IF(F5="","",F5*F$8) -> 0.3 | K5: ='Weekly Tables'!L5*100 -> -4.1 | L5: =IFERROR(ROUND(IFS(K5="","",K5>=3,0,K5>=2,1+(3-K5)/1,K5>=1,2+(2-K5)/1,K5>0,3+(1-K5)/1,K5>=-1,4+(0-K5)/1,TRUE,5),1),"") -> 5 | M5: =IF(L5="","",L5*L$8) -> 0.725 | N5: ='Weekly Tables'!O5*100 -> 0.2 | O5: =IFERROR(ROUND(IFS(N5="","",N5>=3,0,N5>=2,1+(3-N5)/1,N5>=1,2+(2-N5)/1,N5>0,3+(1-N5)/1,N5>=-1,4+(0-N5)/1,TRUE,5),1),"") -> 3.8 | P5: =IF(O5="","",O5*O$8) -> 0.551 | Q5: ='Weekly Tables'!E13 -> 4 | R5: =IFERROR(ROUND(ifs(Q5="","",Value(Q5)="NA","" ,Q5>=4.7,5,Q5>=4.5,4+(Q5-4.5)/0.2,Q5>=4.3,3+(Q5-4.3)/0.2,Q5>=4,2+(Q5-4)/0.3,Q5>=3.8,1+(Q5-3.8)/0.2,TRUE(),0),1),"") -> 2 | S5: =IF(R5="","",R5*R$8) -> 0.58 | T5: ='Weekly Tables'!N20 -> 0.0408 | U5: =IFERROR(ROUND(ifs(T5="","",T5<=0.01,5,T5<=0.015,4+(0.015-T5)/0.005,T5<=0.02,3+(0.02-T5)/0.005,T5<=0.04,2+(0.04-T5)/0.02,T5<=0.06,1+(0.06-T5)/0.02,TRUE(),0),1),"") -> 2 | V5: =IF(U5="","",U5*U$8) -> 0.24 | W5: {=XLOOKUP(A5,'Weekly Tables'!$B$30:$B$34,'Weekly Tables'!$H$30:$H$34)} -> 1.05 | X5: =IFERROR(ROUND(ifs(W5="","",W5<=1,5,W5<=1.5,4+(1.5-W5)/0.5,W5<=2,3+(2-W5)/0.5,W5<=5,2+(5-W5)/3,W5<=8,1+(8-W5)/3,TRUE(),0),1),"") -> 4.9 | Y5: =IF(X5="","",X5*X$8) -> 0.441 | Z5: ='Weekly Tables'!E20 -> 4.5 | AA5: =IFERROR(ROUND(ifs(Z5="","",Z5>=4.7,5,Z5>=4.5,4+(Z5-4.5)/0.2,Z5>=4.3,3+(Z5-4.3)/0.2,Z5>=4,2+(Z5-4)/0.3,Z5>=3.8,1+(Z5-3.8)/0.2,TRUE(),0),1),"") -> 4 | AB5: =IF(AA5="","",AA5*AA$8) -> 0.36 | AC5: =SUM(D5,G5,J5,M5,P5,S5,V5,Y5,AB5) -> 3.497
A6: Rockville | B6: =100%+'Weekly Tables'!I6 -> 0.87077313 | C6: =IFERROR(ROUND(ifs(B6="","",B6>=1.05,5,B6>=1.02,4+(B6-1.02)/0.03,B6>=0.99,3+(B6-0.99)/0.03,B6>=0.95,2+(B6-0.95)/0.04,B6>=0.9,1+(B6-0.9)/0.05,TRUE(),0),1),"") -> 0 | D6: =IF(C6="","",C6*C$8) -> 0 | E6: =100%+'Weekly Tables'!F6 -> 1.0890977 | F6: =IFERROR(ROUND(ifs(E6="","",E6>=1.15,5,E6>=1.075,4+(E6-1.075)/0.075,E6>=1.05,3+(E6-1.05)/0.025,E6>=1,2+(E6-1)/0.05,E6>=0.95,1+(E6-0.95)/0.05,TRUE(),0),1),"") -> 4.2 | G6: =IF(F6="","",F6*F$8) -> 0.252 | K6: ='Weekly Tables'!L6*100 -> -0.7 | L6: =IFERROR(ROUND(IFS(K6="","",K6>=3,0,K6>=2,1+(3-K6)/1,K6>=1,2+(2-K6)/1,K6>0,3+(1-K6)/1,K6>=-1,4+(0-K6)/1,TRUE,5),1),"") -> 4.7 | M6: =IF(L6="","",L6*L$8) -> 0.6815 | N6: ='Weekly Tables'!O6*100 -> 3.3 | O6: =IFERROR(ROUND(IFS(N6="","",N6>=3,0,N6>=2,1+(3-N6)/1,N6>=1,2+(2-N6)/1,N6>0,3+(1-N6)/1,N6>=-1,4+(0-N6)/1,TRUE,5),1),"") -> 0 | P6: =IF(O6="","",O6*O$8) -> 0 | Q6: ='Weekly Tables'!E15 -> 4.25 | R6: =IFERROR(ROUND(ifs(Q6="","",Value(Q6)="NA","" ,Q6>=4.7,5,Q6>=4.5,4+(Q6-4.5)/0.2,Q6>=4.3,3+(Q6-4.3)/0.2,Q6>=4,2+(Q6-4)/0.3,Q6>=3.8,1+(Q6-3.8)/0.2,TRUE(),0),1),"") -> 2.8 | S6: =IF(R6="","",R6*R$8) -> 0.812 | T6: ='Weekly Tables'!N22 -> 0.0294 | U6: =IFERROR(ROUND(ifs(T6="","",T6<=0.01,5,T6<=0.015,4+(0.015-T6)/0.005,T6<=0.02,3+(0.02-T6)/0.005,T6<=0.04,2+(0.04-T6)/0.02,T6<=0.06,1+(0.06-T6)/0.02,TRUE(),0),1),"") -> 2.5 | V6: =IF(U6="","",U6*U$8) -> 0.3 | W6: {=XLOOKUP(A6,'Weekly Tables'!$B$30:$B$34,'Weekly Tables'!$H$30:$H$34)} -> 1.43 | X6: =IFERROR(ROUND(ifs(W6="","",W6<=1,5,W6<=1.5,4+(1.5-W6)/0.5,W6<=2,3+(2-W6)/0.5,W6<=5,2+(5-W6)/3,W6<=8,1+(8-W6)/3,TRUE(),0),1),"") -> 4.1 | Y6: =IF(X6="","",X6*X$8) -> 0.369 | Z6: ='Weekly Tables'!E22 -> 4.2 | AA6: =IFERROR(ROUND(ifs(Z6="","",Z6>=4.7,5,Z6>=4.5,4+(Z6-4.5)/0.2,Z6>=4.3,3+(Z6-4.3)/0.2,Z6>=4,2+(Z6-4)/0.3,Z6>=3.8,1+(Z6-3.8)/0.2,TRUE(),0),1),"") -> 2.7 | AB6: =IF(AA6="","",AA6*AA$8) -> 0.243 | AC6: =SUM(D6,G6,J6,M6,P6,S6,V6,Y6,AB6) -> 2.6575
A7: All Stores | B7: =100%+'Weekly Tables'!I7 -> 0.85242532 | C7: =IFERROR(ROUND(ifs(B7="","",B7>=1.05,5,B7>=1.02,4+(B7-1.02)/0.03,B7>=0.99,3+(B7-0.99)/0.03,B7>=0.95,2+(B7-0.95)/0.04,B7>=0.9,1+(B7-0.9)/0.05,TRUE(),0),1),"") -> 0 | D7: =IF(C7="","",C7*C$8) -> 0 | E7: =100%+'Weekly Tables'!F7 -> 1.0642439 | F7: =IFERROR(ROUND(ifs(E7="","",E7>=1.15,5,E7>=1.075,4+(E7-1.075)/0.075,E7>=1.05,3+(E7-1.05)/0.025,E7>=1,2+(E7-1)/0.05,E7>=0.95,1+(E7-0.95)/0.05,TRUE(),0),1),"") -> 3.6 | G7: =IF(F7="","",F7*F$8) -> 0.216 | K7: ='Weekly Tables'!L7*100 -> -1.9 | L7: =IFERROR(ROUND(IFS(K7="","",K7>=3,0,K7>=2,1+(3-K7)/1,K7>=1,2+(2-K7)/1,K7>0,3+(1-K7)/1,K7>=-1,4+(0-K7)/1,TRUE,5),1),"") -> 5 | M7: =IF(L7="","",L7*L$8) -> 0.725 | N7: ='Weekly Tables'!O7*100 -> -0.1 | O7: =IFERROR(ROUND(IFS(N7="","",N7>=3,0,N7>=2,1+(3-N7)/1,N7>=1,2+(2-N7)/1,N7>0,3+(1-N7)/1,N7>=-1,4+(0-N7)/1,TRUE,5),1),"") -> 4.1 | P7: =IF(O7="","",O7*O$8) -> 0.5945 | Q7: ='Weekly Tables'!E16 -> 3.88 | R7: =IFERROR(ROUND(ifs(Q7="","",Value(Q7)="NA","" ,Q7>=4.7,5,Q7>=4.5,4+(Q7-4.5)/0.2,Q7>=4.3,3+(Q7-4.3)/0.2,Q7>=4,2+(Q7-4)/0.3,Q7>=3.8,1+(Q7-3.8)/0.2,TRUE(),0),1),"") -> 1.4 | S7: =IF(R7="","",R7*R$8) -> 0.406 | T7: ='Weekly Tables'!N23 -> 0.032075 | U7: =IFERROR(ROUND(ifs(T7="","",T7<=0.01,5,T7<=0.015,4+(0.015-T7)/0.005,T7<=0.02,3+(0.02-T7)/0.005,T7<=0.04,2+(0.04-T7)/0.02,T7<=0.06,1+(0.06-T7)/0.02,TRUE(),0),1),"") -> 2.4 | V7: =IF(U7="","",U7*U$8) -> 0.288 | W7: {=XLOOKUP(A7,'Weekly Tables'!$B$30:$B$35,'Weekly Tables'!$H$30:$H$35)} -> 1.2 | X7: =IFERROR(ROUND(ifs(W7="","",W7<=1,5,W7<=1.5,4+(1.5-W7)/0.5,W7<=2,3+(2-W7)/0.5,W7<=5,2+(5-W7)/3,W7<=8,1+(8-W7)/3,TRUE(),0),1),"") -> 4.6 | Y7: =IF(X7="","",X7*X$8) -> 0.414 | Z7: ='Weekly Tables'!E23 -> 4.375 | AA7: =IFERROR(ROUND(ifs(Z7="","",Z7>=4.7,5,Z7>=4.5,4+(Z7-4.5)/0.2,Z7>=4.3,3+(Z7-4.3)/0.2,Z7>=4,2+(Z7-4)/0.3,Z7>=3.8,1+(Z7-3.8)/0.2,TRUE(),0),1),"") -> 3.4 | AB7: =IF(AA7="","",AA7*AA$8) -> 0.306 | AC7: =SUM(D7,G7,J7,M7,P7,S7,V7,Y7,AB7) -> 2.9495
A8: Weight | C8: ='Scoring Matrix'!C20 -> 0.06 | F8: ='Scoring Matrix'!C22 -> 0.06 | L8: ='Scoring Matrix'!C24 -> 0.145 | O8: ='Scoring Matrix'!C26 -> 0.145 | R8: ='Scoring Matrix'!C28 -> 0.29 | U8: ='Scoring Matrix'!C30 -> 0.12 | X8: ='Scoring Matrix'!C32 -> 0.09 | AA8: ='Scoring Matrix'!C34 -> 0.09

Sheet Weekly Area Leader Dashboard
A1: Restaurant | B1: Composite Score | C1: Contributor Band | D1: Sales vs Budget (%) | E1: Sales vs Prior Year (%) | F1: Labor vs Budget Variance (pts) | G1: COGS vs Budget Variance (pts) | H1: In-Store Rating | I1: 3P Rating | J1: 3P Error % | K1: Avoidable Wait (mins)
A2: Mosaic | B2: ='Weekly Store Scorecards '!AC3 -> 2.686 | C2: =IFS(B2<1.7,"Non", B2<2.7,"Low", B2<3.7,"Contributor", B2<4.7,"High", TRUE,"STAR") -> Low | D2: ='Weekly Store Scorecards '!B3 -> 0.94670671 | E2: ='Weekly Store Scorecards '!E3 -> 1.0965152 | F2: ='Weekly Store Scorecards '!K3 -> -2.7 | G2: ='Weekly Store Scorecards '!N3 -> -3.4 | H2: ='Weekly Store Scorecards '!Q3 -> 3.33 | I2: ='Weekly Store Scorecards '!Z3 -> 4.3 | J2: ='Weekly Store Scorecards '!T3 -> 0.0372 | K2: ='Weekly Store Scorecards '!W3 -> 1.6
A3: MVT | B3: ='Weekly Store Scorecards '!AC4 -> 2.3625 | C3: =IFS(B3<1.7,"Non", B3<2.7,"Low", B3<3.7,"Contributor", B3<4.7,"High", TRUE,"STAR") -> Low | D3: ='Weekly Store Scorecards '!B4 -> 1.0190662 | E3: ='Weekly Store Scorecards '!E4 -> 1.3761061 | F3: ='Weekly Store Scorecards '!K4 -> 2.4 | G3: ='Weekly Store Scorecards '!N4 -> 1.1 | H3: ='Weekly Store Scorecards '!Q4 -> NA | I3: ='Weekly Store Scorecards '!Z4 -> 4.5 | J3: ='Weekly Store Scorecards '!T4 -> 0.0209 | K3: ='Weekly Store Scorecards '!W4 -> 1.02
A4: National Landing | B4: ='Weekly Store Scorecards '!AC5 -> 3.497 | C4: =IFS(B4<1.7,"Non", B4<2.7,"Low", B4<3.7,"Contributor", B4<4.7,"High", TRUE,"STAR") -> Contributor | D4: ='Weekly Store Scorecards '!B5 -> 1.2172449 | E4: ='Weekly Store Scorecards '!E5 -> 1.4285788 | F4: ='Weekly Store Scorecards '!K5 -> -4.1 | G4: ='Weekly Store Scorecards '!N5 -> 0.2 | H4: ='Weekly Store Scorecards '!Q5 -> 4 | I4: ='Weekly Store Scorecards '!Z5 -> 4.5 | J4: ='Weekly Store Scorecards '!T5 -> 0.0408 | K4: ='Weekly Store Scorecards '!W5 -> 1.05
A5: Rockville | B5: ='Weekly Store Scorecards '!AC6 -> 2.6575 | C5: =IFS(B5<1.7,"Non", B5<2.7,"Low", B5<3.7,"Contributor", B5<4.7,"High", TRUE,"STAR") -> Low | D5: ='Weekly Store Scorecards '!B6 -> 0.87077313 | E5: ='Weekly Store Scorecards '!E6 -> 1.0890977 | F5: ='Weekly Store Scorecards '!K6 -> -0.7 | G5: ='Weekly Store Scorecards '!N6 -> 3.3 | H5: ='Weekly Store Scorecards '!Q6 -> 4.25 | I5: ='Weekly Store Scorecards '!Z6 -> 4.2 | J5: ='Weekly Store Scorecards '!T6 -> 0.0294 | K5: ='Weekly Store Scorecards '!W6 -> 1.43
A6: All Stores | B6: ='Weekly Store Scorecards '!AC7 -> 2.9495 | D6: ='Weekly Store Scorecards '!B7 -> 0.85242532 | E6: ='Weekly Store Scorecards '!E7 -> 1.0642439 | F6: ='Weekly Store Scorecards '!K7 -> -1.9 | G6: ='Weekly Store Scorecards '!N7 -> -0.1 | H6: ='Weekly Store Scorecards '!Q7 -> 3.88 | I6: ='Weekly Store Scorecards '!Z7 -> 4.375 | J6: ='Weekly Store Scorecards '!T7 -> 0.032075 | K6: ='Weekly Store Scorecards '!W7 -> 1.2

Sheet Weekly Store Scorecards
A1: Restaurant | B1: Sales vs Budget (%) | C1: Score | D1: Weighted | E1: Sales vs Prior Year (%) | F1: Score | G1: Weighted | H1: EBITDA vs Budget (%) | I1: Score | J1: Weighted | K1: Labor Var (pts) | L1: Score | M1: Weighted | N1: COGS Var (pts) | O1: Score | P1: Weighted | Q1: Google Rating | R1: Score | S1: Weighted | T1: Yelp Rating | U1: Score | V1: Weighted | W1: 3P Error Rate (%) | X1: Score | Y1: Weighted | Z1: Avoidable Wait (mins) | AA1: Score | AB1: Weighted | AC1: 3P Rating | AD1: Score | AE1: Weighted | AF1: Full Audit Score | AG1: Score | AH1: Weighted | AI1: Culinary Audit Score | AJ1: Score | AK1: Weighted | AL1: Focus Audit Score | AM1: Score | AN1: Weighted | AO1: Training % (Gate) | AP1: Composite Score (0-5)
A2: Ballpark | B2: =100%+'Weekly Tables'!I3 -> 0.94670671 | C2: =IFS(B2="", "", B2<90%,0, B2<95%,1, B2<=98%,2, B2<=101%,3, B2<=105%,4, TRUE,5) -> 1 | D2: =IF(C2="","",C2*5/100) -> 0.05 | E2: =100%+'Weekly Tables'!F3 -> 1.0965152 | F2: =IFS(E2="", "", E2<90%,0, E2<95%,1, E2<=98%,2, E2<=101%,3, E2<=105%,4, TRUE,5) -> 5 | G2: =IF(F2="","",F2*5/100) -> 0.25 | I2: =IFS(H2="", "", H2<75,0, H2<85,1, H2<95,2, H2<=100,3, H2<=105,4, TRUE,5) | J2: =IF(I2="","",I2*15/100) | K2: ='Weekly Tables'!L3*100 -> -2.7 | L2: =IFS(K2="", "", K2>=3,0, K2>=2,1, K2>=1,2, K2>=0,3, K2<=-1,5, K2<=-0.5,4, TRUE,3) -> 5 | M2: =IF(L2="","",L2*15/100) -> 0.75 | N2: ='Weekly Tables'!O3*100 -> -3.4 | O2: =IFS(N2="", "", N2>=3,0, N2>=2,1, N2>=1,2, N2>=0,3, N2<=-1,5, N2<=-0.5,4, TRUE,3) -> 5 | P2: =IF(O2="","",O2*15/100) -> 0.75 | Q2: ='Weekly Tables'!M12 -> NA | R2: =IFS(Q2="", "", Q2="NA","" ,Q2<3.8,0, Q2<4,1, Q2<4.3,2, Q2<4.5,3, Q2<4.7,4, TRUE,5) | S2: =IF(R2="","",R2*21/100) | T2: ='Weekly Tables'!K12 -> NA | U2: =IFS(T2="", "", T2="NA","" ,T2<3.8,0, T2<4,1, T2<4.3,2, T2<4.5,3, T2<4.7,4, TRUE,5) | V2: =IF(U2="","",U2*7.5/100) | W2: ='Weekly Tables'!N20 -> 0.0408 | X2: =IFS(W2="", "", W2>6%,0, W2>4%,1, W2>2%,2, W2>1.5%,3, W2>1%,4, TRUE,5) -> 1 | Y2: =IF(X2="","",X2*10/100) -> 0.1 | Z2: {=XLOOKUP(A2,'Weekly Tables'!$B$30:$B$34,'Weekly Tables'!$H$30:$H$34)} -> #N/A | AA2: =IFS(Z2="","", VALUE(Z2)>8,0, VALUE(Z2)>5,1, VALUE(Z2)>2,2, VALUE(Z2)>1.5,3, VALUE(Z2)>1,4, TRUE,5) -> #N/A | AB2: =IF(AA2="","",AA2*7.5/100) -> #N/A | AC2: ='Weekly Tables'!E20 -> 4.5 | AD2: =IFS(AC2="", "", AC2<3.8,0, AC2<4,1, AC2<4.3,2, AC2<4.5,3, AC2<4.7,4, TRUE,5) -> 4 | AE2: =IF(AD2="","",AD2*7.5/100) -> 0.3 | AF2: 86 | AG2: =IFS(AF2="", "", AF2<70,0, AF2<75,1, AF2<83,2, AF2<89,3, AF2<94,4, TRUE,5) -> 3 | AH2: =IF(AG2="","",AG2*12.5/100) -> 0.375 | AI2: 90 | AJ2: =IFS(AI2="", "", AI2<70,0, AI2<75,1, AI2<83,2, AI2<89,3, AI2<94,4, TRUE,5) -> 4 | AK2: =IF(AJ2="","",AJ2*6.25/100) -> 0.25 | AL2: 95 | AM2: =IFS(AL2="", "", AL2<70,0, AL2<75,1, AL2<83,2, AL2<89,3, AL2<94,4, TRUE,5) -> 5 | AN2: =IF(AM2="","",AM2*6.25/100) -> 0.3125 | AO2: 85 | AP2: =SUM(D2,G2,J2,M2,P2,S2,V2,Y2,AB2,AE2,AH2,AK2,AN2) -> #N/A
A3: Mosaic | B3: =100%+'Weekly Tables'!I4 -> 1.0190662 | C3: =IFS(B3="", "", B3<90%,0, B3<95%,1, B3<=98%,2, B3<=101%,3, B3<=105%,4, TRUE,5) -> 4 | D3: =IF(C3="","",C3*5/100) -> 0.2 | E3: =100%+'Weekly Tables'!F4 -> 1.3761061 | F3: =IFS(E3="", "", E3<90%,0, E3<95%,1, E3<=98%,2, E3<=101%,3, E3<=105%,4, TRUE,5) -> 5 | G3: =IF(F3="","",F3*5/100) -> 0.25 | I3: =IFS(H3="", "", H3<75,0, H3<85,1, H3<95,2, H3<=100,3, H3<=105,4, TRUE,5) | J3: =IF(I3="","",I3*15/100) | K3: ='Weekly Tables'!L4*100 -> 2.4 | L3: =IFS(K3="", "", K3>=3,0, K3>=2,1, K3>=1,2, K3>=0,3, K3<=-1,5, K3<=-0.5,4, TRUE,3) -> 1 | M3: =IF(L3="","",L3*15/100) -> 0.15 | N3: ='Weekly Tables'!O4*100 -> 1.1 | O3: =IFS(N3="", "", N3>=3,0, N3>=2,1, N3>=1,2, N3>=0,3, N3<=-1,5, N3<=-0.5,4, TRUE,3) -> 2 | P3: =IF(O3="","",O3*15/100) -> 0.3 | Q3: ='Weekly Tables'!M15 -> 5 | R3: =IFS(Q3="", "", Q3="NA","" ,Q3<3.8,0, Q3<4,1, Q3<4.3,2, Q3<4.5,3, Q3<4.7,4, TRUE,5) -> 5 | S3: =IF(R3="","",R3*21/100) -> 1.05 | T3: ='Weekly Tables'!K15 -> 2 | U3: =IFS(T3="", "", T3="NA","" ,T3<3.8,0, T3<4,1, T3<4.3,2, T3<4.5,3, T3<4.7,4, TRUE,5) -> 0 | V3: =IF(U3="","",U3*7.5/100) -> 0 | W3: ='Weekly Tables'!N23 -> 0.032075 | X3: =IFS(W3="", "", W3>6%,0, W3>4%,1, W3>2%,2, W3>1.5%,3, W3>1%,4, TRUE,5) -> 2 | Y3: =IF(X3="","",X3*10/100) -> 0.2 | Z3: {=XLOOKUP(A3,'Weekly Tables'!$B$30:$B$34,'Weekly Tables'!$H$30:$H$34)} -> 1.6 | AA3: =IFS(Z3="","", VALUE(Z3)>8,0, VALUE(Z3)>5,1, VALUE(Z3)>2,2, VALUE(Z3)>1.5,3, VALUE(Z3)>1,4, TRUE,5) -> 3 | AB3: =IF(AA3="","",AA3*7.5/100) -> 0.225 | AC3: ='Weekly Tables'!E23 -> 4.375 | AD3: =IFS(AC3="", "", AC3<3.8,0, AC3<4,1, AC3<4.3,2, AC3<4.5,3, AC3<4.7,4, TRUE,5) -> 3 | AE3: =IF(AD3="","",AD3*7.5/100) -> 0.225 | AF3: 67 | AG3: =IFS(AF3="", "", AF3<70,0, AF3<75,1, AF3<83,2, AF3<89,3, AF3<94,4, TRUE,5) -> 0 | AH3: =IF(AG3="","",AG3*12.5/100) -> 0 | AI3: 70 | AJ3: =IFS(AI3="", "", AI3<70,0, AI3<75,1, AI3<83,2, AI3<89,3, AI3<94,4, TRUE,5) -> 1 | AK3: =IF(AJ3="","",AJ3*6.25/100) -> 0.0625 | AL3: 76 | AM3: =IFS(AL3="", "", AL3<70,0, AL3<75,1, AL3<83,2, AL3<89,3, AL3<94,4, TRUE,5) -> 2 | AN3: =IF(AM3="","",AM3*6.25/100) -> 0.125 | AO3: 87 | AP3: =SUM(D3,G3,J3,M3,P3,S3,V3,Y3,AB3,AE3,AH3,AK3,AN3) -> 2.7875
A4: MVT | B4: =100%+'Weekly Tables'!I5 -> 1.2172449 | C4: =IFS(B4="", "", B4<90%,0, B4<95%,1, B4<=98%,2, B4<=101%,3, B4<=105%,4, TRUE,5) -> 5 | D4: =IF(C4="","",C4*5/100) -> 0.25 | E4: =100%+'Weekly Tables'!F5 -> 1.4285788 | F4: =IFS(E4="", "", E4<90%,0, E4<95%,1, E4<=98%,2, E4<=101%,3, E4<=105%,4, TRUE,5) -> 5 | G4: =IF(F4="","",F4*5/100) -> 0.25 | I4: =IFS(H4="", "", H4<75,0, H4<85,1, H4<95,2, H4<=100,3, H4<=105,4, TRUE,5) | J4: =IF(I4="","",I4*15/100) | K4: ='Weekly Tables'!L5*100 -> -4.1 | L4: =IFS(K4="", "", K4>=3,0, K4>=2,1, K4>=1,2, K4>=0,3, K4<=-1,5, K4<=-0.5,4, TRUE,3) -> 5 | M4: =IF(L4="","",L4*15/100) -> 0.75 | N4: ='Weekly Tables'!O5*100 -> 0.2 | O4: =IFS(N4="", "", N4>=3,0, N4>=2,1, N4>=1,2, N4>=0,3, N4<=-1,5, N4<=-0.5,4, TRUE,3) -> 3 | P4: =IF(O4="","",O4*15/100) -> 0.45 | Q4: ='Weekly Tables'!M13 -> 4 | R4: =IFS(Q4="", "", Q4="NA","" ,Q4<3.8,0, Q4<4,1, Q4<4.3,2, Q4<4.5,3, Q4<4.7,4, TRUE,5) -> 2 | S4: =IF(R4="","",R4*21/100) -> 0.42 | T4: ='Weekly Tables'!K13 -> NA | U4: =IFS(T4="", "", T4="NA","" ,T4<3.8,0, T4<4,1, T4<4.3,2, T4<4.5,3, T4<4.7,4, TRUE,5) | V4: =IF(U4="","",U4*7.5/100) | W4: ='Weekly Tables'!N21 -> 0.0372 | X4: =IFS(W4="", "", W4>6%,0, W4>4%,1, W4>2%,2, W4>1.5%,3, W4>1%,4, TRUE,5) -> 2 | Y4: =IF(X4="","",X4*10/100) -> 0.2 | Z4: {=XLOOKUP(A4,'Weekly Tables'!$B$30:$B$34,'Weekly Tables'!$H$30:$H$34)} -> 1.02 | AA4: =IFS(Z4="","", VALUE(Z4)>8,0, VALUE(Z4)>5,1, VALUE(Z4)>2,2, VALUE(Z4)>1.5,3, VALUE(Z4)>1,4, TRUE,5) -> 4 | AB4: =IF(AA4="","",AA4*7.5/100) -> 0.3 | AC4: ='Weekly Tables'!E21 -> 4.3 | AD4: =IFS(AC4="", "", AC4<3.8,0, AC4<4,1, AC4<4.3,2, AC4<4.5,3, AC4<4.7,4, TRUE,5) -> 3 | AE4: =IF(AD4="","",AD4*7.5/100) -> 0.225 | AF4: 72 | AG4: =IFS(AF4="", "", AF4<70,0, AF4<75,1, AF4<83,2, AF4<89,3, AF4<94,4, TRUE,5) -> 1 | AH4: =IF(AG4="","",AG4*12.5/100) -> 0.125 | AI4: 76 | AJ4: =IFS(AI4="", "", AI4<70,0, AI4<75,1, AI4<83,2, AI4<89,3, AI4<94,4, TRUE,5) -> 2 | AK4: =IF(AJ4="","",AJ4*6.25/100) -> 0.125 | AL4: 78 | AM4: =IFS(AL4="", "", AL4<70,0, AL4<75,1, AL4<83,2, AL4<89,3, AL4<94,4, TRUE,5) -> 2 | AN4: =IF(AM4="","",AM4*6.25/100) -> 0.125 | AO4: 93 | AP4: =SUM(D4,G4,J4,M4,P4,S4,V4,Y4,AB4,AE4,AH4,AK4,AN4) -> 3.22
A5: National Landing | B5: =100%+'Weekly Tables'!I6 -> 0.87077313 | C5: =IFS(B5="", "", B5<90%,0, B5<95%,1, B5<=98%,2, B5<=101%,3, B5<=105%,4, TRUE,5) -> 0 | D5: =IF(C5="","",C5*5/100) -> 0 | E5: =100%+'Weekly Tables'!F6 -> 1.0890977 | F5: =IFS(E5="", "", E5<90%,0, E5<95%,1, E5<=98%,2, E5<=101%,3, E5<=105%,4, TRUE,5) -> 5 | G5: =IF(F5="","",F5*5/100) -> 0.25 | I5: =IFS(H5="", "", H5<75,0, H5<85,1, H5<95,2, H5<=100,3, H5<=105,4, TRUE,5) | J5: =IF(I5="","",I5*15/100) | K5: ='Weekly Tables'!L6*100 -> -0.7 | L5: =IFS(K5="", "", K5>=3,0, K5>=2,1, K5>=1,2, K5>=0,3, K5<=-1,5, K5<=-0.5,4, TRUE,3) -> 4 | M5: =IF(L5="","",L5*15/100) -> 0.6 | N5: ='Weekly Tables'!O6*100 -> 3.3 | O5: =IFS(N5="", "", N5>=3,0, N5>=2,1, N5>=1,2, N5>=0,3, N5<=-1,5, N5<=-0.5,4, TRUE,3) -> 0 | P5: =IF(O5="","",O5*15/100) -> 0 | Q5: ='Weekly Tables'!M14 -> 3.33 | R5: =IFS(Q5="", "", Q5="NA","" ,Q5<3.8,0, Q5<4,1, Q5<4.3,2, Q5<4.5,3, Q5<4.7,4, TRUE,5) -> 0 | S5: =IF(R5="","",R5*21/100) -> 0 | T5: ='Weekly Tables'!K14 -> NA | U5: =IFS(T5="", "", T5="NA","" ,T5<3.8,0, T5<4,1, T5<4.3,2, T5<4.5,3, T5<4.7,4, TRUE,5) | V5: =IF(U5="","",U5*7.5/100) | W5: ='Weekly Tables'!N22 -> 0.0294 | X5: =IFS(W5="", "", W5>6%,0, W5>4%,1, W5>2%,2, W5>1.5%,3, W5>1%,4, TRUE,5) -> 2 | Y5: =IF(X5="","",X5*10/100) -> 0.2 | Z5: {=XLOOKUP(A5,'Weekly Tables'!$B$30:$B$34,'Weekly Tables'!$H$30:$H$34)} -> 1.05 | AA5: =IFS(Z5="","", VALUE(Z5)>8,0, VALUE(Z5)>5,1, VALUE(Z5)>2,2, VALUE(Z5)>1.5,3, VALUE(Z5)>1,4, TRUE,5) -> 4 | AB5: =IF(AA5="","",AA5*7.5/100) -> 0.3 | AC5: ='Weekly Tables'!E22 -> 4.2 | AD5: =IFS(AC5="", "", AC5<3.8,0, AC5<4,1, AC5<4.3,2, AC5<4.5,3, AC5<4.7,4, TRUE,5) -> 2 | AE5: =IF(AD5="","",AD5*7.5/100) -> 0.15 | AF5: 70 | AG5: =IFS(AF5="", "", AF5<70,0, AF5<75,1, AF5<83,2, AF5<89,3, AF5<94,4, TRUE,5) -> 1 | AH5: =IF(AG5="","",AG5*12.5/100) -> 0.125 | AI5: 75 | AJ5: =IFS(AI5="", "", AI5<70,0, AI5<75,1, AI5<83,2, AI5<89,3, AI5<94,4, TRUE,5) -> 2 | AK5: =IF(AJ5="","",AJ5*6.25/100) -> 0.125 | AL5: 71 | AM5: =IFS(AL5="", "", AL5<70,0, AL5<75,1, AL5<83,2, AL5<89,3, AL5<94,4, TRUE,5) -> 1 | AN5: =IF(AM5="","",AM5*6.25/100) -> 0.0625 | AO5: 80 | AP5: =SUM(D5,G5,J5,M5,P5,S5,V5,Y5,AB5,AE5,AH5,AK5,AN5) -> 1.8125
A6: Rockville | B6: =100%+'Weekly Tables'!I7 -> 0.85242532 | C6: =IFS(B6="", "", B6<90%,0, B6<95%,1, B6<=98%,2, B6<=101%,3, B6<=105%,4, TRUE,5) -> 0 | D6: =IF(C6="","",C6*5/100) -> 0 | E6: =100%+'Weekly Tables'!F7 -> 1.0642439 | F6: =IFS(E6="", "", E6<90%,0, E6<95%,1, E6<=98%,2, E6<=101%,3, E6<=105%,4, TRUE,5) -> 5 | G6: =IF(F6="","",F6*5/100) -> 0.25 | I6: =IFS(H6="", "", H6<75,0, H6<85,1, H6<95,2, H6<=100,3, H6<=105,4, TRUE,5) | J6: =IF(I6="","",I6*15/100) | K6: ='Weekly Tables'!L7*100 -> -1.9 | L6: =IFS(K6="", "", K6>=3,0, K6>=2,1, K6>=1,2, K6>=0,3, K6<=-1,5, K6<=-0.5,4, TRUE,3) -> 5 | M6: =IF(L6="","",L6*15/100) -> 0.75 | N6: ='Weekly Tables'!O7*100 -> -0.1 | O6: =IFS(N6="", "", N6>=3,0, N6>=2,1, N6>=1,2, N6>=0,3, N6<=-1,5, N6<=-0.5,4, TRUE,3) -> 3 | P6: =IF(O6="","",O6*15/100) -> 0.45 | Q6: ='Weekly Tables'!M16 -> 4.14 | R6: =IFS(Q6="", "", Q6="NA","" ,Q6<3.8,0, Q6<4,1, Q6<4.3,2, Q6<4.5,3, Q6<4.7,4, TRUE,5) -> 2 | S6: =IF(R6="","",R6*21/100) -> 0.42 | T6: ='Weekly Tables'!K16 -> 2 | U6: =IFS(T6="", "", T6="NA","" ,T6<3.8,0, T6<4,1, T6<4.3,2, T6<4.5,3, T6<4.7,4, TRUE,5) -> 0 | V6: =IF(U6="","",U6*7.5/100) -> 0 | W6: ='Weekly Tables'!N24 | X6: =IFS(W6="", "", W6>6%,0, W6>4%,1, W6>2%,2, W6>1.5%,3, W6>1%,4, TRUE,5) | Y6: =IF(X6="","",X6*10/100) | Z6: {=XLOOKUP(A6,'Weekly Tables'!$B$30:$B$34,'Weekly Tables'!$H$30:$H$34)} -> 1.43 | AA6: =IFS(Z6="","", VALUE(Z6)>8,0, VALUE(Z6)>5,1, VALUE(Z6)>2,2, VALUE(Z6)>1.5,3, VALUE(Z6)>1,4, TRUE,5) -> 4 | AB6: =IF(AA6="","",AA6*7.5/100) -> 0.3 | AC6: ='Weekly Tables'!E24 | AD6: =IFS(AC6="", "", AC6<3.8,0, AC6<4,1, AC6<4.3,2, AC6<4.5,3, AC6<4.7,4, TRUE,5) | AE6: =IF(AD6="","",AD6*7.5/100) | AF6: 56 | AG6: =IFS(AF6="", "", AF6<70,0, AF6<75,1, AF6<83,2, AF6<89,3, AF6<94,4, TRUE,5) -> 0 | AH6: =IF(AG6="","",AG6*12.5/100) -> 0 | AI6: 60 | AJ6: =IFS(AI6="", "", AI6<70,0, AI6<75,1, AI6<83,2, AI6<89,3, AI6<94,4, TRUE,5) -> 0 | AK6: =IF(AJ6="","",AJ6*6.25/100) -> 0 | AL6: 60 | AM6: =IFS(AL6="", "", AL6<70,0, AL6<75,1, AL6<83,2, AL6<89,3, AL6<94,4, TRUE,5) -> 0 | AN6: =IF(AM6="","",AM6*6.25/100) -> 0 | AO6: 78 | AP6: =SUM(D6,G6,J6,M6,P6,S6,V6,Y6,AB6,AE6,AH6,AK6,AN6) -> 2.17
C8: =IF(B2="","",ROUND(IF(B2>=105%,5,IF(B2>=102%,4+(B2-102%)/(105%-102%),IF(B2>=99%,3+(B2-99%)/(102%-99%),IF(B2>=95%,2+(B2-95%)/(99%-95%),IF(B2>=90%,1+(B2-90%)/(95%-90%),0))))),1)) -> 1.9 | F8: =IF(E2="","",ROUND(IF(E2>=105%,5,IF(E2>=102%,4+(E2-102%)/(105%-102%),IF(E2>=99%,3+(E2-99%)/(102%-99%),IF(E2>=95%,2+(E2-95%)/(99%-95%),IF(E2>=90%,1+(E2-90%)/(95%-90%),0))))),1)) -> 5
C9: =IF(B3="","",ROUND(IF(B3>=105%,5,IF(B3>=102%,4+(B3-102%)/(105%-102%),IF(B3>=99%,3+(B3-99%)/(102%-99%),IF(B3>=95%,2+(B3-95%)/(99%-95%),IF(B3>=90%,1+(B3-90%)/(95%-90%),0))))),1)) -> 4 | F9: =IF(E3="","",ROUND(IF(E3>=105%,5,IF(E3>=102%,4+(E3-102%)/(105%-102%),IF(E3>=99%,3+(E3-99%)/(102%-99%),IF(E3>=95%,2+(E3-95%)/(99%-95%),IF(E3>=90%,1+(E3-90%)/(95%-90%),0))))),1)) -> 5
C10: =IF(B4="","",ROUND(IF(B4>=105%,5,IF(B4>=102%,4+(B4-102%)/(105%-102%),IF(B4>=99%,3+(B4-99%)/(102%-99%),IF(B4>=95%,2+(B4-95%)/(99%-95%),IF(B4>=90%,1+(B4-90%)/(95%-90%),0))))),1)) -> 5 | F10: =IF(E4="","",ROUND(IF(E4>=105%,5,IF(E4>=102%,4+(E4-102%)/(105%-102%),IF(E4>=99%,3+(E4-99%)/(102%-99%),IF(E4>=95%,2+(E4-95%)/(99%-95%),IF(E4>=90%,1+(E4-90%)/(95%-90%),0))))),1)) -> 5
C11: =IF(B5="","",ROUND(IF(B5>=105%,5,IF(B5>=102%,4+(B5-102%)/(105%-102%),IF(B5>=99%,3+(B5-99%)/(102%-99%),IF(B5>=95%,2+(B5-95%)/(99%-95%),IF(B5>=90%,1+(B5-90%)/(95%-90%),0))))),1)) -> 0 | F11: =IF(E5="","",ROUND(IF(E5>=105%,5,IF(E5>=102%,4+(E5-102%)/(105%-102%),IF(E5>=99%,3+(E5-99%)/(102%-99%),IF(E5>=95%,2+(E5-95%)/(99%-95%),IF(E5>=90%,1+(E5-90%)/(95%-90%),0))))),1)) -> 5
C12: =IF(B6="","",ROUND(IF(B6>=105%,5,IF(B6>=102%,4+(B6-102%)/(105%-102%),IF(B6>=99%,3+(B6-99%)/(102%-99%),IF(B6>=95%,2+(B6-95%)/(99%-95%),IF(B6>=90%,1+(B6-90%)/(95%-90%),0))))),1)) -> 0 | F12: =IF(E6="","",ROUND(IF(E6>=105%,5,IF(E6>=102%,4+(E6-102%)/(105%-102%),IF(E6>=99%,3+(E6-99%)/(102%-99%),IF(E6>=95%,2+(E6-95%)/(99%-95%),IF(E6>=90%,1+(E6-90%)/(95%-90%),0))))),1)) -> 5

Sheet PERIODIC>>>

Sheet Period Store Scorecards 
A1: Location | B1: Sales vs Budget (%) | E1: Sales vs Prior Year (%) | H1: EBITDA vs Budget (%) | K1: Labor vs Budget Variance (pts) | N1: COGS vs Budget Variance (pts) | Q1: In-Store Rating | T1: 3P Error Rate (%) | W1: Avoidable Wait (mins) | Z1: 3P Rating | AC1: Full Audit Score | AF1: Culinary Audit Score | AI1: Training Completion % (Gate) | AJ1: Composite Score (0–5)
B2: Input | C2: Score | D2: Weighted | E2: Input | F2: Score | G2: Weighted | H2: Input | I2: Score | J2: Weighted | K2: Input | L2: Score | M2: Weighted | N2: Input | O2: Score | P2: Weighted | Q2: Input | R2: Score | S2: Weighted | T2: Input | U2: Score | V2: Weighted | W2: Input | X2: Score | Y2: Weighted | Z2: Input | AA2: Score | AB2: Weighted | AC2: Input | AD2: Score | AE2: Weighted | AF2: Input | AG2: Score | AH2: Weighted | AI2: Input
A3: Ballpark | B3: =100%+'Period Tables'!I3 -> 0.0005532557 | C3: =IFERROR(ROUND(ifs(B3="","",B3>=1.05,5,B3>=1.02,4+(B3-1.02)/0.03,B3>=0.99,3+(B3-0.99)/0.03,B3>=0.95,2+(B3-0.95)/0.04,B3>=0.9,1+(B3-0.9)/0.05,TRUE(),0),1),"") -> 0 | D3: =IF(C3="","",C3*C$9) -> 0 | E3: =100%+'Period Tables'!F3 -> 0.00070625625 | F3: =IFERROR(ROUND(ifs(E3="","",E3>=1.15,5,E3>=1.075,4+(E3-1.075)/0.075,E3>=1.05,3+(E3-1.05)/0.025,E3>=1,2+(E3-1)/0.05,E3>=0.95,1+(E3-0.95)/0.05,TRUE(),0),1),"") -> 0 | G3: =IF(F3="","",F3*F$9) -> 0 | H3: =100%+'Period Tables'!V3 -> #DIV/0! | I3: =IFERROR(ROUND(ifs(H3="","",H3>=1.05,5,H3>=1.01,4+(H3-1.01)/0.04,H3>=0.95,3+(H3-0.95)/0.06,H3>=0.85,2+(H3-0.85)/0.1,H3>=0.75,1+(H3-0.75)/0.1,TRUE(),0),1),"") | J3: =IF(I3="","",I3*I$9) | K3: ='Period Tables'!L3*100 -> -30.8 | L3: =IFERROR(ROUND(IFS(K3="","",K3>=3,0,K3>=2,1+(3-K3)/1,K3>=1,2+(2-K3)/1,K3>0,3+(1-K3)/1,K3>=-1,4+(0-K3)/1,TRUE,5),1),"") -> 5 | M3: =IF(L3="","",L3*L$9) -> 0.525 | N3: ='Period Tables'!O3*100 -> -26.4 | O3: =IFERROR(ROUND(IFS(N3="","",N3>=3,0,N3>=2,1+(3-N3)/1,N3>=1,2+(2-N3)/1,N3>0,3+(1-N3)/1,N3>=-1,4+(0-N3)/1,TRUE,5),1),"") -> 5 | P3: =IF(O3="","",O3*O$9) -> 0.525 | Q3: ='Period Tables'!E12 -> 5 | R3: =IF(OR(NOT(ISNUMBER(Q3)),Q3=0),"",IFERROR(ROUND(ifs(Q3>=4.7,5,Q3>=4.5,4+(Q3-4.5)/0.2,Q3>=4.3,3+(Q3-4.3)/0.2,Q3>=4,2+(Q3-4)/0.3,Q3>=3.8,1+(Q3-3.8)/0.2,TRUE(),0),1),"")) -> 5 | S3: =IF(R3="","",R3*R$9) -> 1.05 | T3: ='Period Tables'!I20 -> 0.0405 | U3: =IFERROR(ROUND(ifs(T3="","",T3<=0.01,5,T3<=0.015,4+(0.015-T3)/0.005,T3<=0.02,3+(0.02-T3)/0.005,T3<=0.04,2+(0.04-T3)/0.02,T3<=0.06,1+(0.06-T3)/0.02,TRUE(),0),1),"") -> 2 | V3: =IF(U3="","",U3*U$9) -> 0.17 | W3: ='Period Tables'!H31 -> 0.57 | X3: =IFERROR(ROUND(ifs(W3="","",W3<=1,5,W3<=1.5,4+(1.5-W3)/0.5,W3<=2,3+(2-W3)/0.5,W3<=5,2+(5-W3)/3,W3<=8,1+(8-W3)/3,TRUE(),0),1),"") -> 5 | Y3: =IF(X3="","",X3*X$9) -> 0.325 | Z3: ='Period Tables'!E20 -> 4 | AA3: =IF(OR(NOT(ISNUMBER(Z3)),Z3=0),"",IFERROR(ROUND(ifs(Z3>=4.7,5,Z3>=4.5,4+(Z3-4.5)/0.2,Z3>=4.3,3+(Z3-4.3)/0.2,Z3>=4,2+(Z3-4)/0.3,Z3>=3.8,1+(Z3-3.8)/0.2,TRUE(),0),1),"")) -> 2 | AB3: =IF(AA3="","",AA3*AA$9) -> 0.13 | AC3: 92 | AD3: =IFERROR(ROUND(ifs(AC3="","",AC3>=94,5,AC3>=89,4+(AC3-89)/5,AC3>=83,3+(AC3-83)/6,AC3>=75,2+(AC3-75)/8,AC3>=70,1+(AC3-70)/5,TRUE(),0),1),"") -> 4.6 | AE3: =IF(AD3="","",AD3*AD$9) -> 0.483 | AF3: 90 | AG3: =IFERROR(ROUND(ifs(AF3="","",AF3>=94,5,AF3>=89,4+(AF3-89)/5,AF3>=83,3+(AF3-83)/6,AF3>=75,2+(AF3-75)/8,AF3>=70,1+(AF3-70)/5,TRUE(),0),1),"") -> 4.2 | AH3: =IF(AG3="","",AG3*AG$9) -> 0.231 | AI3: 0.85 | AJ3: =SUM(D3,G3,J3,M3,P3,S3,V3,Y3,AB3,AE3,AH3) -> 3.439
A4: Mosaic | B4: =100%+'Period Tables'!I4 -> 0.94670671 | C4: =IFERROR(ROUND(ifs(B4="","",B4>=1.05,5,B4>=1.02,4+(B4-1.02)/0.03,B4>=0.99,3+(B4-0.99)/0.03,B4>=0.95,2+(B4-0.95)/0.04,B4>=0.9,1+(B4-0.9)/0.05,TRUE(),0),1),"") -> 1.9 | D4: =IF(C4="","",C4*C$9) -> 0.076 | E4: =100%+'Period Tables'!F4 -> 1.0965152 | F4: =IFERROR(ROUND(ifs(E4="","",E4>=1.15,5,E4>=1.075,4+(E4-1.075)/0.075,E4>=1.05,3+(E4-1.05)/0.025,E4>=1,2+(E4-1)/0.05,E4>=0.95,1+(E4-0.95)/0.05,TRUE(),0),1),"") -> 4.3 | G4: =IF(F4="","",F4*F$9) -> 0.172 | H4: =100%+'Period Tables'!V4 -> #DIV/0! | I4: =IFERROR(ROUND(ifs(H4="","",H4>=1.05,5,H4>=1.01,4+(H4-1.01)/0.04,H4>=0.95,3+(H4-0.95)/0.06,H4>=0.85,2+(H4-0.85)/0.1,H4>=0.75,1+(H4-0.75)/0.1,TRUE(),0),1),"") | J4: =IF(I4="","",I4*I$9) | K4: ='Period Tables'!L4*100 -> -2.7 | L4: =IFERROR(ROUND(IFS(K4="","",K4>=3,0,K4>=2,1+(3-K4)/1,K4>=1,2+(2-K4)/1,K4>0,3+(1-K4)/1,K4>=-1,4+(0-K4)/1,TRUE,5),1),"") -> 5 | M4: =IF(L4="","",L4*L$9) -> 0.525 | N4: ='Period Tables'!O4*100 -> -3.4 | O4: =IFERROR(ROUND(IFS(N4="","",N4>=3,0,N4>=2,1+(3-N4)/1,N4>=1,2+(2-N4)/1,N4>0,3+(1-N4)/1,N4>=-1,4+(0-N4)/1,TRUE,5),1),"") -> 5 | P4: =IF(O4="","",O4*O$9) -> 0.525 | Q4: ='Period Tables'!E15 -> 4.67 | R4: =IF(OR(NOT(ISNUMBER(Q4)),Q4=0),"",IFERROR(ROUND(ifs(Q4>=4.7,5,Q4>=4.5,4+(Q4-4.5)/0.2,Q4>=4.3,3+(Q4-4.3)/0.2,Q4>=4,2+(Q4-4)/0.3,Q4>=3.8,1+(Q4-3.8)/0.2,TRUE(),0),1),"")) -> 4.9 | S4: =IF(R4="","",R4*R$9) -> 1.029 | T4: ='Period Tables'!I23 -> 0.0315 | U4: =IFERROR(ROUND(ifs(T4="","",T4<=0.01,5,T4<=0.015,4+(0.015-T4)/0.005,T4<=0.02,3+(0.02-T4)/0.005,T4<=0.04,2+(0.04-T4)/0.02,T4<=0.06,1+(0.06-T4)/0.02,TRUE(),0),1),"") -> 2.4 | V4: =IF(U4="","",U4*U$9) -> 0.204 | W4: ='Period Tables'!H34 -> 1.48 | X4: =IFERROR(ROUND(ifs(W4="","",W4<=1,5,W4<=1.5,4+(1.5-W4)/0.5,W4<=2,3+(2-W4)/0.5,W4<=5,2+(5-W4)/3,W4<=8,1+(8-W4)/3,TRUE(),0),1),"") -> 4 | Y4: =IF(X4="","",X4*X$9) -> 0.26 | Z4: ='Period Tables'!E23 -> 4.4 | AA4: =IF(OR(NOT(ISNUMBER(Z4)),Z4=0),"",IFERROR(ROUND(ifs(Z4>=4.7,5,Z4>=4.5,4+(Z4-4.5)/0.2,Z4>=4.3,3+(Z4-4.3)/0.2,Z4>=4,2+(Z4-4)/0.3,Z4>=3.8,1+(Z4-3.8)/0.2,TRUE(),0),1),"")) -> 3.5 | AB4: =IF(AA4="","",AA4*AA$9) -> 0.2275 | AC4: 88 | AD4: =IFERROR(ROUND(ifs(AC4="","",AC4>=94,5,AC4>=89,4+(AC4-89)/5,AC4>=83,3+(AC4-83)/6,AC4>=75,2+(AC4-75)/8,AC4>=70,1+(AC4-70)/5,TRUE(),0),1),"") -> 3.8 | AE4: =IF(AD4="","",AD4*AD$9) -> 0.399 | AF4: 86 | AG4: =IFERROR(ROUND(ifs(AF4="","",AF4>=94,5,AF4>=89,4+(AF4-89)/5,AF4>=83,3+(AF4-83)/6,AF4>=75,2+(AF4-75)/8,AF4>=70,1+(AF4-70)/5,TRUE(),0),1),"") -> 3.5 | AH4: =IF(AG4="","",AG4*AG$9) -> 0.1925 | AI4: 0.87 | AJ4: =SUM(D4,G4,J4,M4,P4,S4,V4,Y4,AB4,AE4,AH4) -> 3.61
A5: MVT | B5: =100%+'Period Tables'!I5 -> 1.0190662 | C5: =IFERROR(ROUND(ifs(B5="","",B5>=1.05,5,B5>=1.02,4+(B5-1.02)/0.03,B5>=0.99,3+(B5-0.99)/0.03,B5>=0.95,2+(B5-0.95)/0.04,B5>=0.9,1+(B5-0.9)/0.05,TRUE(),0),1),"") -> 4 | D5: =IF(C5="","",C5*C$9) -> 0.16 | E5: =100%+'Period Tables'!F5 -> 1.3761061 | F5: =IFERROR(ROUND(ifs(E5="","",E5>=1.15,5,E5>=1.075,4+(E5-1.075)/0.075,E5>=1.05,3+(E5-1.05)/0.025,E5>=1,2+(E5-1)/0.05,E5>=0.95,1+(E5-0.95)/0.05,TRUE(),0),1),"") -> 5 | G5: =IF(F5="","",F5*F$9) -> 0.2 | H5: =100%+'Period Tables'!V5 -> #DIV/0! | I5: =IFERROR(ROUND(ifs(H5="","",H5>=1.05,5,H5>=1.01,4+(H5-1.01)/0.04,H5>=0.95,3+(H5-0.95)/0.06,H5>=0.85,2+(H5-0.85)/0.1,H5>=0.75,1+(H5-0.75)/0.1,TRUE(),0),1),"") | J5: =IF(I5="","",I5*I$9) | K5: ='Period Tables'!L5*100 -> 2.4 | L5: =IFERROR(ROUND(IFS(K5="","",K5>=3,0,K5>=2,1+(3-K5)/1,K5>=1,2+(2-K5)/1,K5>0,3+(1-K5)/1,K5>=-1,4+(0-K5)/1,TRUE,5),1),"") -> 1.6 | M5: =IF(L5="","",L5*L$9) -> 0.168 | N5: ='Period Tables'!O5*100 -> 1.1 | O5: =IFERROR(ROUND(IFS(N5="","",N5>=3,0,N5>=2,1+(3-N5)/1,N5>=1,2+(2-N5)/1,N5>0,3+(1-N5)/1,N5>=-1,4+(0-N5)/1,TRUE,5),1),"") -> 2.9 | P5: =IF(O5="","",O5*O$9) -> 0.3045 | Q5: ='Period Tables'!E13 -> 3 | R5: =IF(OR(NOT(ISNUMBER(Q5)),Q5=0),"",IFERROR(ROUND(ifs(Q5>=4.7,5,Q5>=4.5,4+(Q5-4.5)/0.2,Q5>=4.3,3+(Q5-4.3)/0.2,Q5>=4,2+(Q5-4)/0.3,Q5>=3.8,1+(Q5-3.8)/0.2,TRUE(),0),1),"")) -> 0 | S5: =IF(R5="","",R5*R$9) -> 0 | T5: ='Period Tables'!I21 -> 0.0264 | U5: =IFERROR(ROUND(ifs(T5="","",T5<=0.01,5,T5<=0.015,4+(0.015-T5)/0.005,T5<=0.02,3+(0.02-T5)/0.005,T5<=0.04,2+(0.04-T5)/0.02,T5<=0.06,1+(0.06-T5)/0.02,TRUE(),0),1),"") -> 2.7 | V5: =IF(U5="","",U5*U$9) -> 0.2295 | W5: ='Period Tables'!H32 -> 0.59 | X5: =IFERROR(ROUND(ifs(W5="","",W5<=1,5,W5<=1.5,4+(1.5-W5)/0.5,W5<=2,3+(2-W5)/0.5,W5<=5,2+(5-W5)/3,W5<=8,1+(8-W5)/3,TRUE(),0),1),"") -> 5 | Y5: =IF(X5="","",X5*X$9) -> 0.325 | Z5: ='Period Tables'!E21 -> 4.5 | AA5: =IF(OR(NOT(ISNUMBER(Z5)),Z5=0),"",IFERROR(ROUND(ifs(Z5>=4.7,5,Z5>=4.5,4+(Z5-4.5)/0.2,Z5>=4.3,3+(Z5-4.3)/0.2,Z5>=4,2+(Z5-4)/0.3,Z5>=3.8,1+(Z5-3.8)/0.2,TRUE(),0),1),"")) -> 4 | AB5: =IF(AA5="","",AA5*AA$9) -> 0.26 | AC5: 91 | AD5: =IFERROR(ROUND(ifs(AC5="","",AC5>=94,5,AC5>=89,4+(AC5-89)/5,AC5>=83,3+(AC5-83)/6,AC5>=75,2+(AC5-75)/8,AC5>=70,1+(AC5-70)/5,TRUE(),0),1),"") -> 4.4 | AE5: =IF(AD5="","",AD5*AD$9) -> 0.462 | AF5: 93 | AG5: =IFERROR(ROUND(ifs(AF5="","",AF5>=94,5,AF5>=89,4+(AF5-89)/5,AF5>=83,3+(AF5-83)/6,AF5>=75,2+(AF5-75)/8,AF5>=70,1+(AF5-70)/5,TRUE(),0),1),"") -> 4.8 | AH5: =IF(AG5="","",AG5*AG$9) -> 0.264 | AI5: 0.93 | AJ5: =SUM(D5,G5,J5,M5,P5,S5,V5,Y5,AB5,AE5,AH5) -> 2.373
A6: National Landing | B6: =100%+'Period Tables'!I6 -> 1.2172449 | C6: =IFERROR(ROUND(ifs(B6="","",B6>=1.05,5,B6>=1.02,4+(B6-1.02)/0.03,B6>=0.99,3+(B6-0.99)/0.03,B6>=0.95,2+(B6-0.95)/0.04,B6>=0.9,1+(B6-0.9)/0.05,TRUE(),0),1),"") -> 5 | D6: =IF(C6="","",C6*C$9) -> 0.2 | E6: =100%+'Period Tables'!F6 -> 1.4285788 | F6: =IFERROR(ROUND(ifs(E6="","",E6>=1.15,5,E6>=1.075,4+(E6-1.075)/0.075,E6>=1.05,3+(E6-1.05)/0.025,E6>=1,2+(E6-1)/0.05,E6>=0.95,1+(E6-0.95)/0.05,TRUE(),0),1),"") -> 5 | G6: =IF(F6="","",F6*F$9) -> 0.2 | H6: =100%+'Period Tables'!V6 -> #DIV/0! | I6: =IFERROR(ROUND(ifs(H6="","",H6>=1.05,5,H6>=1.01,4+(H6-1.01)/0.04,H6>=0.95,3+(H6-0.95)/0.06,H6>=0.85,2+(H6-0.85)/0.1,H6>=0.75,1+(H6-0.75)/0.1,TRUE(),0),1),"") | J6: =IF(I6="","",I6*I$9) | K6: ='Period Tables'!L6*100 -> -4.1 | L6: =IFERROR(ROUND(IFS(K6="","",K6>=3,0,K6>=2,1+(3-K6)/1,K6>=1,2+(2-K6)/1,K6>0,3+(1-K6)/1,K6>=-1,4+(0-K6)/1,TRUE,5),1),"") -> 5 | M6: =IF(L6="","",L6*L$9) -> 0.525 | N6: ='Period Tables'!O6*100 -> 0.2 | O6: =IFERROR(ROUND(IFS(N6="","",N6>=3,0,N6>=2,1+(3-N6)/1,N6>=1,2+(2-N6)/1,N6>0,3+(1-N6)/1,N6>=-1,4+(0-N6)/1,TRUE,5),1),"") -> 3.8 | P6: =IF(O6="","",O6*O$9) -> 0.399 | Q6: ='Period Tables'!E14 -> 4.33 | R6: =IF(OR(NOT(ISNUMBER(Q6)),Q6=0),"",IFERROR(ROUND(ifs(Q6>=4.7,5,Q6>=4.5,4+(Q6-4.5)/0.2,Q6>=4.3,3+(Q6-4.3)/0.2,Q6>=4,2+(Q6-4)/0.3,Q6>=3.8,1+(Q6-3.8)/0.2,TRUE(),0),1),"")) -> 3.2 | S6: =IF(R6="","",R6*R$9) -> 0.672 | T6: ='Period Tables'!I22 -> 0.0315 | U6: =IFERROR(ROUND(ifs(T6="","",T6<=0.01,5,T6<=0.015,4+(0.015-T6)/0.005,T6<=0.02,3+(0.02-T6)/0.005,T6<=0.04,2+(0.04-T6)/0.02,T6<=0.06,1+(0.06-T6)/0.02,TRUE(),0),1),"") -> 2.4 | V6: =IF(U6="","",U6*U$9) -> 0.204 | W6: ='Period Tables'!H33 -> 1.14 | X6: =IFERROR(ROUND(ifs(W6="","",W6<=1,5,W6<=1.5,4+(1.5-W6)/0.5,W6<=2,3+(2-W6)/0.5,W6<=5,2+(5-W6)/3,W6<=8,1+(8-W6)/3,TRUE(),0),1),"") -> 4.7 | Y6: =IF(X6="","",X6*X$9) -> 0.3055 | Z6: ='Period Tables'!E22 -> 4.3 | AA6: =IF(OR(NOT(ISNUMBER(Z6)),Z6=0),"",IFERROR(ROUND(ifs(Z6>=4.7,5,Z6>=4.5,4+(Z6-4.5)/0.2,Z6>=4.3,3+(Z6-4.3)/0.2,Z6>=4,2+(Z6-4)/0.3,Z6>=3.8,1+(Z6-3.8)/0.2,TRUE(),0),1),"")) -> 3 | AB6: =IF(AA6="","",AA6*AA$9) -> 0.195 | AC6: 78 | AD6: =IFERROR(ROUND(ifs(AC6="","",AC6>=94,5,AC6>=89,4+(AC6-89)/5,AC6>=83,3+(AC6-83)/6,AC6>=75,2+(AC6-75)/8,AC6>=70,1+(AC6-70)/5,TRUE(),0),1),"") -> 2.4 | AE6: =IF(AD6="","",AD6*AD$9) -> 0.252 | AF6: 75 | AG6: =IFERROR(ROUND(ifs(AF6="","",AF6>=94,5,AF6>=89,4+(AF6-89)/5,AF6>=83,3+(AF6-83)/6,AF6>=75,2+(AF6-75)/8,AF6>=70,1+(AF6-70)/5,TRUE(),0),1),"") -> 2 | AH6: =IF(AG6="","",AG6*AG$9) -> 0.11 | AI6: 0.8 | AJ6: =SUM(D6,G6,J6,M6,P6,S6,V6,Y6,AB6,AE6,AH6) -> 3.0625
A7: Rockville | B7: =100%+'Period Tables'!I7 -> 0.87077313 | C7: =IFERROR(ROUND(ifs(B7="","",B7>=1.05,5,B7>=1.02,4+(B7-1.02)/0.03,B7>=0.99,3+(B7-0.99)/0.03,B7>=0.95,2+(B7-0.95)/0.04,B7>=0.9,1+(B7-0.9)/0.05,TRUE(),0),1),"") -> 0 | D7: =IF(C7="","",C7*C$9) -> 0 | E7: =100%+'Period Tables'!F7 -> 1.0890977 | F7: =IFERROR(ROUND(ifs(E7="","",E7>=1.15,5,E7>=1.075,4+(E7-1.075)/0.075,E7>=1.05,3+(E7-1.05)/0.025,E7>=1,2+(E7-1)/0.05,E7>=0.95,1+(E7-0.95)/0.05,TRUE(),0),1),"") -> 4.2 | G7: =IF(F7="","",F7*F$9) -> 0.168 | H7: =100%+'Period Tables'!V7 -> #DIV/0! | I7: =IFERROR(ROUND(ifs(H7="","",H7>=1.05,5,H7>=1.01,4+(H7-1.01)/0.04,H7>=0.95,3+(H7-0.95)/0.06,H7>=0.85,2+(H7-0.85)/0.1,H7>=0.75,1+(H7-0.75)/0.1,TRUE(),0),1),"") | J7: =IF(I7="","",I7*I$9) | K7: ='Period Tables'!L7*100 -> -0.7 | L7: =IFERROR(ROUND(IFS(K7="","",K7>=3,0,K7>=2,1+(3-K7)/1,K7>=1,2+(2-K7)/1,K7>0,3+(1-K7)/1,K7>=-1,4+(0-K7)/1,TRUE,5),1),"") -> 4.7 | M7: =IF(L7="","",L7*L$9) -> 0.4935 | N7: ='Period Tables'!O7*100 -> 3.3 | O7: =IFERROR(ROUND(IFS(N7="","",N7>=3,0,N7>=2,1+(3-N7)/1,N7>=1,2+(2-N7)/1,N7>0,3+(1-N7)/1,N7>=-1,4+(0-N7)/1,TRUE,5),1),"") -> 0 | P7: =IF(O7="","",O7*O$9) -> 0 | Q7: ='Period Tables'!E16 -> 4.47 | R7: =IF(OR(NOT(ISNUMBER(Q7)),Q7=0),"",IFERROR(ROUND(ifs(Q7>=4.7,5,Q7>=4.5,4+(Q7-4.5)/0.2,Q7>=4.3,3+(Q7-4.3)/0.2,Q7>=4,2+(Q7-4)/0.3,Q7>=3.8,1+(Q7-3.8)/0.2,TRUE(),0),1),"")) -> 3.9 | S7: =IF(R7="","",R7*R$9) -> 0.819 | T7: ='Period Tables'!I24 -> 0.045 | U7: =IFERROR(ROUND(ifs(T7="","",T7<=0.01,5,T7<=0.015,4+(0.015-T7)/0.005,T7<=0.02,3+(0.02-T7)/0.005,T7<=0.04,2+(0.04-T7)/0.02,T7<=0.06,1+(0.06-T7)/0.02,TRUE(),0),1),"") -> 1.8 | V7: =IF(U7="","",U7*U$9) -> 0.153 | W7: ='Period Tables'!H30 -> 2.03 | X7: =IFERROR(ROUND(ifs(W7="","",W7<=1,5,W7<=1.5,4+(1.5-W7)/0.5,W7<=2,3+(2-W7)/0.5,W7<=5,2+(5-W7)/3,W7<=8,1+(8-W7)/3,TRUE(),0),1),"") -> 3 | Y7: =IF(X7="","",X7*X$9) -> 0.195 | Z7: ='Period Tables'!E24 -> 4.3 | AA7: =IF(OR(NOT(ISNUMBER(Z7)),Z7=0),"",IFERROR(ROUND(ifs(Z7>=4.7,5,Z7>=4.5,4+(Z7-4.5)/0.2,Z7>=4.3,3+(Z7-4.3)/0.2,Z7>=4,2+(Z7-4)/0.3,Z7>=3.8,1+(Z7-3.8)/0.2,TRUE(),0),1),"")) -> 3 | AB7: =IF(AA7="","",AA7*AA$9) -> 0.195 | AC7: 77 | AD7: =IFERROR(ROUND(ifs(AC7="","",AC7>=94,5,AC7>=89,4+(AC7-89)/5,AC7>=83,3+(AC7-83)/6,AC7>=75,2+(AC7-75)/8,AC7>=70,1+(AC7-70)/5,TRUE(),0),1),"") -> 2.3 | AE7: =IF(AD7="","",AD7*AD$9) -> 0.2415 | AF7: 74 | AG7: =IFERROR(ROUND(ifs(AF7="","",AF7>=94,5,AF7>=89,4+(AF7-89)/5,AF7>=83,3+(AF7-83)/6,AF7>=75,2+(AF7-75)/8,AF7>=70,1+(AF7-70)/5,TRUE(),0),1),"") -> 1.8 | AH7: =IF(AG7="","",AG7*AG$9) -> 0.099 | AI7: 0.78 | AJ7: =SUM(D7,G7,J7,M7,P7,S7,V7,Y7,AB7,AE7,AH7) -> 2.364
A8: All Stores | B8: =100%+'Period Tables'!I8 -> 0.85242532 | C8: =IFERROR(ROUND(ifs(B8="","",B8>=1.05,5,B8>=1.02,4+(B8-1.02)/0.03,B8>=0.99,3+(B8-0.99)/0.03,B8>=0.95,2+(B8-0.95)/0.04,B8>=0.9,1+(B8-0.9)/0.05,TRUE(),0),1),"") -> 0 | D8: =IF(C8="","",C8*C$9) -> 0 | E8: =100%+'Period Tables'!F8 -> 1.0642439 | F8: =IFERROR(ROUND(ifs(E8="","",E8>=1.15,5,E8>=1.075,4+(E8-1.075)/0.075,E8>=1.05,3+(E8-1.05)/0.025,E8>=1,2+(E8-1)/0.05,E8>=0.95,1+(E8-0.95)/0.05,TRUE(),0),1),"") -> 3.6 | G8: =IF(F8="","",F8*F$9) -> 0.144 | H8: =100%+'Period Tables'!V8 -> #DIV/0! | I8: =IFERROR(ROUND(ifs(H8="","",H8>=1.05,5,H8>=1.01,4+(H8-1.01)/0.04,H8>=0.95,3+(H8-0.95)/0.06,H8>=0.85,2+(H8-0.85)/0.1,H8>=0.75,1+(H8-0.75)/0.1,TRUE(),0),1),"") | J8: =IF(I8="","",I8*I$9) | K8: ='Period Tables'!L8*100 -> -1.9 | L8: =IFERROR(ROUND(IFS(K8="","",K8>=3,0,K8>=2,1+(3-K8)/1,K8>=1,2+(2-K8)/1,K8>0,3+(1-K8)/1,K8>=-1,4+(0-K8)/1,TRUE,5),1),"") -> 5 | M8: =IF(L8="","",L8*L$9) -> 0.525 | N8: ='Period Tables'!O8*100 -> -0.1 | O8: =IFERROR(ROUND(IFS(N8="","",N8>=3,0,N8>=2,1+(3-N8)/1,N8>=1,2+(2-N8)/1,N8>0,3+(1-N8)/1,N8>=-1,4+(0-N8)/1,TRUE,5),1),"") -> 4.1 | P8: =IF(O8="","",O8*O$9) -> 0.4305 | Q8: ='Period Tables'!E17 -> 4.294 | R8: =IF(OR(NOT(ISNUMBER(Q8)),Q8=0),"",IFERROR(ROUND(ifs(Q8>=4.7,5,Q8>=4.5,4+(Q8-4.5)/0.2,Q8>=4.3,3+(Q8-4.3)/0.2,Q8>=4,2+(Q8-4)/0.3,Q8>=3.8,1+(Q8-3.8)/0.2,TRUE(),0),1),"")) -> 3 | S8: =IF(R8="","",R8*R$9) -> 0.63 | T8: ='Period Tables'!I25 -> 0.03498 | U8: =IFERROR(ROUND(ifs(T8="","",T8<=0.01,5,T8<=0.015,4+(0.015-T8)/0.005,T8<=0.02,3+(0.02-T8)/0.005,T8<=0.04,2+(0.04-T8)/0.02,T8<=0.06,1+(0.06-T8)/0.02,TRUE(),0),1),"") -> 2.3 | V8: =IF(U8="","",U8*U$9) -> 0.1955 | W8: ='Period Tables'!H35 -> 1.19 | X8: =IFERROR(ROUND(ifs(W8="","",W8<=1,5,W8<=1.5,4+(1.5-W8)/0.5,W8<=2,3+(2-W8)/0.5,W8<=5,2+(5-W8)/3,W8<=8,1+(8-W8)/3,TRUE(),0),1),"") -> 4.6 | Y8: =IF(X8="","",X8*X$9) -> 0.299 | Z8: ='Period Tables'!E25 -> 4.3 | AA8: =IF(OR(NOT(ISNUMBER(Z8)),Z8=0),"",IFERROR(ROUND(ifs(Z8>=4.7,5,Z8>=4.5,4+(Z8-4.5)/0.2,Z8>=4.3,3+(Z8-4.3)/0.2,Z8>=4,2+(Z8-4)/0.3,Z8>=3.8,1+(Z8-3.8)/0.2,TRUE(),0),1),"")) -> 3 | AB8: =IF(AA8="","",AA8*AA$9) -> 0.195 | AC8: =AVERAGE(AC3:AC7) -> 85.2 | AD8: =IFERROR(ROUND(ifs(AC8="","",AC8>=94,5,AC8>=89,4+(AC8-89)/5,AC8>=83,3+(AC8-83)/6,AC8>=75,2+(AC8-75)/8,AC8>=70,1+(AC8-70)/5,TRUE(),0),1),"") -> 3.4 | AE8: =IF(AD8="","",AD8*AD$9) -> 0.357 | AF8: =AVERAGE(AF3:AF7) -> 83.6 | AG8: =IFERROR(ROUND(ifs(AF8="","",AF8>=94,5,AF8>=89,4+(AF8-89)/5,AF8>=83,3+(AF8-83)/6,AF8>=75,2+(AF8-75)/8,AF8>=70,1+(AF8-70)/5,TRUE(),0),1),"") -> 3.1 | AH8: =IF(AG8="","",AG8*AG$9) -> 0.1705 | AI8: =AVERAGE(AI3:AI7) -> 0.846 | AJ8: =SUM(D8,G8,J8,M8,P8,S8,V8,Y8,AB8,AE8,AH8) -> 2.9465
A9: Weight | C9: ='Scoring Matrix'!C42 -> 0.04 | F9: ='Scoring Matrix'!C44 -> 0.04 | I9: ='Scoring Matrix'!C46 -> 0.125 | L9: ='Scoring Matrix'!C48 -> 0.105 | O9: ='Scoring Matrix'!C50 -> 0.105 | R9: ='Scoring Matrix'!C52 -> 0.21 | U9: ='Scoring Matrix'!C54 -> 0.085 | X9: ='Scoring Matrix'!C56 -> 0.065 | AA9: ='Scoring Matrix'!C58 -> 0.065 | AD9: ='Scoring Matrix'!C60 -> 0.105 | AG9: ='Scoring Matrix'!C62 -> 0.055

Sheet Period Store Scorecards
A1: Restaurant | B1: Sales vs Budget (%) | C1: Score | D1: Weighted | E1: Sales vs Prior Year (%) | F1: Score | G1: Weighted | H1: EBITDA vs Budget (%) | I1: Score | J1: Weighted | K1: Labor Var (pts) | L1: Score | M1: Weighted | N1: COGS Var (pts) | O1: Score | P1: Weighted | Q1: Google Rating | R1: Score | S1: Weighted | T1: Yelp Rating | U1: Score | V1: Weighted | W1: 3P Error Rate (%) | X1: Score | Y1: Weighted | Z1: Avoidable Wait (mins) | AA1: Score | AB1: Weighted | AC1: 3P Rating | AD1: Score | AE1: Weighted | AF1: Full Audit Score | AG1: Score | AH1: Weighted | AI1: Culinary Audit Score | AJ1: Score | AK1: Weighted | AL1: Focus Audit Score | AM1: Score | AN1: Weighted | AO1: Training % (Gate) | AP1: Composite Score (0-5)
A2: Ballpark | B2: =100%+'Period Tables'!I3 -> 0.0005532557 | C2: =IFS(B2="", "", B2<90%,0, B2<95%,1, B2<=98%,2, B2<=101%,3, B2<=105%,4, TRUE,5) -> 0 | D2: =IF(C2="","",C2*5/100) -> 0 | E2: =100%+'Period Tables'!F3 -> 0.00070625625 | F2: =IFS(E2="", "", E2<90%,0, E2<95%,1, E2<=98%,2, E2<=101%,3, E2<=105%,4, TRUE,5) -> 0 | G2: =IF(F2="","",F2*5/100) -> 0 | H2: =100%+'Period Tables'!V3 -> #DIV/0! | I2: =IFS(H2="", "", H2<75%,0, H2<85%,1, H2<95%,2, H2<=100%,3, H2<=105%,4, TRUE,5) -> #DIV/0! | J2: =IF(I2="","",I2*15/100) -> #DIV/0! | K2: ='Period Tables'!L3*100 -> -30.8 | L2: =IFS(K2="", "", K2>=3,0, K2>=2,1, K2>=1,2, K2>=0,3, K2<=-1,5, K2<=-0.5,4, TRUE,3) -> 5 | M2: =IF(L2="","",L2*12.5/100) -> 0.625 | N2: ='Period Tables'!O3*100 -> -26.4 | O2: =IFS(N2="", "", N2>=3,0, N2>=2,1, N2>=1,2, N2>=0,3, N2<=-1,5, N2<=-0.5,4, TRUE,3) -> 5 | P2: =IF(O2="","",O2*12.5/100) -> 0.625 | Q2: ='Period Tables'!H12 -> 5 | R2: =IFS(Q2="", "", Q2="NA","" ,Q2<3.8,0, Q2<4,1, Q2<4.3,2, Q2<4.5,3, Q2<4.7,4, TRUE,5) -> 5 | S2: =IF(R2="","",R2*17.5/100) -> 0.875 | T2: ='Period Tables'!F12 -> NA | U2: =IFS(T2="", "", T2="NA","" ,T2<3.8,0, T2<4,1, T2<4.3,2, T2<4.5,3, T2<4.7,4, TRUE,5) | V2: =IF(U2="","",U2*7.5/100) | W2: ='Period Tables'!I20 -> 0.0405 | X2: =IFS(W2="", "", W2>6%,0, W2>4%,1, W2>2%,2, W2>1.5%,3, W2>1%,4, TRUE,5) -> 1 | Y2: =IF(X2="","",X2*10/100) -> 0.1 | Z2: ='Period Tables'!H31 -> 0.57 | AA2: =IFS(Z2="","", VALUE(Z2)>8,0, VALUE(Z2)>5,1, VALUE(Z2)>2,2, VALUE(Z2)>1.5,3, VALUE(Z2)>1,4, TRUE,5) -> 5 | AB2: =IF(AA2="","",AA2*7.5/100) -> 0.375 | AC2: ='Period Tables'!E20 -> 4 | AD2: =IFS(AC2="", "", AC2<3.8,0, AC2<4,1, AC2<4.3,2, AC2<4.5,3, AC2<4.7,4, TRUE,5) -> 2 | AE2: =IF(AD2="","",AD2*7.5/100) -> 0.15 | AF2: 86 | AG2: =IFS(AF2="", "", AF2<70,0, AF2<75,1, AF2<83,2, AF2<89,3, AF2<94,4, TRUE,5) -> 3 | AH2: =IF(AG2="","",AG2*12.5/100) -> 0.375 | AI2: 90 | AJ2: =IFS(AI2="", "", AI2<70,0, AI2<75,1, AI2<83,2, AI2<89,3, AI2<94,4, TRUE,5) -> 4 | AK2: =IF(AJ2="","",AJ2*6.25/100) -> 0.25 | AL2: 95 | AM2: =IFS(AL2="", "", AL2<70,0, AL2<75,1, AL2<83,2, AL2<89,3, AL2<94,4, TRUE,5) -> 5 | AN2: =IF(AM2="","",AM2*6.25/100) -> 0.3125 | AO2: 85 | AP2: =SUM(D2,G2,J2,M2,P2,S2,V2,Y2,AB2,AE2,AH2,AK2,AN2) -> #DIV/0!
A3: Mosaic | B3: =100%+'Period Tables'!I4 -> 0.94670671 | C3: =IFS(B3="", "", B3<90%,0, B3<95%,1, B3<=98%,2, B3<=101%,3, B3<=105%,4, TRUE,5) -> 1 | D3: =IF(C3="","",C3*5/100) -> 0.05 | E3: =100%+'Period Tables'!F4 -> 1.0965152 | F3: =IFS(E3="", "", E3<90%,0, E3<95%,1, E3<=98%,2, E3<=101%,3, E3<=105%,4, TRUE,5) -> 5 | G3: =IF(F3="","",F3*5/100) -> 0.25 | H3: =100%+'Period Tables'!V4 -> #DIV/0! | I3: =IFS(H3="", "", H3<75%,0, H3<85%,1, H3<95%,2, H3<=100%,3, H3<=105%,4, TRUE,5) -> #DIV/0! | J3: =IF(I3="","",I3*15/100) -> #DIV/0! | K3: ='Period Tables'!L4*100 -> -2.7 | L3: =IFS(K3="", "", K3>=3,0, K3>=2,1, K3>=1,2, K3>=0,3, K3<=-1,5, K3<=-0.5,4, TRUE,3) -> 5 | M3: =IF(L3="","",L3*12.5/100) -> 0.625 | N3: ='Period Tables'!O4*100 -> -3.4 | O3: =IFS(N3="", "", N3>=3,0, N3>=2,1, N3>=1,2, N3>=0,3, N3<=-1,5, N3<=-0.5,4, TRUE,3) -> 5 | P3: =IF(O3="","",O3*12.5/100) -> 0.625 | Q3: ='Period Tables'!H15 -> 4.75 | R3: =IFS(Q3="", "", Q3="NA","" ,Q3<3.8,0, Q3<4,1, Q3<4.3,2, Q3<4.5,3, Q3<4.7,4, TRUE,5) -> 5 | S3: =IF(R3="","",R3*17.5/100) -> 0.875 | T3: ='Period Tables'!F15 -> 4 | U3: =IFS(T3="", "", T3="NA","" ,T3<3.8,0, T3<4,1, T3<4.3,2, T3<4.5,3, T3<4.7,4, TRUE,5) -> 2 | V3: =IF(U3="","",U3*7.5/100) -> 0.15 | W3: ='Period Tables'!I23 -> 0.0315 | X3: =IFS(W3="", "", W3>6%,0, W3>4%,1, W3>2%,2, W3>1.5%,3, W3>1%,4, TRUE,5) -> 2 | Y3: =IF(X3="","",X3*10/100) -> 0.2 | Z3: ='Period Tables'!H34 -> 1.48 | AA3: =IFS(Z3="","", VALUE(Z3)>8,0, VALUE(Z3)>5,1, VALUE(Z3)>2,2, VALUE(Z3)>1.5,3, VALUE(Z3)>1,4, TRUE,5) -> 4 | AB3: =IF(AA3="","",AA3*7.5/100) -> 0.3 | AC3: ='Period Tables'!E23 -> 4.4 | AD3: =IFS(AC3="", "", AC3<3.8,0, AC3<4,1, AC3<4.3,2, AC3<4.5,3, AC3<4.7,4, TRUE,5) -> 3 | AE3: =IF(AD3="","",AD3*7.5/100) -> 0.225 | AF3: 67 | AG3: =IFS(AF3="", "", AF3<70,0, AF3<75,1, AF3<83,2, AF3<89,3, AF3<94,4, TRUE,5) -> 0 | AH3: =IF(AG3="","",AG3*12.5/100) -> 0 | AI3: 70 | AJ3: =IFS(AI3="", "", AI3<70,0, AI3<75,1, AI3<83,2, AI3<89,3, AI3<94,4, TRUE,5) -> 1 | AK3: =IF(AJ3="","",AJ3*6.25/100) -> 0.0625 | AL3: 76 | AM3: =IFS(AL3="", "", AL3<70,0, AL3<75,1, AL3<83,2, AL3<89,3, AL3<94,4, TRUE,5) -> 2 | AN3: =IF(AM3="","",AM3*6.25/100) -> 0.125 | AO3: 87 | AP3: =SUM(D3,G3,J3,M3,P3,S3,V3,Y3,AB3,AE3,AH3,AK3,AN3) -> #DIV/0!
A4: MVT | B4: =100%+'Period Tables'!I5 -> 1.0190662 | C4: =IFS(B4="", "", B4<90%,0, B4<95%,1, B4<=98%,2, B4<=101%,3, B4<=105%,4, TRUE,5) -> 4 | D4: =IF(C4="","",C4*5/100) -> 0.2 | E4: =100%+'Period Tables'!F5 -> 1.3761061 | F4: =IFS(E4="", "", E4<90%,0, E4<95%,1, E4<=98%,2, E4<=101%,3, E4<=105%,4, TRUE,5) -> 5 | G4: =IF(F4="","",F4*5/100) -> 0.25 | H4: =100%+'Period Tables'!V5 -> #DIV/0! | I4: =IFS(H4="", "", H4<75%,0, H4<85%,1, H4<95%,2, H4<=100%,3, H4<=105%,4, TRUE,5) -> #DIV/0! | J4: =IF(I4="","",I4*15/100) -> #DIV/0! | K4: ='Period Tables'!L5*100 -> 2.4 | L4: =IFS(K4="", "", K4>=3,0, K4>=2,1, K4>=1,2, K4>=0,3, K4<=-1,5, K4<=-0.5,4, TRUE,3) -> 1 | M4: =IF(L4="","",L4*12.5/100) -> 0.125 | N4: ='Period Tables'!O5*100 -> 1.1 | O4: =IFS(N4="", "", N4>=3,0, N4>=2,1, N4>=1,2, N4>=0,3, N4<=-1,5, N4<=-0.5,4, TRUE,3) -> 2 | P4: =IF(O4="","",O4*12.5/100) -> 0.25 | Q4: ='Period Tables'!H13 -> 3.67 | R4: =IFS(Q4="", "", Q4="NA","" ,Q4<3.8,0, Q4<4,1, Q4<4.3,2, Q4<4.5,3, Q4<4.7,4, TRUE,5) -> 0 | S4: =IF(R4="","",R4*17.5/100) -> 0 | T4: ='Period Tables'!F13 -> 1 | U4: =IFS(T4="", "", T4="NA","" ,T4<3.8,0, T4<4,1, T4<4.3,2, T4<4.5,3, T4<4.7,4, TRUE,5) -> 0 | V4: =IF(U4="","",U4*7.5/100) -> 0 | W4: ='Period Tables'!I21 -> 0.0264 | X4: =IFS(W4="", "", W4>6%,0, W4>4%,1, W4>2%,2, W4>1.5%,3, W4>1%,4, TRUE,5) -> 2 | Y4: =IF(X4="","",X4*10/100) -> 0.2 | Z4: ='Period Tables'!H32 -> 0.59 | AA4: =IFS(Z4="","", VALUE(Z4)>8,0, VALUE(Z4)>5,1, VALUE(Z4)>2,2, VALUE(Z4)>1.5,3, VALUE(Z4)>1,4, TRUE,5) -> 5 | AB4: =IF(AA4="","",AA4*7.5/100) -> 0.375 | AC4: ='Period Tables'!E21 -> 4.5 | AD4: =IFS(AC4="", "", AC4<3.8,0, AC4<4,1, AC4<4.3,2, AC4<4.5,3, AC4<4.7,4, TRUE,5) -> 4 | AE4: =IF(AD4="","",AD4*7.5/100) -> 0.3 | AF4: 72 | AG4: =IFS(AF4="", "", AF4<70,0, AF4<75,1, AF4<83,2, AF4<89,3, AF4<94,4, TRUE,5) -> 1 | AH4: =IF(AG4="","",AG4*12.5/100) -> 0.125 | AI4: 76 | AJ4: =IFS(AI4="", "", AI4<70,0, AI4<75,1, AI4<83,2, AI4<89,3, AI4<94,4, TRUE,5) -> 2 | AK4: =IF(AJ4="","",AJ4*6.25/100) -> 0.125 | AL4: 78 | AM4: =IFS(AL4="", "", AL4<70,0, AL4<75,1, AL4<83,2, AL4<89,3, AL4<94,4, TRUE,5) -> 2 | AN4: =IF(AM4="","",AM4*6.25/100) -> 0.125 | AO4: 93 | AP4: =SUM(D4,G4,J4,M4,P4,S4,V4,Y4,AB4,AE4,AH4,AK4,AN4) -> #DIV/0!
A5: National Landing | B5: =100%+'Period Tables'!I6 -> 1.2172449 | C5: =IFS(B5="", "", B5<90%,0, B5<95%,1, B5<=98%,2, B5<=101%,3, B5<=105%,4, TRUE,5) -> 5 | D5: =IF(C5="","",C5*5/100) -> 0.25 | E5: =100%+'Period Tables'!F6 -> 1.4285788 | F5: =IFS(E5="", "", E5<90%,0, E5<95%,1, E5<=98%,2, E5<=101%,3, E5<=105%,4, TRUE,5) -> 5 | G5: =IF(F5="","",F5*5/100) -> 0.25 | H5: =100%+'Period Tables'!V6 -> #DIV/0! | I5: =IFS(H5="", "", H5<75%,0, H5<85%,1, H5<95%,2, H5<=100%,3, H5<=105%,4, TRUE,5) -> #DIV/0! | J5: =IF(I5="","",I5*15/100) -> #DIV/0! | K5: ='Period Tables'!L6*100 -> -4.1 | L5: =IFS(K5="", "", K5>=3,0, K5>=2,1, K5>=1,2, K5>=0,3, K5<=-1,5, K5<=-0.5,4, TRUE,3) -> 5 | M5: =IF(L5="","",L5*12.5/100) -> 0.625 | N5: ='Period Tables'!O6*100 -> 0.2 | O5: =IFS(N5="", "", N5>=3,0, N5>=2,1, N5>=1,2, N5>=0,3, N5<=-1,5, N5<=-0.5,4, TRUE,3) -> 3 | P5: =IF(O5="","",O5*12.5/100) -> 0.375 | Q5: ='Period Tables'!H14 -> 4.33 | R5: =IFS(Q5="", "", Q5="NA","" ,Q5<3.8,0, Q5<4,1, Q5<4.3,2, Q5<4.5,3, Q5<4.7,4, TRUE,5) -> 3 | S5: =IF(R5="","",R5*17.5/100) -> 0.525 | T5: ='Period Tables'!F14 -> NA | U5: =IFS(T5="", "", T5="NA","" ,T5<3.8,0, T5<4,1, T5<4.3,2, T5<4.5,3, T5<4.7,4, TRUE,5) | V5: =IF(U5="","",U5*7.5/100) | W5: ='Period Tables'!I22 -> 0.0315 | X5: =IFS(W5="", "", W5>6%,0, W5>4%,1, W5>2%,2, W5>1.5%,3, W5>1%,4, TRUE,5) -> 2 | Y5: =IF(X5="","",X5*10/100) -> 0.2 | Z5: ='Period Tables'!H33 -> 1.14 | AA5: =IFS(Z5="","", VALUE(Z5)>8,0, VALUE(Z5)>5,1, VALUE(Z5)>2,2, VALUE(Z5)>1.5,3, VALUE(Z5)>1,4, TRUE,5) -> 4 | AB5: =IF(AA5="","",AA5*7.5/100) -> 0.3 | AC5: ='Period Tables'!E22 -> 4.3 | AD5: =IFS(AC5="", "", AC5<3.8,0, AC5<4,1, AC5<4.3,2, AC5<4.5,3, AC5<4.7,4, TRUE,5) -> 3 | AE5: =IF(AD5="","",AD5*7.5/100) -> 0.225 | AF5: 70 | AG5: =IFS(AF5="", "", AF5<70,0, AF5<75,1, AF5<83,2, AF5<89,3, AF5<94,4, TRUE,5) -> 1 | AH5: =IF(AG5="","",AG5*12.5/100) -> 0.125 | AI5: 75 | AJ5: =IFS(AI5="", "", AI5<70,0, AI5<75,1, AI5<83,2, AI5<89,3, AI5<94,4, TRUE,5) -> 2 | AK5: =IF(AJ5="","",AJ5*6.25/100) -> 0.125 | AL5: 71 | AM5: =IFS(AL5="", "", AL5<70,0, AL5<75,1, AL5<83,2, AL5<89,3, AL5<94,4, TRUE,5) -> 1 | AN5: =IF(AM5="","",AM5*6.25/100) -> 0.0625 | AO5: 80 | AP5: =SUM(D5,G5,J5,M5,P5,S5,V5,Y5,AB5,AE5,AH5,AK5,AN5) -> #DIV/0!
A6: Rockville | B6: =100%+'Period Tables'!I7 -> 0.87077313 | C6: =IFS(B6="", "", B6<90%,0, B6<95%,1, B6<=98%,2, B6<=101%,3, B6<=105%,4, TRUE,5) -> 0 | D6: =IF(C6="","",C6*5/100) -> 0 | E6: =100%+'Period Tables'!F7 -> 1.0890977 | F6: =IFS(E6="", "", E6<90%,0, E6<95%,1, E6<=98%,2, E6<=101%,3, E6<=105%,4, TRUE,5) -> 5 | G6: =IF(F6="","",F6*5/100) -> 0.25 | H6: =100%+'Period Tables'!V7 -> #DIV/0! | I6: =IFS(H6="", "", H6<75%,0, H6<85%,1, H6<95%,2, H6<=100%,3, H6<=105%,4, TRUE,5) -> #DIV/0! | J6: =IF(I6="","",I6*15/100) -> #DIV/0! | K6: ='Period Tables'!L7*100 -> -0.7 | L6: =IFS(K6="", "", K6>=3,0, K6>=2,1, K6>=1,2, K6>=0,3, K6<=-1,5, K6<=-0.5,4, TRUE,3) -> 4 | M6: =IF(L6="","",L6*12.5/100) -> 0.5 | N6: ='Period Tables'!O7*100 -> 3.3 | O6: =IFS(N6="", "", N6>=3,0, N6>=2,1, N6>=1,2, N6>=0,3, N6<=-1,5, N6<=-0.5,4, TRUE,3) -> 0 | P6: =IF(O6="","",O6*12.5/100) -> 0 | Q6: ='Period Tables'!H16 -> 4.47 | R6: =IFS(Q6="", "", Q6="NA","" ,Q6<3.8,0, Q6<4,1, Q6<4.3,2, Q6<4.5,3, Q6<4.7,4, TRUE,5) -> 3 | S6: =IF(R6="","",R6*17.5/100) -> 0.525 | T6: ='Period Tables'!F16 -> NA | U6: =IFS(T6="", "", T6="NA","" ,T6<3.8,0, T6<4,1, T6<4.3,2, T6<4.5,3, T6<4.7,4, TRUE,5) | V6: =IF(U6="","",U6*7.5/100) | W6: ='Period Tables'!I24 -> 0.045 | X6: =IFS(W6="", "", W6>6%,0, W6>4%,1, W6>2%,2, W6>1.5%,3, W6>1%,4, TRUE,5) -> 1 | Y6: =IF(X6="","",X6*10/100) -> 0.1 | Z6: ='Period Tables'!H30 -> 2.03 | AA6: =IFS(Z6="","", VALUE(Z6)>8,0, VALUE(Z6)>5,1, VALUE(Z6)>2,2, VALUE(Z6)>1.5,3, VALUE(Z6)>1,4, TRUE,5) -> 2 | AB6: =IF(AA6="","",AA6*7.5/100) -> 0.15 | AC6: ='Period Tables'!E24 -> 4.3 | AD6: =IFS(AC6="", "", AC6<3.8,0, AC6<4,1, AC6<4.3,2, AC6<4.5,3, AC6<4.7,4, TRUE,5) -> 3 | AE6: =IF(AD6="","",AD6*7.5/100) -> 0.225 | AF6: 56 | AG6: =IFS(AF6="", "", AF6<70,0, AF6<75,1, AF6<83,2, AF6<89,3, AF6<94,4, TRUE,5) -> 0 | AH6: =IF(AG6="","",AG6*12.5/100) -> 0 | AI6: 60 | AJ6: =IFS(AI6="", "", AI6<70,0, AI6<75,1, AI6<83,2, AI6<89,3, AI6<94,4, TRUE,5) -> 0 | AK6: =IF(AJ6="","",AJ6*6.25/100) -> 0 | AL6: 60 | AM6: =IFS(AL6="", "", AL6<70,0, AL6<75,1, AL6<83,2, AL6<89,3, AL6<94,4, TRUE,5) -> 0 | AN6: =IF(AM6="","",AM6*6.25/100) -> 0 | AO6: 78 | AP6: =SUM(D6,G6,J6,M6,P6,S6,V6,Y6,AB6,AE6,AH6,AK6,AN6) -> #DIV/0!
Z7: ='Period Tables'!K36
Z8: ='Period Tables'!K39
Z9: ='Period Tables'!K37
Z10: ='Period Tables'!K38
Z11: ='Period Tables'!K35
Z12: ='Period Tables'!K41
Z13: ='Period Tables'!K42
Z14: ='Period Tables'!K45
Z15: ='Period Tables'!K43
Z16: ='Period Tables'!K44
Z17: ='Period Tables'!K41

Sheet Periodic Area Leader Dashboard
A1: Restaurant | B1: Composite Score | C1: Contributor Band | D1: Sales vs Budget (%) | E1: Sales vs Prior Year (%) | F1: EBITDA % vs Budget | G1: Labor vs Budget Variance (pts) | H1: COGS vs Budget Variance (pts) | I1: In-Store Rating | J1: 3P Rating | K1: 3P Error % | L1: Avoidable Wait (mins) | M1: Full Audit Score | N1: Culinary Audit Score | O1: Training Completion % (Gate)
A2: Ballpark | B2: ='Period Store Scorecards '!AJ3 -> 3.439 | C2: =IFS(B2<1.7,"Non", B2<2.7,"Low", B2<3.7,"Contributor", B2<4.7,"High", TRUE,"STAR") -> Contributor | D2: ='Period Store Scorecards '!B3 -> 0.0005532557 | E2: ='Period Store Scorecards '!E3 -> 0.00070625625 | F2: ='Period Store Scorecards '!H3 -> #DIV/0! | G2: ='Period Store Scorecards '!K3 -> -30.8 | H2: ='Period Store Scorecards '!N3 -> -26.4 | I2: ='Period Store Scorecards '!Q3 -> 5 | J2: ='Period Store Scorecards '!Z3 -> 4 | K2: ='Period Store Scorecards '!T3 -> 0.0405 | L2: ='Period Store Scorecards '!W3 -> 0.57 | M2: ='Period Store Scorecards '!AC3 -> 92 | N2: ='Period Store Scorecards '!AF3 -> 90 | O2: ='Period Store Scorecards '!AI3 -> 0.85
A3: Mosaic | B3: ='Period Store Scorecards '!AJ4 -> 3.61 | C3: =IFS(B3<1.7,"Non", B3<2.7,"Low", B3<3.7,"Contributor", B3<4.7,"High", TRUE,"STAR") -> Contributor | D3: ='Period Store Scorecards '!B4 -> 0.94670671 | E3: ='Period Store Scorecards '!E4 -> 1.0965152 | F3: ='Period Store Scorecards '!H4 -> #DIV/0! | G3: ='Period Store Scorecards '!K4 -> -2.7 | H3: ='Period Store Scorecards '!N4 -> -3.4 | I3: ='Period Store Scorecards '!Q4 -> 4.67 | J3: ='Period Store Scorecards '!Z4 -> 4.4 | K3: ='Period Store Scorecards '!T4 -> 0.0315 | L3: ='Period Store Scorecards '!W4 -> 1.48 | M3: ='Period Store Scorecards '!AC4 -> 88 | N3: ='Period Store Scorecards '!AF4 -> 86 | O3: ='Period Store Scorecards '!AI4 -> 0.87
A4: MVT | B4: ='Period Store Scorecards '!AJ5 -> 2.373 | C4: =IFS(B4<1.7,"Non", B4<2.7,"Low", B4<3.7,"Contributor", B4<4.7,"High", TRUE,"STAR") -> Low | D4: ='Period Store Scorecards '!B5 -> 1.0190662 | E4: ='Period Store Scorecards '!E5 -> 1.3761061 | F4: ='Period Store Scorecards '!H5 -> #DIV/0! | G4: ='Period Store Scorecards '!K5 -> 2.4 | H4: ='Period Store Scorecards '!N5 -> 1.1 | I4: ='Period Store Scorecards '!Q5 -> 3 | J4: ='Period Store Scorecards '!Z5 -> 4.5 | K4: ='Period Store Scorecards '!T5 -> 0.0264 | L4: ='Period Store Scorecards '!W5 -> 0.59 | M4: ='Period Store Scorecards '!AC5 -> 91 | N4: ='Period Store Scorecards '!AF5 -> 93 | O4: ='Period Store Scorecards '!AI5 -> 0.93
A5: National Landing | B5: ='Period Store Scorecards '!AJ6 -> 3.0625 | C5: =IFS(B5<1.7,"Non", B5<2.7,"Low", B5<3.7,"Contributor", B5<4.7,"High", TRUE,"STAR") -> Contributor | D5: ='Period Store Scorecards '!B6 -> 1.2172449 | E5: ='Period Store Scorecards '!E6 -> 1.4285788 | F5: ='Period Store Scorecards '!H6 -> #DIV/0! | G5: ='Period Store Scorecards '!K6 -> -4.1 | H5: ='Period Store Scorecards '!N6 -> 0.2 | I5: ='Period Store Scorecards '!Q6 -> 4.33 | J5: ='Period Store Scorecards '!Z6 -> 4.3 | K5: ='Period Store Scorecards '!T6 -> 0.0315 | L5: ='Period Store Scorecards '!W6 -> 1.14 | M5: ='Period Store Scorecards '!AC6 -> 78 | N5: ='Period Store Scorecards '!AF6 -> 75 | O5: ='Period Store Scorecards '!AI6 -> 0.8
A6: Rockville | B6: ='Period Store Scorecards '!AJ7 -> 2.364 | C6: =IFS(B6<1.7,"Non", B6<2.7,"Low", B6<3.7,"Contributor", B6<4.7,"High", TRUE,"STAR") -> Low | D6: ='Period Store Scorecards '!B7 -> 0.87077313 | E6: ='Period Store Scorecards '!E7 -> 1.0890977 | F6: ='Period Store Scorecards '!H7 -> #DIV/0! | G6: ='Period Store Scorecards '!K7 -> -0.7 | H6: ='Period Store Scorecards '!N7 -> 3.3 | I6: ='Period Store Scorecards '!Q7 -> 4.47 | J6: ='Period Store Scorecards '!Z7 -> 4.3 | K6: ='Period Store Scorecards '!T7 -> 0.045 | L6: ='Period Store Scorecards '!W7 -> 2.03 | M6: ='Period Store Scorecards '!AC7 -> 77 | N6: ='Period Store Scorecards '!AF7 -> 74 | O6: ='Period Store Scorecards '!AI7 -> 0.78
A7: All Stores | B7: ='Period Store Scorecards '!AJ8 -> 2.9465 | C7: =IFS(B7<1.7,"Non", B7<2.7,"Low", B7<3.7,"Contributor", B7<4.7,"High", TRUE,"STAR") -> Contributor | D7: ='Period Store Scorecards '!B8 -> 0.85242532 | E7: ='Period Store Scorecards '!E8 -> 1.0642439 | F7: ='Period Store Scorecards '!H8 -> #DIV/0! | G7: ='Period Store Scorecards '!K8 -> -1.9 | H7: ='Period Store Scorecards '!N8 -> -0.1 | I7: ='Period Store Scorecards '!Q8 -> 4.294 | J7: ='Period Store Scorecards '!Z8 -> 4.3 | K7: ='Period Store Scorecards '!T8 -> 0.03498 | L7: ='Period Store Scorecards '!W8 -> 1.19 | M7: ='Period Store Scorecards '!AC8 -> 85.2 | N7: ='Period Store Scorecards '!AF8 -> 83.6 | O7: ='Period Store Scorecards '!AI8 -> 0.846

Sheet QUATERLY>>>

Sheet Quaterly Store Scorecards
A1: Restaurant | B1: Sales vs Budget (%) | C1: Score | D1: Weighted | E1: Sales vs Prior Year (%) | F1: Score | G1: Weighted | H1: EBITDA vs Budget (%) | I1: Score | J1: Weighted | K1: Labor Var (pts) | L1: Score | M1: Weighted | N1: COGS Var (pts) | O1: Score | P1: Weighted | Q1: Google Rating | R1: Score | S1: Weighted | T1: Yelp Rating | U1: Score | V1: Weighted | W1: 3P Error Rate (%) | X1: Score | Y1: Weighted | Z1: Avoidable Wait (mins) | AA1: Score | AB1: Weighted | AC1: 3P Rating | AD1: Score | AE1: Weighted | AF1: Full Audit Score | AG1: Score | AH1: Weighted | AI1: Culinary Audit Score | AJ1: Score | AK1: Weighted | AL1: Focus Audit Score | AM1: Score | AN1: Weighted | AO1: Training % (Gate) | AP1: Composite Score (0-5) | AQ1: Eligible? | AR1: Payout % | AS1: Annual Bonus Target | AT1: Annual Bonus Earned | AU1: Quarterly Bonus Earned
A2: Ballpark | B2: =100%+'Quaterly Tables'!I3 -> #REF! | C2: =IFS(B2="", "", B2<90%,0, B2<95%,1, B2<=98%,2, B2<=101%,3, B2<=105%,4, TRUE,5) -> #REF! | D2: =IF(C2="","",C2*5/100) -> #REF! | E2: =100%+'Quaterly Tables'!F3 -> #REF! | F2: =IFS(E2="", "", E2<90%,0, E2<95%,1, E2<=98%,2, E2<=101%,3, E2<=105%,4, TRUE,5) -> #REF! | G2: =IF(F2="","",F2*5/100) -> #REF! | H2: =100%+'Quaterly Tables'!V3 -> #REF! | I2: =IFS(H2="", "", H2<75%,0, H2<85%,1, H2<95%,2, H2<=100%,3, H2<=105%,4, TRUE,5) -> #REF! | J2: =IF(I2="","",I2*15/100) -> #REF! | K2: ='Quaterly Tables'!L3*100 -> #REF! | L2: =IFS(K2="", "", K2>=3,0, K2>=2,1, K2>=1,2, K2>=0,3, K2<=-1,5, K2<=-0.5,4, TRUE,3) -> #REF! | M2: =IF(L2="","",L2*12.5/100) -> #REF! | N2: ='Quaterly Tables'!O3*100 -> #REF! | O2: =IFS(N2="", "", N2>=3,0, N2>=2,1, N2>=1,2, N2>=0,3, N2<=-1,5, N2<=-0.5,4, TRUE,3) -> #REF! | P2: =IF(O2="","",O2*12.5/100) -> #REF! | Q2: ='Quaterly Tables'!H12 -> 5 | R2: =IFS(Q2="", "", Q2="NA","" ,Q2<3.8,0, Q2<4,1, Q2<4.3,2, Q2<4.5,3, Q2<4.7,4, TRUE,5) -> 5 | S2: =IF(R2="","",R2*17.5/100) -> 0.875 | T2: ='Quaterly Tables'!F12 -> NA | U2: =IFS(T2="", "", T2="NA","" ,T2<3.8,0, T2<4,1, T2<4.3,2, T2<4.5,3, T2<4.7,4, TRUE,5) | V2: =IF(U2="","",U2*7.5/100) | W2: ='Quaterly Tables'!I20 -> 0.0405 | X2: =IFS(W2="", "", W2>6%,0, W2>4%,1, W2>2%,2, W2>1.5%,3, W2>1%,4, TRUE,5) -> 1 | Y2: =IF(X2="","",X2*10/100) -> 0.1 | Z2: ='Quaterly Tables'!H31 -> 0.57 | AA2: =IFS(Z2="","", VALUE(Z2)>8,0, VALUE(Z2)>5,1, VALUE(Z2)>2,2, VALUE(Z2)>1.5,3, VALUE(Z2)>1,4, TRUE,5) -> 5 | AB2: =IF(AA2="","",AA2*7.5/100) -> 0.375 | AC2: ='Quaterly Tables'!E20 -> 4 | AD2: =IFS(AC2="", "", AC2<3.8,0, AC2<4,1, AC2<4.3,2, AC2<4.5,3, AC2<4.7,4, TRUE,5) -> 2 | AE2: =IF(AD2="","",AD2*7.5/100) -> 0.15 | AF2: 86 | AG2: =IFS(AF2="", "", AF2<70,0, AF2<75,1, AF2<83,2, AF2<89,3, AF2<94,4, TRUE,5) -> 3 | AH2: =IF(AG2="","",AG2*12.5/100) -> 0.375 | AI2: 90 | AJ2: =IFS(AI2="", "", AI2<70,0, AI2<75,1, AI2<83,2, AI2<89,3, AI2<94,4, TRUE,5) -> 4 | AK2: =IF(AJ2="","",AJ2*6.25/100) -> 0.25 | AL2: 95 | AM2: =IFS(AL2="", "", AL2<70,0, AL2<75,1, AL2<83,2, AL2<89,3, AL2<94,4, TRUE,5) -> 5 | AN2: =IF(AM2="","",AM2*6.25/100) -> 0.3125 | AO2: 89 | AP2: =SUM(D2,G2,J2,M2,P2,S2,V2,Y2,AB2,AE2,AH2,AK2,AN2) -> #REF! | AQ2: =IF(AND(AP2>=2.7,AO2>=87),"Eligible","Not Eligible") -> #REF! | AR2: =IF(AQ2<>"Eligible",0,IF(AP2<3.7,0.5,IF(AP2<4.7,0.75,1))) -> #REF! | AS2: 10000 | AT2: =AS2*AR2 -> #REF! | AU2: =AT2/4 -> #REF!
A3: Mosaic | B3: =100%+'Quaterly Tables'!I4 -> #DIV/0! | C3: =IFS(B3="", "", B3<90%,0, B3<95%,1, B3<=98%,2, B3<=101%,3, B3<=105%,4, TRUE,5) -> #DIV/0! | D3: =IF(C3="","",C3*5/100) -> #DIV/0! | E3: =100%+'Quaterly Tables'!F4 -> #DIV/0! | F3: =IFS(E3="", "", E3<90%,0, E3<95%,1, E3<=98%,2, E3<=101%,3, E3<=105%,4, TRUE,5) -> #DIV/0! | G3: =IF(F3="","",F3*5/100) -> #DIV/0! | H3: =100%+'Quaterly Tables'!V4 -> 1 | I3: =IFS(H3="", "", H3<75%,0, H3<85%,1, H3<95%,2, H3<=100%,3, H3<=105%,4, TRUE,5) -> 3 | J3: =IF(I3="","",I3*15/100) -> 0.45 | K3: ='Quaterly Tables'!L4*100 -> 0 | L3: =IFS(K3="", "", K3>=3,0, K3>=2,1, K3>=1,2, K3>=0,3, K3<=-1,5, K3<=-0.5,4, TRUE,3) -> 3 | M3: =IF(L3="","",L3*12.5/100) -> 0.375 | N3: ='Quaterly Tables'!O4*100 -> 0 | O3: =IFS(N3="", "", N3>=3,0, N3>=2,1, N3>=1,2, N3>=0,3, N3<=-1,5, N3<=-0.5,4, TRUE,3) -> 3 | P3: =IF(O3="","",O3*12.5/100) -> 0.375 | Q3: ='Quaterly Tables'!H15 -> 4.75 | R3: =IFS(Q3="", "", Q3="NA","" ,Q3<3.8,0, Q3<4,1, Q3<4.3,2, Q3<4.5,3, Q3<4.7,4, TRUE,5) -> 5 | S3: =IF(R3="","",R3*17.5/100) -> 0.875 | T3: ='Quaterly Tables'!F15 -> 4 | U3: =IFS(T3="", "", T3="NA","" ,T3<3.8,0, T3<4,1, T3<4.3,2, T3<4.5,3, T3<4.7,4, TRUE,5) -> 2 | V3: =IF(U3="","",U3*7.5/100) -> 0.15 | W3: ='Quaterly Tables'!I23 -> 0.0315 | X3: =IFS(W3="", "", W3>6%,0, W3>4%,1, W3>2%,2, W3>1.5%,3, W3>1%,4, TRUE,5) -> 2 | Y3: =IF(X3="","",X3*10/100) -> 0.2 | Z3: ='Quaterly Tables'!H34 -> 1.48 | AA3: =IFS(Z3="","", VALUE(Z3)>8,0, VALUE(Z3)>5,1, VALUE(Z3)>2,2, VALUE(Z3)>1.5,3, VALUE(Z3)>1,4, TRUE,5) -> 4 | AB3: =IF(AA3="","",AA3*7.5/100) -> 0.3 | AC3: ='Quaterly Tables'!E23 -> 4.4 | AD3: =IFS(AC3="", "", AC3<3.8,0, AC3<4,1, AC3<4.3,2, AC3<4.5,3, AC3<4.7,4, TRUE,5) -> 3 | AE3: =IF(AD3="","",AD3*7.5/100) -> 0.225 | AF3: 67 | AG3: =IFS(AF3="", "", AF3<70,0, AF3<75,1, AF3<83,2, AF3<89,3, AF3<94,4, TRUE,5) -> 0 | AH3: =IF(AG3="","",AG3*12.5/100) -> 0 | AI3: 70 | AJ3: =IFS(AI3="", "", AI3<70,0, AI3<75,1, AI3<83,2, AI3<89,3, AI3<94,4, TRUE,5) -> 1 | AK3: =IF(AJ3="","",AJ3*6.25/100) -> 0.0625 | AL3: 76 | AM3: =IFS(AL3="", "", AL3<70,0, AL3<75,1, AL3<83,2, AL3<89,3, AL3<94,4, TRUE,5) -> 2 | AN3: =IF(AM3="","",AM3*6.25/100) -> 0.125 | AO3: 87 | AP3: =SUM(D3,G3,J3,M3,P3,S3,V3,Y3,AB3,AE3,AH3,AK3,AN3) -> #DIV/0! | AQ3: =IF(AND(AP3>=2.7,AO3>=87),"Eligible","Not Eligible") -> #DIV/0! | AR3: =IF(AQ3<>"Eligible",0,IF(AP3<3.7,0.5,IF(AP3<4.7,0.75,1))) -> #DIV/0! | AS3: 10000 | AT3: =AS3*AR3 -> #DIV/0! | AU3: =AT3/4 -> #DIV/0!
A4: MVT | B4: =100%+'Quaterly Tables'!I5 -> #DIV/0! | C4: =IFS(B4="", "", B4<90%,0, B4<95%,1, B4<=98%,2, B4<=101%,3, B4<=105%,4, TRUE,5) -> #DIV/0! | D4: =IF(C4="","",C4*5/100) -> #DIV/0! | E4: =100%+'Quaterly Tables'!F5 -> #DIV/0! | F4: =IFS(E4="", "", E4<90%,0, E4<95%,1, E4<=98%,2, E4<=101%,3, E4<=105%,4, TRUE,5) -> #DIV/0! | G4: =IF(F4="","",F4*5/100) -> #DIV/0! | H4: =100%+'Quaterly Tables'!V5 -> 1 | I4: =IFS(H4="", "", H4<75%,0, H4<85%,1, H4<95%,2, H4<=100%,3, H4<=105%,4, TRUE,5) -> 3 | J4: =IF(I4="","",I4*15/100) -> 0.45 | K4: ='Quaterly Tables'!L5*100 -> 0 | L4: =IFS(K4="", "", K4>=3,0, K4>=2,1, K4>=1,2, K4>=0,3, K4<=-1,5, K4<=-0.5,4, TRUE,3) -> 3 | M4: =IF(L4="","",L4*12.5/100) -> 0.375 | N4: ='Quaterly Tables'!O5*100 -> 0 | O4: =IFS(N4="", "", N4>=3,0, N4>=2,1, N4>=1,2, N4>=0,3, N4<=-1,5, N4<=-0.5,4, TRUE,3) -> 3 | P4: =IF(O4="","",O4*12.5/100) -> 0.375 | Q4: ='Quaterly Tables'!H13 -> 3.97 | R4: =IFS(Q4="", "", Q4="NA","" ,Q4<3.8,0, Q4<4,1, Q4<4.3,2, Q4<4.5,3, Q4<4.7,4, TRUE,5) -> 1 | S4: =IF(R4="","",R4*17.5/100) -> 0.175 | T4: ='Quaterly Tables'!F13 -> 1 | U4: =IFS(T4="", "", T4="NA","" ,T4<3.8,0, T4<4,1, T4<4.3,2, T4<4.5,3, T4<4.7,4, TRUE,5) -> 0 | V4: =IF(U4="","",U4*7.5/100) -> 0 | W4: ='Quaterly Tables'!I21 -> 0.0264 | X4: =IFS(W4="", "", W4>6%,0, W4>4%,1, W4>2%,2, W4>1.5%,3, W4>1%,4, TRUE,5) -> 2 | Y4: =IF(X4="","",X4*10/100) -> 0.2 | Z4: ='Quaterly Tables'!H32 -> 0.59 | AA4: =IFS(Z4="","", VALUE(Z4)>8,0, VALUE(Z4)>5,1, VALUE(Z4)>2,2, VALUE(Z4)>1.5,3, VALUE(Z4)>1,4, TRUE,5) -> 5 | AB4: =IF(AA4="","",AA4*7.5/100) -> 0.375 | AC4: ='Quaterly Tables'!E21 -> 4.5 | AD4: =IFS(AC4="", "", AC4<3.8,0, AC4<4,1, AC4<4.3,2, AC4<4.5,3, AC4<4.7,4, TRUE,5) -> 4 | AE4: =IF(AD4="","",AD4*7.5/100) -> 0.3 | AF4: 72 | AG4: =IFS(AF4="", "", AF4<70,0, AF4<75,1, AF4<83,2, AF4<89,3, AF4<94,4, TRUE,5) -> 1 | AH4: =IF(AG4="","",AG4*12.5/100) -> 0.125 | AI4: 76 | AJ4: =IFS(AI4="", "", AI4<70,0, AI4<75,1, AI4<83,2, AI4<89,3, AI4<94,4, TRUE,5) -> 2 | AK4: =IF(AJ4="","",AJ4*6.25/100) -> 0.125 | AL4: 78 | AM4: =IFS(AL4="", "", AL4<70,0, AL4<75,1, AL4<83,2, AL4<89,3, AL4<94,4, TRUE,5) -> 2 | AN4: =IF(AM4="","",AM4*6.25/100) -> 0.125 | AO4: 93 | AP4: =SUM(D4,G4,J4,M4,P4,S4,V4,Y4,AB4,AE4,AH4,AK4,AN4) -> #DIV/0! | AQ4: =IF(AND(AP4>=2.7,AO4>=87),"Eligible","Not Eligible") -> #DIV/0! | AR4: =IF(AQ4<>"Eligible",0,IF(AP4<3.7,0.5,IF(AP4<4.7,0.75,1))) -> #DIV/0! | AS4: 10000 | AT4: =AS4*AR4 -> #DIV/0! | AU4: =AT4/4 -> #DIV/0!
A5: National Landing | B5: =100%+'Quaterly Tables'!I6 -> #DIV/0! | C5: =IFS(B5="", "", B5<90%,0, B5<95%,1, B5<=98%,2, B5<=101%,3, B5<=105%,4, TRUE,5) -> #DIV/0! | D5: =IF(C5="","",C5*5/100) -> #DIV/0! | E5: =100%+'Quaterly Tables'!F6 -> #DIV/0! | F5: =IFS(E5="", "", E5<90%,0, E5<95%,1, E5<=98%,2, E5<=101%,3, E5<=105%,4, TRUE,5) -> #DIV/0! | G5: =IF(F5="","",F5*5/100) -> #DIV/0! | H5: =100%+'Quaterly Tables'!V6 -> 1 | I5: =IFS(H5="", "", H5<75%,0, H5<85%,1, H5<95%,2, H5<=100%,3, H5<=105%,4, TRUE,5) -> 3 | J5: =IF(I5="","",I5*15/100) -> 0.45 | K5: ='Quaterly Tables'!L6*100 -> 0 | L5: =IFS(K5="", "", K5>=3,0, K5>=2,1, K5>=1,2, K5>=0,3, K5<=-1,5, K5<=-0.5,4, TRUE,3) -> 3 | M5: =IF(L5="","",L5*12.5/100) -> 0.375 | N5: ='Quaterly Tables'!O6*100 -> 0 | O5: =IFS(N5="", "", N5>=3,0, N5>=2,1, N5>=1,2, N5>=0,3, N5<=-1,5, N5<=-0.5,4, TRUE,3) -> 3 | P5: =IF(O5="","",O5*12.5/100) -> 0.375 | Q5: ='Quaterly Tables'!H14 -> 4.33 | R5: =IFS(Q5="", "", Q5="NA","" ,Q5<3.8,0, Q5<4,1, Q5<4.3,2, Q5<4.5,3, Q5<4.7,4, TRUE,5) -> 3 | S5: =IF(R5="","",R5*17.5/100) -> 0.525 | T5: ='Quaterly Tables'!F14 -> NA | U5: =IFS(T5="", "", T5="NA","" ,T5<3.8,0, T5<4,1, T5<4.3,2, T5<4.5,3, T5<4.7,4, TRUE,5) | V5: =IF(U5="","",U5*7.5/100) | W5: ='Quaterly Tables'!I22 -> 0.0315 | X5: =IFS(W5="", "", W5>6%,0, W5>4%,1, W5>2%,2, W5>1.5%,3, W5>1%,4, TRUE,5) -> 2 | Y5: =IF(X5="","",X5*10/100) -> 0.2 | Z5: ='Quaterly Tables'!H33 -> 1.14 | AA5: =IFS(Z5="","", VALUE(Z5)>8,0, VALUE(Z5)>5,1, VALUE(Z5)>2,2, VALUE(Z5)>1.5,3, VALUE(Z5)>1,4, TRUE,5) -> 4 | AB5: =IF(AA5="","",AA5*7.5/100) -> 0.3 | AC5: ='Quaterly Tables'!E22 -> 4.3 | AD5: =IFS(AC5="", "", AC5<3.8,0, AC5<4,1, AC5<4.3,2, AC5<4.5,3, AC5<4.7,4, TRUE,5) -> 3 | AE5: =IF(AD5="","",AD5*7.5/100) -> 0.225 | AF5: 70 | AG5: =IFS(AF5="", "", AF5<70,0, AF5<75,1, AF5<83,2, AF5<89,3, AF5<94,4, TRUE,5) -> 1 | AH5: =IF(AG5="","",AG5*12.5/100) -> 0.125 | AI5: 75 | AJ5: =IFS(AI5="", "", AI5<70,0, AI5<75,1, AI5<83,2, AI5<89,3, AI5<94,4, TRUE,5) -> 2 | AK5: =IF(AJ5="","",AJ5*6.25/100) -> 0.125 | AL5: 71 | AM5: =IFS(AL5="", "", AL5<70,0, AL5<75,1, AL5<83,2, AL5<89,3, AL5<94,4, TRUE,5) -> 1 | AN5: =IF(AM5="","",AM5*6.25/100) -> 0.0625 | AO5: 80 | AP5: =SUM(D5,G5,J5,M5,P5,S5,V5,Y5,AB5,AE5,AH5,AK5,AN5) -> #DIV/0! | AQ5: =IF(AND(AP5>=2.7,AO5>=87),"Eligible","Not Eligible") -> #DIV/0! | AR5: =IF(AQ5<>"Eligible",0,IF(AP5<3.7,0.5,IF(AP5<4.7,0.75,1))) -> #DIV/0! | AS5: 10000 | AT5: =AS5*AR5 -> #DIV/0! | AU5: =AT5/4 -> #DIV/0!
A6: Rockville | B6: =100%+'Quaterly Tables'!I7 -> #DIV/0! | C6: =IFS(B6="", "", B6<90%,0, B6<95%,1, B6<=98%,2, B6<=101%,3, B6<=105%,4, TRUE,5) -> #DIV/0! | D6: =IF(C6="","",C6*5/100) -> #DIV/0! | E6: =100%+'Quaterly Tables'!F7 -> #DIV/0! | F6: =IFS(E6="", "", E6<90%,0, E6<95%,1, E6<=98%,2, E6<=101%,3, E6<=105%,4, TRUE,5) -> #DIV/0! | G6: =IF(F6="","",F6*5/100) -> #DIV/0! | H6: =100%+'Quaterly Tables'!V7 -> 1 | I6: =IFS(H6="", "", H6<75%,0, H6<85%,1, H6<95%,2, H6<=100%,3, H6<=105%,4, TRUE,5) -> 3 | J6: =IF(I6="","",I6*15/100) -> 0.45 | K6: ='Quaterly Tables'!L7*100 -> 0 | L6: =IFS(K6="", "", K6>=3,0, K6>=2,1, K6>=1,2, K6>=0,3, K6<=-1,5, K6<=-0.5,4, TRUE,3) -> 3 | M6: =IF(L6="","",L6*12.5/100) -> 0.375 | N6: ='Quaterly Tables'!O7*100 -> 0 | O6: =IFS(N6="", "", N6>=3,0, N6>=2,1, N6>=1,2, N6>=0,3, N6<=-1,5, N6<=-0.5,4, TRUE,3) -> 3 | P6: =IF(O6="","",O6*12.5/100) -> 0.375 | Q6: ='Quaterly Tables'!H16 -> 4.47 | R6: =IFS(Q6="", "", Q6="NA","" ,Q6<3.8,0, Q6<4,1, Q6<4.3,2, Q6<4.5,3, Q6<4.7,4, TRUE,5) -> 3 | S6: =IF(R6="","",R6*17.5/100) -> 0.525 | T6: ='Quaterly Tables'!F16 -> NA | U6: =IFS(T6="", "", T6="NA","" ,T6<3.8,0, T6<4,1, T6<4.3,2, T6<4.5,3, T6<4.7,4, TRUE,5) | V6: =IF(U6="","",U6*7.5/100) | W6: ='Quaterly Tables'!I24 -> 0.045 | X6: =IFS(W6="", "", W6>6%,0, W6>4%,1, W6>2%,2, W6>1.5%,3, W6>1%,4, TRUE,5) -> 1 | Y6: =IF(X6="","",X6*10/100) -> 0.1 | Z6: ='Quaterly Tables'!H30 -> 2.03 | AA6: =IFS(Z6="","", VALUE(Z6)>8,0, VALUE(Z6)>5,1, VALUE(Z6)>2,2, VALUE(Z6)>1.5,3, VALUE(Z6)>1,4, TRUE,5) -> 2 | AB6: =IF(AA6="","",AA6*7.5/100) -> 0.15 | AC6: ='Quaterly Tables'!E24 -> 4.3 | AD6: =IFS(AC6="", "", AC6<3.8,0, AC6<4,1, AC6<4.3,2, AC6<4.5,3, AC6<4.7,4, TRUE,5) -> 3 | AE6: =IF(AD6="","",AD6*7.5/100) -> 0.225 | AF6: 56 | AG6: =IFS(AF6="", "", AF6<70,0, AF6<75,1, AF6<83,2, AF6<89,3, AF6<94,4, TRUE,5) -> 0 | AH6: =IF(AG6="","",AG6*12.5/100) -> 0 | AI6: 60 | AJ6: =IFS(AI6="", "", AI6<70,0, AI6<75,1, AI6<83,2, AI6<89,3, AI6<94,4, TRUE,5) -> 0 | AK6: =IF(AJ6="","",AJ6*6.25/100) -> 0 | AL6: 60 | AM6: =IFS(AL6="", "", AL6<70,0, AL6<75,1, AL6<83,2, AL6<89,3, AL6<94,4, TRUE,5) -> 0 | AN6: =IF(AM6="","",AM6*6.25/100) -> 0 | AO6: 78 | AP6: =SUM(D6,G6,J6,M6,P6,S6,V6,Y6,AB6,AE6,AH6,AK6,AN6) -> #DIV/0! | AQ6: =IF(AND(AP6>=2.7,AO6>=87),"Eligible","Not Eligible") -> #DIV/0! | AR6: =IF(AQ6<>"Eligible",0,IF(AP6<3.7,0.5,IF(AP6<4.7,0.75,1))) -> #DIV/0! | AS6: 10000 | AT6: =AS6*AR6 -> #DIV/0! | AU6: =AT6/4 -> #DIV/0!

Sheet Quaterly Store Scorecards 
A1: Location | B1: Sales vs Budget (%) | E1: Sales vs Prior Year (%) | H1: EBITDA vs Budget (%) | K1: Labor vs Budget Variance (pts) | N1: COGS vs Budget Variance (pts) | Q1: In-Store Rating | T1: 3P Error Rate (%) | W1: Avoidable Wait (mins) | Z1: 3P Rating | AC1: Full Audit Score | AF1: Culinary Audit Score | AI1: Training Completion % (Gate) | AJ1: Composite Score (0–5) | AK1: Eligible? | AL1: Payout % | AM1: Annual Bonus Target | AN1: Annual Bonus Earned | AO1: Quarterly Bonus Earned
B2: Input | C2: Score | D2: Weighted | E2: Input | F2: Score | G2: Weighted | H2: Input | I2: Score | J2: Weighted | K2: Input | L2: Score | M2: Weighted | N2: Input | O2: Score | P2: Weighted | Q2: Input | R2: Score | S2: Weighted | T2: Input | U2: Score | V2: Weighted | W2: Input | X2: Score | Y2: Weighted | Z2: Input | AA2: Score | AB2: Weighted | AC2: Input | AD2: Score | AE2: Weighted | AF2: Input | AG2: Score | AH2: Weighted | AI2: Input | AJ2: Score
A3: Ballpark | B3: =100%+'Quaterly Tables'!I3 -> #REF! | C3: =IFERROR(ROUND(ifs(B3="","",B3>=1.05,5,B3>=1.02,4+(B3-1.02)/0.03,B3>=0.99,3+(B3-0.99)/0.03,B3>=0.95,2+(B3-0.95)/0.04,B3>=0.9,1+(B3-0.9)/0.05,TRUE(),0),1),"") | D3: =IF(C3="","",C3*C$9) | E3: =100%+'Quaterly Tables'!F3 -> #REF! | F3: =IFERROR(ROUND(ifs(E3="","",E3>=1.15,5,E3>=1.075,4+(E3-1.075)/0.075,E3>=1.05,3+(E3-1.05)/0.025,E3>=1,2+(E3-1)/0.05,E3>=0.95,1+(E3-0.95)/0.05,TRUE(),0),1),"") | G3: =IF(F3="","",F3*F$9) | H3: =100%+'Quaterly Tables'!V3 -> #REF! | I3: =IFERROR(ROUND(ifs(H3="","",H3>=1.05,5,H3>=1.01,4+(H3-1.01)/0.04,H3>=0.95,3+(H3-0.95)/0.06,H3>=0.85,2+(H3-0.85)/0.1,H3>=0.75,1+(H3-0.75)/0.1,TRUE(),0),1),"") | J3: =IF(I3="","",I3*I$9) | K3: ='Quaterly Tables'!L3*100 -> #REF! | L3: =IFERROR(ROUND(IFS(K3="","",K3>=3,0,K3>=2,1+(3-K3)/1,K3>=1,2+(2-K3)/1,K3>0,3+(1-K3)/1,K3>=-1,4+(0-K3)/1,TRUE,5),1),"") | M3: =IF(L3="","",L3*L$9) | N3: ='Quaterly Tables'!O3*100 -> #REF! | O3: =IFERROR(ROUND(IFS(N3="","",N3>=3,0,N3>=2,1+(3-N3)/1,N3>=1,2+(2-N3)/1,N3>0,3+(1-N3)/1,N3>=-1,4+(0-N3)/1,TRUE,5),1),"") | P3: =IF(O3="","",O3*O$9) | Q3: ='Quaterly Tables'!E12 -> 5 | R3: =IF(OR(NOT(ISNUMBER(Q3)),Q3=0),"",IFERROR(ROUND(ifs(Q3>=4.7,5,Q3>=4.5,4+(Q3-4.5)/0.2,Q3>=4.3,3+(Q3-4.3)/0.2,Q3>=4,2+(Q3-4)/0.3,Q3>=3.8,1+(Q3-3.8)/0.2,TRUE(),0),1),"")) -> 5 | S3: =IF(R3="","",R3*R$9) -> 1.05 | T3: ='Quaterly Tables'!I20 -> 0.0405 | U3: =IFERROR(ROUND(ifs(T3="","",T3<=0.01,5,T3<=0.015,4+(0.015-T3)/0.005,T3<=0.02,3+(0.02-T3)/0.005,T3<=0.04,2+(0.04-T3)/0.02,T3<=0.06,1+(0.06-T3)/0.02,TRUE(),0),1),"") -> 2 | V3: =IF(U3="","",U3*U$9) -> 0.17 | W3: ='Quaterly Tables'!H31 -> 0.57 | X3: =IFERROR(ROUND(ifs(W3="","",W3<=1,5,W3<=1.5,4+(1.5-W3)/0.5,W3<=2,3+(2-W3)/0.5,W3<=5,2+(5-W3)/3,W3<=8,1+(8-W3)/3,TRUE(),0),1),"") -> 5 | Y3: =IF(X3="","",X3*X$9) -> 0.325 | Z3: ='Quaterly Tables'!E20 -> 4 | AA3: =IF(OR(NOT(ISNUMBER(Z3)),Z3=0),"",IFERROR(ROUND(ifs(Z3>=4.7,5,Z3>=4.5,4+(Z3-4.5)/0.2,Z3>=4.3,3+(Z3-4.3)/0.2,Z3>=4,2+(Z3-4)/0.3,Z3>=3.8,1+(Z3-3.8)/0.2,TRUE(),0),1),"")) -> 2 | AB3: =IF(AA3="","",AA3*AA$9) -> 0.13 | AC3: 92 | AD3: =IFERROR(ROUND(ifs(AC3="","",AC3>=94,5,AC3>=89,4+(AC3-89)/5,AC3>=83,3+(AC3-83)/6,AC3>=75,2+(AC3-75)/8,AC3>=70,1+(AC3-70)/5,TRUE(),0),1),"") -> 4.6 | AE3: =IF(AD3="","",AD3*AD$9) -> 0.483 | AF3: 90 | AG3: =IFERROR(ROUND(ifs(AF3="","",AF3>=94,5,AF3>=89,4+(AF3-89)/5,AF3>=83,3+(AF3-83)/6,AF3>=75,2+(AF3-75)/8,AF3>=70,1+(AF3-70)/5,TRUE(),0),1),"") -> 4.2 | AH3: =IF(AG3="","",AG3*AG$9) -> 0.231 | AI3: 0.89 | AJ3: =SUM(D3,G3,J3,M3,P3,S3,V3,Y3,AB3,AE3,AH3) -> 2.389 | AK3: =IF(AND(AJ3>=2.7,AI3>=87%),"Eligible","Not Eligible") -> Not Eligible | AL3: =IF(AK3<>"Eligible",0,IF(AJ3<3.7,0.5,IF(AJ3<4.7,0.75,1))) -> 0 | AM3: 10000 | AN3: =AM3*AL3 -> 0 | AO3: =AN3/4 -> 0
A4: Mosaic | B4: =100%+'Quaterly Tables'!I4 -> #DIV/0! | C4: =IFERROR(ROUND(ifs(B4="","",B4>=1.05,5,B4>=1.02,4+(B4-1.02)/0.03,B4>=0.99,3+(B4-0.99)/0.03,B4>=0.95,2+(B4-0.95)/0.04,B4>=0.9,1+(B4-0.9)/0.05,TRUE(),0),1),"") | D4: =IF(C4="","",C4*C$9) | E4: =100%+'Quaterly Tables'!F4 -> #DIV/0! | F4: =IFERROR(ROUND(ifs(E4="","",E4>=1.15,5,E4>=1.075,4+(E4-1.075)/0.075,E4>=1.05,3+(E4-1.05)/0.025,E4>=1,2+(E4-1)/0.05,E4>=0.95,1+(E4-0.95)/0.05,TRUE(),0),1),"") | G4: =IF(F4="","",F4*F$9) | H4: =100%+'Quaterly Tables'!V4 -> 1 | I4: =IFERROR(ROUND(ifs(H4="","",H4>=1.05,5,H4>=1.01,4+(H4-1.01)/0.04,H4>=0.95,3+(H4-0.95)/0.06,H4>=0.85,2+(H4-0.85)/0.1,H4>=0.75,1+(H4-0.75)/0.1,TRUE(),0),1),"") -> 3.8 | J4: =IF(I4="","",I4*I$9) -> 0.475 | K4: ='Quaterly Tables'!L4*100 -> 0 | L4: =IFERROR(ROUND(IFS(K4="","",K4>=3,0,K4>=2,1+(3-K4)/1,K4>=1,2+(2-K4)/1,K4>0,3+(1-K4)/1,K4>=-1,4+(0-K4)/1,TRUE,5),1),"") -> 4 | M4: =IF(L4="","",L4*L$9) -> 0.42 | N4: ='Quaterly Tables'!O4*100 -> 0 | O4: =IFERROR(ROUND(IFS(N4="","",N4>=3,0,N4>=2,1+(3-N4)/1,N4>=1,2+(2-N4)/1,N4>0,3+(1-N4)/1,N4>=-1,4+(0-N4)/1,TRUE,5),1),"") -> 4 | P4: =IF(O4="","",O4*O$9) -> 0.42 | Q4: ='Quaterly Tables'!E13 -> 3 | R4: =IF(OR(NOT(ISNUMBER(Q4)),Q4=0),"",IFERROR(ROUND(ifs(Q4>=4.7,5,Q4>=4.5,4+(Q4-4.5)/0.2,Q4>=4.3,3+(Q4-4.3)/0.2,Q4>=4,2+(Q4-4)/0.3,Q4>=3.8,1+(Q4-3.8)/0.2,TRUE(),0),1),"")) -> 0 | S4: =IF(R4="","",R4*R$9) -> 0 | T4: ='Quaterly Tables'!I23 -> 0.0315 | U4: =IFERROR(ROUND(ifs(T4="","",T4<=0.01,5,T4<=0.015,4+(0.015-T4)/0.005,T4<=0.02,3+(0.02-T4)/0.005,T4<=0.04,2+(0.04-T4)/0.02,T4<=0.06,1+(0.06-T4)/0.02,TRUE(),0),1),"") -> 2.4 | V4: =IF(U4="","",U4*U$9) -> 0.204 | W4: ='Quaterly Tables'!H34 -> 1.48 | X4: =IFERROR(ROUND(ifs(W4="","",W4<=1,5,W4<=1.5,4+(1.5-W4)/0.5,W4<=2,3+(2-W4)/0.5,W4<=5,2+(5-W4)/3,W4<=8,1+(8-W4)/3,TRUE(),0),1),"") -> 4 | Y4: =IF(X4="","",X4*X$9) -> 0.26 | Z4: ='Quaterly Tables'!E23 -> 4.4 | AA4: =IF(OR(NOT(ISNUMBER(Z4)),Z4=0),"",IFERROR(ROUND(ifs(Z4>=4.7,5,Z4>=4.5,4+(Z4-4.5)/0.2,Z4>=4.3,3+(Z4-4.3)/0.2,Z4>=4,2+(Z4-4)/0.3,Z4>=3.8,1+(Z4-3.8)/0.2,TRUE(),0),1),"")) -> 3.5 | AB4: =IF(AA4="","",AA4*AA$9) -> 0.2275 | AC4: 88 | AD4: =IFERROR(ROUND(ifs(AC4="","",AC4>=94,5,AC4>=89,4+(AC4-89)/5,AC4>=83,3+(AC4-83)/6,AC4>=75,2+(AC4-75)/8,AC4>=70,1+(AC4-70)/5,TRUE(),0),1),"") -> 3.8 | AE4: =IF(AD4="","",AD4*AD$9) -> 0.399 | AF4: 86 | AG4: =IFERROR(ROUND(ifs(AF4="","",AF4>=94,5,AF4>=89,4+(AF4-89)/5,AF4>=83,3+(AF4-83)/6,AF4>=75,2+(AF4-75)/8,AF4>=70,1+(AF4-70)/5,TRUE(),0),1),"") -> 3.5 | AH4: =IF(AG4="","",AG4*AG$9) -> 0.1925 | AI4: 0.87 | AJ4: =SUM(D4,G4,J4,M4,P4,S4,V4,Y4,AB4,AE4,AH4) -> 2.598 | AK4: =IF(AND(AJ4>=2.7,AI4>=87%),"Eligible","Not Eligible") -> Not Eligible | AL4: =IF(AK4<>"Eligible",0,IF(AJ4<3.7,0.5,IF(AJ4<4.7,0.75,1))) -> 0 | AM4: 10000 | AN4: =AM4*AL4 -> 0 | AO4: =AN4/4 -> 0
A5: MVT | B5: =100%+'Quaterly Tables'!I5 -> #DIV/0! | C5: =IFERROR(ROUND(ifs(B5="","",B5>=1.05,5,B5>=1.02,4+(B5-1.02)/0.03,B5>=0.99,3+(B5-0.99)/0.03,B5>=0.95,2+(B5-0.95)/0.04,B5>=0.9,1+(B5-0.9)/0.05,TRUE(),0),1),"") | D5: =IF(C5="","",C5*C$9) | E5: =100%+'Quaterly Tables'!F5 -> #DIV/0! | F5: =IFERROR(ROUND(ifs(E5="","",E5>=1.15,5,E5>=1.075,4+(E5-1.075)/0.075,E5>=1.05,3+(E5-1.05)/0.025,E5>=1,2+(E5-1)/0.05,E5>=0.95,1+(E5-0.95)/0.05,TRUE(),0),1),"") | G5: =IF(F5="","",F5*F$9) | H5: =100%+'Quaterly Tables'!V5 -> 1 | I5: =IFERROR(ROUND(ifs(H5="","",H5>=1.05,5,H5>=1.01,4+(H5-1.01)/0.04,H5>=0.95,3+(H5-0.95)/0.06,H5>=0.85,2+(H5-0.85)/0.1,H5>=0.75,1+(H5-0.75)/0.1,TRUE(),0),1),"") -> 3.8 | J5: =IF(I5="","",I5*I$9) -> 0.475 | K5: ='Quaterly Tables'!L5*100 -> 0 | L5: =IFERROR(ROUND(IFS(K5="","",K5>=3,0,K5>=2,1+(3-K5)/1,K5>=1,2+(2-K5)/1,K5>0,3+(1-K5)/1,K5>=-1,4+(0-K5)/1,TRUE,5),1),"") -> 4 | M5: =IF(L5="","",L5*L$9) -> 0.42 | N5: ='Quaterly Tables'!O5*100 -> 0 | O5: =IFERROR(ROUND(IFS(N5="","",N5>=3,0,N5>=2,1+(3-N5)/1,N5>=1,2+(2-N5)/1,N5>0,3+(1-N5)/1,N5>=-1,4+(0-N5)/1,TRUE,5),1),"") -> 4 | P5: =IF(O5="","",O5*O$9) -> 0.42 | Q5: ='Quaterly Tables'!E14 -> 4.33 | R5: =IF(OR(NOT(ISNUMBER(Q5)),Q5=0),"",IFERROR(ROUND(ifs(Q5>=4.7,5,Q5>=4.5,4+(Q5-4.5)/0.2,Q5>=4.3,3+(Q5-4.3)/0.2,Q5>=4,2+(Q5-4)/0.3,Q5>=3.8,1+(Q5-3.8)/0.2,TRUE(),0),1),"")) -> 3.2 | S5: =IF(R5="","",R5*R$9) -> 0.672 | T5: ='Quaterly Tables'!I21 -> 0.0264 | U5: =IFERROR(ROUND(ifs(T5="","",T5<=0.01,5,T5<=0.015,4+(0.015-T5)/0.005,T5<=0.02,3+(0.02-T5)/0.005,T5<=0.04,2+(0.04-T5)/0.02,T5<=0.06,1+(0.06-T5)/0.02,TRUE(),0),1),"") -> 2.7 | V5: =IF(U5="","",U5*U$9) -> 0.2295 | W5: ='Quaterly Tables'!H32 -> 0.59 | X5: =IFERROR(ROUND(ifs(W5="","",W5<=1,5,W5<=1.5,4+(1.5-W5)/0.5,W5<=2,3+(2-W5)/0.5,W5<=5,2+(5-W5)/3,W5<=8,1+(8-W5)/3,TRUE(),0),1),"") -> 5 | Y5: =IF(X5="","",X5*X$9) -> 0.325 | Z5: ='Quaterly Tables'!E21 -> 4.5 | AA5: =IF(OR(NOT(ISNUMBER(Z5)),Z5=0),"",IFERROR(ROUND(ifs(Z5>=4.7,5,Z5>=4.5,4+(Z5-4.5)/0.2,Z5>=4.3,3+(Z5-4.3)/0.2,Z5>=4,2+(Z5-4)/0.3,Z5>=3.8,1+(Z5-3.8)/0.2,TRUE(),0),1),"")) -> 4 | AB5: =IF(AA5="","",AA5*AA$9) -> 0.26 | AC5: 91 | AD5: =IFERROR(ROUND(ifs(AC5="","",AC5>=94,5,AC5>=89,4+(AC5-89)/5,AC5>=83,3+(AC5-83)/6,AC5>=75,2+(AC5-75)/8,AC5>=70,1+(AC5-70)/5,TRUE(),0),1),"") -> 4.4 | AE5: =IF(AD5="","",AD5*AD$9) -> 0.462 | AF5: 93 | AG5: =IFERROR(ROUND(ifs(AF5="","",AF5>=94,5,AF5>=89,4+(AF5-89)/5,AF5>=83,3+(AF5-83)/6,AF5>=75,2+(AF5-75)/8,AF5>=70,1+(AF5-70)/5,TRUE(),0),1),"") -> 4.8 | AH5: =IF(AG5="","",AG5*AG$9) -> 0.264 | AI5: 0.93 | AJ5: =SUM(D5,G5,J5,M5,P5,S5,V5,Y5,AB5,AE5,AH5) -> 3.5275 | AK5: =IF(AND(AJ5>=2.7,AI5>=87%),"Eligible","Not Eligible") -> Eligible | AL5: =IF(AK5<>"Eligible",0,IF(AJ5<3.7,0.5,IF(AJ5<4.7,0.75,1))) -> 0.5 | AM5: 10000 | AN5: =AM5*AL5 -> 5000 | AO5: =AN5/4 -> 1250
A6: National Landing | B6: =100%+'Quaterly Tables'!I6 -> #DIV/0! | C6: =IFERROR(ROUND(ifs(B6="","",B6>=1.05,5,B6>=1.02,4+(B6-1.02)/0.03,B6>=0.99,3+(B6-0.99)/0.03,B6>=0.95,2+(B6-0.95)/0.04,B6>=0.9,1+(B6-0.9)/0.05,TRUE(),0),1),"") | D6: =IF(C6="","",C6*C$9) | E6: =100%+'Quaterly Tables'!F6 -> #DIV/0! | F6: =IFERROR(ROUND(ifs(E6="","",E6>=1.15,5,E6>=1.075,4+(E6-1.075)/0.075,E6>=1.05,3+(E6-1.05)/0.025,E6>=1,2+(E6-1)/0.05,E6>=0.95,1+(E6-0.95)/0.05,TRUE(),0),1),"") | G6: =IF(F6="","",F6*F$9) | H6: =100%+'Quaterly Tables'!V6 -> 1 | I6: =IFERROR(ROUND(ifs(H6="","",H6>=1.05,5,H6>=1.01,4+(H6-1.01)/0.04,H6>=0.95,3+(H6-0.95)/0.06,H6>=0.85,2+(H6-0.85)/0.1,H6>=0.75,1+(H6-0.75)/0.1,TRUE(),0),1),"") -> 3.8 | J6: =IF(I6="","",I6*I$9) -> 0.475 | K6: ='Quaterly Tables'!L6*100 -> 0 | L6: =IFERROR(ROUND(IFS(K6="","",K6>=3,0,K6>=2,1+(3-K6)/1,K6>=1,2+(2-K6)/1,K6>0,3+(1-K6)/1,K6>=-1,4+(0-K6)/1,TRUE,5),1),"") -> 4 | M6: =IF(L6="","",L6*L$9) -> 0.42 | N6: ='Quaterly Tables'!O6*100 -> 0 | O6: =IFERROR(ROUND(IFS(N6="","",N6>=3,0,N6>=2,1+(3-N6)/1,N6>=1,2+(2-N6)/1,N6>0,3+(1-N6)/1,N6>=-1,4+(0-N6)/1,TRUE,5),1),"") -> 4 | P6: =IF(O6="","",O6*O$9) -> 0.42 | Q6: ='Quaterly Tables'!E15 -> 4.67 | R6: =IF(OR(NOT(ISNUMBER(Q6)),Q6=0),"",IFERROR(ROUND(ifs(Q6>=4.7,5,Q6>=4.5,4+(Q6-4.5)/0.2,Q6>=4.3,3+(Q6-4.3)/0.2,Q6>=4,2+(Q6-4)/0.3,Q6>=3.8,1+(Q6-3.8)/0.2,TRUE(),0),1),"")) -> 4.9 | S6: =IF(R6="","",R6*R$9) -> 1.029 | T6: ='Quaterly Tables'!I22 -> 0.0315 | U6: =IFERROR(ROUND(ifs(T6="","",T6<=0.01,5,T6<=0.015,4+(0.015-T6)/0.005,T6<=0.02,3+(0.02-T6)/0.005,T6<=0.04,2+(0.04-T6)/0.02,T6<=0.06,1+(0.06-T6)/0.02,TRUE(),0),1),"") -> 2.4 | V6: =IF(U6="","",U6*U$9) -> 0.204 | W6: ='Quaterly Tables'!H33 -> 1.14 | X6: =IFERROR(ROUND(ifs(W6="","",W6<=1,5,W6<=1.5,4+(1.5-W6)/0.5,W6<=2,3+(2-W6)/0.5,W6<=5,2+(5-W6)/3,W6<=8,1+(8-W6)/3,TRUE(),0),1),"") -> 4.7 | Y6: =IF(X6="","",X6*X$9) -> 0.3055 | Z6: ='Quaterly Tables'!E22 -> 4.3 | AA6: =IF(OR(NOT(ISNUMBER(Z6)),Z6=0),"",IFERROR(ROUND(ifs(Z6>=4.7,5,Z6>=4.5,4+(Z6-4.5)/0.2,Z6>=4.3,3+(Z6-4.3)/0.2,Z6>=4,2+(Z6-4)/0.3,Z6>=3.8,1+(Z6-3.8)/0.2,TRUE(),0),1),"")) -> 3 | AB6: =IF(AA6="","",AA6*AA$9) -> 0.195 | AC6: 78 | AD6: =IFERROR(ROUND(ifs(AC6="","",AC6>=94,5,AC6>=89,4+(AC6-89)/5,AC6>=83,3+(AC6-83)/6,AC6>=75,2+(AC6-75)/8,AC6>=70,1+(AC6-70)/5,TRUE(),0),1),"") -> 2.4 | AE6: =IF(AD6="","",AD6*AD$9) -> 0.252 | AF6: 75 | AG6: =IFERROR(ROUND(ifs(AF6="","",AF6>=94,5,AF6>=89,4+(AF6-89)/5,AF6>=83,3+(AF6-83)/6,AF6>=75,2+(AF6-75)/8,AF6>=70,1+(AF6-70)/5,TRUE(),0),1),"") -> 2 | AH6: =IF(AG6="","",AG6*AG$9) -> 0.11 | AI6: 0.88 | AJ6: =SUM(D6,G6,J6,M6,P6,S6,V6,Y6,AB6,AE6,AH6) -> 3.4105 | AK6: =IF(AND(AJ6>=2.7,AI6>=87%),"Eligible","Not Eligible") -> Eligible | AL6: =IF(AK6<>"Eligible",0,IF(AJ6<3.7,0.5,IF(AJ6<4.7,0.75,1))) -> 0.5 | AM6: 10000 | AN6: =AM6*AL6 -> 5000 | AO6: =AN6/4 -> 1250
A7: Rockville | B7: =100%+'Quaterly Tables'!I7 -> #DIV/0! | C7: =IFERROR(ROUND(ifs(B7="","",B7>=1.05,5,B7>=1.02,4+(B7-1.02)/0.03,B7>=0.99,3+(B7-0.99)/0.03,B7>=0.95,2+(B7-0.95)/0.04,B7>=0.9,1+(B7-0.9)/0.05,TRUE(),0),1),"") | D7: =IF(C7="","",C7*C$9) | E7: =100%+'Quaterly Tables'!F7 -> #DIV/0! | F7: =IFERROR(ROUND(ifs(E7="","",E7>=1.15,5,E7>=1.075,4+(E7-1.075)/0.075,E7>=1.05,3+(E7-1.05)/0.025,E7>=1,2+(E7-1)/0.05,E7>=0.95,1+(E7-0.95)/0.05,TRUE(),0),1),"") | G7: =IF(F7="","",F7*F$9) | H7: =100%+'Quaterly Tables'!V7 -> 1 | I7: =IFERROR(ROUND(ifs(H7="","",H7>=1.05,5,H7>=1.01,4+(H7-1.01)/0.04,H7>=0.95,3+(H7-0.95)/0.06,H7>=0.85,2+(H7-0.85)/0.1,H7>=0.75,1+(H7-0.75)/0.1,TRUE(),0),1),"") -> 3.8 | J7: =IF(I7="","",I7*I$9) -> 0.475 | K7: ='Quaterly Tables'!L7*100 -> 0 | L7: =IFERROR(ROUND(IFS(K7="","",K7>=3,0,K7>=2,1+(3-K7)/1,K7>=1,2+(2-K7)/1,K7>0,3+(1-K7)/1,K7>=-1,4+(0-K7)/1,TRUE,5),1),"") -> 4 | M7: =IF(L7="","",L7*L$9) -> 0.42 | N7: ='Quaterly Tables'!O7*100 -> 0 | O7: =IFERROR(ROUND(IFS(N7="","",N7>=3,0,N7>=2,1+(3-N7)/1,N7>=1,2+(2-N7)/1,N7>0,3+(1-N7)/1,N7>=-1,4+(0-N7)/1,TRUE,5),1),"") -> 4 | P7: =IF(O7="","",O7*O$9) -> 0.42 | Q7: ='Quaterly Tables'!E16 -> 4.47 | R7: =IF(OR(NOT(ISNUMBER(Q7)),Q7=0),"",IFERROR(ROUND(ifs(Q7>=4.7,5,Q7>=4.5,4+(Q7-4.5)/0.2,Q7>=4.3,3+(Q7-4.3)/0.2,Q7>=4,2+(Q7-4)/0.3,Q7>=3.8,1+(Q7-3.8)/0.2,TRUE(),0),1),"")) -> 3.9 | S7: =IF(R7="","",R7*R$9) -> 0.819 | T7: ='Quaterly Tables'!I24 -> 0.045 | U7: =IFERROR(ROUND(ifs(T7="","",T7<=0.01,5,T7<=0.015,4+(0.015-T7)/0.005,T7<=0.02,3+(0.02-T7)/0.005,T7<=0.04,2+(0.04-T7)/0.02,T7<=0.06,1+(0.06-T7)/0.02,TRUE(),0),1),"") -> 1.8 | V7: =IF(U7="","",U7*U$9) -> 0.153 | W7: ='Quaterly Tables'!H30 -> 2.03 | X7: =IFERROR(ROUND(ifs(W7="","",W7<=1,5,W7<=1.5,4+(1.5-W7)/0.5,W7<=2,3+(2-W7)/0.5,W7<=5,2+(5-W7)/3,W7<=8,1+(8-W7)/3,TRUE(),0),1),"") -> 3 | Y7: =IF(X7="","",X7*X$9) -> 0.195 | Z7: ='Quaterly Tables'!E24 -> 4.3 | AA7: =IF(OR(NOT(ISNUMBER(Z7)),Z7=0),"",IFERROR(ROUND(ifs(Z7>=4.7,5,Z7>=4.5,4+(Z7-4.5)/0.2,Z7>=4.3,3+(Z7-4.3)/0.2,Z7>=4,2+(Z7-4)/0.3,Z7>=3.8,1+(Z7-3.8)/0.2,TRUE(),0),1),"")) -> 3 | AB7: =IF(AA7="","",AA7*AA$9) -> 0.195 | AC7: 77 | AD7: =IFERROR(ROUND(ifs(AC7="","",AC7>=94,5,AC7>=89,4+(AC7-89)/5,AC7>=83,3+(AC7-83)/6,AC7>=75,2+(AC7-75)/8,AC7>=70,1+(AC7-70)/5,TRUE(),0),1),"") -> 2.3 | AE7: =IF(AD7="","",AD7*AD$9) -> 0.2415 | AF7: 74 | AG7: =IFERROR(ROUND(ifs(AF7="","",AF7>=94,5,AF7>=89,4+(AF7-89)/5,AF7>=83,3+(AF7-83)/6,AF7>=75,2+(AF7-75)/8,AF7>=70,1+(AF7-70)/5,TRUE(),0),1),"") -> 1.8 | AH7: =IF(AG7="","",AG7*AG$9) -> 0.099 | AI7: 0.78 | AJ7: =SUM(D7,G7,J7,M7,P7,S7,V7,Y7,AB7,AE7,AH7) -> 3.0175 | AK7: =IF(AND(AJ7>=2.7,AI7>=87%),"Eligible","Not Eligible") -> Not Eligible | AL7: =IF(AK7<>"Eligible",0,IF(AJ7<3.7,0.5,IF(AJ7<4.7,0.75,1))) -> 0 | AM7: 10000 | AN7: =AM7*AL7 -> 0 | AO7: =AN7/4 -> 0
A8: All Stores | B8: =100%+'Quaterly Tables'!I8 -> #DIV/0! | C8: =IFERROR(ROUND(ifs(B8="","",B8>=1.05,5,B8>=1.02,4+(B8-1.02)/0.03,B8>=0.99,3+(B8-0.99)/0.03,B8>=0.95,2+(B8-0.95)/0.04,B8>=0.9,1+(B8-0.9)/0.05,TRUE(),0),1),"") | D8: =IF(C8="","",C8*C$9) | E8: =100%+'Quaterly Tables'!F8 -> #DIV/0! | F8: =IFERROR(ROUND(ifs(E8="","",E8>=1.15,5,E8>=1.075,4+(E8-1.075)/0.075,E8>=1.05,3+(E8-1.05)/0.025,E8>=1,2+(E8-1)/0.05,E8>=0.95,1+(E8-0.95)/0.05,TRUE(),0),1),"") | G8: =IF(F8="","",F8*F$9) | H8: =100%+'Quaterly Tables'!V8 -> 1 | I8: =IFERROR(ROUND(ifs(H8="","",H8>=1.05,5,H8>=1.01,4+(H8-1.01)/0.04,H8>=0.95,3+(H8-0.95)/0.06,H8>=0.85,2+(H8-0.85)/0.1,H8>=0.75,1+(H8-0.75)/0.1,TRUE(),0),1),"") -> 3.8 | J8: =IF(I8="","",I8*I$9) -> 0.475 | K8: ='Quaterly Tables'!L8*100 -> 0 | L8: =IFERROR(ROUND(IFS(K8="","",K8>=3,0,K8>=2,1+(3-K8)/1,K8>=1,2+(2-K8)/1,K8>0,3+(1-K8)/1,K8>=-1,4+(0-K8)/1,TRUE,5),1),"") -> 4 | M8: =IF(L8="","",L8*L$9) -> 0.42 | N8: ='Quaterly Tables'!O8*100 -> 0 | O8: =IFERROR(ROUND(IFS(N8="","",N8>=3,0,N8>=2,1+(3-N8)/1,N8>=1,2+(2-N8)/1,N8>0,3+(1-N8)/1,N8>=-1,4+(0-N8)/1,TRUE,5),1),"") -> 4 | P8: =IF(O8="","",O8*O$9) -> 0.42 | Q8: ='Quaterly Tables'!E17 -> 4.294 | R8: =IF(OR(NOT(ISNUMBER(Q8)),Q8=0),"",IFERROR(ROUND(ifs(Q8>=4.7,5,Q8>=4.5,4+(Q8-4.5)/0.2,Q8>=4.3,3+(Q8-4.3)/0.2,Q8>=4,2+(Q8-4)/0.3,Q8>=3.8,1+(Q8-3.8)/0.2,TRUE(),0),1),"")) -> 3 | S8: =IF(R8="","",R8*R$9) -> 0.63 | T8: ='Quaterly Tables'!I25 -> 0.03498 | U8: =IFERROR(ROUND(ifs(T8="","",T8<=0.01,5,T8<=0.015,4+(0.015-T8)/0.005,T8<=0.02,3+(0.02-T8)/0.005,T8<=0.04,2+(0.04-T8)/0.02,T8<=0.06,1+(0.06-T8)/0.02,TRUE(),0),1),"") -> 2.3 | V8: =IF(U8="","",U8*U$9) -> 0.1955 | W8: ='Quaterly Tables'!H35 -> 1.19 | X8: =IFERROR(ROUND(ifs(W8="","",W8<=1,5,W8<=1.5,4+(1.5-W8)/0.5,W8<=2,3+(2-W8)/0.5,W8<=5,2+(5-W8)/3,W8<=8,1+(8-W8)/3,TRUE(),0),1),"") -> 4.6 | Y8: =IF(X8="","",X8*X$9) -> 0.299 | Z8: ='Quaterly Tables'!E25 -> 4.3 | AA8: =IF(OR(NOT(ISNUMBER(Z8)),Z8=0),"",IFERROR(ROUND(ifs(Z8>=4.7,5,Z8>=4.5,4+(Z8-4.5)/0.2,Z8>=4.3,3+(Z8-4.3)/0.2,Z8>=4,2+(Z8-4)/0.3,Z8>=3.8,1+(Z8-3.8)/0.2,TRUE(),0),1),"")) -> 3 | AB8: =IF(AA8="","",AA8*AA$9) -> 0.195 | AC8: =AVERAGE(AC3:AC7) -> 85.2 | AD8: =IFERROR(ROUND(ifs(AC8="","",AC8>=94,5,AC8>=89,4+(AC8-89)/5,AC8>=83,3+(AC8-83)/6,AC8>=75,2+(AC8-75)/8,AC8>=70,1+(AC8-70)/5,TRUE(),0),1),"") -> 3.4 | AE8: =IF(AD8="","",AD8*AD$9) -> 0.357 | AF8: =AVERAGE(AF3:AF7) -> 83.6 | AG8: =IFERROR(ROUND(ifs(AF8="","",AF8>=94,5,AF8>=89,4+(AF8-89)/5,AF8>=83,3+(AF8-83)/6,AF8>=75,2+(AF8-75)/8,AF8>=70,1+(AF8-70)/5,TRUE(),0),1),"") -> 3.1 | AH8: =IF(AG8="","",AG8*AG$9) -> 0.1705 | AI8: =AVERAGE(AI3:AI7) -> 0.87 | AJ8: =SUM(D8,G8,J8,M8,P8,S8,V8,Y8,AB8,AE8,AH8) -> 3.162 | AM8: =SUM(AM3:AM7) -> 50000 | AN8: =SUM(AN3:AN7) -> 10000 | AO8: =AN8/4 -> 2500
A9: Weight | C9: ='Scoring Matrix'!C72 -> 0.04 | F9: ='Scoring Matrix'!C74 -> 0.04 | I9: ='Scoring Matrix'!C76 -> 0.125 | L9: ='Scoring Matrix'!C78 -> 0.105 | O9: ='Scoring Matrix'!C80 -> 0.105 | R9: ='Scoring Matrix'!C82 -> 0.21 | U9: ='Scoring Matrix'!C84 -> 0.085 | X9: ='Scoring Matrix'!C86 -> 0.065 | AA9: ='Scoring Matrix'!C88 -> 0.065 | AD9: ='Scoring Matrix'!C90 -> 0.105 | AG9: ='Scoring Matrix'!C92 -> 0.055

Sheet Quaterly Area Leader Dashboard
A1: Restaurant | B1: Composite Score | C1: Contributor Band | D1: Sales vs Budget (%) | E1: Sales vs Prior Year (%) | F1: EBITDA % vs Budget | G1: Labor vs Budget Variance (pts) | H1: COGS vs Budget Variance (pts) | I1: Prime Cost Var (avg pts) | J1: In-Store Rating | K1: 3P Rating | L1: 3P Error % | M1: Avoidable Wait (mins) | N1: Full Audit Score | O1: Culinary Audit Score | P1: Training Completion % (Gate) | Q1: Eligible? | R1: Payout % | S1: Quarterly Bonus Earned
A2: Ballpark | B2: ='Quaterly Store Scorecards '!AJ3 -> 2.389 | C2: =IFS(B2<1.7,"Non", B2<2.7,"Low", B2<3.7,"Contributor", B2<4.7,"High", TRUE,"STAR") -> Low | D2: ='Quaterly Store Scorecards '!B3 -> #REF! | E2: ='Quaterly Store Scorecards '!E3 -> #REF! | F2: ='Quaterly Store Scorecards '!H3 -> #REF! | G2: ='Quaterly Store Scorecards '!K3 -> #REF! | H2: ='Quaterly Store Scorecards '!N3 -> #REF! | I2: =AVERAGE('Quaterly Store Scorecards '!K3,'Quaterly Store Scorecards '!N3) -> #REF! | J2: ='Quaterly Store Scorecards '!Q3 -> 5 | K2: ='Quaterly Store Scorecards '!Z3 -> 4 | L2: ='Quaterly Store Scorecards '!T3 -> 0.0405 | M2: ='Quaterly Store Scorecards '!W3 -> 0.57 | N2: ='Quaterly Store Scorecards '!AC3 -> 92 | O2: ='Quaterly Store Scorecards '!AF3 -> 90 | P2: ='Quaterly Store Scorecards '!AI3 -> 0.89 | Q2: ='Quaterly Store Scorecards '!AK3 -> Not Eligible | R2: ='Quaterly Store Scorecards '!AL3 -> 0 | S2: ='Quaterly Store Scorecards '!AO3 -> 0
A3: Mosaic | B3: ='Quaterly Store Scorecards '!AJ4 -> 2.598 | C3: =IFS(B3<1.7,"Non", B3<2.7,"Low", B3<3.7,"Contributor", B3<4.7,"High", TRUE,"STAR") -> Low | D3: ='Quaterly Store Scorecards '!B4 -> #DIV/0! | E3: ='Quaterly Store Scorecards '!E4 -> #DIV/0! | F3: ='Quaterly Store Scorecards '!H4 -> 1 | G3: ='Quaterly Store Scorecards '!K4 -> 0 | H3: ='Quaterly Store Scorecards '!N4 -> 0 | I3: =AVERAGE('Quaterly Store Scorecards '!K4,'Quaterly Store Scorecards '!N4) -> 0 | J3: ='Quaterly Store Scorecards '!Q4 -> 3 | K3: ='Quaterly Store Scorecards '!Z4 -> 4.4 | L3: ='Quaterly Store Scorecards '!T4 -> 0.0315 | M3: ='Quaterly Store Scorecards '!W4 -> 1.48 | N3: ='Quaterly Store Scorecards '!AC4 -> 88 | O3: ='Quaterly Store Scorecards '!AF4 -> 86 | P3: ='Quaterly Store Scorecards '!AI4 -> 0.87 | Q3: ='Quaterly Store Scorecards '!AK4 -> Not Eligible | R3: ='Quaterly Store Scorecards '!AL4 -> 0 | S3: ='Quaterly Store Scorecards '!AO4 -> 0
A4: MVT | B4: ='Quaterly Store Scorecards '!AJ5 -> 3.5275 | C4: =IFS(B4<1.7,"Non", B4<2.7,"Low", B4<3.7,"Contributor", B4<4.7,"High", TRUE,"STAR") -> Contributor | D4: ='Quaterly Store Scorecards '!B5 -> #DIV/0! | E4: ='Quaterly Store Scorecards '!E5 -> #DIV/0! | F4: ='Quaterly Store Scorecards '!H5 -> 1 | G4: ='Quaterly Store Scorecards '!K5 -> 0 | H4: ='Quaterly Store Scorecards '!N5 -> 0 | I4: =AVERAGE('Quaterly Store Scorecards '!K5,'Quaterly Store Scorecards '!N5) -> 0 | J4: ='Quaterly Store Scorecards '!Q5 -> 4.33 | K4: ='Quaterly Store Scorecards '!Z5 -> 4.5 | L4: ='Quaterly Store Scorecards '!T5 -> 0.0264 | M4: ='Quaterly Store Scorecards '!W5 -> 0.59 | N4: ='Quaterly Store Scorecards '!AC5 -> 91 | O4: ='Quaterly Store Scorecards '!AF5 -> 93 | P4: ='Quaterly Store Scorecards '!AI5 -> 0.93 | Q4: ='Quaterly Store Scorecards '!AK5 -> Eligible | R4: ='Quaterly Store Scorecards '!AL5 -> 0.5 | S4: ='Quaterly Store Scorecards '!AO5 -> 1250
A5: National Landing | B5: ='Quaterly Store Scorecards '!AJ6 -> 3.4105 | C5: =IFS(B5<1.7,"Non", B5<2.7,"Low", B5<3.7,"Contributor", B5<4.7,"High", TRUE,"STAR") -> Contributor | D5: ='Quaterly Store Scorecards '!B6 -> #DIV/0! | E5: ='Quaterly Store Scorecards '!E6 -> #DIV/0! | F5: ='Quaterly Store Scorecards '!H6 -> 1 | G5: ='Quaterly Store Scorecards '!K6 -> 0 | H5: ='Quaterly Store Scorecards '!N6 -> 0 | I5: =AVERAGE('Quaterly Store Scorecards '!K6,'Quaterly Store Scorecards '!N6) -> 0 | J5: ='Quaterly Store Scorecards '!Q6 -> 4.67 | K5: ='Quaterly Store Scorecards '!Z6 -> 4.3 | L5: ='Quaterly Store Scorecards '!T6 -> 0.0315 | M5: ='Quaterly Store Scorecards '!W6 -> 1.14 | N5: ='Quaterly Store Scorecards '!AC6 -> 78 | O5: ='Quaterly Store Scorecards '!AF6 -> 75 | P5: ='Quaterly Store Scorecards '!AI6 -> 0.88 | Q5: ='Quaterly Store Scorecards '!AK6 -> Eligible | R5: ='Quaterly Store Scorecards '!AL6 -> 0.5 | S5: ='Quaterly Store Scorecards '!AO6 -> 1250
A6: Rockville | B6: ='Quaterly Store Scorecards '!AJ7 -> 3.0175 | C6: =IFS(B6<1.7,"Non", B6<2.7,"Low", B6<3.7,"Contributor", B6<4.7,"High", TRUE,"STAR") -> Contributor | D6: ='Quaterly Store Scorecards '!B7 -> #DIV/0! | E6: ='Quaterly Store Scorecards '!E7 -> #DIV/0! | F6: ='Quaterly Store Scorecards '!H7 -> 1 | G6: ='Quaterly Store Scorecards '!K7 -> 0 | H6: ='Quaterly Store Scorecards '!N7 -> 0 | I6: =AVERAGE('Quaterly Store Scorecards '!K7,'Quaterly Store Scorecards '!N7) -> 0 | J6: ='Quaterly Store Scorecards '!Q7 -> 4.47 | K6: ='Quaterly Store Scorecards '!Z7 -> 4.3 | L6: ='Quaterly Store Scorecards '!T7 -> 0.045 | M6: ='Quaterly Store Scorecards '!W7 -> 2.03 | N6: ='Quaterly Store Scorecards '!AC7 -> 77 | O6: ='Quaterly Store Scorecards '!AF7 -> 74 | P6: ='Quaterly Store Scorecards '!AI7 -> 0.78 | Q6: ='Quaterly Store Scorecards '!AK7 -> Not Eligible | R6: ='Quaterly Store Scorecards '!AL7 -> 0 | S6: ='Quaterly Store Scorecards '!AO7 -> 0
A7: All Stores | B7: ='Quaterly Store Scorecards '!AJ8 -> 3.162 | C7: =IFS(B7<1.7,"Non", B7<2.7,"Low", B7<3.7,"Contributor", B7<4.7,"High", TRUE,"STAR") -> Contributor | D7: ='Quaterly Store Scorecards '!B8 -> #DIV/0! | E7: ='Quaterly Store Scorecards '!E8 -> #DIV/0! | F7: ='Quaterly Store Scorecards '!H8 -> 1 | G7: ='Quaterly Store Scorecards '!K8 -> 0 | H7: ='Quaterly Store Scorecards '!N8 -> 0 | I7: =AVERAGE('Quaterly Store Scorecards '!K8,'Quaterly Store Scorecards '!N8) -> 0 | J7: ='Quaterly Store Scorecards '!Q8 -> 4.294 | K7: ='Quaterly Store Scorecards '!Z8 -> 4.3 | L7: ='Quaterly Store Scorecards '!T8 -> 0.03498 | M7: ='Quaterly Store Scorecards '!W8 -> 1.19 | N7: ='Quaterly Store Scorecards '!AC8 -> 85.2 | O7: ='Quaterly Store Scorecards '!AF8 -> 83.6 | P7: ='Quaterly Store Scorecards '!AI8 -> 0.87 | Q7: ='Quaterly Store Scorecards '!AK8 | R7: ='Quaterly Store Scorecards '!AL8 | S7: ='Quaterly Store Scorecards '!AO8 -> 2500

Sheet Derived Tables>>>

Sheet Weekly Tables
B2: =IFERROR(__xludf.DUMMYFUNCTION("IMPORTRANGE(""https://docs.google.com/spreadsheets/d/1rvSw8TokJxxMPNo9zCeN0TVGCwqWJYqsUgV1Y381wpc/edit?gid=1529235844#gid=1529235844"",""Weekly Flash Report!A31:Q31"")"),"Location") -> Location | C2: =IFERROR(__xludf.DUMMYFUNCTION("""COMPUTED_VALUE"""),"Sales") -> Sales | D2: =IFERROR(__xludf.DUMMYFUNCTION("""COMPUTED_VALUE"""),"Same Week LY") -> Same Week LY | E2: =IFERROR(__xludf.DUMMYFUNCTION("""COMPUTED_VALUE"""),"Dollar Change") -> Dollar Change | F2: =IFERROR(__xludf.DUMMYFUNCTION("""COMPUTED_VALUE"""),"Percent Change") -> Percent Change | G2: =IFERROR(__xludf.DUMMYFUNCTION("""COMPUTED_VALUE"""),"Weekly Budget") -> Weekly Budget | H2: =IFERROR(__xludf.DUMMYFUNCTION("""COMPUTED_VALUE"""),"Var to Bud +/-") -> Var to Bud +/- | I2: =IFERROR(__xludf.DUMMYFUNCTION("""COMPUTED_VALUE"""),"Var to Bud") -> Var to Bud | J2: =IFERROR(__xludf.DUMMYFUNCTION("""COMPUTED_VALUE"""),"Total Labor ") -> Total Labor | K2: =IFERROR(__xludf.DUMMYFUNCTION("""COMPUTED_VALUE"""),"Bud Labor") -> Bud Labor | L2: =IFERROR(__xludf.DUMMYFUNCTION("""COMPUTED_VALUE"""),"Var Lbr to Bud") -> Var Lbr to Bud | M2: =IFERROR(__xludf.DUMMYFUNCTION("""COMPUTED_VALUE"""),"Total COGS") -> Total COGS | N2: =IFERROR(__xludf.DUMMYFUNCTION("""COMPUTED_VALUE"""),"Bud COGS") -> Bud COGS | O2: =IFERROR(__xludf.DUMMYFUNCTION("""COMPUTED_VALUE"""),"Var COGS to Bud") -> Var COGS to Bud | P2: =IFERROR(__xludf.DUMMYFUNCTION("""COMPUTED_VALUE"""),"Total PC ") -> Total PC | Q2: =IFERROR(__xludf.DUMMYFUNCTION("""COMPUTED_VALUE"""),"Bud PC ") -> Bud PC | R2: =IFERROR(__xludf.DUMMYFUNCTION("""COMPUTED_VALUE"""),"Var PC to Bud") -> Var PC to Bud
B3: =IFERROR(__xludf.DUMMYFUNCTION("IMPORTRANGE(""https://docs.google.com/spreadsheets/d/1rvSw8TokJxxMPNo9zCeN0TVGCwqWJYqsUgV1Y381wpc/edit?gid=1529235844#gid=1529235844"",""Weekly Flash Report!A33:Q37"")"),"Mosaic") -> Mosaic | C3: =IFERROR(__xludf.DUMMYFUNCTION("""COMPUTED_VALUE"""),26903.0) -> 26903 | D3: =IFERROR(__xludf.DUMMYFUNCTION("""COMPUTED_VALUE"""),24535.0) -> 24535 | E3: =IFERROR(__xludf.DUMMYFUNCTION("""COMPUTED_VALUE"""),2368.0) -> 2368 | F3: =IFERROR(__xludf.DUMMYFUNCTION("""COMPUTED_VALUE"""),0.09651518239250051) -> 0.096515182 | G3: =IFERROR(__xludf.DUMMYFUNCTION("""COMPUTED_VALUE"""),28417.46) -> 28417.46 | H3: =IFERROR(__xludf.DUMMYFUNCTION("""COMPUTED_VALUE"""),-1514.4599999999991) -> -1514.46 | I3: =IFERROR(__xludf.DUMMYFUNCTION("""COMPUTED_VALUE"""),-0.05329329222245757) -> -0.053293292 | J3: =IFERROR(__xludf.DUMMYFUNCTION("""COMPUTED_VALUE"""),0.231) -> 0.231 | K3: =IFERROR(__xludf.DUMMYFUNCTION("""COMPUTED_VALUE"""),0.258) -> 0.258 | L3: =IFERROR(__xludf.DUMMYFUNCTION("""COMPUTED_VALUE"""),-0.026999999999999996) -> -0.027 | M3: =IFERROR(__xludf.DUMMYFUNCTION("""COMPUTED_VALUE"""),0.233) -> 0.233 | N3: =IFERROR(__xludf.DUMMYFUNCTION("""COMPUTED_VALUE"""),0.267) -> 0.267 | O3: =IFERROR(__xludf.DUMMYFUNCTION("""COMPUTED_VALUE"""),-0.034) -> -0.034 | P3: =IFERROR(__xludf.DUMMYFUNCTION("""COMPUTED_VALUE"""),0.464) -> 0.464 | Q3: =IFERROR(__xludf.DUMMYFUNCTION("""COMPUTED_VALUE"""),0.525) -> 0.525 | R3: =IFERROR(__xludf.DUMMYFUNCTION("""COMPUTED_VALUE"""),-0.061) -> -0.061
B4: =IFERROR(__xludf.DUMMYFUNCTION("""COMPUTED_VALUE"""),"MVT") -> MVT | C4: =IFERROR(__xludf.DUMMYFUNCTION("""COMPUTED_VALUE"""),42457.0) -> 42457 | D4: =IFERROR(__xludf.DUMMYFUNCTION("""COMPUTED_VALUE"""),30853.0) -> 30853 | E4: =IFERROR(__xludf.DUMMYFUNCTION("""COMPUTED_VALUE"""),11604.0) -> 11604 | F4: =IFERROR(__xludf.DUMMYFUNCTION("""COMPUTED_VALUE"""),0.3761060512754027) -> 0.37610605 | G4: =IFERROR(__xludf.DUMMYFUNCTION("""COMPUTED_VALUE"""),41662.65) -> 41662.65 | H4: =IFERROR(__xludf.DUMMYFUNCTION("""COMPUTED_VALUE"""),794.3499999999985) -> 794.35 | I4: =IFERROR(__xludf.DUMMYFUNCTION("""COMPUTED_VALUE"""),0.019066237985341752) -> 0.019066238 | J4: =IFERROR(__xludf.DUMMYFUNCTION("""COMPUTED_VALUE"""),0.273) -> 0.273 | K4: =IFERROR(__xludf.DUMMYFUNCTION("""COMPUTED_VALUE"""),0.249) -> 0.249 | L4: =IFERROR(__xludf.DUMMYFUNCTION("""COMPUTED_VALUE"""),0.02400000000000002) -> 0.024 | M4: =IFERROR(__xludf.DUMMYFUNCTION("""COMPUTED_VALUE"""),0.265) -> 0.265 | N4: =IFERROR(__xludf.DUMMYFUNCTION("""COMPUTED_VALUE"""),0.254) -> 0.254 | O4: =IFERROR(__xludf.DUMMYFUNCTION("""COMPUTED_VALUE"""),0.01100000000000001) -> 0.011 | P4: =IFERROR(__xludf.DUMMYFUNCTION("""COMPUTED_VALUE"""),0.538) -> 0.538 | Q4: =IFERROR(__xludf.DUMMYFUNCTION("""COMPUTED_VALUE"""),0.503) -> 0.503 | R4: =IFERROR(__xludf.DUMMYFUNCTION("""COMPUTED_VALUE"""),0.03500000000000003) -> 0.035
B5: =IFERROR(__xludf.DUMMYFUNCTION("""COMPUTED_VALUE"""),"National Landing") -> National Landing | C5: =IFERROR(__xludf.DUMMYFUNCTION("""COMPUTED_VALUE"""),27793.0) -> 27793 | D5: =IFERROR(__xludf.DUMMYFUNCTION("""COMPUTED_VALUE"""),19455.0) -> 19455 | E5: =IFERROR(__xludf.DUMMYFUNCTION("""COMPUTED_VALUE"""),8338.0) -> 8338 | F5: =IFERROR(__xludf.DUMMYFUNCTION("""COMPUTED_VALUE"""),0.4285787715240298) -> 0.42857877 | G5: =IFERROR(__xludf.DUMMYFUNCTION("""COMPUTED_VALUE"""),22832.71) -> 22832.71 | H5: =IFERROR(__xludf.DUMMYFUNCTION("""COMPUTED_VALUE"""),4960.290000000001) -> 4960.29 | I5: =IFERROR(__xludf.DUMMYFUNCTION("""COMPUTED_VALUE"""),0.2172449087296252) -> 0.21724491 | J5: =IFERROR(__xludf.DUMMYFUNCTION("""COMPUTED_VALUE"""),0.251) -> 0.251 | K5: =IFERROR(__xludf.DUMMYFUNCTION("""COMPUTED_VALUE"""),0.292) -> 0.292 | L5: =IFERROR(__xludf.DUMMYFUNCTION("""COMPUTED_VALUE"""),-0.04099999999999998) -> -0.041 | M5: =IFERROR(__xludf.DUMMYFUNCTION("""COMPUTED_VALUE"""),0.266) -> 0.266 | N5: =IFERROR(__xludf.DUMMYFUNCTION("""COMPUTED_VALUE"""),0.264) -> 0.264 | O5: =IFERROR(__xludf.DUMMYFUNCTION("""COMPUTED_VALUE"""),0.0020000000000000018) -> 0.002 | P5: =IFERROR(__xludf.DUMMYFUNCTION("""COMPUTED_VALUE"""),0.517) -> 0.517 | Q5: =IFERROR(__xludf.DUMMYFUNCTION("""COMPUTED_VALUE"""),0.556) -> 0.556 | R5: =IFERROR(__xludf.DUMMYFUNCTION("""COMPUTED_VALUE"""),-0.039000000000000035) -> -0.039
B6: =IFERROR(__xludf.DUMMYFUNCTION("""COMPUTED_VALUE"""),"Rockville") -> Rockville | C6: =IFERROR(__xludf.DUMMYFUNCTION("""COMPUTED_VALUE"""),24924.0) -> 24924 | D6: =IFERROR(__xludf.DUMMYFUNCTION("""COMPUTED_VALUE"""),22885.0) -> 22885 | E6: =IFERROR(__xludf.DUMMYFUNCTION("""COMPUTED_VALUE"""),2039.0) -> 2039 | F6: =IFERROR(__xludf.DUMMYFUNCTION("""COMPUTED_VALUE"""),0.0890976622241643) -> 0.089097662 | G6: =IFERROR(__xludf.DUMMYFUNCTION("""COMPUTED_VALUE"""),28622.84) -> 28622.84 | H6: =IFERROR(__xludf.DUMMYFUNCTION("""COMPUTED_VALUE"""),-3698.84) -> -3698.84 | I6: =IFERROR(__xludf.DUMMYFUNCTION("""COMPUTED_VALUE"""),-0.1292268691716126) -> -0.12922687 | J6: =IFERROR(__xludf.DUMMYFUNCTION("""COMPUTED_VALUE"""),0.281) -> 0.281 | K6: =IFERROR(__xludf.DUMMYFUNCTION("""COMPUTED_VALUE"""),0.288) -> 0.288 | L6: =IFERROR(__xludf.DUMMYFUNCTION("""COMPUTED_VALUE"""),-0.006999999999999951) -> -0.007 | M6: =IFERROR(__xludf.DUMMYFUNCTION("""COMPUTED_VALUE"""),0.3) -> 0.3 | N6: =IFERROR(__xludf.DUMMYFUNCTION("""COMPUTED_VALUE"""),0.267) -> 0.267 | O6: =IFERROR(__xludf.DUMMYFUNCTION("""COMPUTED_VALUE"""),0.032999999999999974) -> 0.033 | P6: =IFERROR(__xludf.DUMMYFUNCTION("""COMPUTED_VALUE"""),0.581) -> 0.581 | Q6: =IFERROR(__xludf.DUMMYFUNCTION("""COMPUTED_VALUE"""),0.5549999999999999) -> 0.555 | R6: =IFERROR(__xludf.DUMMYFUNCTION("""COMPUTED_VALUE"""),0.026000000000000023) -> 0.026
B7: =IFERROR(__xludf.DUMMYFUNCTION("""COMPUTED_VALUE"""),"Totals") -> Totals | C7: =IFERROR(__xludf.DUMMYFUNCTION("""COMPUTED_VALUE"""),122089.0) -> 122089 | D7: =IFERROR(__xludf.DUMMYFUNCTION("""COMPUTED_VALUE"""),114719.0) -> 114719 | E7: =IFERROR(__xludf.DUMMYFUNCTION("""COMPUTED_VALUE"""),7370.0) -> 7370 | F7: =IFERROR(__xludf.DUMMYFUNCTION("""COMPUTED_VALUE"""),0.064243935180746) -> 0.064243935 | G7: =IFERROR(__xludf.DUMMYFUNCTION("""COMPUTED_VALUE"""),143225.44999999998) -> 143225.45 | H7: =IFERROR(__xludf.DUMMYFUNCTION("""COMPUTED_VALUE"""),-21136.45) -> -21136.45 | I7: =IFERROR(__xludf.DUMMYFUNCTION("""COMPUTED_VALUE"""),-0.1475746803378869) -> -0.14757468 | J7: =IFERROR(__xludf.DUMMYFUNCTION("""COMPUTED_VALUE"""),0.255) -> 0.255 | K7: =IFERROR(__xludf.DUMMYFUNCTION("""COMPUTED_VALUE"""),0.274) -> 0.274 | L7: =IFERROR(__xludf.DUMMYFUNCTION("""COMPUTED_VALUE"""),-0.019000000000000017) -> -0.019 | M7: =IFERROR(__xludf.DUMMYFUNCTION("""COMPUTED_VALUE"""),0.261) -> 0.261 | N7: =IFERROR(__xludf.DUMMYFUNCTION("""COMPUTED_VALUE"""),0.262) -> 0.262 | O7: =IFERROR(__xludf.DUMMYFUNCTION("""COMPUTED_VALUE"""),-0.0010000000000000009) -> -0.001 | P7: =IFERROR(__xludf.DUMMYFUNCTION("""COMPUTED_VALUE"""),0.516) -> 0.516 | Q7: =IFERROR(__xludf.DUMMYFUNCTION("""COMPUTED_VALUE"""),0.536) -> 0.536 | R7: =IFERROR(__xludf.DUMMYFUNCTION("""COMPUTED_VALUE"""),-0.020000000000000018) -> -0.02
B11: =IFERROR(__xludf.DUMMYFUNCTION("IMPORTRANGE(""https://docs.google.com/spreadsheets/d/1rvSw8TokJxxMPNo9zCeN0TVGCwqWJYqsUgV1Y381wpc/edit?gid=1529235844#gid=1529235844"",""Weekly in-store leadership metrics!A1:M15"")"),"S") -> S | C11: =IFERROR(__xludf.DUMMYFUNCTION("""COMPUTED_VALUE"""),"Location") -> Location | D11: =IFERROR(__xludf.DUMMYFUNCTION("""COMPUTED_VALUE"""),"# Reviews") -> # Reviews | E11: =IFERROR(__xludf.DUMMYFUNCTION("""COMPUTED_VALUE"""),"Rating") -> Rating | F11: =IFERROR(__xludf.DUMMYFUNCTION("""COMPUTED_VALUE"""),"5 Star") -> 5 Star | G11: =IFERROR(__xludf.DUMMYFUNCTION("""COMPUTED_VALUE"""),"4 Star") -> 4 Star | H11: =IFERROR(__xludf.DUMMYFUNCTION("""COMPUTED_VALUE"""),"3 Star") -> 3 Star | I11: =IFERROR(__xludf.DUMMYFUNCTION("""COMPUTED_VALUE"""),"2 Star") -> 2 Star | J11: =IFERROR(__xludf.DUMMYFUNCTION("""COMPUTED_VALUE"""),"1 Star") -> 1 Star | K11: =IFERROR(__xludf.DUMMYFUNCTION("""COMPUTED_VALUE"""),"Yelp") -> Yelp | L11: =IFERROR(__xludf.DUMMYFUNCTION("""COMPUTED_VALUE"""),"Yelp #") -> Yelp # | M11: =IFERROR(__xludf.DUMMYFUNCTION("""COMPUTED_VALUE"""),"Google") -> Google | N11: =IFERROR(__xludf.DUMMYFUNCTION("""COMPUTED_VALUE"""),"Google #") -> Google #
B12: =IFERROR(__xludf.DUMMYFUNCTION("""COMPUTED_VALUE"""),"Weekly") -> Weekly | C12: =IFERROR(__xludf.DUMMYFUNCTION("""COMPUTED_VALUE"""),"MVT") -> MVT | D12: =IFERROR(__xludf.DUMMYFUNCTION("""COMPUTED_VALUE"""),0.0) -> 0 | E12: =IFERROR(__xludf.DUMMYFUNCTION("""COMPUTED_VALUE"""),"NA") -> NA | F12: =IFERROR(__xludf.DUMMYFUNCTION("""COMPUTED_VALUE"""),0.0) -> 0 | G12: =IFERROR(__xludf.DUMMYFUNCTION("""COMPUTED_VALUE"""),0.0) -> 0 | H12: =IFERROR(__xludf.DUMMYFUNCTION("""COMPUTED_VALUE"""),0.0) -> 0 | I12: =IFERROR(__xludf.DUMMYFUNCTION("""COMPUTED_VALUE"""),0.0) -> 0 | J12: =IFERROR(__xludf.DUMMYFUNCTION("""COMPUTED_VALUE"""),0.0) -> 0 | K12: =IFERROR(__xludf.DUMMYFUNCTION("""COMPUTED_VALUE"""),"NA") -> NA | L12: =IFERROR(__xludf.DUMMYFUNCTION("""COMPUTED_VALUE"""),0.0) -> 0 | M12: =IFERROR(__xludf.DUMMYFUNCTION("""COMPUTED_VALUE"""),"NA") -> NA | N12: =IFERROR(__xludf.DUMMYFUNCTION("""COMPUTED_VALUE"""),0.0) -> 0
B13: =IFERROR(__xludf.DUMMYFUNCTION("""COMPUTED_VALUE"""),"Yelp and Google") -> Yelp and Google | C13: =IFERROR(__xludf.DUMMYFUNCTION("""COMPUTED_VALUE"""),"NL") -> NL | D13: =IFERROR(__xludf.DUMMYFUNCTION("""COMPUTED_VALUE"""),1.0) -> 1 | E13: =IFERROR(__xludf.DUMMYFUNCTION("""COMPUTED_VALUE"""),4.0) -> 4 | F13: =IFERROR(__xludf.DUMMYFUNCTION("""COMPUTED_VALUE"""),0.0) -> 0 | G13: =IFERROR(__xludf.DUMMYFUNCTION("""COMPUTED_VALUE"""),1.0) -> 1 | H13: =IFERROR(__xludf.DUMMYFUNCTION("""COMPUTED_VALUE"""),0.0) -> 0 | I13: =IFERROR(__xludf.DUMMYFUNCTION("""COMPUTED_VALUE"""),0.0) -> 0 | J13: =IFERROR(__xludf.DUMMYFUNCTION("""COMPUTED_VALUE"""),0.0) -> 0 | K13: =IFERROR(__xludf.DUMMYFUNCTION("""COMPUTED_VALUE"""),"NA") -> NA | L13: =IFERROR(__xludf.DUMMYFUNCTION("""COMPUTED_VALUE"""),0.0) -> 0 | M13: =IFERROR(__xludf.DUMMYFUNCTION("""COMPUTED_VALUE"""),4.0) -> 4 | N13: =IFERROR(__xludf.DUMMYFUNCTION("""COMPUTED_VALUE"""),1.0) -> 1
C14: =IFERROR(__xludf.DUMMYFUNCTION("""COMPUTED_VALUE"""),"Mosaic") -> Mosaic | D14: =IFERROR(__xludf.DUMMYFUNCTION("""COMPUTED_VALUE"""),3.0) -> 3 | E14: =IFERROR(__xludf.DUMMYFUNCTION("""COMPUTED_VALUE"""),3.33) -> 3.33 | F14: =IFERROR(__xludf.DUMMYFUNCTION("""COMPUTED_VALUE"""),1.0) -> 1 | G14: =IFERROR(__xludf.DUMMYFUNCTION("""COMPUTED_VALUE"""),1.0) -> 1 | H14: =IFERROR(__xludf.DUMMYFUNCTION("""COMPUTED_VALUE"""),0.0) -> 0 | I14: =IFERROR(__xludf.DUMMYFUNCTION("""COMPUTED_VALUE"""),0.0) -> 0 | J14: =IFERROR(__xludf.DUMMYFUNCTION("""COMPUTED_VALUE"""),1.0) -> 1 | K14: =IFERROR(__xludf.DUMMYFUNCTION("""COMPUTED_VALUE"""),"NA") -> NA | L14: =IFERROR(__xludf.DUMMYFUNCTION("""COMPUTED_VALUE"""),0.0) -> 0 | M14: =IFERROR(__xludf.DUMMYFUNCTION("""COMPUTED_VALUE"""),3.33) -> 3.33 | N14: =IFERROR(__xludf.DUMMYFUNCTION("""COMPUTED_VALUE"""),3.0) -> 3
C15: =IFERROR(__xludf.DUMMYFUNCTION("""COMPUTED_VALUE"""),"Rockville") -> Rockville | D15: =IFERROR(__xludf.DUMMYFUNCTION("""COMPUTED_VALUE"""),4.0) -> 4 | E15: =IFERROR(__xludf.DUMMYFUNCTION("""COMPUTED_VALUE"""),4.25) -> 4.25 | F15: =IFERROR(__xludf.DUMMYFUNCTION("""COMPUTED_VALUE"""),3.0) -> 3 | G15: =IFERROR(__xludf.DUMMYFUNCTION("""COMPUTED_VALUE"""),0.0) -> 0 | H15: =IFERROR(__xludf.DUMMYFUNCTION("""COMPUTED_VALUE"""),0.0) -> 0 | I15: =IFERROR(__xludf.DUMMYFUNCTION("""COMPUTED_VALUE"""),1.0) -> 1 | J15: =IFERROR(__xludf.DUMMYFUNCTION("""COMPUTED_VALUE"""),0.0) -> 0 | K15: =IFERROR(__xludf.DUMMYFUNCTION("""COMPUTED_VALUE"""),2.0) -> 2 | L15: =IFERROR(__xludf.DUMMYFUNCTION("""COMPUTED_VALUE"""),1.0) -> 1 | M15: =IFERROR(__xludf.DUMMYFUNCTION("""COMPUTED_VALUE"""),5.0) -> 5 | N15: =IFERROR(__xludf.DUMMYFUNCTION("""COMPUTED_VALUE"""),3.0) -> 3
C16: =IFERROR(__xludf.DUMMYFUNCTION("""COMPUTED_VALUE"""),"Total") -> Total | D16: =IFERROR(__xludf.DUMMYFUNCTION("""COMPUTED_VALUE"""),8.0) -> 8 | E16: =IFERROR(__xludf.DUMMYFUNCTION("""COMPUTED_VALUE"""),3.88) -> 3.88 | F16: =IFERROR(__xludf.DUMMYFUNCTION("""COMPUTED_VALUE"""),4.0) -> 4 | G16: =IFERROR(__xludf.DUMMYFUNCTION("""COMPUTED_VALUE"""),2.0) -> 2 | H16: =IFERROR(__xludf.DUMMYFUNCTION("""COMPUTED_VALUE"""),0.0) -> 0 | I16: =IFERROR(__xludf.DUMMYFUNCTION("""COMPUTED_VALUE"""),1.0) -> 1 | J16: =IFERROR(__xludf.DUMMYFUNCTION("""COMPUTED_VALUE"""),1.0) -> 1 | K16: =IFERROR(__xludf.DUMMYFUNCTION("""COMPUTED_VALUE"""),2.0) -> 2 | L16: =IFERROR(__xludf.DUMMYFUNCTION("""COMPUTED_VALUE"""),1.0) -> 1 | M16: =IFERROR(__xludf.DUMMYFUNCTION("""COMPUTED_VALUE"""),4.14) -> 4.14 | N16: =IFERROR(__xludf.DUMMYFUNCTION("""COMPUTED_VALUE"""),7.0) -> 7
B18: =IFERROR(__xludf.DUMMYFUNCTION("""COMPUTED_VALUE"""),"3rd Party Metrics") -> 3rd Party Metrics | C18: =IFERROR(__xludf.DUMMYFUNCTION("""COMPUTED_VALUE"""),"Location") -> Location | D18: =IFERROR(__xludf.DUMMYFUNCTION("""COMPUTED_VALUE"""),"# Reviews") -> # Reviews | E18: =IFERROR(__xludf.DUMMYFUNCTION("""COMPUTED_VALUE"""),"Rating") -> Rating | F18: =IFERROR(__xludf.DUMMYFUNCTION("""COMPUTED_VALUE"""),"5 Star") -> 5 Star | G18: =IFERROR(__xludf.DUMMYFUNCTION("""COMPUTED_VALUE"""),"4 Star") -> 4 Star | H18: =IFERROR(__xludf.DUMMYFUNCTION("""COMPUTED_VALUE"""),"3 Star") -> 3 Star | I18: =IFERROR(__xludf.DUMMYFUNCTION("""COMPUTED_VALUE"""),"2 Star") -> 2 Star | J18: =IFERROR(__xludf.DUMMYFUNCTION("""COMPUTED_VALUE"""),"1 Star") -> 1 Star | K18: =IFERROR(__xludf.DUMMYFUNCTION("""COMPUTED_VALUE"""),"Uber") -> Uber | L18: =IFERROR(__xludf.DUMMYFUNCTION("""COMPUTED_VALUE"""),"DD") -> DD | M18: =IFERROR(__xludf.DUMMYFUNCTION("""COMPUTED_VALUE"""),"GH") -> GH | N18: =IFERROR(__xludf.DUMMYFUNCTION("""COMPUTED_VALUE"""),"Error Rate") -> Error Rate
B19: =IFERROR(__xludf.DUMMYFUNCTION("""COMPUTED_VALUE"""),"Weekly") -> Weekly | C19: =IFERROR(__xludf.DUMMYFUNCTION("""COMPUTED_VALUE"""),"MVT") -> MVT | D19: =IFERROR(__xludf.DUMMYFUNCTION("""COMPUTED_VALUE"""),52.0) -> 52 | E19: =IFERROR(__xludf.DUMMYFUNCTION("""COMPUTED_VALUE"""),4.5) -> 4.5 | F19: =IFERROR(__xludf.DUMMYFUNCTION("""COMPUTED_VALUE"""),37.0) -> 37 | G19: =IFERROR(__xludf.DUMMYFUNCTION("""COMPUTED_VALUE"""),9.0) -> 9 | H19: =IFERROR(__xludf.DUMMYFUNCTION("""COMPUTED_VALUE"""),2.0) -> 2 | I19: =IFERROR(__xludf.DUMMYFUNCTION("""COMPUTED_VALUE"""),2.0) -> 2 | J19: =IFERROR(__xludf.DUMMYFUNCTION("""COMPUTED_VALUE"""),2.0) -> 2 | K19: =IFERROR(__xludf.DUMMYFUNCTION("""COMPUTED_VALUE"""),4.67) -> 4.67 | L19: =IFERROR(__xludf.DUMMYFUNCTION("""COMPUTED_VALUE"""),3.83) -> 3.83 | M19: =IFERROR(__xludf.DUMMYFUNCTION("""COMPUTED_VALUE"""),"NA") -> NA | N19: =IFERROR(__xludf.DUMMYFUNCTION("""COMPUTED_VALUE"""),0.0209) -> 0.0209
B20: =IFERROR(__xludf.DUMMYFUNCTION("""COMPUTED_VALUE"""),"UE / DD / GH") -> UE / DD / GH | C20: =IFERROR(__xludf.DUMMYFUNCTION("""COMPUTED_VALUE"""),"NL") -> NL | D20: =IFERROR(__xludf.DUMMYFUNCTION("""COMPUTED_VALUE"""),28.0) -> 28 | E20: =IFERROR(__xludf.DUMMYFUNCTION("""COMPUTED_VALUE"""),4.5) -> 4.5 | F20: =IFERROR(__xludf.DUMMYFUNCTION("""COMPUTED_VALUE"""),20.0) -> 20 | G20: =IFERROR(__xludf.DUMMYFUNCTION("""COMPUTED_VALUE"""),5.0) -> 5 | H20: =IFERROR(__xludf.DUMMYFUNCTION("""COMPUTED_VALUE"""),0.0) -> 0 | I20: =IFERROR(__xludf.DUMMYFUNCTION("""COMPUTED_VALUE"""),3.0) -> 3 | J20: =IFERROR(__xludf.DUMMYFUNCTION("""COMPUTED_VALUE"""),0.0) -> 0 | K20: =IFERROR(__xludf.DUMMYFUNCTION("""COMPUTED_VALUE"""),5.0) -> 5 | L20: =IFERROR(__xludf.DUMMYFUNCTION("""COMPUTED_VALUE"""),3.62) -> 3.62 | M20: =IFERROR(__xludf.DUMMYFUNCTION("""COMPUTED_VALUE"""),"NA") -> NA | N20: =IFERROR(__xludf.DUMMYFUNCTION("""COMPUTED_VALUE"""),0.0408) -> 0.0408
C21: =IFERROR(__xludf.DUMMYFUNCTION("""COMPUTED_VALUE"""),"Mosaic") -> Mosaic | D21: =IFERROR(__xludf.DUMMYFUNCTION("""COMPUTED_VALUE"""),19.0) -> 19 | E21: =IFERROR(__xludf.DUMMYFUNCTION("""COMPUTED_VALUE"""),4.3) -> 4.3 | F21: =IFERROR(__xludf.DUMMYFUNCTION("""COMPUTED_VALUE"""),13.0) -> 13 | G21: =IFERROR(__xludf.DUMMYFUNCTION("""COMPUTED_VALUE"""),3.0) -> 3 | H21: =IFERROR(__xludf.DUMMYFUNCTION("""COMPUTED_VALUE"""),0.0) -> 0 | I21: =IFERROR(__xludf.DUMMYFUNCTION("""COMPUTED_VALUE"""),1.0) -> 1 | J21: =IFERROR(__xludf.DUMMYFUNCTION("""COMPUTED_VALUE"""),2.0) -> 2 | K21: =IFERROR(__xludf.DUMMYFUNCTION("""COMPUTED_VALUE"""),4.1) -> 4.1 | L21: =IFERROR(__xludf.DUMMYFUNCTION("""COMPUTED_VALUE"""),4.67) -> 4.67 | M21: =IFERROR(__xludf.DUMMYFUNCTION("""COMPUTED_VALUE"""),"NA") -> NA | N21: =IFERROR(__xludf.DUMMYFUNCTION("""COMPUTED_VALUE"""),0.0372) -> 0.0372
C22: =IFERROR(__xludf.DUMMYFUNCTION("""COMPUTED_VALUE"""),"Rockville") -> Rockville | D22: =IFERROR(__xludf.DUMMYFUNCTION("""COMPUTED_VALUE"""),19.0) -> 19 | E22: =IFERROR(__xludf.DUMMYFUNCTION("""COMPUTED_VALUE"""),4.2) -> 4.2 | F22: =IFERROR(__xludf.DUMMYFUNCTION("""COMPUTED_VALUE"""),12.0) -> 12 | G22: =IFERROR(__xludf.DUMMYFUNCTION("""COMPUTED_VALUE"""),2.0) -> 2 | H22: =IFERROR(__xludf.DUMMYFUNCTION("""COMPUTED_VALUE"""),3.0) -> 3 | I22: =IFERROR(__xludf.DUMMYFUNCTION("""COMPUTED_VALUE"""),1.0) -> 1 | J22: =IFERROR(__xludf.DUMMYFUNCTION("""COMPUTED_VALUE"""),1.0) -> 1 | K22: =IFERROR(__xludf.DUMMYFUNCTION("""COMPUTED_VALUE"""),4.17) -> 4.17 | L22: =IFERROR(__xludf.DUMMYFUNCTION("""COMPUTED_VALUE"""),3.67) -> 3.67 | M22: =IFERROR(__xludf.DUMMYFUNCTION("""COMPUTED_VALUE"""),"NA") -> NA | N22: =IFERROR(__xludf.DUMMYFUNCTION("""COMPUTED_VALUE"""),0.0294) -> 0.0294
C23: =IFERROR(__xludf.DUMMYFUNCTION("""COMPUTED_VALUE"""),"Total") -> Total | D23: =IFERROR(__xludf.DUMMYFUNCTION("""COMPUTED_VALUE"""),118.0) -> 118 | E23: =IFERROR(__xludf.DUMMYFUNCTION("""COMPUTED_VALUE"""),4.375) -> 4.375 | F23: =IFERROR(__xludf.DUMMYFUNCTION("""COMPUTED_VALUE"""),82.0) -> 82 | G23: =IFERROR(__xludf.DUMMYFUNCTION("""COMPUTED_VALUE"""),19.0) -> 19 | H23: =IFERROR(__xludf.DUMMYFUNCTION("""COMPUTED_VALUE"""),5.0) -> 5 | I23: =IFERROR(__xludf.DUMMYFUNCTION("""COMPUTED_VALUE"""),7.0) -> 7 | J23: =IFERROR(__xludf.DUMMYFUNCTION("""COMPUTED_VALUE"""),5.0) -> 5 | K23: =IFERROR(__xludf.DUMMYFUNCTION("""COMPUTED_VALUE"""),4.57) -> 4.57 | L23: =IFERROR(__xludf.DUMMYFUNCTION("""COMPUTED_VALUE"""),3.85) -> 3.85 | M23: =IFERROR(__xludf.DUMMYFUNCTION("""COMPUTED_VALUE"""),"NA") -> NA | N23: =IFERROR(__xludf.DUMMYFUNCTION("""COMPUTED_VALUE"""),0.032075) -> 0.032075
B27: Weighted avoidable wait time
C28: Uber Eats | E28: Door Dash
B29: =IFERROR(__xludf.DUMMYFUNCTION("IMPORTRANGE(""https://docs.google.com/spreadsheets/d/1rvSw8TokJxxMPNo9zCeN0TVGCwqWJYqsUgV1Y381wpc/edit?gid=1529235844#gid=1529235844"",""3PD Reporting - UE & DD!A14:A20"")"),"Location") -> Location | C29: =IFERROR(__xludf.DUMMYFUNCTION("IMPORTRANGE(""https://docs.google.com/spreadsheets/d/1rvSw8TokJxxMPNo9zCeN0TVGCwqWJYqsUgV1Y381wpc/edit?gid=1529235844#gid=1529235844"",""3PD Reporting - UE & DD!H14:H20"")"),"Avoidable Wait Time") -> Avoidable Wait Time | D29: =IFERROR(__xludf.DUMMYFUNCTION("IMPORTRANGE(""https://docs.google.com/spreadsheets/d/1rvSw8TokJxxMPNo9zCeN0TVGCwqWJYqsUgV1Y381wpc/edit?gid=1529235844#gid=1529235844"",""3PD Reporting - UE & DD!D3:D9"")"),"Order Volume") -> Order Volume | E29: =IFERROR(__xludf.DUMMYFUNCTION("IMPORTRANGE(""https://docs.google.com/spreadsheets/d/1rvSw8TokJxxMPNo9zCeN0TVGCwqWJYqsUgV1Y381wpc/edit?gid=1529235844#gid=1529235844"",""3PD Reporting - UE & DD!U14:U20"")"),"Avoidable Wait Time") -> Avoidable Wait Time | F29: =IFERROR(__xludf.DUMMYFUNCTION("IMPORTRANGE(""https://docs.google.com/spreadsheets/d/1rvSw8TokJxxMPNo9zCeN0TVGCwqWJYqsUgV1Y381wpc/edit?gid=1529235844#gid=1529235844"",""3PD Reporting - UE & DD!Q3:Q9"")"),"Order Volume") -> Order Volume | G29: Weighted Average | H29: Final weighted average
B30: =IFERROR(__xludf.DUMMYFUNCTION("""COMPUTED_VALUE"""),"Rockville") -> Rockville | C30: =IFERROR(__xludf.DUMMYFUNCTION("""COMPUTED_VALUE"""),"0 min 49 sec") -> 0 min 49 sec | D30: =IFERROR(__xludf.DUMMYFUNCTION("""COMPUTED_VALUE"""),166.0) -> 166 | E30: =IFERROR(__xludf.DUMMYFUNCTION("""COMPUTED_VALUE"""),"3 min 00 sec") -> 3 min 00 sec | F30: =IFERROR(__xludf.DUMMYFUNCTION("""COMPUTED_VALUE"""),65.0) -> 65 | G30: =TEXT( ( ( (LEFT(C30,FIND("min",C30)-2)*60 + MID(C30,FIND("min",C30)+4,FIND("sec",C30)-FIND("min",C30)-4))*D30 + (LEFT(E30,FIND("min",E30)-2)*60 + MID(E30,FIND("min",E30)+4,FIND("sec",E30)-FIND("min",E30)-4))*F30 ) / (D30+F30) )/86400, "m ""min"" s ""sec""" ) -> 1 min 26 sec | H30: =ROUND(VALUE(LEFT(G30,FIND(" min",G30)-1)) + VALUE(MID(G30,FIND("min",G30)+4,FIND("sec",G30)-FIND("min",G30)-4))/60, 2) -> 1.43
B31: =IFERROR(__xludf.DUMMYFUNCTION("""COMPUTED_VALUE"""),"MVT") -> MVT | C31: =IFERROR(__xludf.DUMMYFUNCTION("""COMPUTED_VALUE"""),"0 min 31 sec") -> 0 min 31 sec | D31: =IFERROR(__xludf.DUMMYFUNCTION("""COMPUTED_VALUE"""),392.0) -> 392 | E31: =IFERROR(__xludf.DUMMYFUNCTION("""COMPUTED_VALUE"""),"2 min 07 sec") -> 2 min 07 sec | F31: =IFERROR(__xludf.DUMMYFUNCTION("""COMPUTED_VALUE"""),174.0) -> 174 | G31: =TEXT( ( ( (LEFT(C31,FIND("min",C31)-2)*60 + MID(C31,FIND("min",C31)+4,FIND("sec",C31)-FIND("min",C31)-4))*D31 + (LEFT(E31,FIND("min",E31)-2)*60 + MID(E31,FIND("min",E31)+4,FIND("sec",E31)-FIND("min",E31)-4))*F31 ) / (D31+F31) )/86400, "m ""min"" s ""sec""" ) -> 1 min 1 sec | H31: =ROUND(VALUE(LEFT(G31,FIND(" min",G31)-1)) + VALUE(MID(G31,FIND("min",G31)+4,FIND("sec",G31)-FIND("min",G31)-4))/60, 2) -> 1.02
B32: =IFERROR(__xludf.DUMMYFUNCTION("""COMPUTED_VALUE"""),"National Landing") -> National Landing | C32: =IFERROR(__xludf.DUMMYFUNCTION("""COMPUTED_VALUE"""),"0 min 34 sec") -> 0 min 34 sec | D32: =IFERROR(__xludf.DUMMYFUNCTION("""COMPUTED_VALUE"""),176.0) -> 176 | E32: =IFERROR(__xludf.DUMMYFUNCTION("""COMPUTED_VALUE"""),"1 min 50 sec") -> 1 min 50 sec | F32: =IFERROR(__xludf.DUMMYFUNCTION("""COMPUTED_VALUE"""),106.0) -> 106 | G32: =TEXT( ( ( (LEFT(C32,FIND("min",C32)-2)*60 + MID(C32,FIND("min",C32)+4,FIND("sec",C32)-FIND("min",C32)-4))*D32 + (LEFT(E32,FIND("min",E32)-2)*60 + MID(E32,FIND("min",E32)+4,FIND("sec",E32)-FIND("min",E32)-4))*F32 ) / (D32+F32) )/86400, "m ""min"" s ""sec""" ) -> 1 min 3 sec | H32: =ROUND(VALUE(LEFT(G32,FIND(" min",G32)-1)) + VALUE(MID(G32,FIND("min",G32)+4,FIND("sec",G32)-FIND("min",G32)-4))/60, 2) -> 1.05
B33: =IFERROR(__xludf.DUMMYFUNCTION("""COMPUTED_VALUE"""),"Mosaic") -> Mosaic | C33: =IFERROR(__xludf.DUMMYFUNCTION("""COMPUTED_VALUE"""),"0 min 55 sec") -> 0 min 55 sec | D33: =IFERROR(__xludf.DUMMYFUNCTION("""COMPUTED_VALUE"""),154.0) -> 154 | E33: =IFERROR(__xludf.DUMMYFUNCTION("""COMPUTED_VALUE"""),"2 min 52 sec") -> 2 min 52 sec | F33: =IFERROR(__xludf.DUMMYFUNCTION("""COMPUTED_VALUE"""),84.0) -> 84 | G33: =TEXT( ( ( (LEFT(C33,FIND("min",C33)-2)*60 + MID(C33,FIND("min",C33)+4,FIND("sec",C33)-FIND("min",C33)-4))*D33 + (LEFT(E33,FIND("min",E33)-2)*60 + MID(E33,FIND("min",E33)+4,FIND("sec",E33)-FIND("min",E33)-4))*F33 ) / (D33+F33) )/86400, "m ""min"" s ""sec""" ) -> 1 min 36 sec | H33: =ROUND(VALUE(LEFT(G33,FIND(" min",G33)-1)) + VALUE(MID(G33,FIND("min",G33)+4,FIND("sec",G33)-FIND("min",G33)-4))/60, 2) -> 1.6
B34: =IFERROR(__xludf.DUMMYFUNCTION("""COMPUTED_VALUE"""),"All Stores") -> All Stores | C34: =IFERROR(__xludf.DUMMYFUNCTION("""COMPUTED_VALUE"""),"0 min 38 sec") -> 0 min 38 sec | D34: =IFERROR(__xludf.DUMMYFUNCTION("""COMPUTED_VALUE"""),888.0) -> 888 | E34: =IFERROR(__xludf.DUMMYFUNCTION("""COMPUTED_VALUE"""),"2 min 21 sec") -> 2 min 21 sec | F34: =IFERROR(__xludf.DUMMYFUNCTION("""COMPUTED_VALUE"""),429.0) -> 429 | G34: =TEXT( ( ( (LEFT(C34,FIND("min",C34)-2)*60 + MID(C34,FIND("min",C34)+4,FIND("sec",C34)-FIND("min",C34)-4))*D34 + (LEFT(E34,FIND("min",E34)-2)*60 + MID(E34,FIND("min",E34)+4,FIND("sec",E34)-FIND("min",E34)-4))*F34 ) / (D34+F34) )/86400, "m ""min"" s ""sec""" ) -> 1 min 12 sec | H34: =ROUND(VALUE(LEFT(G34,FIND(" min",G34)-1)) + VALUE(MID(G34,FIND("min",G34)+4,FIND("sec",G34)-FIND("min",G34)-4))/60, 2) -> 1.2

Sheet Period Tables
B2: =IFERROR(__xludf.DUMMYFUNCTION("IMPORTRANGE(""https://docs.google.com/spreadsheets/d/1rvSw8TokJxxMPNo9zCeN0TVGCwqWJYqsUgV1Y381wpc/edit?gid=1529235844#gid=1529235844"",""Weekly Flash Report!A40:Q46"")"),"Location ") -> Location | C2: =IFERROR(__xludf.DUMMYFUNCTION("""COMPUTED_VALUE"""),"Sales") -> Sales | D2: =IFERROR(__xludf.DUMMYFUNCTION("""COMPUTED_VALUE"""),"Same PD LY") -> Same PD LY | E2: =IFERROR(__xludf.DUMMYFUNCTION("""COMPUTED_VALUE"""),"Dollar Change") -> Dollar Change | F2: =IFERROR(__xludf.DUMMYFUNCTION("""COMPUTED_VALUE"""),"Percent Change") -> Percent Change | G2: =IFERROR(__xludf.DUMMYFUNCTION("""COMPUTED_VALUE"""),"PD Budget") -> PD Budget | H2: =IFERROR(__xludf.DUMMYFUNCTION("""COMPUTED_VALUE"""),"Var to Bud +/-") -> Var to Bud +/- | I2: =IFERROR(__xludf.DUMMYFUNCTION("""COMPUTED_VALUE"""),"Var to Bud ") -> Var to Bud | J2: =IFERROR(__xludf.DUMMYFUNCTION("""COMPUTED_VALUE"""),"Total Labor ") -> Total Labor | K2: =IFERROR(__xludf.DUMMYFUNCTION("""COMPUTED_VALUE"""),"Bud Labor ") -> Bud Labor | L2: =IFERROR(__xludf.DUMMYFUNCTION("""COMPUTED_VALUE"""),"Var Lbr to Bud") -> Var Lbr to Bud | M2: =IFERROR(__xludf.DUMMYFUNCTION("""COMPUTED_VALUE"""),"Total COGS") -> Total COGS | N2: =IFERROR(__xludf.DUMMYFUNCTION("""COMPUTED_VALUE"""),"Bud COGS") -> Bud COGS | O2: =IFERROR(__xludf.DUMMYFUNCTION("""COMPUTED_VALUE"""),"Var COGS to Bud") -> Var COGS to Bud | P2: =IFERROR(__xludf.DUMMYFUNCTION("""COMPUTED_VALUE"""),"Total PC ") -> Total PC | Q2: =IFERROR(__xludf.DUMMYFUNCTION("""COMPUTED_VALUE"""),"Bud PC") -> Bud PC | R2: =IFERROR(__xludf.DUMMYFUNCTION("""COMPUTED_VALUE"""),"Var PC to Bud") -> Var PC to Bud | S2: EBIDTA Actual $ | T2: EBIDTA Budget $ | U2: Var $ Budget | V2: Var % Budget
B3: =IFERROR(__xludf.DUMMYFUNCTION("""COMPUTED_VALUE"""),"Ballpark") -> Ballpark | C3: =IFERROR(__xludf.DUMMYFUNCTION("""COMPUTED_VALUE"""),12.0) -> 12 | D3: =IFERROR(__xludf.DUMMYFUNCTION("""COMPUTED_VALUE"""),16991.0) -> 16991 | E3: =IFERROR(__xludf.DUMMYFUNCTION("""COMPUTED_VALUE"""),-16979.0) -> -16979 | F3: =IFERROR(__xludf.DUMMYFUNCTION("""COMPUTED_VALUE"""),-0.9992937437466894) -> -0.99929374 | G3: =IFERROR(__xludf.DUMMYFUNCTION("""COMPUTED_VALUE"""),21689.79) -> 21689.79 | H3: =IFERROR(__xludf.DUMMYFUNCTION("""COMPUTED_VALUE"""),-21677.79) -> -21677.79 | I3: =IFERROR(__xludf.DUMMYFUNCTION("""COMPUTED_VALUE"""),-0.9994467442976627) -> -0.99944674 | J3: =IFERROR(__xludf.DUMMYFUNCTION("""COMPUTED_VALUE"""),0.0) -> 0 | K3: =IFERROR(__xludf.DUMMYFUNCTION("""COMPUTED_VALUE"""),0.308) -> 0.308 | L3: =IFERROR(__xludf.DUMMYFUNCTION("""COMPUTED_VALUE"""),-0.308) -> -0.308 | M3: =IFERROR(__xludf.DUMMYFUNCTION("""COMPUTED_VALUE"""),0.0) -> 0 | N3: =IFERROR(__xludf.DUMMYFUNCTION("""COMPUTED_VALUE"""),0.264) -> 0.264 | O3: =IFERROR(__xludf.DUMMYFUNCTION("""COMPUTED_VALUE"""),-0.264) -> -0.264 | P3: =IFERROR(__xludf.DUMMYFUNCTION("""COMPUTED_VALUE"""),0.0) -> 0 | Q3: =IFERROR(__xludf.DUMMYFUNCTION("""COMPUTED_VALUE"""),0.5720000000000001) -> 0.572 | R3: =IFERROR(__xludf.DUMMYFUNCTION("""COMPUTED_VALUE"""),-0.5720000000000001) -> -0.572 | S3: =IFERROR(__xludf.DUMMYFUNCTION("IMPORTRANGE(""https://docs.google.com/spreadsheets/d/1rvSw8TokJxxMPNo9zCeN0TVGCwqWJYqsUgV1Y381wpc/edit?gid=1529235844#gid=1529235844"",""Profit and Loss_Sas_BP!Q387"")"),"") | T3: =IFERROR(__xludf.DUMMYFUNCTION("IMPORTRANGE(""https://docs.google.com/spreadsheets/d/1rvSw8TokJxxMPNo9zCeN0TVGCwqWJYqsUgV1Y381wpc/edit?gid=1529235844#gid=1529235844"",""Profit and Loss_Sas_BP!AA387"")"),0.0) -> 0 | U3: =S3-T3 -> 0 | V3: =U3/T3 -> #DIV/0!
B4: =IFERROR(__xludf.DUMMYFUNCTION("""COMPUTED_VALUE"""),"Mosaic") -> Mosaic | C4: =IFERROR(__xludf.DUMMYFUNCTION("""COMPUTED_VALUE"""),26903.0) -> 26903 | D4: =IFERROR(__xludf.DUMMYFUNCTION("""COMPUTED_VALUE"""),24535.0) -> 24535 | E4: =IFERROR(__xludf.DUMMYFUNCTION("""COMPUTED_VALUE"""),2368.0) -> 2368 | F4: =IFERROR(__xludf.DUMMYFUNCTION("""COMPUTED_VALUE"""),0.09651518239250051) -> 0.096515182 | G4: =IFERROR(__xludf.DUMMYFUNCTION("""COMPUTED_VALUE"""),28417.46) -> 28417.46 | H4: =IFERROR(__xludf.DUMMYFUNCTION("""COMPUTED_VALUE"""),-1514.4599999999991) -> -1514.46 | I4: =IFERROR(__xludf.DUMMYFUNCTION("""COMPUTED_VALUE"""),-0.05329329222245757) -> -0.053293292 | J4: =IFERROR(__xludf.DUMMYFUNCTION("""COMPUTED_VALUE"""),0.231) -> 0.231 | K4: =IFERROR(__xludf.DUMMYFUNCTION("""COMPUTED_VALUE"""),0.258) -> 0.258 | L4: =IFERROR(__xludf.DUMMYFUNCTION("""COMPUTED_VALUE"""),-0.026999999999999996) -> -0.027 | M4: =IFERROR(__xludf.DUMMYFUNCTION("""COMPUTED_VALUE"""),0.233) -> 0.233 | N4: =IFERROR(__xludf.DUMMYFUNCTION("""COMPUTED_VALUE"""),0.267) -> 0.267 | O4: =IFERROR(__xludf.DUMMYFUNCTION("""COMPUTED_VALUE"""),-0.034) -> -0.034 | P4: =IFERROR(__xludf.DUMMYFUNCTION("""COMPUTED_VALUE"""),0.464) -> 0.464 | Q4: =IFERROR(__xludf.DUMMYFUNCTION("""COMPUTED_VALUE"""),0.525) -> 0.525 | R4: =IFERROR(__xludf.DUMMYFUNCTION("""COMPUTED_VALUE"""),-0.061) -> -0.061 | S4: =IFERROR(__xludf.DUMMYFUNCTION("IMPORTRANGE(""https://docs.google.com/spreadsheets/d/1rvSw8TokJxxMPNo9zCeN0TVGCwqWJYqsUgV1Y381wpc/edit?gid=1529235844#gid=1529235844"",""Profit and Loss_Sas_MO!Q387"")"),"") | T4: =IFERROR(__xludf.DUMMYFUNCTION("IMPORTRANGE(""https://docs.google.com/spreadsheets/d/1rvSw8TokJxxMPNo9zCeN0TVGCwqWJYqsUgV1Y381wpc/edit?gid=1529235844#gid=1529235844"",""Profit and Loss_Sas_MO!AA387"")"),0.0) -> 0 | U4: =S4-T4 -> 0 | V4: =U4/T4 -> #DIV/0!
B5: =IFERROR(__xludf.DUMMYFUNCTION("""COMPUTED_VALUE"""),"MVT") -> MVT | C5: =IFERROR(__xludf.DUMMYFUNCTION("""COMPUTED_VALUE"""),42457.0) -> 42457 | D5: =IFERROR(__xludf.DUMMYFUNCTION("""COMPUTED_VALUE"""),30853.0) -> 30853 | E5: =IFERROR(__xludf.DUMMYFUNCTION("""COMPUTED_VALUE"""),11604.0) -> 11604 | F5: =IFERROR(__xludf.DUMMYFUNCTION("""COMPUTED_VALUE"""),0.3761060512754027) -> 0.37610605 | G5: =IFERROR(__xludf.DUMMYFUNCTION("""COMPUTED_VALUE"""),41662.65) -> 41662.65 | H5: =IFERROR(__xludf.DUMMYFUNCTION("""COMPUTED_VALUE"""),794.3499999999985) -> 794.35 | I5: =IFERROR(__xludf.DUMMYFUNCTION("""COMPUTED_VALUE"""),0.019066237985341752) -> 0.019066238 | J5: =IFERROR(__xludf.DUMMYFUNCTION("""COMPUTED_VALUE"""),0.273) -> 0.273 | K5: =IFERROR(__xludf.DUMMYFUNCTION("""COMPUTED_VALUE"""),0.249) -> 0.249 | L5: =IFERROR(__xludf.DUMMYFUNCTION("""COMPUTED_VALUE"""),0.02400000000000002) -> 0.024 | M5: =IFERROR(__xludf.DUMMYFUNCTION("""COMPUTED_VALUE"""),0.265) -> 0.265 | N5: =IFERROR(__xludf.DUMMYFUNCTION("""COMPUTED_VALUE"""),0.254) -> 0.254 | O5: =IFERROR(__xludf.DUMMYFUNCTION("""COMPUTED_VALUE"""),0.01100000000000001) -> 0.011 | P5: =IFERROR(__xludf.DUMMYFUNCTION("""COMPUTED_VALUE"""),0.538) -> 0.538 | Q5: =IFERROR(__xludf.DUMMYFUNCTION("""COMPUTED_VALUE"""),0.503) -> 0.503 | R5: =IFERROR(__xludf.DUMMYFUNCTION("""COMPUTED_VALUE"""),0.03500000000000003) -> 0.035 | S5: =IFERROR(__xludf.DUMMYFUNCTION("IMPORTRANGE(""https://docs.google.com/spreadsheets/d/1rvSw8TokJxxMPNo9zCeN0TVGCwqWJYqsUgV1Y381wpc/edit?gid=1529235844#gid=1529235844"",""Profit and Loss_Sas_MVT!Q387"")"),"") | T5: =IFERROR(__xludf.DUMMYFUNCTION("IMPORTRANGE(""https://docs.google.com/spreadsheets/d/1rvSw8TokJxxMPNo9zCeN0TVGCwqWJYqsUgV1Y381wpc/edit?gid=1529235844#gid=1529235844"",""Profit and Loss_Sas_MVT!AA387"")"),0.0) -> 0 | U5: =S5-T5 -> 0 | V5: =U5/T5 -> #DIV/0!
B6: =IFERROR(__xludf.DUMMYFUNCTION("""COMPUTED_VALUE"""),"National Landing") -> National Landing | C6: =IFERROR(__xludf.DUMMYFUNCTION("""COMPUTED_VALUE"""),27793.0) -> 27793 | D6: =IFERROR(__xludf.DUMMYFUNCTION("""COMPUTED_VALUE"""),19455.0) -> 19455 | E6: =IFERROR(__xludf.DUMMYFUNCTION("""COMPUTED_VALUE"""),8338.0) -> 8338 | F6: =IFERROR(__xludf.DUMMYFUNCTION("""COMPUTED_VALUE"""),0.4285787715240298) -> 0.42857877 | G6: =IFERROR(__xludf.DUMMYFUNCTION("""COMPUTED_VALUE"""),22832.71) -> 22832.71 | H6: =IFERROR(__xludf.DUMMYFUNCTION("""COMPUTED_VALUE"""),4960.290000000001) -> 4960.29 | I6: =IFERROR(__xludf.DUMMYFUNCTION("""COMPUTED_VALUE"""),0.2172449087296252) -> 0.21724491 | J6: =IFERROR(__xludf.DUMMYFUNCTION("""COMPUTED_VALUE"""),0.251) -> 0.251 | K6: =IFERROR(__xludf.DUMMYFUNCTION("""COMPUTED_VALUE"""),0.292) -> 0.292 | L6: =IFERROR(__xludf.DUMMYFUNCTION("""COMPUTED_VALUE"""),-0.04099999999999998) -> -0.041 | M6: =IFERROR(__xludf.DUMMYFUNCTION("""COMPUTED_VALUE"""),0.266) -> 0.266 | N6: =IFERROR(__xludf.DUMMYFUNCTION("""COMPUTED_VALUE"""),0.264) -> 0.264 | O6: =IFERROR(__xludf.DUMMYFUNCTION("""COMPUTED_VALUE"""),0.0020000000000000018) -> 0.002 | P6: =IFERROR(__xludf.DUMMYFUNCTION("""COMPUTED_VALUE"""),0.517) -> 0.517 | Q6: =IFERROR(__xludf.DUMMYFUNCTION("""COMPUTED_VALUE"""),0.556) -> 0.556 | R6: =IFERROR(__xludf.DUMMYFUNCTION("""COMPUTED_VALUE"""),-0.039000000000000035) -> -0.039 | S6: =IFERROR(__xludf.DUMMYFUNCTION("IMPORTRANGE(""https://docs.google.com/spreadsheets/d/1rvSw8TokJxxMPNo9zCeN0TVGCwqWJYqsUgV1Y381wpc/edit?gid=1529235844#gid=1529235844"",""Profit and Loss_Sas_NL!Q387"")"),"") | T6: =IFERROR(__xludf.DUMMYFUNCTION("IMPORTRANGE(""https://docs.google.com/spreadsheets/d/1rvSw8TokJxxMPNo9zCeN0TVGCwqWJYqsUgV1Y381wpc/edit?gid=1529235844#gid=1529235844"",""Profit and Loss_Sas_NL!AA387"")"),0.0) -> 0 | U6: =S6-T6 -> 0 | V6: =U6/T6 -> #DIV/0!
B7: =IFERROR(__xludf.DUMMYFUNCTION("""COMPUTED_VALUE"""),"Rockville") -> Rockville | C7: =IFERROR(__xludf.DUMMYFUNCTION("""COMPUTED_VALUE"""),24924.0) -> 24924 | D7: =IFERROR(__xludf.DUMMYFUNCTION("""COMPUTED_VALUE"""),22885.0) -> 22885 | E7: =IFERROR(__xludf.DUMMYFUNCTION("""COMPUTED_VALUE"""),2039.0) -> 2039 | F7: =IFERROR(__xludf.DUMMYFUNCTION("""COMPUTED_VALUE"""),0.0890976622241643) -> 0.089097662 | G7: =IFERROR(__xludf.DUMMYFUNCTION("""COMPUTED_VALUE"""),28622.84) -> 28622.84 | H7: =IFERROR(__xludf.DUMMYFUNCTION("""COMPUTED_VALUE"""),-3698.84) -> -3698.84 | I7: =IFERROR(__xludf.DUMMYFUNCTION("""COMPUTED_VALUE"""),-0.1292268691716126) -> -0.12922687 | J7: =IFERROR(__xludf.DUMMYFUNCTION("""COMPUTED_VALUE"""),0.281) -> 0.281 | K7: =IFERROR(__xludf.DUMMYFUNCTION("""COMPUTED_VALUE"""),0.288) -> 0.288 | L7: =IFERROR(__xludf.DUMMYFUNCTION("""COMPUTED_VALUE"""),-0.006999999999999951) -> -0.007 | M7: =IFERROR(__xludf.DUMMYFUNCTION("""COMPUTED_VALUE"""),0.3) -> 0.3 | N7: =IFERROR(__xludf.DUMMYFUNCTION("""COMPUTED_VALUE"""),0.267) -> 0.267 | O7: =IFERROR(__xludf.DUMMYFUNCTION("""COMPUTED_VALUE"""),0.032999999999999974) -> 0.033 | P7: =IFERROR(__xludf.DUMMYFUNCTION("""COMPUTED_VALUE"""),0.581) -> 0.581 | Q7: =IFERROR(__xludf.DUMMYFUNCTION("""COMPUTED_VALUE"""),0.5549999999999999) -> 0.555 | R7: =IFERROR(__xludf.DUMMYFUNCTION("""COMPUTED_VALUE"""),0.026000000000000023) -> 0.026 | S7: =IFERROR(__xludf.DUMMYFUNCTION("IMPORTRANGE(""https://docs.google.com/spreadsheets/d/1rvSw8TokJxxMPNo9zCeN0TVGCwqWJYqsUgV1Y381wpc/edit?gid=1529235844#gid=1529235844"",""Profit and Loss_Sas_RV!Q387"")"),"") | T7: =IFERROR(__xludf.DUMMYFUNCTION("IMPORTRANGE(""https://docs.google.com/spreadsheets/d/1rvSw8TokJxxMPNo9zCeN0TVGCwqWJYqsUgV1Y381wpc/edit?gid=1529235844#gid=1529235844"",""Profit and Loss_Sas_RV!AA387"")"),0.0) -> 0 | U7: =S7-T7 -> 0 | V7: =U7/T7 -> #DIV/0!
B8: =IFERROR(__xludf.DUMMYFUNCTION("""COMPUTED_VALUE"""),"Totals") -> Totals | C8: =IFERROR(__xludf.DUMMYFUNCTION("""COMPUTED_VALUE"""),122089.0) -> 122089 | D8: =IFERROR(__xludf.DUMMYFUNCTION("""COMPUTED_VALUE"""),114719.0) -> 114719 | E8: =IFERROR(__xludf.DUMMYFUNCTION("""COMPUTED_VALUE"""),7370.0) -> 7370 | F8: =IFERROR(__xludf.DUMMYFUNCTION("""COMPUTED_VALUE"""),0.064243935180746) -> 0.064243935 | G8: =IFERROR(__xludf.DUMMYFUNCTION("""COMPUTED_VALUE"""),143225.44999999998) -> 143225.45 | H8: =IFERROR(__xludf.DUMMYFUNCTION("""COMPUTED_VALUE"""),-21136.45) -> -21136.45 | I8: =IFERROR(__xludf.DUMMYFUNCTION("""COMPUTED_VALUE"""),-0.1475746803378869) -> -0.14757468 | J8: =IFERROR(__xludf.DUMMYFUNCTION("""COMPUTED_VALUE"""),0.255) -> 0.255 | K8: =IFERROR(__xludf.DUMMYFUNCTION("""COMPUTED_VALUE"""),0.274) -> 0.274 | L8: =IFERROR(__xludf.DUMMYFUNCTION("""COMPUTED_VALUE"""),-0.019000000000000017) -> -0.019 | M8: =IFERROR(__xludf.DUMMYFUNCTION("""COMPUTED_VALUE"""),0.261) -> 0.261 | N8: =IFERROR(__xludf.DUMMYFUNCTION("""COMPUTED_VALUE"""),0.262) -> 0.262 | O8: =IFERROR(__xludf.DUMMYFUNCTION("""COMPUTED_VALUE"""),-0.0010000000000000009) -> -0.001 | P8: =IFERROR(__xludf.DUMMYFUNCTION("""COMPUTED_VALUE"""),0.516) -> 0.516 | Q8: =IFERROR(__xludf.DUMMYFUNCTION("""COMPUTED_VALUE"""),0.536) -> 0.536 | R8: =IFERROR(__xludf.DUMMYFUNCTION("""COMPUTED_VALUE"""),-0.020000000000000018) -> -0.02 | S8: =IFERROR(__xludf.DUMMYFUNCTION("IMPORTRANGE(""https://docs.google.com/spreadsheets/d/1rvSw8TokJxxMPNo9zCeN0TVGCwqWJYqsUgV1Y381wpc/edit?gid=1529235844#gid=1529235844"",""Profit and Loss_Sas_Overall!Q387"")"),"") | T8: =IFERROR(__xludf.DUMMYFUNCTION("IMPORTRANGE(""https://docs.google.com/spreadsheets/d/1rvSw8TokJxxMPNo9zCeN0TVGCwqWJYqsUgV1Y381wpc/edit?gid=1529235844#gid=1529235844"",""Profit and Loss_Sas_Overall!AA387"")"),0.0) -> 0 | U8: =S8-T8 -> 0 | V8: =U8/T8 -> #DIV/0!
B11: In-Store Metrics | C11: Location | D11: # Reviews | E11: Rating | F11: Yelp | G11: Yelp # | H11: Google | I11: Google #
B12: Weekly | C12: Ballpark | D12: 2 | E12: 5 | F12: NA | G12: 0 | H12: 5 | I12: 2
B13: Yelp and Google | C13: MVT | D13: 4 | E13: 3 | F13: 1 | G13: 1 | H13: 3.67 | I13: 3
C14: NL | D14: 6 | E14: 4.33 | F14: NA | G14: 0 | H14: 4.33 | I14: 6
C15: Mosaic | D15: 9 | E15: 4.67 | F15: 4 | G15: 1 | H15: 4.75 | I15: 8
C16: Rockville | D16: 15 | E16: 4.47 | F16: NA | G16: 0 | H16: 4.47 | I16: 15
C17: Total | D17: =SUM(D12:D16) -> 36 | E17: =AVERAGE(E12:E16) -> 4.294 | F17: =AVERAGE(F12:F16) -> 2.5 | H17: =AVERAGE(H12:H16) -> 4.444
B19: 3rd Party Metrics | C19: Location | D19: # Reviews | E19: Rating | F19: Uber | G19: DD | H19: GH | I19: Error Rate
B20: Weekly | C20: Ballpark | D20: 19 | E20: 4 | F20: 4.73 | G20: 4 | H20: NA | I20: 0.0405
B21: UE / DD / GH | C21: MVT | D21: 107 | E21: 4.5 | F21: 4.59 | G21: 4.25 | H21: NA | I21: 0.0264
C22: NL | D22: 66 | E22: 4.3 | F22: 4.69 | G22: 3.97 | H22: NA | I22: 0.0315
C23: Mosaic | D23: 40 | E23: 4.4 | F23: 4.57 | G23: 4.31 | H23: NA | I23: 0.0315
C24: Rockville | D24: 49 | E24: 4.3 | F24: 4.61 | G24: 4.19 | H24: NA | I24: 0.045
C25: Total | D25: =SUM(D20:D24) -> 281 | E25: =AVERAGE(E20:E24) -> 4.3 | I25: 0.03498
B27: Weighted avoidable wait time
C28: Uber Eats | E28: Door Dash | I28: 2 Star | J28: 1 Star
B29: Location | C29: Avoidable Wait Time | D29: Order Volume | E29: Avoidable Wait Time | F29: Order Volume | G29: Weighted Average | H29: Final weighted average
B30: Rockville | C30: 0 min 56 sec | D30: 214 | E30: 2 min 42 sec | F30: 374 | G30: =TEXT( ( ( (LEFT(C30,FIND("min",C30)-2)*60 + MID(C30,FIND("min",C30)+4,FIND("sec",C30)-FIND("min",C30)-4))*D30 + (LEFT(E30,FIND("min",E30)-2)*60 + MID(E30,FIND("min",E30)+4,FIND("sec",E30)-FIND("min",E30)-4))*F30 ) / (D30+F30) )/86400, "m ""min"" s ""sec""" ) -> 2 min 3 sec | H30: =VALUE(LEFT(G30,FIND("min",G30)-1)) + VALUE(MID(G30,FIND("min",G30)+4,FIND("sec",G30)-FIND("min",G30)-4))/100 -> 2.03
B31: Ballpark | C31: 0 min 26 sec | D31: 361 | E31: 1 min 39 sec | F31: 263 | G31: =TEXT( ( ( (LEFT(C31,FIND("min",C31)-2)*60 + MID(C31,FIND("min",C31)+4,FIND("sec",C31)-FIND("min",C31)-4))*D31 + (LEFT(E31,FIND("min",E31)-2)*60 + MID(E31,FIND("min",E31)+4,FIND("sec",E31)-FIND("min",E31)-4))*F31 ) / (D31+F31) )/86400, "m ""min"" s ""sec""" ) -> 0 min 57 sec | H31: =VALUE(LEFT(G31,FIND("min",G31)-1)) + VALUE(MID(G31,FIND("min",G31)+4,FIND("sec",G31)-FIND("min",G31)-4))/100 -> 0.57
B32: MVT | C32: 0 min 23 sec | D32: 784 | E32: 1 min 36 sec | F32: 761 | G32: =TEXT( ( ( (LEFT(C32,FIND("min",C32)-2)*60 + MID(C32,FIND("min",C32)+4,FIND("sec",C32)-FIND("min",C32)-4))*D32 + (LEFT(E32,FIND("min",E32)-2)*60 + MID(E32,FIND("min",E32)+4,FIND("sec",E32)-FIND("min",E32)-4))*F32 ) / (D32+F32) )/86400, "m ""min"" s ""sec""" ) -> 0 min 59 sec | H32: =VALUE(LEFT(G32,FIND("min",G32)-1)) + VALUE(MID(G32,FIND("min",G32)+4,FIND("sec",G32)-FIND("min",G32)-4))/100 -> 0.59
B33: National Landing | C33: 0 min 29 sec | D33: 439 | E33: 1 min 55 sec | F33: 483 | G33: =TEXT( ( ( (LEFT(C33,FIND("min",C33)-2)*60 + MID(C33,FIND("min",C33)+4,FIND("sec",C33)-FIND("min",C33)-4))*D33 + (LEFT(E33,FIND("min",E33)-2)*60 + MID(E33,FIND("min",E33)+4,FIND("sec",E33)-FIND("min",E33)-4))*F33 ) / (D33+F33) )/86400, "m ""min"" s ""sec""" ) -> 1 min 14 sec | H33: =VALUE(LEFT(G33,FIND("min",G33)-1)) + VALUE(MID(G33,FIND("min",G33)+4,FIND("sec",G33)-FIND("min",G33)-4))/100 -> 1.14
B34: Mosaic | C34: 0 min 28 sec | D34: 156 | E34: 2 min 20 sec | F34: 382 | G34: =TEXT( ( ( (LEFT(C34,FIND("min",C34)-2)*60 + MID(C34,FIND("min",C34)+4,FIND("sec",C34)-FIND("min",C34)-4))*D34 + (LEFT(E34,FIND("min",E34)-2)*60 + MID(E34,FIND("min",E34)+4,FIND("sec",E34)-FIND("min",E34)-4))*F34 ) / (D34+F34) )/86400, "m ""min"" s ""sec""" ) -> 1 min 48 sec | H34: =VALUE(LEFT(G34,FIND("min",G34)-1)) + VALUE(MID(G34,FIND("min",G34)+4,FIND("sec",G34)-FIND("min",G34)-4))/100 -> 1.48
B35: All Stores | C35: 0 min 30 sec | D35: =sum(D30:D34) -> 1954 | E35: 2 min 1 sec | F35: =SUM(F30:F34) -> 2263 | G35: =TEXT( ( ( (LEFT(C35,FIND("min",C35)-2)*60 + MID(C35,FIND("min",C35)+4,FIND("sec",C35)-FIND("min",C35)-4))*D35 + (LEFT(E35,FIND("min",E35)-2)*60 + MID(E35,FIND("min",E35)+4,FIND("sec",E35)-FIND("min",E35)-4))*F35 ) / (D35+F35) )/86400, "m ""min"" s ""sec""" ) -> 1 min 19 sec | H35: =VALUE(LEFT(G35,FIND("min",G35)-1)) + VALUE(MID(G35,FIND("min",G35)+4,FIND("sec",G35)-FIND("min",G35)-4))/100 -> 1.19
F36: 5 Star | G36: 4 Star | I36: 2 Star | J36: 1 Star

Sheet Quaterly Tables
B2: Location | C2: Sales | D2: Same Q LY | E2: Dollar Change | F2: Percent Change | G2: PD Budget | H2: Var to Bud +/- | I2: Var to Bud | J2: Total Labor | K2: Bud Labor | L2: Var Lbr to Bud | M2: Total COGS | N2: Bud COGS | O2: Var COGS to Bud | P2: Total PC | Q2: Bud PC | R2: Var PC to Bud | S2: EBIDTA Actual $ | T2: EBIDTA Budget $ | U2: Var $ Budget | V2: Var % Budget
B3: Ballpark | C3: =IFERROR(__xludf.DUMMYFUNCTION("IMPORTRANGE(""https://docs.google.com/spreadsheets/d/1TW_RsaigtJP9yoaGaPBfE07-92H6VNOYrHbLByvNJmg/edit?gid=1646739031#gid=1646739031"",""Revenue Q4!D8:D13"")"),"#REF!") -> #REF! | D3: =IFERROR(__xludf.DUMMYFUNCTION("IMPORTRANGE(""https://docs.google.com/spreadsheets/d/1TW_RsaigtJP9yoaGaPBfE07-92H6VNOYrHbLByvNJmg/edit?gid=1646739031#gid=1646739031"",""Revenue Q4!I8:I13"")"),"#REF!") -> #REF! | E3: =C3-D3 -> #REF! | F3: =E3/D3 -> #REF! | G3: =IFERROR(__xludf.DUMMYFUNCTION("IMPORTRANGE(""https://docs.google.com/spreadsheets/d/1TW_RsaigtJP9yoaGaPBfE07-92H6VNOYrHbLByvNJmg/edit?gid=1646739031#gid=1646739031"",""Revenue Q4!F8:F13"")"),"#REF!") -> #REF! | H3: =C3-G3 -> #REF! | I3: =H3/G3 -> #REF! | J3: =IFERROR(__xludf.DUMMYFUNCTION("IMPORTRANGE(""https://docs.google.com/spreadsheets/d/1TW_RsaigtJP9yoaGaPBfE07-92H6VNOYrHbLByvNJmg/edit?gid=1646739031#gid=1646739031"",""Q4 Overall PC!R13:R18"")"),"#REF!") -> #REF! | K3: =IFERROR(__xludf.DUMMYFUNCTION("IMPORTRANGE(""https://docs.google.com/spreadsheets/d/1TW_RsaigtJP9yoaGaPBfE07-92H6VNOYrHbLByvNJmg/edit?gid=1646739031#gid=1646739031"",""Q4 Overall PC!T13:T18"")"),"#REF!") -> #REF! | L3: =IFERROR(__xludf.DUMMYFUNCTION("IMPORTRANGE(""https://docs.google.com/spreadsheets/d/1TW_RsaigtJP9yoaGaPBfE07-92H6VNOYrHbLByvNJmg/edit?gid=1646739031#gid=1646739031"",""Q4 Overall PC!U13:U18"")"),"#REF!") -> #REF! | M3: =IFERROR(__xludf.DUMMYFUNCTION("IMPORTRANGE(""https://docs.google.com/spreadsheets/d/1TW_RsaigtJP9yoaGaPBfE07-92H6VNOYrHbLByvNJmg/edit?gid=1646739031#gid=1646739031"",""Q4 Overall PC!F13:F18"")"),"#REF!") -> #REF! | N3: =IFERROR(__xludf.DUMMYFUNCTION("IMPORTRANGE(""https://docs.google.com/spreadsheets/d/1TW_RsaigtJP9yoaGaPBfE07-92H6VNOYrHbLByvNJmg/edit?gid=1646739031#gid=1646739031"",""Q4 Overall PC!H13:H18"")"),"#REF!") -> #REF! | O3: =IFERROR(__xludf.DUMMYFUNCTION("IMPORTRANGE(""https://docs.google.com/spreadsheets/d/1TW_RsaigtJP9yoaGaPBfE07-92H6VNOYrHbLByvNJmg/edit?gid=1646739031#gid=1646739031"",""Q4 Overall PC!I13:I18"")"),"#REF!") -> #REF! | P3: =IFERROR(__xludf.DUMMYFUNCTION("IMPORTRANGE(""https://docs.google.com/spreadsheets/d/1TW_RsaigtJP9yoaGaPBfE07-92H6VNOYrHbLByvNJmg/edit?gid=1646739031#gid=1646739031"",""Q4 Overall PC!AF13:AF18"")"),"#REF!") -> #REF! | Q3: =IFERROR(__xludf.DUMMYFUNCTION("IMPORTRANGE(""https://docs.google.com/spreadsheets/d/1TW_RsaigtJP9yoaGaPBfE07-92H6VNOYrHbLByvNJmg/edit?gid=1646739031#gid=1646739031"",""Q4 Overall PC!AH13:AH18"")"),"#REF!") -> #REF! | R3: =IFERROR(__xludf.DUMMYFUNCTION("IMPORTRANGE(""https://docs.google.com/spreadsheets/d/1TW_RsaigtJP9yoaGaPBfE07-92H6VNOYrHbLByvNJmg/edit?gid=1646739031#gid=1646739031"",""Q4 Overall PC!AH13:AH18"")"),"#REF!") -> #REF! | S3: =IFERROR(__xludf.DUMMYFUNCTION("IMPORTRANGE(""https://docs.google.com/spreadsheets/d/1TW_RsaigtJP9yoaGaPBfE07-92H6VNOYrHbLByvNJmg/edit?gid=1646739031#gid=1646739031"",""Q4 EBIDTA!B7:B12"")"),"#REF!") -> #REF! | T3: =IFERROR(__xludf.DUMMYFUNCTION("IMPORTRANGE(""https://docs.google.com/spreadsheets/d/1TW_RsaigtJP9yoaGaPBfE07-92H6VNOYrHbLByvNJmg/edit?gid=1646739031#gid=1646739031"",""Q4 EBIDTA!C7:C12"")"),"#REF!") -> #REF! | U3: =IFERROR(__xludf.DUMMYFUNCTION("IMPORTRANGE(""https://docs.google.com/spreadsheets/d/1TW_RsaigtJP9yoaGaPBfE07-92H6VNOYrHbLByvNJmg/edit?gid=1646739031#gid=1646739031"",""Q4 EBIDTA!D7:D12"")"),"#REF!") -> #REF! | V3: =IFERROR(__xludf.DUMMYFUNCTION("IMPORTRANGE(""https://docs.google.com/spreadsheets/d/1TW_RsaigtJP9yoaGaPBfE07-92H6VNOYrHbLByvNJmg/edit?gid=1646739031#gid=1646739031"",""Q4 EBIDTA!E7:E12"")"),"#REF!") -> #REF!
B4: Mosaic | E4: =C4-D4 -> 0 | F4: =E4/D4 -> #DIV/0! | H4: =C4-G4 -> 0 | I4: =H4/G4 -> #DIV/0!
B5: MVT | E5: =C5-D5 -> 0 | F5: =E5/D5 -> #DIV/0! | H5: =C5-G5 -> 0 | I5: =H5/G5 -> #DIV/0!
B6: National Landing | E6: =C6-D6 -> 0 | F6: =E6/D6 -> #DIV/0! | H6: =C6-G6 -> 0 | I6: =H6/G6 -> #DIV/0!
B7: Rockville | E7: =C7-D7 -> 0 | F7: =E7/D7 -> #DIV/0! | H7: =C7-G7 -> 0 | I7: =H7/G7 -> #DIV/0!
B8: Totals | E8: =C8-D8 -> 0 | F8: =E8/D8 -> #DIV/0! | H8: =C8-G8 -> 0 | I8: =H8/G8 -> #DIV/0!
B11: In-Store Metrics | C11: Location | D11: # Reviews | E11: Rating | F11: Yelp | G11: Yelp # | H11: Google | I11: Google #
B12: Weekly | C12: Ballpark | D12: 2 | E12: 5 | F12: NA | G12: 0 | H12: 5 | I12: 2
B13: Yelp and Google | C13: MVT | D13: 4 | E13: 3 | F13: 1 | G13: 1 | H13: 3.97 | I13: 3
C14: NL | D14: 6 | E14: 4.33 | F14: NA | G14: 0 | H14: 4.33 | I14: 6
C15: Mosaic | D15: 9 | E15: 4.67 | F15: 4 | G15: 1 | H15: 4.75 | I15: 8
C16: Rockville | D16: 15 | E16: 4.47 | F16: NA | G16: 0 | H16: 4.47 | I16: 15
C17: Total | D17: =SUM(D12:D16) -> 36 | E17: =AVERAGE(E12:E16) -> 4.294 | F17: =AVERAGE(F12:F16) -> 2.5 | H17: =AVERAGE(H12:H16) -> 4.504
B19: 3rd Party Metrics | C19: Location | D19: # Reviews | E19: Rating | F19: Uber | G19: DD | H19: GH | I19: Error Rate
B20: Weekly | C20: Ballpark | D20: 19 | E20: 4 | F20: 4.73 | G20: 4 | H20: NA | I20: 0.0405
B21: UE / DD / GH | C21: MVT | D21: 107 | E21: 4.5 | F21: 4.59 | G21: 4.25 | H21: NA | I21: 0.0264
C22: NL | D22: 66 | E22: 4.3 | F22: 4.69 | G22: 3.97 | H22: NA | I22: 0.0315
C23: Mosaic | D23: 40 | E23: 4.4 | F23: 4.57 | G23: 4.31 | H23: NA | I23: 0.0315
C24: Rockville | D24: 49 | E24: 4.3 | F24: 4.61 | G24: 4.19 | H24: NA | I24: 0.045
C25: Total | D25: =SUM(D20:D24) -> 281 | E25: =AVERAGE(E20:E24) -> 4.3 | I25: =AVERAGE(I20:I24) -> 0.03498
B27: Weighted avoidable wait time
C28: Uber Eats | E28: Door Dash | I28: 2 Star | J28: 1 Star
B29: Location | C29: Avoidable Wait Time | D29: Order Volume | E29: Avoidable Wait Time | F29: Order Volume | G29: Weighted Average | H29: Final weighted average
B30: Rockville | C30: 0 min 56 sec | D30: 214 | E30: 2 min 42 sec | F30: 374 | G30: =TEXT( ( ( (LEFT(C30,FIND("min",C30)-2)*60 + MID(C30,FIND("min",C30)+4,FIND("sec",C30)-FIND("min",C30)-4))*D30 + (LEFT(E30,FIND("min",E30)-2)*60 + MID(E30,FIND("min",E30)+4,FIND("sec",E30)-FIND("min",E30)-4))*F30 ) / (D30+F30) )/86400, "m ""min"" s ""sec""" ) -> 2 min 3 sec | H30: =VALUE(LEFT(G30,FIND("min",G30)-1)) + VALUE(MID(G30,FIND("min",G30)+4,FIND("sec",G30)-FIND("min",G30)-4))/100 -> 2.03
B31: Ballpark | C31: 0 min 26 sec | D31: 361 | E31: 1 min 39 sec | F31: 263 | G31: =TEXT( ( ( (LEFT(C31,FIND("min",C31)-2)*60 + MID(C31,FIND("min",C31)+4,FIND("sec",C31)-FIND("min",C31)-4))*D31 + (LEFT(E31,FIND("min",E31)-2)*60 + MID(E31,FIND("min",E31)+4,FIND("sec",E31)-FIND("min",E31)-4))*F31 ) / (D31+F31) )/86400, "m ""min"" s ""sec""" ) -> 0 min 57 sec | H31: =VALUE(LEFT(G31,FIND("min",G31)-1)) + VALUE(MID(G31,FIND("min",G31)+4,FIND("sec",G31)-FIND("min",G31)-4))/100 -> 0.57
B32: MVT | C32: 0 min 23 sec | D32: 784 | E32: 1 min 36 sec | F32: 761 | G32: =TEXT( ( ( (LEFT(C32,FIND("min",C32)-2)*60 + MID(C32,FIND("min",C32)+4,FIND("sec",C32)-FIND("min",C32)-4))*D32 + (LEFT(E32,FIND("min",E32)-2)*60 + MID(E32,FIND("min",E32)+4,FIND("sec",E32)-FIND("min",E32)-4))*F32 ) / (D32+F32) )/86400, "m ""min"" s ""sec""" ) -> 0 min 59 sec | H32: =VALUE(LEFT(G32,FIND("min",G32)-1)) + VALUE(MID(G32,FIND("min",G32)+4,FIND("sec",G32)-FIND("min",G32)-4))/100 -> 0.59
B33: National Landing | C33: 0 min 29 sec | D33: 439 | E33: 1 min 55 sec | F33: 483 | G33: =TEXT( ( ( (LEFT(C33,FIND("min",C33)-2)*60 + MID(C33,FIND("min",C33)+4,FIND("sec",C33)-FIND("min",C33)-4))*D33 + (LEFT(E33,FIND("min",E33)-2)*60 + MID(E33,FIND("min",E33)+4,FIND("sec",E33)-FIND("min",E33)-4))*F33 ) / (D33+F33) )/86400, "m ""min"" s ""sec""" ) -> 1 min 14 sec | H33: =VALUE(LEFT(G33,FIND("min",G33)-1)) + VALUE(MID(G33,FIND("min",G33)+4,FIND("sec",G33)-FIND("min",G33)-4))/100 -> 1.14
B34: Mosaic | C34: 0 min 28 sec | D34: 156 | E34: 2 min 20 sec | F34: 382 | G34: =TEXT( ( ( (LEFT(C34,FIND("min",C34)-2)*60 + MID(C34,FIND("min",C34)+4,FIND("sec",C34)-FIND("min",C34)-4))*D34 + (LEFT(E34,FIND("min",E34)-2)*60 + MID(E34,FIND("min",E34)+4,FIND("sec",E34)-FIND("min",E34)-4))*F34 ) / (D34+F34) )/86400, "m ""min"" s ""sec""" ) -> 1 min 48 sec | H34: =VALUE(LEFT(G34,FIND("min",G34)-1)) + VALUE(MID(G34,FIND("min",G34)+4,FIND("sec",G34)-FIND("min",G34)-4))/100 -> 1.48
B35: All Stores | C35: 0 min 30 sec | D35: =sum(D30:D34) -> 1954 | E35: 2 min 1 sec | F35: =SUM(F30:F34) -> 2263 | G35: =TEXT( ( ( (LEFT(C35,FIND("min",C35)-2)*60 + MID(C35,FIND("min",C35)+4,FIND("sec",C35)-FIND("min",C35)-4))*D35 + (LEFT(E35,FIND("min",E35)-2)*60 + MID(E35,FIND("min",E35)+4,FIND("sec",E35)-FIND("min",E35)-4))*F35 ) / (D35+F35) )/86400, "m ""min"" s ""sec""" ) -> 1 min 19 sec | H35: =VALUE(LEFT(G35,FIND("min",G35)-1)) + VALUE(MID(G35,FIND("min",G35)+4,FIND("sec",G35)-FIND("min",G35)-4))/100 -> 1.19
F36: 5 Star | G36: 4 Star | H36: 3 Star | I36: 2 Star | J36: 1 Star
