Workbook

Sheet Sheet1

Sheet Sheet1 (1)

Sheet Summary
C1: =B2 -> Week Ending 01/25/2026 | D1: =C1 -> Week Ending 01/25/2026 | E1: =+D1 -> Week Ending 01/25/2026 | F1: =+E1 -> Week Ending 01/25/2026 | G1: Period To Date | H1: Period To Date | I1: Period To Date | J1: Period To Date | K1: Trailing 4 week | L1: Trailing 4 week | M1: Trailing 4 week | N1: Trailing 4 week | R1: Trailing 8 week | S1: Trailing 8 week | T1: Trailing 8 week | U1: Trailing 8 week
B2: Week Ending 01/25/2026 | G2: Current Period | K2: 4-Week Average | O2: 4-Week Average Comparison | R2: 8-Week Average | V2: 8-Week Average Comparison
B3: Location | C3: Sales | D3: COGS | E3: Labor | F3: Prime Margin | G3: Sales | H3: COGS | I3: Total Labor Cost | J3: Prime Margin | K3: Sales | L3: COGS | M3: Total Labor Cost | N3: Prime Margin | O3: Sales Current Week vs 4-week | P3: COGS Current Week vs 4-week | Q3: Labor Current Week vs 4-week | R3: Sales | S3: COGS | T3: Total Labor Cost | U3: Prime Margin | V3: Sales Current Week vs 8-week | W3: COGS Current Week vs 8-week | X3: Labor Current Week vs 8-week
B4: Location | C4: Total Sales | D4: Total Cost of Goods Sold | E4: Total Payroll Expenses | F4: Prime Profit | G4: Total Sales | H4: Total Cost of Goods Sold | I4: Total Payroll Expenses | J4: Prime Profit | K4: Total Sales | L4: Total Cost of Goods Sold | M4: Total Payroll Expenses | N4: Prime Profit | R4: Total Sales | S4: Total Cost of Goods Sold | T4: Total Payroll Expenses | U4: Prime Profit
A5: 2 - RASA - Ballpark | B5: =A5 -> 2 - RASA - Ballpark | C5: =INDEX(INDIRECT("'"&$A5&"'!$1:$1048576"),MATCH(C$4,INDIRECT("'"&$A5&"'!A:A"),0),MATCH(C$1,INDIRECT("'"&$A5&"'!$5:$5"),0)) -> 20034.79 | D5: {=INDEX(INDIRECT("'"&$A5&"'!$1:$1048576"),MATCH(D$4,INDIRECT("'"&$A5&"'!A:A"),0),MATCH(D$1,INDIRECT("'"&$A5&"'!$5:$5"),0)+1)} -> 0.27586613 | E5: {=INDEX(INDIRECT("'"&$A5&"'!$1:$1048576"),MATCH(E$4,INDIRECT("'"&$A5&"'!A:A"),0),MATCH(E$1,INDIRECT("'"&$A5&"'!$5:$5"),0)+1)} -> 0.30742973 | F5: {=INDEX(INDIRECT("'"&$A5&"'!$1:$1048576"),MATCH(F$4,INDIRECT("'"&$A5&"'!A:A"),0),MATCH(F$1,INDIRECT("'"&$A5&"'!$5:$5"),0)+1)} -> 0.41670414 | G5: =INDEX(INDIRECT("'"&$A5&"'!$1:$1048576"),MATCH(G$4,INDIRECT("'"&$A5&"'!A:A"),0),MATCH(G$1,INDIRECT("'"&$A5&"'!$5:$5"),0)) -> 67478.95 | H5: {=INDEX(INDIRECT("'"&$A5&"'!$1:$1048576"),MATCH(H$4,INDIRECT("'"&$A5&"'!A:A"),0),MATCH(H$1,INDIRECT("'"&$A5&"'!$5:$5"),0)+1)} -> 0.28315749 | I5: {=INDEX(INDIRECT("'"&$A5&"'!$1:$1048576"),MATCH(I$4,INDIRECT("'"&$A5&"'!A:A"),0),MATCH(I$1,INDIRECT("'"&$A5&"'!$5:$5"),0)+1)} -> 0.35384531 | J5: {=INDEX(INDIRECT("'"&$A5&"'!$1:$1048576"),MATCH(J$4,INDIRECT("'"&$A5&"'!A:A"),0),MATCH(J$1,INDIRECT("'"&$A5&"'!$5:$5"),0)+1)} -> 0.3629972 | K5: =INDEX(INDIRECT("'"&$A5&"'!$1:$1048576"),MATCH(K$4,INDIRECT("'"&$A5&"'!A:A"),0),MATCH(K$1,INDIRECT("'"&$A5&"'!$5:$5"),0)) -> 16869.737 | L5: {=INDEX(INDIRECT("'"&$A5&"'!$1:$1048576"),MATCH(L$4,INDIRECT("'"&$A5&"'!A:A"),0),MATCH(L$1,INDIRECT("'"&$A5&"'!$5:$5"),0)+1)} -> 0.28315749 | M5: {=INDEX(INDIRECT("'"&$A5&"'!$1:$1048576"),MATCH(M$4,INDIRECT("'"&$A5&"'!A:A"),0),MATCH(M$1,INDIRECT("'"&$A5&"'!$5:$5"),0)+1)} -> 0.35384531 | N5: {=INDEX(INDIRECT("'"&$A5&"'!$1:$1048576"),MATCH(N$4,INDIRECT("'"&$A5&"'!A:A"),0),MATCH(N$1,INDIRECT("'"&$A5&"'!$5:$5"),0)+1)} -> 0.3629972 | O5: =+(C5-K5)/K5 -> 0.18761718 | P5: =+D5-L5 -> -0.0072913575 | Q5: =+E5-M5 -> -0.046415584 | R5: =INDEX(INDIRECT("'"&$A5&"'!$1:$1048576"),MATCH(R$4,INDIRECT("'"&$A5&"'!A:A"),0),MATCH(R$1,INDIRECT("'"&$A5&"'!$5:$5"),0)) -> 17353.603 | S5: {=INDEX(INDIRECT("'"&$A5&"'!$1:$1048576"),MATCH(S$4,INDIRECT("'"&$A5&"'!A:A"),0),MATCH(S$1,INDIRECT("'"&$A5&"'!$5:$5"),0)+1)} -> 0.27992084 | T5: {=INDEX(INDIRECT("'"&$A5&"'!$1:$1048576"),MATCH(T$4,INDIRECT("'"&$A5&"'!A:A"),0),MATCH(T$1,INDIRECT("'"&$A5&"'!$5:$5"),0)+1)} -> 0.35029492 | U5: {=INDEX(INDIRECT("'"&$A5&"'!$1:$1048576"),MATCH(U$4,INDIRECT("'"&$A5&"'!A:A"),0),MATCH(U$1,INDIRECT("'"&$A5&"'!$5:$5"),0)+1)} -> 0.36978424 | V5: =+(C5-R5)/R5 -> 0.15450322 | W5: =+D5-S5 -> -0.0040547098 | X5: =+E5-T5 -> -0.042865191 | AK5: Week 1 | AL5: 46026 | AM5: =YEAR(AL5) -> 2026 | AN5: =AK5&", "&AM5 -> Week 1, 2026 | AO5: ="Week Ending "&TEXT(AL5,"mm/dd/yyyy") -> Week Ending 01/04/2026
A6: 4 - RASA - MVT | B6: =A6 -> 4 - RASA - MVT | C6: =INDEX(INDIRECT("'"&$A6&"'!$1:$1048576"),MATCH(C$4,INDIRECT("'"&$A6&"'!A:A"),0),MATCH(C$1,INDIRECT("'"&$A6&"'!$5:$5"),0)) -> 39699.41 | D6: {=INDEX(INDIRECT("'"&$A6&"'!$1:$1048576"),MATCH(D$4,INDIRECT("'"&$A6&"'!A:A"),0),MATCH(D$1,INDIRECT("'"&$A6&"'!$5:$5"),0)+1)} -> 0.24622608 | E6: {=INDEX(INDIRECT("'"&$A6&"'!$1:$1048576"),MATCH(E$4,INDIRECT("'"&$A6&"'!A:A"),0),MATCH(E$1,INDIRECT("'"&$A6&"'!$5:$5"),0)+1)} -> 0.26941332 | F6: {=INDEX(INDIRECT("'"&$A6&"'!$1:$1048576"),MATCH(F$4,INDIRECT("'"&$A6&"'!A:A"),0),MATCH(F$1,INDIRECT("'"&$A6&"'!$5:$5"),0)+1)} -> 0.4843606 | G6: =INDEX(INDIRECT("'"&$A6&"'!$1:$1048576"),MATCH(G$4,INDIRECT("'"&$A6&"'!A:A"),0),MATCH(G$1,INDIRECT("'"&$A6&"'!$5:$5"),0)) -> 130404.64 | H6: {=INDEX(INDIRECT("'"&$A6&"'!$1:$1048576"),MATCH(H$4,INDIRECT("'"&$A6&"'!A:A"),0),MATCH(H$1,INDIRECT("'"&$A6&"'!$5:$5"),0)+1)} -> 0.27629584 | I6: {=INDEX(INDIRECT("'"&$A6&"'!$1:$1048576"),MATCH(I$4,INDIRECT("'"&$A6&"'!A:A"),0),MATCH(I$1,INDIRECT("'"&$A6&"'!$5:$5"),0)+1)} -> 0.28441695 | J6: {=INDEX(INDIRECT("'"&$A6&"'!$1:$1048576"),MATCH(J$4,INDIRECT("'"&$A6&"'!A:A"),0),MATCH(J$1,INDIRECT("'"&$A6&"'!$5:$5"),0)+1)} -> 0.43928721 | K6: =INDEX(INDIRECT("'"&$A6&"'!$1:$1048576"),MATCH(K$4,INDIRECT("'"&$A6&"'!A:A"),0),MATCH(K$1,INDIRECT("'"&$A6&"'!$5:$5"),0)) -> 32601.16 | L6: {=INDEX(INDIRECT("'"&$A6&"'!$1:$1048576"),MATCH(L$4,INDIRECT("'"&$A6&"'!A:A"),0),MATCH(L$1,INDIRECT("'"&$A6&"'!$5:$5"),0)+1)} -> 0.27629584 | M6: {=INDEX(INDIRECT("'"&$A6&"'!$1:$1048576"),MATCH(M$4,INDIRECT("'"&$A6&"'!A:A"),0),MATCH(M$1,INDIRECT("'"&$A6&"'!$5:$5"),0)+1)} -> 0.28441695 | N6: {=INDEX(INDIRECT("'"&$A6&"'!$1:$1048576"),MATCH(N$4,INDIRECT("'"&$A6&"'!A:A"),0),MATCH(N$1,INDIRECT("'"&$A6&"'!$5:$5"),0)+1)} -> 0.43928721 | O6: =+(C6-K6)/K6 -> 0.21772998 | P6: =+D6-L6 -> -0.030069766 | Q6: =+E6-M6 -> -0.015003626 | R6: =INDEX(INDIRECT("'"&$A6&"'!$1:$1048576"),MATCH(R$4,INDIRECT("'"&$A6&"'!A:A"),0),MATCH(R$1,INDIRECT("'"&$A6&"'!$5:$5"),0)) -> 33185.844 | S6: {=INDEX(INDIRECT("'"&$A6&"'!$1:$1048576"),MATCH(S$4,INDIRECT("'"&$A6&"'!A:A"),0),MATCH(S$1,INDIRECT("'"&$A6&"'!$5:$5"),0)+1)} -> 0.27627454 | T6: {=INDEX(INDIRECT("'"&$A6&"'!$1:$1048576"),MATCH(T$4,INDIRECT("'"&$A6&"'!A:A"),0),MATCH(T$1,INDIRECT("'"&$A6&"'!$5:$5"),0)+1)} -> 0.27740209 | U6: {=INDEX(INDIRECT("'"&$A6&"'!$1:$1048576"),MATCH(U$4,INDIRECT("'"&$A6&"'!A:A"),0),MATCH(U$1,INDIRECT("'"&$A6&"'!$5:$5"),0)+1)} -> 0.44632337 | V6: =+(C6-R6)/R6 -> 0.19627544 | W6: =+D6-S6 -> -0.030048464 | X6: =+E6-T6 -> -0.0079887688 | AK6: Week 2 | AL6: 46033 | AM6: =YEAR(AL6) -> 2026 | AN6: =AK6&", "&AM6 -> Week 2, 2026 | AO6: ="Week Ending "&TEXT(AL6,"mm/dd/yyyy") -> Week Ending 01/11/2026
A7: 5 - RASA - National Landin | B7: =A7 -> 5 - RASA - National Landin | C7: =INDEX(INDIRECT("'"&$A7&"'!$1:$1048576"),MATCH(C$4,INDIRECT("'"&$A7&"'!A:A"),0),MATCH(C$1,INDIRECT("'"&$A7&"'!$5:$5"),0)) -> 16370.43 | D7: {=INDEX(INDIRECT("'"&$A7&"'!$1:$1048576"),MATCH(D$4,INDIRECT("'"&$A7&"'!A:A"),0),MATCH(D$1,INDIRECT("'"&$A7&"'!$5:$5"),0)+1)} -> 0.25379663 | E7: {=INDEX(INDIRECT("'"&$A7&"'!$1:$1048576"),MATCH(E$4,INDIRECT("'"&$A7&"'!A:A"),0),MATCH(E$1,INDIRECT("'"&$A7&"'!$5:$5"),0)+1)} -> 0.33503213 | F7: {=INDEX(INDIRECT("'"&$A7&"'!$1:$1048576"),MATCH(F$4,INDIRECT("'"&$A7&"'!A:A"),0),MATCH(F$1,INDIRECT("'"&$A7&"'!$5:$5"),0)+1)} -> 0.41117124 | G7: =INDEX(INDIRECT("'"&$A7&"'!$1:$1048576"),MATCH(G$4,INDIRECT("'"&$A7&"'!A:A"),0),MATCH(G$1,INDIRECT("'"&$A7&"'!$5:$5"),0)) -> 71792.78 | H7: {=INDEX(INDIRECT("'"&$A7&"'!$1:$1048576"),MATCH(H$4,INDIRECT("'"&$A7&"'!A:A"),0),MATCH(H$1,INDIRECT("'"&$A7&"'!$5:$5"),0)+1)} -> 0.26518321 | I7: {=INDEX(INDIRECT("'"&$A7&"'!$1:$1048576"),MATCH(I$4,INDIRECT("'"&$A7&"'!A:A"),0),MATCH(I$1,INDIRECT("'"&$A7&"'!$5:$5"),0)+1)} -> 0.30130272 | J7: {=INDEX(INDIRECT("'"&$A7&"'!$1:$1048576"),MATCH(J$4,INDIRECT("'"&$A7&"'!A:A"),0),MATCH(J$1,INDIRECT("'"&$A7&"'!$5:$5"),0)+1)} -> 0.43351407 | K7: =INDEX(INDIRECT("'"&$A7&"'!$1:$1048576"),MATCH(K$4,INDIRECT("'"&$A7&"'!A:A"),0),MATCH(K$1,INDIRECT("'"&$A7&"'!$5:$5"),0)) -> 17948.195 | L7: {=INDEX(INDIRECT("'"&$A7&"'!$1:$1048576"),MATCH(L$4,INDIRECT("'"&$A7&"'!A:A"),0),MATCH(L$1,INDIRECT("'"&$A7&"'!$5:$5"),0)+1)} -> 0.26518321 | M7: {=INDEX(INDIRECT("'"&$A7&"'!$1:$1048576"),MATCH(M$4,INDIRECT("'"&$A7&"'!A:A"),0),MATCH(M$1,INDIRECT("'"&$A7&"'!$5:$5"),0)+1)} -> 0.30130272 | N7: {=INDEX(INDIRECT("'"&$A7&"'!$1:$1048576"),MATCH(N$4,INDIRECT("'"&$A7&"'!A:A"),0),MATCH(N$1,INDIRECT("'"&$A7&"'!$5:$5"),0)+1)} -> 0.43351407 | O7: =+(C7-K7)/K7 -> -0.087906611 | P7: =+D7-L7 -> -0.01138658 | Q7: =+E7-M7 -> 0.033729407 | R7: =INDEX(INDIRECT("'"&$A7&"'!$1:$1048576"),MATCH(R$4,INDIRECT("'"&$A7&"'!A:A"),0),MATCH(R$1,INDIRECT("'"&$A7&"'!$5:$5"),0)) -> 18114.14 | S7: {=INDEX(INDIRECT("'"&$A7&"'!$1:$1048576"),MATCH(S$4,INDIRECT("'"&$A7&"'!A:A"),0),MATCH(S$1,INDIRECT("'"&$A7&"'!$5:$5"),0)+1)} -> 0.27066031 | T7: {=INDEX(INDIRECT("'"&$A7&"'!$1:$1048576"),MATCH(T$4,INDIRECT("'"&$A7&"'!A:A"),0),MATCH(T$1,INDIRECT("'"&$A7&"'!$5:$5"),0)+1)} -> 0.31367256 | U7: {=INDEX(INDIRECT("'"&$A7&"'!$1:$1048576"),MATCH(U$4,INDIRECT("'"&$A7&"'!A:A"),0),MATCH(U$1,INDIRECT("'"&$A7&"'!$5:$5"),0)+1)} -> 0.41566713 | V7: =+(C7-R7)/R7 -> -0.096262367 | W7: =+D7-S7 -> -0.016863678 | X7: =+E7-T7 -> 0.021359563 | AK7: Week 3 | AL7: 46040 | AM7: =YEAR(AL7) -> 2026 | AN7: =AK7&", "&AM7 -> Week 3, 2026 | AO7: ="Week Ending "&TEXT(AL7,"mm/dd/yyyy") -> Week Ending 01/18/2026
A8: 6 - RASA - Mosaic | B8: =A8 -> 6 - RASA - Mosaic | C8: =INDEX(INDIRECT("'"&$A8&"'!$1:$1048576"),MATCH(C$4,INDIRECT("'"&$A8&"'!A:A"),0),MATCH(C$1,INDIRECT("'"&$A8&"'!$5:$5"),0)) -> 17376.74 | D8: {=INDEX(INDIRECT("'"&$A8&"'!$1:$1048576"),MATCH(D$4,INDIRECT("'"&$A8&"'!A:A"),0),MATCH(D$1,INDIRECT("'"&$A8&"'!$5:$5"),0)+1)} -> 0.27953402 | E8: {=INDEX(INDIRECT("'"&$A8&"'!$1:$1048576"),MATCH(E$4,INDIRECT("'"&$A8&"'!A:A"),0),MATCH(E$1,INDIRECT("'"&$A8&"'!$5:$5"),0)+1)} -> 0.30349191 | F8: {=INDEX(INDIRECT("'"&$A8&"'!$1:$1048576"),MATCH(F$4,INDIRECT("'"&$A8&"'!A:A"),0),MATCH(F$1,INDIRECT("'"&$A8&"'!$5:$5"),0)+1)} -> 0.41697407 | G8: =INDEX(INDIRECT("'"&$A8&"'!$1:$1048576"),MATCH(G$4,INDIRECT("'"&$A8&"'!A:A"),0),MATCH(G$1,INDIRECT("'"&$A8&"'!$5:$5"),0)) -> 72028.36 | H8: {=INDEX(INDIRECT("'"&$A8&"'!$1:$1048576"),MATCH(H$4,INDIRECT("'"&$A8&"'!A:A"),0),MATCH(H$1,INDIRECT("'"&$A8&"'!$5:$5"),0)+1)} -> 0.28608995 | I8: {=INDEX(INDIRECT("'"&$A8&"'!$1:$1048576"),MATCH(I$4,INDIRECT("'"&$A8&"'!A:A"),0),MATCH(I$1,INDIRECT("'"&$A8&"'!$5:$5"),0)+1)} -> 0.33807878 | J8: {=INDEX(INDIRECT("'"&$A8&"'!$1:$1048576"),MATCH(J$4,INDIRECT("'"&$A8&"'!A:A"),0),MATCH(J$1,INDIRECT("'"&$A8&"'!$5:$5"),0)+1)} -> 0.37583127 | K8: =INDEX(INDIRECT("'"&$A8&"'!$1:$1048576"),MATCH(K$4,INDIRECT("'"&$A8&"'!A:A"),0),MATCH(K$1,INDIRECT("'"&$A8&"'!$5:$5"),0)) -> 18007.09 | L8: {=INDEX(INDIRECT("'"&$A8&"'!$1:$1048576"),MATCH(L$4,INDIRECT("'"&$A8&"'!A:A"),0),MATCH(L$1,INDIRECT("'"&$A8&"'!$5:$5"),0)+1)} -> 0.28608995 | M8: {=INDEX(INDIRECT("'"&$A8&"'!$1:$1048576"),MATCH(M$4,INDIRECT("'"&$A8&"'!A:A"),0),MATCH(M$1,INDIRECT("'"&$A8&"'!$5:$5"),0)+1)} -> 0.33807878 | N8: {=INDEX(INDIRECT("'"&$A8&"'!$1:$1048576"),MATCH(N$4,INDIRECT("'"&$A8&"'!A:A"),0),MATCH(N$1,INDIRECT("'"&$A8&"'!$5:$5"),0)+1)} -> 0.37583127 | O8: =+(C8-K8)/K8 -> -0.035005656 | P8: =+D8-L8 -> -0.0065559305 | Q8: =+E8-M8 -> -0.03458687 | R8: =INDEX(INDIRECT("'"&$A8&"'!$1:$1048576"),MATCH(R$4,INDIRECT("'"&$A8&"'!A:A"),0),MATCH(R$1,INDIRECT("'"&$A8&"'!$5:$5"),0)) -> 20085.236 | S8: {=INDEX(INDIRECT("'"&$A8&"'!$1:$1048576"),MATCH(S$4,INDIRECT("'"&$A8&"'!A:A"),0),MATCH(S$1,INDIRECT("'"&$A8&"'!$5:$5"),0)+1)} -> 0.28645002 | T8: {=INDEX(INDIRECT("'"&$A8&"'!$1:$1048576"),MATCH(T$4,INDIRECT("'"&$A8&"'!A:A"),0),MATCH(T$1,INDIRECT("'"&$A8&"'!$5:$5"),0)+1)} -> 0.33482317 | U8: {=INDEX(INDIRECT("'"&$A8&"'!$1:$1048576"),MATCH(U$4,INDIRECT("'"&$A8&"'!A:A"),0),MATCH(U$1,INDIRECT("'"&$A8&"'!$5:$5"),0)+1)} -> 0.37872681 | V8: =+(C8-R8)/R8 -> -0.13485011 | W8: =+D8-S8 -> -0.0069159955 | X8: =+E8-T8 -> -0.031331262 | AK8: Week 4 | AL8: 46047 | AM8: =YEAR(AL8) -> 2026 | AN8: =AK8&", "&AM8 -> Week 4, 2026 | AO8: ="Week Ending "&TEXT(AL8,"mm/dd/yyyy") -> Week Ending 01/25/2026
A9: 7 - RASA - Rockville | B9: =A9 -> 7 - RASA - Rockville | C9: =INDEX(INDIRECT("'"&$A9&"'!$1:$1048576"),MATCH(C$4,INDIRECT("'"&$A9&"'!A:A"),0),MATCH(C$1,INDIRECT("'"&$A9&"'!$5:$5"),0)) -> 22461.46 | D9: {=INDEX(INDIRECT("'"&$A9&"'!$1:$1048576"),MATCH(D$4,INDIRECT("'"&$A9&"'!A:A"),0),MATCH(D$1,INDIRECT("'"&$A9&"'!$5:$5"),0)+1)} -> 0.31231496 | E9: {=INDEX(INDIRECT("'"&$A9&"'!$1:$1048576"),MATCH(E$4,INDIRECT("'"&$A9&"'!A:A"),0),MATCH(E$1,INDIRECT("'"&$A9&"'!$5:$5"),0)+1)} -> 0.30120437 | F9: {=INDEX(INDIRECT("'"&$A9&"'!$1:$1048576"),MATCH(F$4,INDIRECT("'"&$A9&"'!A:A"),0),MATCH(F$1,INDIRECT("'"&$A9&"'!$5:$5"),0)+1)} -> 0.38648067 | G9: =INDEX(INDIRECT("'"&$A9&"'!$1:$1048576"),MATCH(G$4,INDIRECT("'"&$A9&"'!A:A"),0),MATCH(G$1,INDIRECT("'"&$A9&"'!$5:$5"),0)) -> 89282.66 | H9: {=INDEX(INDIRECT("'"&$A9&"'!$1:$1048576"),MATCH(H$4,INDIRECT("'"&$A9&"'!A:A"),0),MATCH(H$1,INDIRECT("'"&$A9&"'!$5:$5"),0)+1)} -> 0.30209237 | I9: {=INDEX(INDIRECT("'"&$A9&"'!$1:$1048576"),MATCH(I$4,INDIRECT("'"&$A9&"'!A:A"),0),MATCH(I$1,INDIRECT("'"&$A9&"'!$5:$5"),0)+1)} -> 0.3205282 | J9: {=INDEX(INDIRECT("'"&$A9&"'!$1:$1048576"),MATCH(J$4,INDIRECT("'"&$A9&"'!A:A"),0),MATCH(J$1,INDIRECT("'"&$A9&"'!$5:$5"),0)+1)} -> 0.37737944 | K9: =INDEX(INDIRECT("'"&$A9&"'!$1:$1048576"),MATCH(K$4,INDIRECT("'"&$A9&"'!A:A"),0),MATCH(K$1,INDIRECT("'"&$A9&"'!$5:$5"),0)) -> 22320.665 | L9: {=INDEX(INDIRECT("'"&$A9&"'!$1:$1048576"),MATCH(L$4,INDIRECT("'"&$A9&"'!A:A"),0),MATCH(L$1,INDIRECT("'"&$A9&"'!$5:$5"),0)+1)} -> 0.30209237 | M9: {=INDEX(INDIRECT("'"&$A9&"'!$1:$1048576"),MATCH(M$4,INDIRECT("'"&$A9&"'!A:A"),0),MATCH(M$1,INDIRECT("'"&$A9&"'!$5:$5"),0)+1)} -> 0.3205282 | N9: {=INDEX(INDIRECT("'"&$A9&"'!$1:$1048576"),MATCH(N$4,INDIRECT("'"&$A9&"'!A:A"),0),MATCH(N$1,INDIRECT("'"&$A9&"'!$5:$5"),0)+1)} -> 0.37737944 | O9: =+(C9-K9)/K9 -> 0.0063078318 | P9: =+D9-L9 -> 0.010222595 | Q9: =+E9-M9 -> -0.019323823 | R9: =INDEX(INDIRECT("'"&$A9&"'!$1:$1048576"),MATCH(R$4,INDIRECT("'"&$A9&"'!A:A"),0),MATCH(R$1,INDIRECT("'"&$A9&"'!$5:$5"),0)) -> 22103.178 | S9: {=INDEX(INDIRECT("'"&$A9&"'!$1:$1048576"),MATCH(S$4,INDIRECT("'"&$A9&"'!A:A"),0),MATCH(S$1,INDIRECT("'"&$A9&"'!$5:$5"),0)+1)} -> 0.29579638 | T9: {=INDEX(INDIRECT("'"&$A9&"'!$1:$1048576"),MATCH(T$4,INDIRECT("'"&$A9&"'!A:A"),0),MATCH(T$1,INDIRECT("'"&$A9&"'!$5:$5"),0)+1)} -> 0.31621234 | U9: {=INDEX(INDIRECT("'"&$A9&"'!$1:$1048576"),MATCH(U$4,INDIRECT("'"&$A9&"'!A:A"),0),MATCH(U$1,INDIRECT("'"&$A9&"'!$5:$5"),0)+1)} -> 0.38799127 | V9: =+(C9-R9)/R9 -> 0.016209547 | W9: =+D9-S9 -> 0.016518576 | X9: =+E9-T9 -> -0.015007967 | AK9: Week 5 | AL9: 46054 | AM9: =YEAR(AL9) -> 2026 | AN9: =AK9&", "&AM9 -> Week 5, 2026 | AO9: ="Week Ending "&TEXT(AL9,"mm/dd/yyyy") -> Week Ending 02/01/2026
A10: Consolidated | B10: All | C10: =INDEX(INDIRECT("'"&$A10&"'!$1:$1048576"),MATCH(C$4,INDIRECT("'"&$A10&"'!A:A"),0),MATCH(C$1,INDIRECT("'"&$A10&"'!$5:$5"),0)) -> 115942.83 | D10: {=INDEX(INDIRECT("'"&$A10&"'!$1:$1048576"),MATCH(D$4,INDIRECT("'"&$A10&"'!A:A"),0),MATCH(D$1,INDIRECT("'"&$A10&"'!$5:$5"),0)+1)} -> 0.27021205 | E10: {=INDEX(INDIRECT("'"&$A10&"'!$1:$1048576"),MATCH(E$4,INDIRECT("'"&$A10&"'!A:A"),0),MATCH(E$1,INDIRECT("'"&$A10&"'!$5:$5"),0)+1)} -> 0.29651381 | F10: {=INDEX(INDIRECT("'"&$A10&"'!$1:$1048576"),MATCH(F$4,INDIRECT("'"&$A10&"'!A:A"),0),MATCH(F$1,INDIRECT("'"&$A10&"'!$5:$5"),0)+1)} -> 0.43327414 | G10: =INDEX(INDIRECT("'"&$A10&"'!$1:$1048576"),MATCH(G$4,INDIRECT("'"&$A10&"'!A:A"),0),MATCH(G$1,INDIRECT("'"&$A10&"'!$5:$5"),0)) -> 430987.39 | H10: {=INDEX(INDIRECT("'"&$A10&"'!$1:$1048576"),MATCH(H$4,INDIRECT("'"&$A10&"'!A:A"),0),MATCH(H$1,INDIRECT("'"&$A10&"'!$5:$5"),0)+1)} -> 0.28249984 | I10: {=INDEX(INDIRECT("'"&$A10&"'!$1:$1048576"),MATCH(I$4,INDIRECT("'"&$A10&"'!A:A"),0),MATCH(I$1,INDIRECT("'"&$A10&"'!$5:$5"),0)+1)} -> 0.31454895 | J10: {=INDEX(INDIRECT("'"&$A10&"'!$1:$1048576"),MATCH(J$4,INDIRECT("'"&$A10&"'!A:A"),0),MATCH(J$1,INDIRECT("'"&$A10&"'!$5:$5"),0)+1)} -> 0.40295121 | K10: =INDEX(INDIRECT("'"&$A10&"'!$1:$1048576"),MATCH(K$4,INDIRECT("'"&$A10&"'!A:A"),0),MATCH(K$1,INDIRECT("'"&$A10&"'!$5:$5"),0)) -> 107746.85 | L10: {=INDEX(INDIRECT("'"&$A10&"'!$1:$1048576"),MATCH(L$4,INDIRECT("'"&$A10&"'!A:A"),0),MATCH(L$1,INDIRECT("'"&$A10&"'!$5:$5"),0)+1)} -> 0.28249984 | M10: {=INDEX(INDIRECT("'"&$A10&"'!$1:$1048576"),MATCH(M$4,INDIRECT("'"&$A10&"'!A:A"),0),MATCH(M$1,INDIRECT("'"&$A10&"'!$5:$5"),0)+1)} -> 0.31454895 | N10: {=INDEX(INDIRECT("'"&$A10&"'!$1:$1048576"),MATCH(N$4,INDIRECT("'"&$A10&"'!A:A"),0),MATCH(N$1,INDIRECT("'"&$A10&"'!$5:$5"),0)+1)} -> 0.40295121 | O10: =+(C10-K10)/K10 -> 0.076067028 | P10: =+D10-L10 -> -0.012287791 | Q10: =+E10-M10 -> -0.01803514 | R10: =INDEX(INDIRECT("'"&$A10&"'!$1:$1048576"),MATCH(R$4,INDIRECT("'"&$A10&"'!A:A"),0),MATCH(R$1,INDIRECT("'"&$A10&"'!$5:$5"),0)) -> 110842 | S10: {=INDEX(INDIRECT("'"&$A10&"'!$1:$1048576"),MATCH(S$4,INDIRECT("'"&$A10&"'!A:A"),0),MATCH(S$1,INDIRECT("'"&$A10&"'!$5:$5"),0)+1)} -> 0.28166466 | T10: {=INDEX(INDIRECT("'"&$A10&"'!$1:$1048576"),MATCH(T$4,INDIRECT("'"&$A10&"'!A:A"),0),MATCH(T$1,INDIRECT("'"&$A10&"'!$5:$5"),0)+1)} -> 0.312886 | U10: {=INDEX(INDIRECT("'"&$A10&"'!$1:$1048576"),MATCH(U$4,INDIRECT("'"&$A10&"'!A:A"),0),MATCH(U$1,INDIRECT("'"&$A10&"'!$5:$5"),0)+1)} -> 0.40544934 | V10: =+(C10-R10)/R10 -> 0.046018928 | W10: =+D10-S10 -> -0.011452604 | X10: =+E10-T10 -> -0.016372192 | AK10: Week 6 | AL10: 46061 | AM10: =YEAR(AL10) -> 2026 | AN10: =AK10&", "&AM10 -> Week 6, 2026 | AO10: ="Week Ending "&TEXT(AL10,"mm/dd/yyyy") -> Week Ending 02/08/2026
AK11: Week 7 | AL11: 46068 | AM11: =YEAR(AL11) -> 2026 | AN11: =AK11&", "&AM11 -> Week 7, 2026 | AO11: ="Week Ending "&TEXT(AL11,"mm/dd/yyyy") -> Week Ending 02/15/2026
AK12: Week 8 | AL12: 46075 | AM12: =YEAR(AL12) -> 2026 | AN12: =AK12&", "&AM12 -> Week 8, 2026 | AO12: ="Week Ending "&TEXT(AL12,"mm/dd/yyyy") -> Week Ending 02/22/2026
B13: Notes: | AK13: Week 9 | AL13: 46082 | AM13: =YEAR(AL13) -> 2026 | AN13: =AK13&", "&AM13 -> Week 9, 2026 | AO13: ="Week Ending "&TEXT(AL13,"mm/dd/yyyy") -> Week Ending 03/01/2026
AK14: Week 10 | AL14: 46089 | AM14: =YEAR(AL14) -> 2026 | AN14: =AK14&", "&AM14 -> Week 10, 2026 | AO14: ="Week Ending "&TEXT(AL14,"mm/dd/yyyy") -> Week Ending 03/08/2026
B15: RASA - Ballpark | AK15: Week 11 | AL15: 46096 | AM15: =YEAR(AL15) -> 2026 | AN15: =AK15&", "&AM15 -> Week 11, 2026 | AO15: ="Week Ending "&TEXT(AL15,"mm/dd/yyyy") -> Week Ending 03/15/2026
B16: COGS - | C16: No notes | AK16: Week 12 | AL16: 46103 | AM16: =YEAR(AL16) -> 2026 | AN16: =AK16&", "&AM16 -> Week 12, 2026 | AO16: ="Week Ending "&TEXT(AL16,"mm/dd/yyyy") -> Week Ending 03/22/2026
B17: Labor - | C17: Sales up 17% vs 4-8 week comp but total labor $s are only up 2.3% as a % of sales vs same comp. | AK17: Week 13 | AL17: 46110 | AM17: =YEAR(AL17) -> 2026 | AN17: =AK17&", "&AM17 -> Week 13, 2026 | AO17: ="Week Ending "&TEXT(AL17,"mm/dd/yyyy") -> Week Ending 03/29/2026
AK18: Week 14 | AL18: 46117 | AM18: =YEAR(AL18) -> 2026 | AN18: =AK18&", "&AM18 -> Week 14, 2026 | AO18: ="Week Ending "&TEXT(AL18,"mm/dd/yyyy") -> Week Ending 04/05/2026
B19: RASA - MVT | AK19: Week 15 | AL19: 46124 | AM19: =YEAR(AL19) -> 2026 | AN19: =AK19&", "&AM19 -> Week 15, 2026 | AO19: ="Week Ending "&TEXT(AL19,"mm/dd/yyyy") -> Week Ending 04/12/2026
B20: COGS - | C20: Prepped food - 5.8% vs 7.0% 4-8 week comp. However, PTD is comparable at 7.0%. | AK20: Week 16 | AL20: 46131 | AM20: =YEAR(AL20) -> 2026 | AN20: =AK20&", "&AM20 -> Week 16, 2026 | AO20: ="Week Ending "&TEXT(AL20,"mm/dd/yyyy") -> Week Ending 04/19/2026
B21: Labor - | C21: No notes | AK21: Week 17 | AL21: 46138 | AM21: =YEAR(AL21) -> 2026 | AN21: =AK21&", "&AM21 -> Week 17, 2026 | AO21: ="Week Ending "&TEXT(AL21,"mm/dd/yyyy") -> Week Ending 04/26/2026
AK22: Week 18 | AL22: 46145 | AM22: =YEAR(AL22) -> 2026 | AN22: =AK22&", "&AM22 -> Week 18, 2026 | AO22: ="Week Ending "&TEXT(AL22,"mm/dd/yyyy") -> Week Ending 05/03/2026
B23: RASA - National Landing | AK23: Week 19 | AL23: 46152 | AM23: =YEAR(AL23) -> 2026 | AN23: =AK23&", "&AM23 -> Week 19, 2026 | AO23: ="Week Ending "&TEXT(AL23,"mm/dd/yyyy") -> Week Ending 05/10/2026
B24: COGS - | C24: No notes | AK24: Week 20 | AL24: 46159 | AM24: =YEAR(AL24) -> 2026 | AN24: =AK24&", "&AM24 -> Week 20, 2026 | AO24: ="Week Ending "&TEXT(AL24,"mm/dd/yyyy") -> Week Ending 05/17/2026
B25: Labor - | C25: Sales down 9% vs 4-8 week comp but total labor $s are only down 1.0% as a % of sales vs same comp. P1 bonus expense was posted this week. | AK25: Week 21 | AL25: 46166 | AM25: =YEAR(AL25) -> 2026 | AN25: =AK25&", "&AM25 -> Week 21, 2026 | AO25: ="Week Ending "&TEXT(AL25,"mm/dd/yyyy") -> Week Ending 05/24/2026
AK26: Week 22 | AL26: 46173 | AM26: =YEAR(AL26) -> 2026 | AN26: =AK26&", "&AM26 -> Week 22, 2026 | AO26: ="Week Ending "&TEXT(AL26,"mm/dd/yyyy") -> Week Ending 05/31/2026
B27: RASA - Mosaic | AK27: Week 23 | AL27: 46180 | AM27: =YEAR(AL27) -> 2026 | AN27: =AK27&", "&AM27 -> Week 23, 2026 | AO27: ="Week Ending "&TEXT(AL27,"mm/dd/yyyy") -> Week Ending 06/07/2026
B28: COGS - | C28: No notes | AK28: Week 24 | AL28: 46187 | AM28: =YEAR(AL28) -> 2026 | AN28: =AK28&", "&AM28 -> Week 24, 2026 | AO28: ="Week Ending "&TEXT(AL28,"mm/dd/yyyy") -> Week Ending 06/14/2026
B29: Labor - | C29: Sales down 8% vs 4-8 week comp but total labor $s are down 17.5% as a % of sales vs same comp. | AK29: Week 25 | AL29: 46194 | AM29: =YEAR(AL29) -> 2026 | AN29: =AK29&", "&AM29 -> Week 25, 2026 | AO29: ="Week Ending "&TEXT(AL29,"mm/dd/yyyy") -> Week Ending 06/21/2026
AK30: Week 26 | AL30: 46201 | AM30: =YEAR(AL30) -> 2026 | AN30: =AK30&", "&AM30 -> Week 26, 2026 | AO30: ="Week Ending "&TEXT(AL30,"mm/dd/yyyy") -> Week Ending 06/28/2026
B31: RASA - Rockville | AK31: Week 27 | AL31: 46208 | AM31: =YEAR(AL31) -> 2026 | AN31: =AK31&", "&AM31 -> Week 27, 2026 | AO31: ="Week Ending "&TEXT(AL31,"mm/dd/yyyy") -> Week Ending 07/05/2026
B32: COGS - | C32: No notes | AK32: Week 28 | AL32: 46215 | AM32: =YEAR(AL32) -> 2026 | AN32: =AK32&", "&AM32 -> Week 28, 2026 | AO32: ="Week Ending "&TEXT(AL32,"mm/dd/yyyy") -> Week Ending 07/12/2026
B33: Labor - | C33: No notes | AK33: Week 29 | AL33: 46222 | AM33: =YEAR(AL33) -> 2026 | AN33: =AK33&", "&AM33 -> Week 29, 2026 | AO33: ="Week Ending "&TEXT(AL33,"mm/dd/yyyy") -> Week Ending 07/19/2026
AK34: Week 30 | AL34: 46229 | AM34: =YEAR(AL34) -> 2026 | AN34: =AK34&", "&AM34 -> Week 30, 2026 | AO34: ="Week Ending "&TEXT(AL34,"mm/dd/yyyy") -> Week Ending 07/26/2026
AK35: Week 31 | AL35: 46236 | AM35: =YEAR(AL35) -> 2026 | AN35: =AK35&", "&AM35 -> Week 31, 2026 | AO35: ="Week Ending "&TEXT(AL35,"mm/dd/yyyy") -> Week Ending 08/02/2026
AK36: Week 32 | AL36: 46243 | AM36: =YEAR(AL36) -> 2026 | AN36: =AK36&", "&AM36 -> Week 32, 2026 | AO36: ="Week Ending "&TEXT(AL36,"mm/dd/yyyy") -> Week Ending 08/09/2026
AK37: Week 33 | AL37: 46250 | AM37: =YEAR(AL37) -> 2026 | AN37: =AK37&", "&AM37 -> Week 33, 2026 | AO37: ="Week Ending "&TEXT(AL37,"mm/dd/yyyy") -> Week Ending 08/16/2026
AK38: Week 34 | AL38: 46257 | AM38: =YEAR(AL38) -> 2026 | AN38: =AK38&", "&AM38 -> Week 34, 2026 | AO38: ="Week Ending "&TEXT(AL38,"mm/dd/yyyy") -> Week Ending 08/23/2026
AK39: Week 35 | AL39: 46264 | AM39: =YEAR(AL39) -> 2026 | AN39: =AK39&", "&AM39 -> Week 35, 2026 | AO39: ="Week Ending "&TEXT(AL39,"mm/dd/yyyy") -> Week Ending 08/30/2026
AK40: Week 36 | AL40: 46271 | AM40: =YEAR(AL40) -> 2026 | AN40: =AK40&", "&AM40 -> Week 36, 2026 | AO40: ="Week Ending "&TEXT(AL40,"mm/dd/yyyy") -> Week Ending 09/06/2026
AK41: Week 37 | AL41: 46278 | AM41: =YEAR(AL41) -> 2026 | AN41: =AK41&", "&AM41 -> Week 37, 2026 | AO41: ="Week Ending "&TEXT(AL41,"mm/dd/yyyy") -> Week Ending 09/13/2026
AK42: Week 38 | AL42: 46285 | AM42: =YEAR(AL42) -> 2026 | AN42: =AK42&", "&AM42 -> Week 38, 2026 | AO42: ="Week Ending "&TEXT(AL42,"mm/dd/yyyy") -> Week Ending 09/20/2026
AK43: Week 39 | AL43: 46292 | AM43: =YEAR(AL43) -> 2026 | AN43: =AK43&", "&AM43 -> Week 39, 2026 | AO43: ="Week Ending "&TEXT(AL43,"mm/dd/yyyy") -> Week Ending 09/27/2026
AK44: Week 40 | AL44: 46299 | AM44: =YEAR(AL44) -> 2026 | AN44: =AK44&", "&AM44 -> Week 40, 2026 | AO44: ="Week Ending "&TEXT(AL44,"mm/dd/yyyy") -> Week Ending 10/04/2026
AK45: Week 41 | AL45: 46306 | AM45: =YEAR(AL45) -> 2026 | AN45: =AK45&", "&AM45 -> Week 41, 2026 | AO45: ="Week Ending "&TEXT(AL45,"mm/dd/yyyy") -> Week Ending 10/11/2026
... AK56: Week 52 | AL56: 46383 | AM56: =YEAR(AL56) -> 2026 | AN56: =AK56&", "&AM56 -> Week 52, 2026 | AO56: ="Week Ending "&TEXT(AL56,"mm/dd/yyyy") -> Week Ending 12/27/2026

Sheet Comparison by Store
A1: Prime Margin - Trailing 12 Week
A2: =+Summary!B2 -> Week Ending 01/25/2026
A3: 7 - RASA - Rockville
B4: 2 - Rasa - Ballpark | D4: 4 - Rasa - MVT | F4: 5 - Rasa - National Landin | H4: 6 - Rasa - Mosaic | J4: 7 - RASA - Rockville | L4: Total
A5: Sales
A6: Single Plate In-House Sales | B6: =INDEX(INDIRECT("'"&B$4&"'!$1:$1048576"),MATCH($A6,INDIRECT("'"&B$4&"'!$A:$A"),0),MATCH($A$2,INDIRECT("'"&B$4&"'!$5:$5"),0)) -> #N/A | C6: =IFERROR(B6/B16, "NA") -> NA | D6: =INDEX(INDIRECT("'"&D$4&"'!$1:$1048576"),MATCH($A6,INDIRECT("'"&D$4&"'!$A:$A"),0),MATCH($A$2,INDIRECT("'"&D$4&"'!$5:$5"),0)) -> #N/A | E6: =IFERROR(D6/D16, "NA") -> NA | F6: =INDEX(INDIRECT("'"&F$4&"'!$1:$1048576"),MATCH($A6,INDIRECT("'"&F$4&"'!$A:$A"),0),MATCH($A$2,INDIRECT("'"&F$4&"'!$5:$5"),0)) -> #N/A | G6: =IFERROR(F6/F16, "NA") -> NA | H6: =INDEX(INDIRECT("'"&H$4&"'!$1:$1048576"),MATCH($A6,INDIRECT("'"&H$4&"'!$A:$A"),0),MATCH($A$2,INDIRECT("'"&H$4&"'!$5:$5"),0)) -> #N/A | I6: =IFERROR(H6/H16, "NA") -> NA | J6: =INDEX(INDIRECT("'"&J$4&"'!$1:$1048576"),MATCH($A6,INDIRECT("'"&J$4&"'!$A:$A"),0),MATCH($A$2,INDIRECT("'"&J$4&"'!$5:$5"),0)) -> #N/A | K6: =IFERROR(J6/J16, "NA") -> NA | L6: =+J6+H6+F6+D6+B6 -> #N/A | M6: =IFERROR(L6/L16, "NA") -> NA
A7: Digital Sales | B7: =INDEX(INDIRECT("'"&B$4&"'!$1:$1048576"),MATCH($A7,INDIRECT("'"&B$4&"'!$A:$A"),0),MATCH($A$2,INDIRECT("'"&B$4&"'!$5:$5"),0)) -> #N/A | C7: =IFERROR(B7/B16, "NA") -> NA | D7: =INDEX(INDIRECT("'"&D$4&"'!$1:$1048576"),MATCH($A7,INDIRECT("'"&D$4&"'!$A:$A"),0),MATCH($A$2,INDIRECT("'"&D$4&"'!$5:$5"),0)) -> #N/A | E7: =IFERROR(D7/D16, "NA") -> NA | F7: =INDEX(INDIRECT("'"&F$4&"'!$1:$1048576"),MATCH($A7,INDIRECT("'"&F$4&"'!$A:$A"),0),MATCH($A$2,INDIRECT("'"&F$4&"'!$5:$5"),0)) -> #N/A | G7: =IFERROR(F7/F16, "NA") -> NA | H7: =INDEX(INDIRECT("'"&H$4&"'!$1:$1048576"),MATCH($A7,INDIRECT("'"&H$4&"'!$A:$A"),0),MATCH($A$2,INDIRECT("'"&H$4&"'!$5:$5"),0)) -> #N/A | I7: =IFERROR(H7/H16, "NA") -> NA | J7: =INDEX(INDIRECT("'"&J$4&"'!$1:$1048576"),MATCH($A7,INDIRECT("'"&J$4&"'!$A:$A"),0),MATCH($A$2,INDIRECT("'"&J$4&"'!$5:$5"),0)) -> #N/A | K7: =IFERROR(J7/J16, "NA") -> NA | L7: =+J7+H7+F7+D7+B7 -> #N/A | M7: =IFERROR(L7/L16, "NA") -> NA
A8: Catering Sales | B8: =INDEX(INDIRECT("'"&B$4&"'!$1:$1048576"),MATCH($A8,INDIRECT("'"&B$4&"'!$A:$A"),0),MATCH($A$2,INDIRECT("'"&B$4&"'!$5:$5"),0)) -> #N/A | C8: =IFERROR(B8/B16, "NA") -> NA | D8: =INDEX(INDIRECT("'"&D$4&"'!$1:$1048576"),MATCH($A8,INDIRECT("'"&D$4&"'!$A:$A"),0),MATCH($A$2,INDIRECT("'"&D$4&"'!$5:$5"),0)) -> #N/A | E8: =IFERROR(D8/D16, "NA") -> NA | F8: =INDEX(INDIRECT("'"&F$4&"'!$1:$1048576"),MATCH($A8,INDIRECT("'"&F$4&"'!$A:$A"),0),MATCH($A$2,INDIRECT("'"&F$4&"'!$5:$5"),0)) -> #N/A | G8: =IFERROR(F8/F16, "NA") -> NA | H8: =INDEX(INDIRECT("'"&H$4&"'!$1:$1048576"),MATCH($A8,INDIRECT("'"&H$4&"'!$A:$A"),0),MATCH($A$2,INDIRECT("'"&H$4&"'!$5:$5"),0)) -> #N/A | I8: =IFERROR(H8/H16, "NA") -> NA | J8: =INDEX(INDIRECT("'"&J$4&"'!$1:$1048576"),MATCH($A8,INDIRECT("'"&J$4&"'!$A:$A"),0),MATCH($A$2,INDIRECT("'"&J$4&"'!$5:$5"),0)) -> #N/A | K8: =IFERROR(J8/J16, "NA") -> NA | L8: =+J8+H8+F8+D8+B8 -> #N/A | M8: =IFERROR(L8/L16, "NA") -> NA
A9: 43000 - Delivery Sales - Rasa Website | B9: =INDEX(INDIRECT("'"&B$4&"'!$1:$1048576"),MATCH($A9,INDIRECT("'"&B$4&"'!$A:$A"),0),MATCH($A$2,INDIRECT("'"&B$4&"'!$5:$5"),0)) -> #N/A | C9: =IFERROR(B9/B16, "NA") -> NA | D9: =INDEX(INDIRECT("'"&D$4&"'!$1:$1048576"),MATCH($A9,INDIRECT("'"&D$4&"'!$A:$A"),0),MATCH($A$2,INDIRECT("'"&D$4&"'!$5:$5"),0)) -> #N/A | E9: =IFERROR(D9/D16, "NA") -> NA | F9: =INDEX(INDIRECT("'"&F$4&"'!$1:$1048576"),MATCH($A9,INDIRECT("'"&F$4&"'!$A:$A"),0),MATCH($A$2,INDIRECT("'"&F$4&"'!$5:$5"),0)) -> #N/A | G9: =IFERROR(F9/F16, "NA") -> NA | H9: =INDEX(INDIRECT("'"&H$4&"'!$1:$1048576"),MATCH($A9,INDIRECT("'"&H$4&"'!$A:$A"),0),MATCH($A$2,INDIRECT("'"&H$4&"'!$5:$5"),0)) -> #N/A | I9: =IFERROR(H9/H16, "NA") -> NA | J9: =INDEX(INDIRECT("'"&J$4&"'!$1:$1048576"),MATCH($A9,INDIRECT("'"&J$4&"'!$A:$A"),0),MATCH($A$2,INDIRECT("'"&J$4&"'!$5:$5"),0)) -> #N/A | K9: =IFERROR(J9/J16, "NA") -> NA | L9: =+J9+H9+F9+D9+B9 -> #N/A | M9: =IFERROR(L9/L16, "NA") -> NA
A10: Delivery Fee Income | B10: =INDEX(INDIRECT("'"&B$4&"'!$1:$1048576"),MATCH($A10,INDIRECT("'"&B$4&"'!$A:$A"),0),MATCH($A$2,INDIRECT("'"&B$4&"'!$5:$5"),0)) -> #N/A | C10: =IFERROR(B10/B16, "NA") -> NA | D10: =INDEX(INDIRECT("'"&D$4&"'!$1:$1048576"),MATCH($A10,INDIRECT("'"&D$4&"'!$A:$A"),0),MATCH($A$2,INDIRECT("'"&D$4&"'!$5:$5"),0)) -> #N/A | E10: =IFERROR(D10/D16, "NA") -> NA | F10: =INDEX(INDIRECT("'"&F$4&"'!$1:$1048576"),MATCH($A10,INDIRECT("'"&F$4&"'!$A:$A"),0),MATCH($A$2,INDIRECT("'"&F$4&"'!$5:$5"),0)) -> #N/A | G10: =IFERROR(F10/F16, "NA") -> NA | H10: =INDEX(INDIRECT("'"&H$4&"'!$1:$1048576"),MATCH($A10,INDIRECT("'"&H$4&"'!$A:$A"),0),MATCH($A$2,INDIRECT("'"&H$4&"'!$5:$5"),0)) -> #N/A | I10: =IFERROR(H10/H16, "NA") -> NA | J10: =INDEX(INDIRECT("'"&J$4&"'!$1:$1048576"),MATCH($A10,INDIRECT("'"&J$4&"'!$A:$A"),0),MATCH($A$2,INDIRECT("'"&J$4&"'!$5:$5"),0)) -> #N/A | K10: =IFERROR(J10/J16, "NA") -> NA | L10: =+J10+H10+F10+D10+B10 -> #N/A | M10: =IFERROR(L10/L16, "NA") -> NA
A11: 45000 - Sales Adjustments | B11: =INDEX(INDIRECT("'"&B$4&"'!$1:$1048576"),MATCH($A11,INDIRECT("'"&B$4&"'!$A:$A"),0),MATCH($A$2,INDIRECT("'"&B$4&"'!$5:$5"),0)) -> #N/A | C11: =IFERROR(B11/B16, "NA") -> NA | D11: =INDEX(INDIRECT("'"&D$4&"'!$1:$1048576"),MATCH($A11,INDIRECT("'"&D$4&"'!$A:$A"),0),MATCH($A$2,INDIRECT("'"&D$4&"'!$5:$5"),0)) -> #N/A | E11: =IFERROR(D11/D16, "NA") -> NA | F11: =INDEX(INDIRECT("'"&F$4&"'!$1:$1048576"),MATCH($A11,INDIRECT("'"&F$4&"'!$A:$A"),0),MATCH($A$2,INDIRECT("'"&F$4&"'!$5:$5"),0)) -> #N/A | G11: =IFERROR(F11/F16, "NA") -> NA | H11: =INDEX(INDIRECT("'"&H$4&"'!$1:$1048576"),MATCH($A11,INDIRECT("'"&H$4&"'!$A:$A"),0),MATCH($A$2,INDIRECT("'"&H$4&"'!$5:$5"),0)) -> #N/A | I11: =IFERROR(H11/H16, "NA") -> NA | J11: =INDEX(INDIRECT("'"&J$4&"'!$1:$1048576"),MATCH($A11,INDIRECT("'"&J$4&"'!$A:$A"),0),MATCH($A$2,INDIRECT("'"&J$4&"'!$5:$5"),0)) -> #N/A | K11: =IFERROR(J11/J16, "NA") -> NA | L11: =+J11+H11+F11+D11+B11 -> #N/A | M11: =IFERROR(L11/L16, "NA") -> NA
A12: Discounts / Refunds | B12: =INDEX(INDIRECT("'"&B$4&"'!$1:$1048576"),MATCH($A12,INDIRECT("'"&B$4&"'!$A:$A"),0),MATCH($A$2,INDIRECT("'"&B$4&"'!$5:$5"),0)) -> #N/A | C12: =IFERROR(B12/B16, "NA") -> NA | D12: =INDEX(INDIRECT("'"&D$4&"'!$1:$1048576"),MATCH($A12,INDIRECT("'"&D$4&"'!$A:$A"),0),MATCH($A$2,INDIRECT("'"&D$4&"'!$5:$5"),0)) -> #N/A | E12: =IFERROR(D12/D16, "NA") -> NA | F12: =INDEX(INDIRECT("'"&F$4&"'!$1:$1048576"),MATCH($A12,INDIRECT("'"&F$4&"'!$A:$A"),0),MATCH($A$2,INDIRECT("'"&F$4&"'!$5:$5"),0)) -> #N/A | G12: =IFERROR(F12/F16, "NA") -> NA | H12: =INDEX(INDIRECT("'"&H$4&"'!$1:$1048576"),MATCH($A12,INDIRECT("'"&H$4&"'!$A:$A"),0),MATCH($A$2,INDIRECT("'"&H$4&"'!$5:$5"),0)) -> #N/A | I12: =IFERROR(H12/H16, "NA") -> NA | J12: =INDEX(INDIRECT("'"&J$4&"'!$1:$1048576"),MATCH($A12,INDIRECT("'"&J$4&"'!$A:$A"),0),MATCH($A$2,INDIRECT("'"&J$4&"'!$5:$5"),0)) -> #N/A | K12: =IFERROR(J12/J16, "NA") -> NA | L12: =+J12+H12+F12+D12+B12 -> #N/A | M12: =IFERROR(L12/L16, "NA") -> NA
A13: 82602 - Other Income_WCK | B13: =INDEX(INDIRECT("'"&B$4&"'!$1:$1048576"),MATCH($A13,INDIRECT("'"&B$4&"'!$A:$A"),0),MATCH($A$2,INDIRECT("'"&B$4&"'!$5:$5"),0)) -> #N/A | C13: =IFERROR(B13/B16, "NA") -> NA | D13: =INDEX(INDIRECT("'"&D$4&"'!$1:$1048576"),MATCH($A13,INDIRECT("'"&D$4&"'!$A:$A"),0),MATCH($A$2,INDIRECT("'"&D$4&"'!$5:$5"),0)) -> #N/A | E13: =IFERROR(D13/D16, "NA") -> NA | F13: =INDEX(INDIRECT("'"&F$4&"'!$1:$1048576"),MATCH($A13,INDIRECT("'"&F$4&"'!$A:$A"),0),MATCH($A$2,INDIRECT("'"&F$4&"'!$5:$5"),0)) -> #N/A | G13: =IFERROR(F13/F16, "NA") -> NA | H13: =INDEX(INDIRECT("'"&H$4&"'!$1:$1048576"),MATCH($A13,INDIRECT("'"&H$4&"'!$A:$A"),0),MATCH($A$2,INDIRECT("'"&H$4&"'!$5:$5"),0)) -> #N/A | I13: =IFERROR(H13/H16, "NA") -> NA | J13: =INDEX(INDIRECT("'"&J$4&"'!$1:$1048576"),MATCH($A13,INDIRECT("'"&J$4&"'!$A:$A"),0),MATCH($A$2,INDIRECT("'"&J$4&"'!$5:$5"),0)) -> #N/A | K13: =IFERROR(J13/J16, "NA") -> NA | L13: =+J13+H13+F13+D13+B13 -> #N/A | M13: =IFERROR(L13/L16, "NA") -> NA
A14: 82604 - Other Income_OTP | B14: =INDEX(INDIRECT("'"&B$4&"'!$1:$1048576"),MATCH($A14,INDIRECT("'"&B$4&"'!$A:$A"),0),MATCH($A$2,INDIRECT("'"&B$4&"'!$5:$5"),0)) -> #N/A | C14: =IFERROR(B14/B16, "NA") -> NA | D14: =INDEX(INDIRECT("'"&D$4&"'!$1:$1048576"),MATCH($A14,INDIRECT("'"&D$4&"'!$A:$A"),0),MATCH($A$2,INDIRECT("'"&D$4&"'!$5:$5"),0)) -> #N/A | E14: =IFERROR(D14/D16, "NA") -> NA | F14: =INDEX(INDIRECT("'"&F$4&"'!$1:$1048576"),MATCH($A14,INDIRECT("'"&F$4&"'!$A:$A"),0),MATCH($A$2,INDIRECT("'"&F$4&"'!$5:$5"),0)) -> #N/A | G14: =IFERROR(F14/F16, "NA") -> NA | H14: =INDEX(INDIRECT("'"&H$4&"'!$1:$1048576"),MATCH($A14,INDIRECT("'"&H$4&"'!$A:$A"),0),MATCH($A$2,INDIRECT("'"&H$4&"'!$5:$5"),0)) -> #N/A | I14: =IFERROR(H14/H16, "NA") -> NA | J14: =INDEX(INDIRECT("'"&J$4&"'!$1:$1048576"),MATCH($A14,INDIRECT("'"&J$4&"'!$A:$A"),0),MATCH($A$2,INDIRECT("'"&J$4&"'!$5:$5"),0)) -> #N/A | K14: =IFERROR(J14/J16, "NA") -> NA | L14: =+J14+H14+F14+D14+B14 -> #N/A | M14: =IFERROR(L14/L16, "NA") -> NA
A15: 82605 - Other Income_To Good To Go | B15: =INDEX(INDIRECT("'"&B$4&"'!$1:$1048576"),MATCH($A15,INDIRECT("'"&B$4&"'!$A:$A"),0),MATCH($A$2,INDIRECT("'"&B$4&"'!$5:$5"),0)) -> #N/A | C15: =IFERROR(B15/B16, "NA") -> NA | D15: =INDEX(INDIRECT("'"&D$4&"'!$1:$1048576"),MATCH($A15,INDIRECT("'"&D$4&"'!$A:$A"),0),MATCH($A$2,INDIRECT("'"&D$4&"'!$5:$5"),0)) -> #N/A | E15: =IFERROR(D15/D16, "NA") -> NA | F15: =INDEX(INDIRECT("'"&F$4&"'!$1:$1048576"),MATCH($A15,INDIRECT("'"&F$4&"'!$A:$A"),0),MATCH($A$2,INDIRECT("'"&F$4&"'!$5:$5"),0)) -> #N/A | G15: =IFERROR(F15/F16, "NA") -> NA | H15: =INDEX(INDIRECT("'"&H$4&"'!$1:$1048576"),MATCH($A15,INDIRECT("'"&H$4&"'!$A:$A"),0),MATCH($A$2,INDIRECT("'"&H$4&"'!$5:$5"),0)) -> #N/A | I15: =IFERROR(H15/H16, "NA") -> NA | J15: =INDEX(INDIRECT("'"&J$4&"'!$1:$1048576"),MATCH($A15,INDIRECT("'"&J$4&"'!$A:$A"),0),MATCH($A$2,INDIRECT("'"&J$4&"'!$5:$5"),0)) -> #N/A | K15: =IFERROR(J15/J16, "NA") -> NA | L15: =+J15+H15+F15+D15+B15 -> #N/A | M15: =IFERROR(L15/L16, "NA") -> NA
A16: Total Sales | B16: =INDEX(INDIRECT("'"&B$4&"'!$1:$1048576"),MATCH($A16,INDIRECT("'"&B$4&"'!$A:$A"),0),MATCH($A$2,INDIRECT("'"&B$4&"'!$5:$5"),0)) -> 20034.79 | C16: =IFERROR(B16/B16, "NA") -> 1 | D16: =INDEX(INDIRECT("'"&D$4&"'!$1:$1048576"),MATCH($A16,INDIRECT("'"&D$4&"'!$A:$A"),0),MATCH($A$2,INDIRECT("'"&D$4&"'!$5:$5"),0)) -> 39699.41 | E16: =IFERROR(D16/D16, "NA") -> 1 | F16: =INDEX(INDIRECT("'"&F$4&"'!$1:$1048576"),MATCH($A16,INDIRECT("'"&F$4&"'!$A:$A"),0),MATCH($A$2,INDIRECT("'"&F$4&"'!$5:$5"),0)) -> 16370.43 | G16: =IFERROR(F16/F16, "NA") -> 1 | H16: =INDEX(INDIRECT("'"&H$4&"'!$1:$1048576"),MATCH($A16,INDIRECT("'"&H$4&"'!$A:$A"),0),MATCH($A$2,INDIRECT("'"&H$4&"'!$5:$5"),0)) -> 17376.74 | I16: =IFERROR(H16/H16, "NA") -> 1 | J16: =INDEX(INDIRECT("'"&J$4&"'!$1:$1048576"),MATCH($A16,INDIRECT("'"&J$4&"'!$A:$A"),0),MATCH($A$2,INDIRECT("'"&J$4&"'!$5:$5"),0)) -> 22461.46 | K16: =IFERROR(J16/J16, "NA") -> 1 | L16: =+J16+H16+F16+D16+B16 -> 115942.83 | M16: =IFERROR(L16/L16, "NA") -> 1
A18: Cost of Goods Sold
A19: Food & Beverage Costs
A20: 50000 - Food & Beverage Costs
A21: Food Costs
A22: 50100 - Food Costs | B22: =INDEX(INDIRECT("'"&B$4&"'!$1:$1048576"),MATCH($A22,INDIRECT("'"&B$4&"'!$A:$A"),0),MATCH($A$2,INDIRECT("'"&B$4&"'!$5:$5"),0)) -> 0 | C22: =IFERROR(B22/B16, "NA") -> 0 | D22: =INDEX(INDIRECT("'"&D$4&"'!$1:$1048576"),MATCH($A22,INDIRECT("'"&D$4&"'!$A:$A"),0),MATCH($A$2,INDIRECT("'"&D$4&"'!$5:$5"),0)) -> 0 | E22: =IFERROR(D22/D16, "NA") -> 0 | F22: =INDEX(INDIRECT("'"&F$4&"'!$1:$1048576"),MATCH($A22,INDIRECT("'"&F$4&"'!$A:$A"),0),MATCH($A$2,INDIRECT("'"&F$4&"'!$5:$5"),0)) -> 0 | G22: =IFERROR(F22/F16, "NA") -> 0 | H22: =INDEX(INDIRECT("'"&H$4&"'!$1:$1048576"),MATCH($A22,INDIRECT("'"&H$4&"'!$A:$A"),0),MATCH($A$2,INDIRECT("'"&H$4&"'!$5:$5"),0)) -> 0 | I22: =IFERROR(H22/H16, "NA") -> 0 | J22: =INDEX(INDIRECT("'"&J$4&"'!$1:$1048576"),MATCH($A22,INDIRECT("'"&J$4&"'!$A:$A"),0),MATCH($A$2,INDIRECT("'"&J$4&"'!$5:$5"),0)) -> 0 | K22: =IFERROR(J22/J16, "NA") -> 0 | M22: =IFERROR(L22/L16, "NA") -> 0
A23: 50110 - COGS - Produce | B23: =INDEX(INDIRECT("'"&B$4&"'!$1:$1048576"),MATCH($A23,INDIRECT("'"&B$4&"'!$A:$A"),0),MATCH($A$2,INDIRECT("'"&B$4&"'!$5:$5"),0)) -> 1038.36 | C23: =IFERROR(B23/B16, "NA") -> 0.051827845 | D23: =INDEX(INDIRECT("'"&D$4&"'!$1:$1048576"),MATCH($A23,INDIRECT("'"&D$4&"'!$A:$A"),0),MATCH($A$2,INDIRECT("'"&D$4&"'!$5:$5"),0)) -> 1910.6 | E23: =IFERROR(D23/D16, "NA") -> 0.04812666 | F23: =INDEX(INDIRECT("'"&F$4&"'!$1:$1048576"),MATCH($A23,INDIRECT("'"&F$4&"'!$A:$A"),0),MATCH($A$2,INDIRECT("'"&F$4&"'!$5:$5"),0)) -> 816.91 | G23: =IFERROR(F23/F16, "NA") -> 0.04990156 | H23: =INDEX(INDIRECT("'"&H$4&"'!$1:$1048576"),MATCH($A23,INDIRECT("'"&H$4&"'!$A:$A"),0),MATCH($A$2,INDIRECT("'"&H$4&"'!$5:$5"),0)) -> 691.24 | I23: =IFERROR(H23/H16, "NA") -> 0.039779613 | J23: =INDEX(INDIRECT("'"&J$4&"'!$1:$1048576"),MATCH($A23,INDIRECT("'"&J$4&"'!$A:$A"),0),MATCH($A$2,INDIRECT("'"&J$4&"'!$5:$5"),0)) -> 1249.54 | K23: =IFERROR(J23/J16, "NA") -> 0.0556304 | L23: =+J23+H23+F23+D23+B23 -> 5706.65 | M23: =IFERROR(L23/L16, "NA") -> 0.049219516
A24: 50120 - COGS - Grocery Dry & Canned | B24: =INDEX(INDIRECT("'"&B$4&"'!$1:$1048576"),MATCH($A24,INDIRECT("'"&B$4&"'!$A:$A"),0),MATCH($A$2,INDIRECT("'"&B$4&"'!$5:$5"),0)) -> 579.79 | C24: =IFERROR(B24/B16, "NA") -> 0.02893916 | D24: =INDEX(INDIRECT("'"&D$4&"'!$1:$1048576"),MATCH($A24,INDIRECT("'"&D$4&"'!$A:$A"),0),MATCH($A$2,INDIRECT("'"&D$4&"'!$5:$5"),0)) -> 1091.48 | E24: =IFERROR(D24/D16, "NA") -> 0.027493608 | F24: =INDEX(INDIRECT("'"&F$4&"'!$1:$1048576"),MATCH($A24,INDIRECT("'"&F$4&"'!$A:$A"),0),MATCH($A$2,INDIRECT("'"&F$4&"'!$5:$5"),0)) -> 377.75 | G24: =IFERROR(F24/F16, "NA") -> 0.023075142 | H24: =INDEX(INDIRECT("'"&H$4&"'!$1:$1048576"),MATCH($A24,INDIRECT("'"&H$4&"'!$A:$A"),0),MATCH($A$2,INDIRECT("'"&H$4&"'!$5:$5"),0)) -> 519.04 | I24: =IFERROR(H24/H16, "NA") -> 0.029869814 | J24: =INDEX(INDIRECT("'"&J$4&"'!$1:$1048576"),MATCH($A24,INDIRECT("'"&J$4&"'!$A:$A"),0),MATCH($A$2,INDIRECT("'"&J$4&"'!$5:$5"),0)) -> 765.99 | K24: =IFERROR(J24/J16, "NA") -> 0.034102414 | L24: =+J24+H24+F24+D24+B24 -> 3334.05 | M24: =IFERROR(L24/L16, "NA") -> 0.028755983
A25: 50130 - COGS - Poultry | B25: =INDEX(INDIRECT("'"&B$4&"'!$1:$1048576"),MATCH($A25,INDIRECT("'"&B$4&"'!$A:$A"),0),MATCH($A$2,INDIRECT("'"&B$4&"'!$5:$5"),0)) -> 618.5 | C25: =IFERROR(B25/B16, "NA") -> 0.030871299 | D25: =INDEX(INDIRECT("'"&D$4&"'!$1:$1048576"),MATCH($A25,INDIRECT("'"&D$4&"'!$A:$A"),0),MATCH($A$2,INDIRECT("'"&D$4&"'!$5:$5"),0)) -> 1062.92 | E25: =IFERROR(D25/D16, "NA") -> 0.026774201 | F25: =INDEX(INDIRECT("'"&F$4&"'!$1:$1048576"),MATCH($A25,INDIRECT("'"&F$4&"'!$A:$A"),0),MATCH($A$2,INDIRECT("'"&F$4&"'!$5:$5"),0)) -> 358.18 | G25: =IFERROR(F25/F16, "NA") -> 0.021879694 | H25: =INDEX(INDIRECT("'"&H$4&"'!$1:$1048576"),MATCH($A25,INDIRECT("'"&H$4&"'!$A:$A"),0),MATCH($A$2,INDIRECT("'"&H$4&"'!$5:$5"),0)) -> 451.53 | I25: =IFERROR(H25/H16, "NA") -> 0.025984736 | J25: =INDEX(INDIRECT("'"&J$4&"'!$1:$1048576"),MATCH($A25,INDIRECT("'"&J$4&"'!$A:$A"),0),MATCH($A$2,INDIRECT("'"&J$4&"'!$5:$5"),0)) -> 752.13 | K25: =IFERROR(J25/J16, "NA") -> 0.033485357 | L25: =+J25+H25+F25+D25+B25 -> 3243.26 | M25: =IFERROR(L25/L16, "NA") -> 0.027972924
A26: 50140 - COGS - Dairy | B26: =INDEX(INDIRECT("'"&B$4&"'!$1:$1048576"),MATCH($A26,INDIRECT("'"&B$4&"'!$A:$A"),0),MATCH($A$2,INDIRECT("'"&B$4&"'!$5:$5"),0)) -> 409.97 | C26: =IFERROR(B26/B16, "NA") -> 0.020462905 | D26: =INDEX(INDIRECT("'"&D$4&"'!$1:$1048576"),MATCH($A26,INDIRECT("'"&D$4&"'!$A:$A"),0),MATCH($A$2,INDIRECT("'"&D$4&"'!$5:$5"),0)) -> 573.87 | E26: =IFERROR(D26/D16, "NA") -> 0.014455379 | F26: =INDEX(INDIRECT("'"&F$4&"'!$1:$1048576"),MATCH($A26,INDIRECT("'"&F$4&"'!$A:$A"),0),MATCH($A$2,INDIRECT("'"&F$4&"'!$5:$5"),0)) -> 387.48 | G26: =IFERROR(F26/F16, "NA") -> 0.023669507 | H26: =INDEX(INDIRECT("'"&H$4&"'!$1:$1048576"),MATCH($A26,INDIRECT("'"&H$4&"'!$A:$A"),0),MATCH($A$2,INDIRECT("'"&H$4&"'!$5:$5"),0)) -> 435.55 | I26: =IFERROR(H26/H16, "NA") -> 0.025065116 | J26: =INDEX(INDIRECT("'"&J$4&"'!$1:$1048576"),MATCH($A26,INDIRECT("'"&J$4&"'!$A:$A"),0),MATCH($A$2,INDIRECT("'"&J$4&"'!$5:$5"),0)) -> 601.5 | K26: =IFERROR(J26/J16, "NA") -> 0.026779203 | L26: =+J26+H26+F26+D26+B26 -> 2408.37 | M26: =IFERROR(L26/L16, "NA") -> 0.020772048
A27: 50150 - COGS - Frozen | B27: =INDEX(INDIRECT("'"&B$4&"'!$1:$1048576"),MATCH($A27,INDIRECT("'"&B$4&"'!$A:$A"),0),MATCH($A$2,INDIRECT("'"&B$4&"'!$5:$5"),0)) -> 231.81 | C27: =IFERROR(B27/B16, "NA") -> 0.011570373 | D27: =INDEX(INDIRECT("'"&D$4&"'!$1:$1048576"),MATCH($A27,INDIRECT("'"&D$4&"'!$A:$A"),0),MATCH($A$2,INDIRECT("'"&D$4&"'!$5:$5"),0)) -> 331.07 | E27: =IFERROR(D27/D16, "NA") -> 0.0083394186 | F27: =INDEX(INDIRECT("'"&F$4&"'!$1:$1048576"),MATCH($A27,INDIRECT("'"&F$4&"'!$A:$A"),0),MATCH($A$2,INDIRECT("'"&F$4&"'!$5:$5"),0)) -> 228.25 | G27: =IFERROR(F27/F16, "NA") -> 0.013942823 | H27: =INDEX(INDIRECT("'"&H$4&"'!$1:$1048576"),MATCH($A27,INDIRECT("'"&H$4&"'!$A:$A"),0),MATCH($A$2,INDIRECT("'"&H$4&"'!$5:$5"),0)) -> 202.79 | I27: =IFERROR(H27/H16, "NA") -> 0.011670198 | J27: =INDEX(INDIRECT("'"&J$4&"'!$1:$1048576"),MATCH($A27,INDIRECT("'"&J$4&"'!$A:$A"),0),MATCH($A$2,INDIRECT("'"&J$4&"'!$5:$5"),0)) -> 304.34 | K27: =IFERROR(J27/J16, "NA") -> 0.013549431 | L27: =+J27+H27+F27+D27+B27 -> 1298.26 | M27: =IFERROR(L27/L16, "NA") -> 0.011197415
A28: 50160 - COGS - Meat | B28: =INDEX(INDIRECT("'"&B$4&"'!$1:$1048576"),MATCH($A28,INDIRECT("'"&B$4&"'!$A:$A"),0),MATCH($A$2,INDIRECT("'"&B$4&"'!$5:$5"),0)) -> 199.82 | C28: =IFERROR(B28/B16, "NA") -> 0.0099736508 | D28: =INDEX(INDIRECT("'"&D$4&"'!$1:$1048576"),MATCH($A28,INDIRECT("'"&D$4&"'!$A:$A"),0),MATCH($A$2,INDIRECT("'"&D$4&"'!$5:$5"),0)) -> 488.88 | E28: =IFERROR(D28/D16, "NA") -> 0.012314541 | F28: =INDEX(INDIRECT("'"&F$4&"'!$1:$1048576"),MATCH($A28,INDIRECT("'"&F$4&"'!$A:$A"),0),MATCH($A$2,INDIRECT("'"&F$4&"'!$5:$5"),0)) -> 130.39 | G28: =IFERROR(F28/F16, "NA") -> 0.007964971 | H28: =INDEX(INDIRECT("'"&H$4&"'!$1:$1048576"),MATCH($A28,INDIRECT("'"&H$4&"'!$A:$A"),0),MATCH($A$2,INDIRECT("'"&H$4&"'!$5:$5"),0)) -> 153.94 | I28: =IFERROR(H28/H16, "NA") -> 0.0088589689 | J28: =INDEX(INDIRECT("'"&J$4&"'!$1:$1048576"),MATCH($A28,INDIRECT("'"&J$4&"'!$A:$A"),0),MATCH($A$2,INDIRECT("'"&J$4&"'!$5:$5"),0)) -> 195.91 | K28: =IFERROR(J28/J16, "NA") -> 0.008722051 | L28: =+J28+H28+F28+D28+B28 -> 1168.94 | M28: =IFERROR(L28/L16, "NA") -> 0.010082038
A29: 50170 - COGS - Seafood | B29: =INDEX(INDIRECT("'"&B$4&"'!$1:$1048576"),MATCH($A29,INDIRECT("'"&B$4&"'!$A:$A"),0),MATCH($A$2,INDIRECT("'"&B$4&"'!$5:$5"),0)) -> 0 | C29: =IFERROR(B29/B16, "NA") -> 0 | D29: =INDEX(INDIRECT("'"&D$4&"'!$1:$1048576"),MATCH($A29,INDIRECT("'"&D$4&"'!$A:$A"),0),MATCH($A$2,INDIRECT("'"&D$4&"'!$5:$5"),0)) -> 0 | E29: =IFERROR(D29/D16, "NA") -> 0 | F29: =INDEX(INDIRECT("'"&F$4&"'!$1:$1048576"),MATCH($A29,INDIRECT("'"&F$4&"'!$A:$A"),0),MATCH($A$2,INDIRECT("'"&F$4&"'!$5:$5"),0)) -> 0 | G29: =IFERROR(F29/F16, "NA") -> 0 | H29: =INDEX(INDIRECT("'"&H$4&"'!$1:$1048576"),MATCH($A29,INDIRECT("'"&H$4&"'!$A:$A"),0),MATCH($A$2,INDIRECT("'"&H$4&"'!$5:$5"),0)) -> 0 | I29: =IFERROR(H29/H16, "NA") -> 0 | J29: =INDEX(INDIRECT("'"&J$4&"'!$1:$1048576"),MATCH($A29,INDIRECT("'"&J$4&"'!$A:$A"),0),MATCH($A$2,INDIRECT("'"&J$4&"'!$5:$5"),0)) -> 0 | K29: =IFERROR(J29/J16, "NA") -> 0 | L29: =+J29+H29+F29+D29+B29 -> 0 | M29: =IFERROR(L29/L16, "NA") -> 0
A30: 50180 - COGS - Spices | B30: =INDEX(INDIRECT("'"&B$4&"'!$1:$1048576"),MATCH($A30,INDIRECT("'"&B$4&"'!$A:$A"),0),MATCH($A$2,INDIRECT("'"&B$4&"'!$5:$5"),0)) -> 107.93 | C30: =IFERROR(B30/B16, "NA") -> 0.0053871291 | D30: =INDEX(INDIRECT("'"&D$4&"'!$1:$1048576"),MATCH($A30,INDIRECT("'"&D$4&"'!$A:$A"),0),MATCH($A$2,INDIRECT("'"&D$4&"'!$5:$5"),0)) -> 46.78 | E30: =IFERROR(D30/D16, "NA") -> 0.001178355 | F30: =INDEX(INDIRECT("'"&F$4&"'!$1:$1048576"),MATCH($A30,INDIRECT("'"&F$4&"'!$A:$A"),0),MATCH($A$2,INDIRECT("'"&F$4&"'!$5:$5"),0)) -> 110.85 | G30: =IFERROR(F30/F16, "NA") -> 0.0067713554 | H30: =INDEX(INDIRECT("'"&H$4&"'!$1:$1048576"),MATCH($A30,INDIRECT("'"&H$4&"'!$A:$A"),0),MATCH($A$2,INDIRECT("'"&H$4&"'!$5:$5"),0)) -> 71.56 | I30: =IFERROR(H30/H16, "NA") -> 0.0041181487 | J30: =INDEX(INDIRECT("'"&J$4&"'!$1:$1048576"),MATCH($A30,INDIRECT("'"&J$4&"'!$A:$A"),0),MATCH($A$2,INDIRECT("'"&J$4&"'!$5:$5"),0)) -> 205.02 | K30: =IFERROR(J30/J16, "NA") -> 0.0091276346 | L30: =+J30+H30+F30+D30+B30 -> 542.14 | M30: =IFERROR(L30/L16, "NA") -> 0.0046759252
A31: 50190 - COGS - Prepped Food | B31: =INDEX(INDIRECT("'"&B$4&"'!$1:$1048576"),MATCH($A31,INDIRECT("'"&B$4&"'!$A:$A"),0),MATCH($A$2,INDIRECT("'"&B$4&"'!$5:$5"),0)) -> 1150.01 | C31: =IFERROR(B31/B16, "NA") -> 0.057400652 | D31: =INDEX(INDIRECT("'"&D$4&"'!$1:$1048576"),MATCH($A31,INDIRECT("'"&D$4&"'!$A:$A"),0),MATCH($A$2,INDIRECT("'"&D$4&"'!$5:$5"),0)) -> 2283.11 | E31: =IFERROR(D31/D16, "NA") -> 0.057509923 | F31: =INDEX(INDIRECT("'"&F$4&"'!$1:$1048576"),MATCH($A31,INDIRECT("'"&F$4&"'!$A:$A"),0),MATCH($A$2,INDIRECT("'"&F$4&"'!$5:$5"),0)) -> 1048.29 | G31: =IFERROR(F31/F16, "NA") -> 0.064035581 | H31: =INDEX(INDIRECT("'"&H$4&"'!$1:$1048576"),MATCH($A31,INDIRECT("'"&H$4&"'!$A:$A"),0),MATCH($A$2,INDIRECT("'"&H$4&"'!$5:$5"),0)) -> 1228.48 | I31: =IFERROR(H31/H16, "NA") -> 0.070696805 | J31: =INDEX(INDIRECT("'"&J$4&"'!$1:$1048576"),MATCH($A31,INDIRECT("'"&J$4&"'!$A:$A"),0),MATCH($A$2,INDIRECT("'"&J$4&"'!$5:$5"),0)) -> 1833.13 | K31: =IFERROR(J31/J16, "NA") -> 0.081612237 | L31: =+J31+H31+F31+D31+B31 -> 7543.02 | M31: =IFERROR(L31/L16, "NA") -> 0.065058098
A32: 50191 - COGS - Wow Bao | B32: =INDEX(INDIRECT("'"&B$4&"'!$1:$1048576"),MATCH($A32,INDIRECT("'"&B$4&"'!$A:$A"),0),MATCH($A$2,INDIRECT("'"&B$4&"'!$5:$5"),0)) -> 0 | C32: =IFERROR(B32/B16, "NA") -> 0 | D32: =INDEX(INDIRECT("'"&D$4&"'!$1:$1048576"),MATCH($A32,INDIRECT("'"&D$4&"'!$A:$A"),0),MATCH($A$2,INDIRECT("'"&D$4&"'!$5:$5"),0)) -> 0 | E32: =IFERROR(D32/D16, "NA") -> 0 | F32: =INDEX(INDIRECT("'"&F$4&"'!$1:$1048576"),MATCH($A32,INDIRECT("'"&F$4&"'!$A:$A"),0),MATCH($A$2,INDIRECT("'"&F$4&"'!$5:$5"),0)) -> 0 | G32: =IFERROR(F32/F16, "NA") -> 0 | H32: =INDEX(INDIRECT("'"&H$4&"'!$1:$1048576"),MATCH($A32,INDIRECT("'"&H$4&"'!$A:$A"),0),MATCH($A$2,INDIRECT("'"&H$4&"'!$5:$5"),0)) -> 0 | I32: =IFERROR(H32/H16, "NA") -> 0 | J32: =INDEX(INDIRECT("'"&J$4&"'!$1:$1048576"),MATCH($A32,INDIRECT("'"&J$4&"'!$A:$A"),0),MATCH($A$2,INDIRECT("'"&J$4&"'!$5:$5"),0)) -> 0 | K32: =IFERROR(J32/J16, "NA") -> 0 | L32: =+J32+H32+F32+D32+B32 -> 0 | M32: =IFERROR(L32/L16, "NA") -> 0
A33: 50195 - COGS - Distribution | B33: =INDEX(INDIRECT("'"&B$4&"'!$1:$1048576"),MATCH($A33,INDIRECT("'"&B$4&"'!$A:$A"),0),MATCH($A$2,INDIRECT("'"&B$4&"'!$5:$5"),0)) -> 0 | C33: =IFERROR(B33/B16, "NA") -> 0 | D33: =INDEX(INDIRECT("'"&D$4&"'!$1:$1048576"),MATCH($A33,INDIRECT("'"&D$4&"'!$A:$A"),0),MATCH($A$2,INDIRECT("'"&D$4&"'!$5:$5"),0)) -> 0 | E33: =IFERROR(D33/D16, "NA") -> 0 | F33: =INDEX(INDIRECT("'"&F$4&"'!$1:$1048576"),MATCH($A33,INDIRECT("'"&F$4&"'!$A:$A"),0),MATCH($A$2,INDIRECT("'"&F$4&"'!$5:$5"),0)) -> 0 | G33: =IFERROR(F33/F16, "NA") -> 0 | H33: =INDEX(INDIRECT("'"&H$4&"'!$1:$1048576"),MATCH($A33,INDIRECT("'"&H$4&"'!$A:$A"),0),MATCH($A$2,INDIRECT("'"&H$4&"'!$5:$5"),0)) -> 0 | I33: =IFERROR(H33/H16, "NA") -> 0 | J33: =INDEX(INDIRECT("'"&J$4&"'!$1:$1048576"),MATCH($A33,INDIRECT("'"&J$4&"'!$A:$A"),0),MATCH($A$2,INDIRECT("'"&J$4&"'!$5:$5"),0)) -> 0 | K33: =IFERROR(J33/J16, "NA") -> 0 | L33: =+J33+H33+F33+D33+B33 -> 0 | M33: =IFERROR(L33/L16, "NA") -> 0
A34: Total Food Costs | B34: =INDEX(INDIRECT("'"&B$4&"'!$1:$1048576"),MATCH($A34,INDIRECT("'"&B$4&"'!$A:$A"),0),MATCH($A$2,INDIRECT("'"&B$4&"'!$5:$5"),0)) -> 4336.19 | C34: =IFERROR(B34/B16, "NA") -> 0.21643301 | D34: =INDEX(INDIRECT("'"&D$4&"'!$1:$1048576"),MATCH($A34,INDIRECT("'"&D$4&"'!$A:$A"),0),MATCH($A$2,INDIRECT("'"&D$4&"'!$5:$5"),0)) -> 7788.71 | E34: =IFERROR(D34/D16, "NA") -> 0.19619208 | F34: =INDEX(INDIRECT("'"&F$4&"'!$1:$1048576"),MATCH($A34,INDIRECT("'"&F$4&"'!$A:$A"),0),MATCH($A$2,INDIRECT("'"&F$4&"'!$5:$5"),0)) -> 3458.1 | G34: =IFERROR(F34/F16, "NA") -> 0.21124063 | H34: =INDEX(INDIRECT("'"&H$4&"'!$1:$1048576"),MATCH($A34,INDIRECT("'"&H$4&"'!$A:$A"),0),MATCH($A$2,INDIRECT("'"&H$4&"'!$5:$5"),0)) -> 3754.13 | I34: =IFERROR(H34/H16, "NA") -> 0.2160434 | J34: =INDEX(INDIRECT("'"&J$4&"'!$1:$1048576"),MATCH($A34,INDIRECT("'"&J$4&"'!$A:$A"),0),MATCH($A$2,INDIRECT("'"&J$4&"'!$5:$5"),0)) -> 5907.56 | K34: =IFERROR(J34/J16, "NA") -> 0.26300873 | L34: =+J34+H34+F34+D34+B34 -> 25244.69 | M34: =IFERROR(L34/L16, "NA") -> 0.21773395
A35: Beverage Costs
A36: 50101 - Beverage Costs | B36: =INDEX(INDIRECT("'"&B$4&"'!$1:$1048576"),MATCH($A36,INDIRECT("'"&B$4&"'!$A:$A"),0),MATCH($A$2,INDIRECT("'"&B$4&"'!$5:$5"),0)) -> 0 | C36: =IFERROR(B36/B16, "NA") -> 0 | D36: =INDEX(INDIRECT("'"&D$4&"'!$1:$1048576"),MATCH($A36,INDIRECT("'"&D$4&"'!$A:$A"),0),MATCH($A$2,INDIRECT("'"&D$4&"'!$5:$5"),0)) -> 0 | E36: =IFERROR(D36/D16, "NA") -> 0 | F36: =INDEX(INDIRECT("'"&F$4&"'!$1:$1048576"),MATCH($A36,INDIRECT("'"&F$4&"'!$A:$A"),0),MATCH($A$2,INDIRECT("'"&F$4&"'!$5:$5"),0)) -> 0 | G36: =IFERROR(F36/F16, "NA") -> 0 | H36: =INDEX(INDIRECT("'"&H$4&"'!$1:$1048576"),MATCH($A36,INDIRECT("'"&H$4&"'!$A:$A"),0),MATCH($A$2,INDIRECT("'"&H$4&"'!$5:$5"),0)) -> 0 | I36: =IFERROR(H36/H16, "NA") -> 0 | J36: =INDEX(INDIRECT("'"&J$4&"'!$1:$1048576"),MATCH($A36,INDIRECT("'"&J$4&"'!$A:$A"),0),MATCH($A$2,INDIRECT("'"&J$4&"'!$5:$5"),0)) -> 0 | K36: =IFERROR(J36/J16, "NA") -> 0 | M36: =IFERROR(L36/L16, "NA") -> 0
A37: 50200 - COGS - N/A Beverage | B37: =INDEX(INDIRECT("'"&B$4&"'!$1:$1048576"),MATCH($A37,INDIRECT("'"&B$4&"'!$A:$A"),0),MATCH($A$2,INDIRECT("'"&B$4&"'!$5:$5"),0)) -> 278.64 | C37: =IFERROR(B37/B16, "NA") -> 0.013907807 | D37: =INDEX(INDIRECT("'"&D$4&"'!$1:$1048576"),MATCH($A37,INDIRECT("'"&D$4&"'!$A:$A"),0),MATCH($A$2,INDIRECT("'"&D$4&"'!$5:$5"),0)) -> 450.47 | E37: =IFERROR(D37/D16, "NA") -> 0.01134702 | F37: =INDEX(INDIRECT("'"&F$4&"'!$1:$1048576"),MATCH($A37,INDIRECT("'"&F$4&"'!$A:$A"),0),MATCH($A$2,INDIRECT("'"&F$4&"'!$5:$5"),0)) -> 58.22 | G37: =IFERROR(F37/F16, "NA") -> 0.0035564124 | H37: =INDEX(INDIRECT("'"&H$4&"'!$1:$1048576"),MATCH($A37,INDIRECT("'"&H$4&"'!$A:$A"),0),MATCH($A$2,INDIRECT("'"&H$4&"'!$5:$5"),0)) -> 337.44 | I37: =IFERROR(H37/H16, "NA") -> 0.019419062 | J37: =INDEX(INDIRECT("'"&J$4&"'!$1:$1048576"),MATCH($A37,INDIRECT("'"&J$4&"'!$A:$A"),0),MATCH($A$2,INDIRECT("'"&J$4&"'!$5:$5"),0)) -> 309.21 | K37: =IFERROR(J37/J16, "NA") -> 0.013766247 | L37: =+J37+H37+F37+D37+B37 -> 1433.98 | M37: =IFERROR(L37/L16, "NA") -> 0.012367992
A38: 50300 - COGS - Beer | B38: =INDEX(INDIRECT("'"&B$4&"'!$1:$1048576"),MATCH($A38,INDIRECT("'"&B$4&"'!$A:$A"),0),MATCH($A$2,INDIRECT("'"&B$4&"'!$5:$5"),0)) -> 19.39 | C38: =IFERROR(B38/B16, "NA") -> 0.00096781648 | D38: =INDEX(INDIRECT("'"&D$4&"'!$1:$1048576"),MATCH($A38,INDIRECT("'"&D$4&"'!$A:$A"),0),MATCH($A$2,INDIRECT("'"&D$4&"'!$5:$5"),0)) -> 13.77 | E38: =IFERROR(D38/D16, "NA") -> 0.00034685654 | F38: =INDEX(INDIRECT("'"&F$4&"'!$1:$1048576"),MATCH($A38,INDIRECT("'"&F$4&"'!$A:$A"),0),MATCH($A$2,INDIRECT("'"&F$4&"'!$5:$5"),0)) -> 5.64 | G38: =IFERROR(F38/F16, "NA") -> 0.00034452363 | H38: =INDEX(INDIRECT("'"&H$4&"'!$1:$1048576"),MATCH($A38,INDIRECT("'"&H$4&"'!$A:$A"),0),MATCH($A$2,INDIRECT("'"&H$4&"'!$5:$5"),0)) -> 12.18 | I38: =IFERROR(H38/H16, "NA") -> 0.000700937 | J38: =INDEX(INDIRECT("'"&J$4&"'!$1:$1048576"),MATCH($A38,INDIRECT("'"&J$4&"'!$A:$A"),0),MATCH($A$2,INDIRECT("'"&J$4&"'!$5:$5"),0)) -> 8.3 | K38: =IFERROR(J38/J16, "NA") -> 0.00036952184 | L38: =+J38+H38+F38+D38+B38 -> 59.28 | M38: =IFERROR(L38/L16, "NA") -> 0.00051128647
A39: 50400 - COGS - Liquor | B39: =INDEX(INDIRECT("'"&B$4&"'!$1:$1048576"),MATCH($A39,INDIRECT("'"&B$4&"'!$A:$A"),0),MATCH($A$2,INDIRECT("'"&B$4&"'!$5:$5"),0)) -> 0 | C39: =IFERROR(B39/B16, "NA") -> 0 | D39: =INDEX(INDIRECT("'"&D$4&"'!$1:$1048576"),MATCH($A39,INDIRECT("'"&D$4&"'!$A:$A"),0),MATCH($A$2,INDIRECT("'"&D$4&"'!$5:$5"),0)) -> 0.8 | E39: =IFERROR(D39/D16, "NA") -> 2.0151433e-05 | F39: =INDEX(INDIRECT("'"&F$4&"'!$1:$1048576"),MATCH($A39,INDIRECT("'"&F$4&"'!$A:$A"),0),MATCH($A$2,INDIRECT("'"&F$4&"'!$5:$5"),0)) -> 0 | G39: =IFERROR(F39/F16, "NA") -> 0 | H39: =INDEX(INDIRECT("'"&H$4&"'!$1:$1048576"),MATCH($A39,INDIRECT("'"&H$4&"'!$A:$A"),0),MATCH($A$2,INDIRECT("'"&H$4&"'!$5:$5"),0)) -> 29.9 | I39: =IFERROR(H39/H16, "NA") -> 0.001720691 | J39: =INDEX(INDIRECT("'"&J$4&"'!$1:$1048576"),MATCH($A39,INDIRECT("'"&J$4&"'!$A:$A"),0),MATCH($A$2,INDIRECT("'"&J$4&"'!$5:$5"),0)) -> 0 | K39: =IFERROR(J39/J16, "NA") -> 0 | L39: =+J39+H39+F39+D39+B39 -> 30.7 | M39: =IFERROR(L39/L16, "NA") -> 0.00026478567
A40: 50500 - COGS - Wine | B40: =INDEX(INDIRECT("'"&B$4&"'!$1:$1048576"),MATCH($A40,INDIRECT("'"&B$4&"'!$A:$A"),0),MATCH($A$2,INDIRECT("'"&B$4&"'!$5:$5"),0)) -> 24.71 | C40: =IFERROR(B40/B16, "NA") -> 0.0012333546 | D40: =INDEX(INDIRECT("'"&D$4&"'!$1:$1048576"),MATCH($A40,INDIRECT("'"&D$4&"'!$A:$A"),0),MATCH($A$2,INDIRECT("'"&D$4&"'!$5:$5"),0)) -> -11.7 | E40: =IFERROR(D40/D16, "NA") -> -0.00029471471 | F40: =INDEX(INDIRECT("'"&F$4&"'!$1:$1048576"),MATCH($A40,INDIRECT("'"&F$4&"'!$A:$A"),0),MATCH($A$2,INDIRECT("'"&F$4&"'!$5:$5"),0)) -> 6.99 | G40: =IFERROR(F40/F16, "NA") -> 0.00042698939 | H40: =INDEX(INDIRECT("'"&H$4&"'!$1:$1048576"),MATCH($A40,INDIRECT("'"&H$4&"'!$A:$A"),0),MATCH($A$2,INDIRECT("'"&H$4&"'!$5:$5"),0)) -> 14.36 | I40: =IFERROR(H40/H16, "NA") -> 0.00082639206 | J40: =INDEX(INDIRECT("'"&J$4&"'!$1:$1048576"),MATCH($A40,INDIRECT("'"&J$4&"'!$A:$A"),0),MATCH($A$2,INDIRECT("'"&J$4&"'!$5:$5"),0)) -> 5.92 | K40: =IFERROR(J40/J16, "NA") -> 0.00026356256 | L40: =+J40+H40+F40+D40+B40 -> 40.28 | M40: =IFERROR(L40/L16, "NA") -> 0.0003474126
A41: Total Beverage Costs | B41: =INDEX(INDIRECT("'"&B$4&"'!$1:$1048576"),MATCH($A41,INDIRECT("'"&B$4&"'!$A:$A"),0),MATCH($A$2,INDIRECT("'"&B$4&"'!$5:$5"),0)) -> 322.74 | C41: =IFERROR(B41/B16, "NA") -> 0.016108978 | D41: =INDEX(INDIRECT("'"&D$4&"'!$1:$1048576"),MATCH($A41,INDIRECT("'"&D$4&"'!$A:$A"),0),MATCH($A$2,INDIRECT("'"&D$4&"'!$5:$5"),0)) -> 453.34 | E41: =IFERROR(D41/D16, "NA") -> 0.011419313 | F41: =INDEX(INDIRECT("'"&F$4&"'!$1:$1048576"),MATCH($A41,INDIRECT("'"&F$4&"'!$A:$A"),0),MATCH($A$2,INDIRECT("'"&F$4&"'!$5:$5"),0)) -> 70.85 | G41: =IFERROR(F41/F16, "NA") -> 0.0043279254 | H41: =INDEX(INDIRECT("'"&H$4&"'!$1:$1048576"),MATCH($A41,INDIRECT("'"&H$4&"'!$A:$A"),0),MATCH($A$2,INDIRECT("'"&H$4&"'!$5:$5"),0)) -> 393.88 | I41: =IFERROR(H41/H16, "NA") -> 0.022667083 | J41: =INDEX(INDIRECT("'"&J$4&"'!$1:$1048576"),MATCH($A41,INDIRECT("'"&J$4&"'!$A:$A"),0),MATCH($A$2,INDIRECT("'"&J$4&"'!$5:$5"),0)) -> 323.43 | K41: =IFERROR(J41/J16, "NA") -> 0.014399331 | L41: =+J41+H41+F41+D41+B41 -> 1564.24 | M41: =IFERROR(L41/L16, "NA") -> 0.013491477
A42: Total Food & Beverage Costs | B42: =INDEX(INDIRECT("'"&B$4&"'!$1:$1048576"),MATCH($A42,INDIRECT("'"&B$4&"'!$A:$A"),0),MATCH($A$2,INDIRECT("'"&B$4&"'!$5:$5"),0)) -> 4658.93 | C42: =IFERROR(B42/B16, "NA") -> 0.23254199 | D42: =INDEX(INDIRECT("'"&D$4&"'!$1:$1048576"),MATCH($A42,INDIRECT("'"&D$4&"'!$A:$A"),0),MATCH($A$2,INDIRECT("'"&D$4&"'!$5:$5"),0)) -> 8242.05 | E42: =IFERROR(D42/D16, "NA") -> 0.2076114 | F42: =INDEX(INDIRECT("'"&F$4&"'!$1:$1048576"),MATCH($A42,INDIRECT("'"&F$4&"'!$A:$A"),0),MATCH($A$2,INDIRECT("'"&F$4&"'!$5:$5"),0)) -> 3528.95 | G42: =IFERROR(F42/F16, "NA") -> 0.21556856 | H42: =INDEX(INDIRECT("'"&H$4&"'!$1:$1048576"),MATCH($A42,INDIRECT("'"&H$4&"'!$A:$A"),0),MATCH($A$2,INDIRECT("'"&H$4&"'!$5:$5"),0)) -> 4148.01 | I42: =IFERROR(H42/H16, "NA") -> 0.23871048 | J42: =INDEX(INDIRECT("'"&J$4&"'!$1:$1048576"),MATCH($A42,INDIRECT("'"&J$4&"'!$A:$A"),0),MATCH($A$2,INDIRECT("'"&J$4&"'!$5:$5"),0)) -> 6230.99 | K42: =IFERROR(J42/J16, "NA") -> 0.27740806 | L42: =+J42+H42+F42+D42+B42 -> 26808.93 | M42: =IFERROR(L42/L16, "NA") -> 0.23122542
A43: Other Costs
A44: 50550 - Other Costs
A45: Paper Costs
A46: 50600 - Paper Costs | B46: =INDEX(INDIRECT("'"&B$4&"'!$1:$1048576"),MATCH($A46,INDIRECT("'"&B$4&"'!$A:$A"),0),MATCH($A$2,INDIRECT("'"&B$4&"'!$5:$5"),0)) -> 0 | C46: =IFERROR(B46/B16, "NA") -> 0 | D46: =INDEX(INDIRECT("'"&D$4&"'!$1:$1048576"),MATCH($A46,INDIRECT("'"&D$4&"'!$A:$A"),0),MATCH($A$2,INDIRECT("'"&D$4&"'!$5:$5"),0)) -> 0 | E46: =IFERROR(D46/D16, "NA") -> 0 | F46: =INDEX(INDIRECT("'"&F$4&"'!$1:$1048576"),MATCH($A46,INDIRECT("'"&F$4&"'!$A:$A"),0),MATCH($A$2,INDIRECT("'"&F$4&"'!$5:$5"),0)) -> 0 | G46: =IFERROR(F46/F16, "NA") -> 0 | H46: =INDEX(INDIRECT("'"&H$4&"'!$1:$1048576"),MATCH($A46,INDIRECT("'"&H$4&"'!$A:$A"),0),MATCH($A$2,INDIRECT("'"&H$4&"'!$5:$5"),0)) -> 0 | I46: =IFERROR(H46/H16, "NA") -> 0 | J46: =INDEX(INDIRECT("'"&J$4&"'!$1:$1048576"),MATCH($A46,INDIRECT("'"&J$4&"'!$A:$A"),0),MATCH($A$2,INDIRECT("'"&J$4&"'!$5:$5"),0)) -> 0 | K46: =IFERROR(J46/J16, "NA") -> 0 | M46: =IFERROR(L46/L16, "NA") -> 0
A47: 50610 - COGS - Paper Supplies | B47: =INDEX(INDIRECT("'"&B$4&"'!$1:$1048576"),MATCH($A47,INDIRECT("'"&B$4&"'!$A:$A"),0),MATCH($A$2,INDIRECT("'"&B$4&"'!$5:$5"),0)) -> 502.4 | C47: =IFERROR(B47/B16, "NA") -> 0.02507638 | D47: =INDEX(INDIRECT("'"&D$4&"'!$1:$1048576"),MATCH($A47,INDIRECT("'"&D$4&"'!$A:$A"),0),MATCH($A$2,INDIRECT("'"&D$4&"'!$5:$5"),0)) -> 1217.14 | E47: =IFERROR(D47/D16, "NA") -> 0.030658894 | F47: =INDEX(INDIRECT("'"&F$4&"'!$1:$1048576"),MATCH($A47,INDIRECT("'"&F$4&"'!$A:$A"),0),MATCH($A$2,INDIRECT("'"&F$4&"'!$5:$5"),0)) -> 563.77 | G47: =IFERROR(F47/F16, "NA") -> 0.034438313 | H47: =INDEX(INDIRECT("'"&H$4&"'!$1:$1048576"),MATCH($A47,INDIRECT("'"&H$4&"'!$A:$A"),0),MATCH($A$2,INDIRECT("'"&H$4&"'!$5:$5"),0)) -> 541.15 | I47: =IFERROR(H47/H16, "NA") -> 0.031142205 | J47: =INDEX(INDIRECT("'"&J$4&"'!$1:$1048576"),MATCH($A47,INDIRECT("'"&J$4&"'!$A:$A"),0),MATCH($A$2,INDIRECT("'"&J$4&"'!$5:$5"),0)) -> 671.66 | K47: =IFERROR(J47/J16, "NA") -> 0.029902776 | L47: =+J47+H47+F47+D47+B47 -> 3496.12 | M47: =IFERROR(L47/L16, "NA") -> 0.030153827
A48: 50620 - COGS - Catering Supplies | B48: =INDEX(INDIRECT("'"&B$4&"'!$1:$1048576"),MATCH($A48,INDIRECT("'"&B$4&"'!$A:$A"),0),MATCH($A$2,INDIRECT("'"&B$4&"'!$5:$5"),0)) -> 461.92 | C48: =IFERROR(B48/B16, "NA") -> 0.023055894 | D48: =INDEX(INDIRECT("'"&D$4&"'!$1:$1048576"),MATCH($A48,INDIRECT("'"&D$4&"'!$A:$A"),0),MATCH($A$2,INDIRECT("'"&D$4&"'!$5:$5"),0)) -> 407.25 | E48: =IFERROR(D48/D16, "NA") -> 0.010258339 | F48: =INDEX(INDIRECT("'"&F$4&"'!$1:$1048576"),MATCH($A48,INDIRECT("'"&F$4&"'!$A:$A"),0),MATCH($A$2,INDIRECT("'"&F$4&"'!$5:$5"),0)) -> 180.11 | G48: =IFERROR(F48/F16, "NA") -> 0.011002154 | H48: =INDEX(INDIRECT("'"&H$4&"'!$1:$1048576"),MATCH($A48,INDIRECT("'"&H$4&"'!$A:$A"),0),MATCH($A$2,INDIRECT("'"&H$4&"'!$5:$5"),0)) -> 284.74 | I48: =IFERROR(H48/H16, "NA") -> 0.016386273 | J48: =INDEX(INDIRECT("'"&J$4&"'!$1:$1048576"),MATCH($A48,INDIRECT("'"&J$4&"'!$A:$A"),0),MATCH($A$2,INDIRECT("'"&J$4&"'!$5:$5"),0)) -> 311.66 | K48: =IFERROR(J48/J16, "NA") -> 0.013875322 | L48: =+J48+H48+F48+D48+B48 -> 1645.68 | M48: =IFERROR(L48/L16, "NA") -> 0.014193892
A49: 50630 - COGS - Event Supplies | B49: =INDEX(INDIRECT("'"&B$4&"'!$1:$1048576"),MATCH($A49,INDIRECT("'"&B$4&"'!$A:$A"),0),MATCH($A$2,INDIRECT("'"&B$4&"'!$5:$5"),0)) -> 0 | C49: =IFERROR(B49/B16, "NA") -> 0 | D49: =INDEX(INDIRECT("'"&D$4&"'!$1:$1048576"),MATCH($A49,INDIRECT("'"&D$4&"'!$A:$A"),0),MATCH($A$2,INDIRECT("'"&D$4&"'!$5:$5"),0)) -> 0 | E49: =IFERROR(D49/D16, "NA") -> 0 | F49: =INDEX(INDIRECT("'"&F$4&"'!$1:$1048576"),MATCH($A49,INDIRECT("'"&F$4&"'!$A:$A"),0),MATCH($A$2,INDIRECT("'"&F$4&"'!$5:$5"),0)) -> 0 | G49: =IFERROR(F49/F16, "NA") -> 0 | H49: =INDEX(INDIRECT("'"&H$4&"'!$1:$1048576"),MATCH($A49,INDIRECT("'"&H$4&"'!$A:$A"),0),MATCH($A$2,INDIRECT("'"&H$4&"'!$5:$5"),0)) -> 0 | I49: =IFERROR(H49/H16, "NA") -> 0 | J49: =INDEX(INDIRECT("'"&J$4&"'!$1:$1048576"),MATCH($A49,INDIRECT("'"&J$4&"'!$A:$A"),0),MATCH($A$2,INDIRECT("'"&J$4&"'!$5:$5"),0)) -> 0 | K49: =IFERROR(J49/J16, "NA") -> 0 | M49: =IFERROR(L49/L16, "NA") -> 0
A50: 50640 - COGS - Wow Bao Supplies | B50: =INDEX(INDIRECT("'"&B$4&"'!$1:$1048576"),MATCH($A50,INDIRECT("'"&B$4&"'!$A:$A"),0),MATCH($A$2,INDIRECT("'"&B$4&"'!$5:$5"),0)) -> 0 | C50: =IFERROR(B50/B16, "NA") -> 0 | D50: =INDEX(INDIRECT("'"&D$4&"'!$1:$1048576"),MATCH($A50,INDIRECT("'"&D$4&"'!$A:$A"),0),MATCH($A$2,INDIRECT("'"&D$4&"'!$5:$5"),0)) -> 0 | E50: =IFERROR(D50/D16, "NA") -> 0 | F50: =INDEX(INDIRECT("'"&F$4&"'!$1:$1048576"),MATCH($A50,INDIRECT("'"&F$4&"'!$A:$A"),0),MATCH($A$2,INDIRECT("'"&F$4&"'!$5:$5"),0)) -> 0 | G50: =IFERROR(F50/F16, "NA") -> 0 | H50: =INDEX(INDIRECT("'"&H$4&"'!$1:$1048576"),MATCH($A50,INDIRECT("'"&H$4&"'!$A:$A"),0),MATCH($A$2,INDIRECT("'"&H$4&"'!$5:$5"),0)) -> 0 | I50: =IFERROR(H50/H16, "NA") -> 0 | J50: =INDEX(INDIRECT("'"&J$4&"'!$1:$1048576"),MATCH($A50,INDIRECT("'"&J$4&"'!$A:$A"),0),MATCH($A$2,INDIRECT("'"&J$4&"'!$5:$5"),0)) -> 0 | K50: =IFERROR(J50/J16, "NA") -> 0 | M50: =IFERROR(L50/L16, "NA") -> 0
A51: Total Paper Costs | B51: =INDEX(INDIRECT("'"&B$4&"'!$1:$1048576"),MATCH($A51,INDIRECT("'"&B$4&"'!$A:$A"),0),MATCH($A$2,INDIRECT("'"&B$4&"'!$5:$5"),0)) -> 964.32 | C51: =IFERROR(B51/B16, "NA") -> 0.048132274 | D51: =INDEX(INDIRECT("'"&D$4&"'!$1:$1048576"),MATCH($A51,INDIRECT("'"&D$4&"'!$A:$A"),0),MATCH($A$2,INDIRECT("'"&D$4&"'!$5:$5"),0)) -> 1624.39 | E51: =IFERROR(D51/D16, "NA") -> 0.040917233 | F51: =INDEX(INDIRECT("'"&F$4&"'!$1:$1048576"),MATCH($A51,INDIRECT("'"&F$4&"'!$A:$A"),0),MATCH($A$2,INDIRECT("'"&F$4&"'!$5:$5"),0)) -> 743.88 | G51: =IFERROR(F51/F16, "NA") -> 0.045440468 | H51: =INDEX(INDIRECT("'"&H$4&"'!$1:$1048576"),MATCH($A51,INDIRECT("'"&H$4&"'!$A:$A"),0),MATCH($A$2,INDIRECT("'"&H$4&"'!$5:$5"),0)) -> 825.89 | I51: =IFERROR(H51/H16, "NA") -> 0.047528478 | J51: =INDEX(INDIRECT("'"&J$4&"'!$1:$1048576"),MATCH($A51,INDIRECT("'"&J$4&"'!$A:$A"),0),MATCH($A$2,INDIRECT("'"&J$4&"'!$5:$5"),0)) -> 983.32 | K51: =IFERROR(J51/J16, "NA") -> 0.043778098 | L51: =+J51+H51+F51+D51+B51 -> 5141.8 | M51: =IFERROR(L51/L16, "NA") -> 0.044347719
A52: Waste Costs
A53: 50700 - Waste Costs | B53: =INDEX(INDIRECT("'"&B$4&"'!$1:$1048576"),MATCH($A53,INDIRECT("'"&B$4&"'!$A:$A"),0),MATCH($A$2,INDIRECT("'"&B$4&"'!$5:$5"),0)) -> 0 | C53: =IFERROR(B53/B16, "NA") -> 0 | D53: =INDEX(INDIRECT("'"&D$4&"'!$1:$1048576"),MATCH($A53,INDIRECT("'"&D$4&"'!$A:$A"),0),MATCH($A$2,INDIRECT("'"&D$4&"'!$5:$5"),0)) -> 0 | E53: =IFERROR(D53/D16, "NA") -> 0 | F53: =INDEX(INDIRECT("'"&F$4&"'!$1:$1048576"),MATCH($A53,INDIRECT("'"&F$4&"'!$A:$A"),0),MATCH($A$2,INDIRECT("'"&F$4&"'!$5:$5"),0)) -> 0 | G53: =IFERROR(F53/F16, "NA") -> 0 | H53: =INDEX(INDIRECT("'"&H$4&"'!$1:$1048576"),MATCH($A53,INDIRECT("'"&H$4&"'!$A:$A"),0),MATCH($A$2,INDIRECT("'"&H$4&"'!$5:$5"),0)) -> 0 | I53: =IFERROR(H53/H16, "NA") -> 0 | J53: =INDEX(INDIRECT("'"&J$4&"'!$1:$1048576"),MATCH($A53,INDIRECT("'"&J$4&"'!$A:$A"),0),MATCH($A$2,INDIRECT("'"&J$4&"'!$5:$5"),0)) -> 0 | K53: =IFERROR(J53/J16, "NA") -> 0 | M53: =IFERROR(L53/L16, "NA") -> 0
A54: 50710 - Waste - Food | B54: =INDEX(INDIRECT("'"&B$4&"'!$1:$1048576"),MATCH($A54,INDIRECT("'"&B$4&"'!$A:$A"),0),MATCH($A$2,INDIRECT("'"&B$4&"'!$5:$5"),0)) -> 82.17 | C54: =IFERROR(B54/B16, "NA") -> 0.0041013657 | D54: =INDEX(INDIRECT("'"&D$4&"'!$1:$1048576"),MATCH($A54,INDIRECT("'"&D$4&"'!$A:$A"),0),MATCH($A$2,INDIRECT("'"&D$4&"'!$5:$5"),0)) -> 49.37 | E54: =IFERROR(D54/D16, "NA") -> 0.0012435953 | F54: =INDEX(INDIRECT("'"&F$4&"'!$1:$1048576"),MATCH($A54,INDIRECT("'"&F$4&"'!$A:$A"),0),MATCH($A$2,INDIRECT("'"&F$4&"'!$5:$5"),0)) -> 37.2 | G54: =IFERROR(F54/F16, "NA") -> 0.0022723899 | H54: =INDEX(INDIRECT("'"&H$4&"'!$1:$1048576"),MATCH($A54,INDIRECT("'"&H$4&"'!$A:$A"),0),MATCH($A$2,INDIRECT("'"&H$4&"'!$5:$5"),0)) -> 35.47 | I54: =IFERROR(H54/H16, "NA") -> 0.0020412344 | J54: =INDEX(INDIRECT("'"&J$4&"'!$1:$1048576"),MATCH($A54,INDIRECT("'"&J$4&"'!$A:$A"),0),MATCH($A$2,INDIRECT("'"&J$4&"'!$5:$5"),0)) -> 10.38 | K54: =IFERROR(J54/J16, "NA") -> 0.0004621249 | L54: =+J54+H54+F54+D54+B54 -> 214.59 | M54: =IFERROR(L54/L16, "NA") -> 0.001850826
A55: 50720 - Waste - N/A Beverage | B55: =INDEX(INDIRECT("'"&B$4&"'!$1:$1048576"),MATCH($A55,INDIRECT("'"&B$4&"'!$A:$A"),0),MATCH($A$2,INDIRECT("'"&B$4&"'!$5:$5"),0)) -> 0 | C55: =IFERROR(B55/B16, "NA") -> 0 | D55: =INDEX(INDIRECT("'"&D$4&"'!$1:$1048576"),MATCH($A55,INDIRECT("'"&D$4&"'!$A:$A"),0),MATCH($A$2,INDIRECT("'"&D$4&"'!$5:$5"),0)) -> 0 | E55: =IFERROR(D55/D16, "NA") -> 0 | F55: =INDEX(INDIRECT("'"&F$4&"'!$1:$1048576"),MATCH($A55,INDIRECT("'"&F$4&"'!$A:$A"),0),MATCH($A$2,INDIRECT("'"&F$4&"'!$5:$5"),0)) -> 0 | G55: =IFERROR(F55/F16, "NA") -> 0 | H55: =INDEX(INDIRECT("'"&H$4&"'!$1:$1048576"),MATCH($A55,INDIRECT("'"&H$4&"'!$A:$A"),0),MATCH($A$2,INDIRECT("'"&H$4&"'!$5:$5"),0)) -> 0 | I55: =IFERROR(H55/H16, "NA") -> 0 | J55: =INDEX(INDIRECT("'"&J$4&"'!$1:$1048576"),MATCH($A55,INDIRECT("'"&J$4&"'!$A:$A"),0),MATCH($A$2,INDIRECT("'"&J$4&"'!$5:$5"),0)) -> 0 | K55: =IFERROR(J55/J16, "NA") -> 0 | L55: =+J55+H55+F55+D55+B55 -> 0 | M55: =IFERROR(L55/L16, "NA") -> 0
A56: 50730 - Waste - Beer | B56: =INDEX(INDIRECT("'"&B$4&"'!$1:$1048576"),MATCH($A56,INDIRECT("'"&B$4&"'!$A:$A"),0),MATCH($A$2,INDIRECT("'"&B$4&"'!$5:$5"),0)) -> 0 | C56: =IFERROR(B56/B16, "NA") -> 0 | D56: =INDEX(INDIRECT("'"&D$4&"'!$1:$1048576"),MATCH($A56,INDIRECT("'"&D$4&"'!$A:$A"),0),MATCH($A$2,INDIRECT("'"&D$4&"'!$5:$5"),0)) -> 0 | E56: =IFERROR(D56/D16, "NA") -> 0 | F56: =INDEX(INDIRECT("'"&F$4&"'!$1:$1048576"),MATCH($A56,INDIRECT("'"&F$4&"'!$A:$A"),0),MATCH($A$2,INDIRECT("'"&F$4&"'!$5:$5"),0)) -> 0 | G56: =IFERROR(F56/F16, "NA") -> 0 | H56: =INDEX(INDIRECT("'"&H$4&"'!$1:$1048576"),MATCH($A56,INDIRECT("'"&H$4&"'!$A:$A"),0),MATCH($A$2,INDIRECT("'"&H$4&"'!$5:$5"),0)) -> 0 | I56: =IFERROR(H56/H16, "NA") -> 0 | J56: =INDEX(INDIRECT("'"&J$4&"'!$1:$1048576"),MATCH($A56,INDIRECT("'"&J$4&"'!$A:$A"),0),MATCH($A$2,INDIRECT("'"&J$4&"'!$5:$5"),0)) -> 0 | K56: =IFERROR(J56/J16, "NA") -> 0 | L56: =+J56+H56+F56+D56+B56 -> 0 | M56: =IFERROR(L56/L16, "NA") -> 0
A57: 50740 - Waste - Liquor | B57: =INDEX(INDIRECT("'"&B$4&"'!$1:$1048576"),MATCH($A57,INDIRECT("'"&B$4&"'!$A:$A"),0),MATCH($A$2,INDIRECT("'"&B$4&"'!$5:$5"),0)) -> 0 | C57: =IFERROR(B57/B16, "NA") -> 0 | D57: =INDEX(INDIRECT("'"&D$4&"'!$1:$1048576"),MATCH($A57,INDIRECT("'"&D$4&"'!$A:$A"),0),MATCH($A$2,INDIRECT("'"&D$4&"'!$5:$5"),0)) -> 0 | E57: =IFERROR(D57/D16, "NA") -> 0 | F57: =INDEX(INDIRECT("'"&F$4&"'!$1:$1048576"),MATCH($A57,INDIRECT("'"&F$4&"'!$A:$A"),0),MATCH($A$2,INDIRECT("'"&F$4&"'!$5:$5"),0)) -> 0 | G57: =IFERROR(F57/F16, "NA") -> 0 | H57: =INDEX(INDIRECT("'"&H$4&"'!$1:$1048576"),MATCH($A57,INDIRECT("'"&H$4&"'!$A:$A"),0),MATCH($A$2,INDIRECT("'"&H$4&"'!$5:$5"),0)) -> 0 | I57: =IFERROR(H57/H16, "NA") -> 0 | J57: =INDEX(INDIRECT("'"&J$4&"'!$1:$1048576"),MATCH($A57,INDIRECT("'"&J$4&"'!$A:$A"),0),MATCH($A$2,INDIRECT("'"&J$4&"'!$5:$5"),0)) -> 0 | K57: =IFERROR(J57/J16, "NA") -> 0 | L57: =+J57+H57+F57+D57+B57 -> 0 | M57: =IFERROR(L57/L16, "NA") -> 0
A58: 50750 - Waste - Wine | B58: =INDEX(INDIRECT("'"&B$4&"'!$1:$1048576"),MATCH($A58,INDIRECT("'"&B$4&"'!$A:$A"),0),MATCH($A$2,INDIRECT("'"&B$4&"'!$5:$5"),0)) -> 0 | C58: =IFERROR(B58/B16, "NA") -> 0 | D58: =INDEX(INDIRECT("'"&D$4&"'!$1:$1048576"),MATCH($A58,INDIRECT("'"&D$4&"'!$A:$A"),0),MATCH($A$2,INDIRECT("'"&D$4&"'!$5:$5"),0)) -> 0 | E58: =IFERROR(D58/D16, "NA") -> 0 | F58: =INDEX(INDIRECT("'"&F$4&"'!$1:$1048576"),MATCH($A58,INDIRECT("'"&F$4&"'!$A:$A"),0),MATCH($A$2,INDIRECT("'"&F$4&"'!$5:$5"),0)) -> 0 | G58: =IFERROR(F58/F16, "NA") -> 0 | H58: =INDEX(INDIRECT("'"&H$4&"'!$1:$1048576"),MATCH($A58,INDIRECT("'"&H$4&"'!$A:$A"),0),MATCH($A$2,INDIRECT("'"&H$4&"'!$5:$5"),0)) -> 0 | I58: =IFERROR(H58/H16, "NA") -> 0 | J58: =INDEX(INDIRECT("'"&J$4&"'!$1:$1048576"),MATCH($A58,INDIRECT("'"&J$4&"'!$A:$A"),0),MATCH($A$2,INDIRECT("'"&J$4&"'!$5:$5"),0)) -> 0 | K58: =IFERROR(J58/J16, "NA") -> 0 | L58: =+J58+H58+F58+D58+B58 -> 0 | M58: =IFERROR(L58/L16, "NA") -> 0
A59: Total Waste Costs | B59: =INDEX(INDIRECT("'"&B$4&"'!$1:$1048576"),MATCH($A59,INDIRECT("'"&B$4&"'!$A:$A"),0),MATCH($A$2,INDIRECT("'"&B$4&"'!$5:$5"),0)) -> 82.17 | C59: =IFERROR(B59/B16, "NA") -> 0.0041013657 | D59: =INDEX(INDIRECT("'"&D$4&"'!$1:$1048576"),MATCH($A59,INDIRECT("'"&D$4&"'!$A:$A"),0),MATCH($A$2,INDIRECT("'"&D$4&"'!$5:$5"),0)) -> 49.37 | E59: =IFERROR(D59/D16, "NA") -> 0.0012435953 | F59: =INDEX(INDIRECT("'"&F$4&"'!$1:$1048576"),MATCH($A59,INDIRECT("'"&F$4&"'!$A:$A"),0),MATCH($A$2,INDIRECT("'"&F$4&"'!$5:$5"),0)) -> 37.2 | G59: =IFERROR(F59/F16, "NA") -> 0.0022723899 | H59: =INDEX(INDIRECT("'"&H$4&"'!$1:$1048576"),MATCH($A59,INDIRECT("'"&H$4&"'!$A:$A"),0),MATCH($A$2,INDIRECT("'"&H$4&"'!$5:$5"),0)) -> 35.47 | I59: =IFERROR(H59/H16, "NA") -> 0.0020412344 | J59: =INDEX(INDIRECT("'"&J$4&"'!$1:$1048576"),MATCH($A59,INDIRECT("'"&J$4&"'!$A:$A"),0),MATCH($A$2,INDIRECT("'"&J$4&"'!$5:$5"),0)) -> 10.38 | K59: =IFERROR(J59/J16, "NA") -> 0.0004621249 | L59: =+J59+H59+F59+D59+B59 -> 214.59 | M59: =IFERROR(L59/L16, "NA") -> 0.001850826
A60: 50800 - COGS - Freight, Delivery, & Sales Tax | B60: =INDEX(INDIRECT("'"&B$4&"'!$1:$1048576"),MATCH($A60,INDIRECT("'"&B$4&"'!$A:$A"),0),MATCH($A$2,INDIRECT("'"&B$4&"'!$5:$5"),0)) -> 25.68 | C60: =IFERROR(B60/B16, "NA") -> 0.0012817704 | D60: =INDEX(INDIRECT("'"&D$4&"'!$1:$1048576"),MATCH($A60,INDIRECT("'"&D$4&"'!$A:$A"),0),MATCH($A$2,INDIRECT("'"&D$4&"'!$5:$5"),0)) -> 7.2 | E60: =IFERROR(D60/D16, "NA") -> 0.0001813629 | F60: =INDEX(INDIRECT("'"&F$4&"'!$1:$1048576"),MATCH($A60,INDIRECT("'"&F$4&"'!$A:$A"),0),MATCH($A$2,INDIRECT("'"&F$4&"'!$5:$5"),0)) -> 43.74 | G60: =IFERROR(F60/F16, "NA") -> 0.0026718907 | H60: =INDEX(INDIRECT("'"&H$4&"'!$1:$1048576"),MATCH($A60,INDIRECT("'"&H$4&"'!$A:$A"),0),MATCH($A$2,INDIRECT("'"&H$4&"'!$5:$5"),0)) -> 42.33 | I60: =IFERROR(H60/H16, "NA") -> 0.002436015 | J60: =INDEX(INDIRECT("'"&J$4&"'!$1:$1048576"),MATCH($A60,INDIRECT("'"&J$4&"'!$A:$A"),0),MATCH($A$2,INDIRECT("'"&J$4&"'!$5:$5"),0)) -> 24.4 | K60: =IFERROR(J60/J16, "NA") -> 0.0010863052 | L60: =+J60+H60+F60+D60+B60 -> 143.35 | M60: =IFERROR(L60/L16, "NA") -> 0.0012363852
A61: 50850 - COGS - Fuel Surcharge | B61: =INDEX(INDIRECT("'"&B$4&"'!$1:$1048576"),MATCH($A61,INDIRECT("'"&B$4&"'!$A:$A"),0),MATCH($A$2,INDIRECT("'"&B$4&"'!$5:$5"),0)) -> 6 | C61: =IFERROR(B61/B16, "NA") -> 0.00029947906 | D61: =INDEX(INDIRECT("'"&D$4&"'!$1:$1048576"),MATCH($A61,INDIRECT("'"&D$4&"'!$A:$A"),0),MATCH($A$2,INDIRECT("'"&D$4&"'!$5:$5"),0)) -> 12 | E61: =IFERROR(D61/D16, "NA") -> 0.00030227149 | F61: =INDEX(INDIRECT("'"&F$4&"'!$1:$1048576"),MATCH($A61,INDIRECT("'"&F$4&"'!$A:$A"),0),MATCH($A$2,INDIRECT("'"&F$4&"'!$5:$5"),0)) -> 12.31 | G61: =IFERROR(F61/F16, "NA") -> 0.00075196559 | H61: =INDEX(INDIRECT("'"&H$4&"'!$1:$1048576"),MATCH($A61,INDIRECT("'"&H$4&"'!$A:$A"),0),MATCH($A$2,INDIRECT("'"&H$4&"'!$5:$5"),0)) -> 9.31 | I61: =IFERROR(H61/H16, "NA") -> 0.00053577368 | J61: =INDEX(INDIRECT("'"&J$4&"'!$1:$1048576"),MATCH($A61,INDIRECT("'"&J$4&"'!$A:$A"),0),MATCH($A$2,INDIRECT("'"&J$4&"'!$5:$5"),0)) -> 9.31 | K61: =IFERROR(J61/J16, "NA") -> 0.00041448775 | L61: =+J61+H61+F61+D61+B61 -> 48.93 | M61: =IFERROR(L61/L16, "NA") -> 0.00042201833
A62: 50900 - COGS - Credit for Discounts | B62: =INDEX(INDIRECT("'"&B$4&"'!$1:$1048576"),MATCH($A62,INDIRECT("'"&B$4&"'!$A:$A"),0),MATCH($A$2,INDIRECT("'"&B$4&"'!$5:$5"),0)) -> -210.18 | C62: =IFERROR(B62/B16, "NA") -> -0.010490751 | D62: =INDEX(INDIRECT("'"&D$4&"'!$1:$1048576"),MATCH($A62,INDIRECT("'"&D$4&"'!$A:$A"),0),MATCH($A$2,INDIRECT("'"&D$4&"'!$5:$5"),0)) -> -159.98 | E62: =IFERROR(D62/D16, "NA") -> -0.0040297828 | F62: =INDEX(INDIRECT("'"&F$4&"'!$1:$1048576"),MATCH($A62,INDIRECT("'"&F$4&"'!$A:$A"),0),MATCH($A$2,INDIRECT("'"&F$4&"'!$5:$5"),0)) -> -211.32 | G62: =IFERROR(F62/F16, "NA") -> -0.012908641 | H62: =INDEX(INDIRECT("'"&H$4&"'!$1:$1048576"),MATCH($A62,INDIRECT("'"&H$4&"'!$A:$A"),0),MATCH($A$2,INDIRECT("'"&H$4&"'!$5:$5"),0)) -> -203.62 | I62: =IFERROR(H62/H16, "NA") -> -0.011717963 | J62: =INDEX(INDIRECT("'"&J$4&"'!$1:$1048576"),MATCH($A62,INDIRECT("'"&J$4&"'!$A:$A"),0),MATCH($A$2,INDIRECT("'"&J$4&"'!$5:$5"),0)) -> -243.35 | K62: =IFERROR(J62/J16, "NA") -> -0.010834113 | L62: =+J62+H62+F62+D62+B62 -> -1028.45 | M62: =IFERROR(L62/L16, "NA") -> -0.00887032
A63: Total Other Costs | B63: =INDEX(INDIRECT("'"&B$4&"'!$1:$1048576"),MATCH($A63,INDIRECT("'"&B$4&"'!$A:$A"),0),MATCH($A$2,INDIRECT("'"&B$4&"'!$5:$5"),0)) -> 867.99 | C63: =IFERROR(B63/B16, "NA") -> 0.043324138 | D63: =INDEX(INDIRECT("'"&D$4&"'!$1:$1048576"),MATCH($A63,INDIRECT("'"&D$4&"'!$A:$A"),0),MATCH($A$2,INDIRECT("'"&D$4&"'!$5:$5"),0)) -> 1532.98 | E63: =IFERROR(D63/D16, "NA") -> 0.03861468 | F63: =INDEX(INDIRECT("'"&F$4&"'!$1:$1048576"),MATCH($A63,INDIRECT("'"&F$4&"'!$A:$A"),0),MATCH($A$2,INDIRECT("'"&F$4&"'!$5:$5"),0)) -> 625.81 | G63: =IFERROR(F63/F16, "NA") -> 0.038228073 | H63: =INDEX(INDIRECT("'"&H$4&"'!$1:$1048576"),MATCH($A63,INDIRECT("'"&H$4&"'!$A:$A"),0),MATCH($A$2,INDIRECT("'"&H$4&"'!$5:$5"),0)) -> 709.38 | I63: =IFERROR(H63/H16, "NA") -> 0.040823538 | J63: =INDEX(INDIRECT("'"&J$4&"'!$1:$1048576"),MATCH($A63,INDIRECT("'"&J$4&"'!$A:$A"),0),MATCH($A$2,INDIRECT("'"&J$4&"'!$5:$5"),0)) -> 784.06 | K63: =IFERROR(J63/J16, "NA") -> 0.034906903 | L63: =+J63+H63+F63+D63+B63 -> 4520.22 | M63: =IFERROR(L63/L16, "NA") -> 0.038986628
A64: Total Cost of Goods Sold | B64: =INDEX(INDIRECT("'"&B$4&"'!$1:$1048576"),MATCH($A64,INDIRECT("'"&B$4&"'!$A:$A"),0),MATCH($A$2,INDIRECT("'"&B$4&"'!$5:$5"),0)) -> 5526.92 | C64: =IFERROR(B64/B16, "NA") -> 0.27586613 | D64: =INDEX(INDIRECT("'"&D$4&"'!$1:$1048576"),MATCH($A64,INDIRECT("'"&D$4&"'!$A:$A"),0),MATCH($A$2,INDIRECT("'"&D$4&"'!$5:$5"),0)) -> 9775.03 | E64: =IFERROR(D64/D16, "NA") -> 0.24622608 | F64: =INDEX(INDIRECT("'"&F$4&"'!$1:$1048576"),MATCH($A64,INDIRECT("'"&F$4&"'!$A:$A"),0),MATCH($A$2,INDIRECT("'"&F$4&"'!$5:$5"),0)) -> 4154.76 | G64: =IFERROR(F64/F16, "NA") -> 0.25379663 | H64: =INDEX(INDIRECT("'"&H$4&"'!$1:$1048576"),MATCH($A64,INDIRECT("'"&H$4&"'!$A:$A"),0),MATCH($A$2,INDIRECT("'"&H$4&"'!$5:$5"),0)) -> 4857.39 | I64: =IFERROR(H64/H16, "NA") -> 0.27953402 | J64: =INDEX(INDIRECT("'"&J$4&"'!$1:$1048576"),MATCH($A64,INDIRECT("'"&J$4&"'!$A:$A"),0),MATCH($A$2,INDIRECT("'"&J$4&"'!$5:$5"),0)) -> 7015.05 | K64: =IFERROR(J64/J16, "NA") -> 0.31231496 | L64: =+J64+H64+F64+D64+B64 -> 31329.15 | M64: =IFERROR(L64/L16, "NA") -> 0.27021205
A66: Gross Profit | B66: {=INDEX(INDIRECT("'"&B$4&"'!$1:$1048576"),MATCH($A66,INDIRECT("'"&B$4&"'!$A:$A"),0),MATCH($A$2,INDIRECT("'"&B$4&"'!$5:$5"),0))} -> 14507.87 | C66: =IFERROR(B66/B16, "NA") -> 0.72413387 | D66: {=INDEX(INDIRECT("'"&D$4&"'!$1:$1048576"),MATCH($A66,INDIRECT("'"&D$4&"'!$A:$A"),0),MATCH($A$2,INDIRECT("'"&D$4&"'!$5:$5"),0))} -> 29924.38 | E66: =IFERROR(D66/D16, "NA") -> 0.75377392 | F66: {=INDEX(INDIRECT("'"&F$4&"'!$1:$1048576"),MATCH($A66,INDIRECT("'"&F$4&"'!$A:$A"),0),MATCH($A$2,INDIRECT("'"&F$4&"'!$5:$5"),0))} -> 12215.67 | G66: =IFERROR(F66/F16, "NA") -> 0.74620337 | H66: {=INDEX(INDIRECT("'"&H$4&"'!$1:$1048576"),MATCH($A66,INDIRECT("'"&H$4&"'!$A:$A"),0),MATCH($A$2,INDIRECT("'"&H$4&"'!$5:$5"),0))} -> 12519.35 | I66: =IFERROR(H66/H16, "NA") -> 0.72046598 | J66: {=INDEX(INDIRECT("'"&J$4&"'!$1:$1048576"),MATCH($A66,INDIRECT("'"&J$4&"'!$A:$A"),0),MATCH($A$2,INDIRECT("'"&J$4&"'!$5:$5"),0))} -> 15446.41 | K66: =IFERROR(J66/J16, "NA") -> 0.68768504 | L66: =+J66+H66+F66+D66+B66 -> 84613.68 | M66: =IFERROR(L66/L16, "NA") -> 0.72978795
A68: Payroll Expenses
A69: Payroll Expenses
A70: 61000 - Payroll Expenses
A71: Salaries & Wages
A72: 61100 - Salaries & Wages | B72: =INDEX(INDIRECT("'"&B$4&"'!$1:$1048576"),MATCH($A72,INDIRECT("'"&B$4&"'!$A:$A"),0),MATCH($A$2,INDIRECT("'"&B$4&"'!$5:$5"),0)) -> 0 | C72: =IFERROR(B72/B16, "NA") -> 0 | D72: =INDEX(INDIRECT("'"&D$4&"'!$1:$1048576"),MATCH($A72,INDIRECT("'"&D$4&"'!$A:$A"),0),MATCH($A$2,INDIRECT("'"&D$4&"'!$5:$5"),0)) -> 0 | E72: =IFERROR(D72/D16, "NA") -> 0 | F72: =INDEX(INDIRECT("'"&F$4&"'!$1:$1048576"),MATCH($A72,INDIRECT("'"&F$4&"'!$A:$A"),0),MATCH($A$2,INDIRECT("'"&F$4&"'!$5:$5"),0)) -> 0 | G72: =IFERROR(F72/F16, "NA") -> 0 | H72: =INDEX(INDIRECT("'"&H$4&"'!$1:$1048576"),MATCH($A72,INDIRECT("'"&H$4&"'!$A:$A"),0),MATCH($A$2,INDIRECT("'"&H$4&"'!$5:$5"),0)) -> 0 | I72: =IFERROR(H72/H16, "NA") -> 0 | J72: =INDEX(INDIRECT("'"&J$4&"'!$1:$1048576"),MATCH($A72,INDIRECT("'"&J$4&"'!$A:$A"),0),MATCH($A$2,INDIRECT("'"&J$4&"'!$5:$5"),0)) -> 0 | K72: =IFERROR(J72/J16, "NA") -> 0 | M72: =IFERROR(L72/L16, "NA") -> 0
A73: 61110 - Management | B73: =INDEX(INDIRECT("'"&B$4&"'!$1:$1048576"),MATCH($A73,INDIRECT("'"&B$4&"'!$A:$A"),0),MATCH($A$2,INDIRECT("'"&B$4&"'!$5:$5"),0)) -> 1269.23 | C73: =IFERROR(B73/B16, "NA") -> 0.0633513 | D73: =INDEX(INDIRECT("'"&D$4&"'!$1:$1048576"),MATCH($A73,INDIRECT("'"&D$4&"'!$A:$A"),0),MATCH($A$2,INDIRECT("'"&D$4&"'!$5:$5"),0)) -> 2519.23 | E73: =IFERROR(D73/D16, "NA") -> 0.063457618 | F73: =INDEX(INDIRECT("'"&F$4&"'!$1:$1048576"),MATCH($A73,INDIRECT("'"&F$4&"'!$A:$A"),0),MATCH($A$2,INDIRECT("'"&F$4&"'!$5:$5"),0)) -> 1410 | G73: =IFERROR(F73/F16, "NA") -> 0.086130908 | H73: =INDEX(INDIRECT("'"&H$4&"'!$1:$1048576"),MATCH($A73,INDIRECT("'"&H$4&"'!$A:$A"),0),MATCH($A$2,INDIRECT("'"&H$4&"'!$5:$5"),0)) -> 1461.54 | I73: =IFERROR(H73/H16, "NA") -> 0.084108987 | J73: =INDEX(INDIRECT("'"&J$4&"'!$1:$1048576"),MATCH($A73,INDIRECT("'"&J$4&"'!$A:$A"),0),MATCH($A$2,INDIRECT("'"&J$4&"'!$5:$5"),0)) -> 1298.08 | K73: =IFERROR(J73/J16, "NA") -> 0.057791435 | L73: =+J73+H73+F73+D73+B73 -> 7958.08 | M73: =IFERROR(L73/L16, "NA") -> 0.068637966
A74: 61120 - Culinary | B74: =INDEX(INDIRECT("'"&B$4&"'!$1:$1048576"),MATCH($A74,INDIRECT("'"&B$4&"'!$A:$A"),0),MATCH($A$2,INDIRECT("'"&B$4&"'!$5:$5"),0)) -> 0 | C74: =IFERROR(B74/B16, "NA") -> 0 | D74: =INDEX(INDIRECT("'"&D$4&"'!$1:$1048576"),MATCH($A74,INDIRECT("'"&D$4&"'!$A:$A"),0),MATCH($A$2,INDIRECT("'"&D$4&"'!$5:$5"),0)) -> 0 | E74: =IFERROR(D74/D16, "NA") -> 0 | F74: =INDEX(INDIRECT("'"&F$4&"'!$1:$1048576"),MATCH($A74,INDIRECT("'"&F$4&"'!$A:$A"),0),MATCH($A$2,INDIRECT("'"&F$4&"'!$5:$5"),0)) -> 0 | G74: =IFERROR(F74/F16, "NA") -> 0 | H74: =INDEX(INDIRECT("'"&H$4&"'!$1:$1048576"),MATCH($A74,INDIRECT("'"&H$4&"'!$A:$A"),0),MATCH($A$2,INDIRECT("'"&H$4&"'!$5:$5"),0)) -> 0 | I74: =IFERROR(H74/H16, "NA") -> 0 | J74: =INDEX(INDIRECT("'"&J$4&"'!$1:$1048576"),MATCH($A74,INDIRECT("'"&J$4&"'!$A:$A"),0),MATCH($A$2,INDIRECT("'"&J$4&"'!$5:$5"),0)) -> 0 | K74: =IFERROR(J74/J16, "NA") -> 0 | L74: =+J74+H74+F74+D74+B74 -> 0 | M74: =IFERROR(L74/L16, "NA") -> 0
A75: 61150 - Hourly | B75: =INDEX(INDIRECT("'"&B$4&"'!$1:$1048576"),MATCH($A75,INDIRECT("'"&B$4&"'!$A:$A"),0),MATCH($A$2,INDIRECT("'"&B$4&"'!$5:$5"),0)) -> 3781.92 | C75: =IFERROR(B75/B16, "NA") -> 0.18876764 | D75: =INDEX(INDIRECT("'"&D$4&"'!$1:$1048576"),MATCH($A75,INDIRECT("'"&D$4&"'!$A:$A"),0),MATCH($A$2,INDIRECT("'"&D$4&"'!$5:$5"),0)) -> 6057.23 | E75: =IFERROR(D75/D16, "NA") -> 0.15257733 | F75: =INDEX(INDIRECT("'"&F$4&"'!$1:$1048576"),MATCH($A75,INDIRECT("'"&F$4&"'!$A:$A"),0),MATCH($A$2,INDIRECT("'"&F$4&"'!$5:$5"),0)) -> 3143.97 | G75: =IFERROR(F75/F16, "NA") -> 0.19205177 | H75: =INDEX(INDIRECT("'"&H$4&"'!$1:$1048576"),MATCH($A75,INDIRECT("'"&H$4&"'!$A:$A"),0),MATCH($A$2,INDIRECT("'"&H$4&"'!$5:$5"),0)) -> 3112.87 | I75: =IFERROR(H75/H16, "NA") -> 0.17914005 | J75: =INDEX(INDIRECT("'"&J$4&"'!$1:$1048576"),MATCH($A75,INDIRECT("'"&J$4&"'!$A:$A"),0),MATCH($A$2,INDIRECT("'"&J$4&"'!$5:$5"),0)) -> 4398.98 | K75: =IFERROR(J75/J16, "NA") -> 0.19584568 | L75: =+J75+H75+F75+D75+B75 -> 20494.97 | M75: =IFERROR(L75/L16, "NA") -> 0.1767679
A76: 61200 - Overtime | B76: =INDEX(INDIRECT("'"&B$4&"'!$1:$1048576"),MATCH($A76,INDIRECT("'"&B$4&"'!$A:$A"),0),MATCH($A$2,INDIRECT("'"&B$4&"'!$5:$5"),0)) -> 194.4 | C76: =IFERROR(B76/B16, "NA") -> 0.0097031214 | D76: =INDEX(INDIRECT("'"&D$4&"'!$1:$1048576"),MATCH($A76,INDIRECT("'"&D$4&"'!$A:$A"),0),MATCH($A$2,INDIRECT("'"&D$4&"'!$5:$5"),0)) -> 4.73 | E76: =IFERROR(D76/D16, "NA") -> 0.00011914535 | F76: =INDEX(INDIRECT("'"&F$4&"'!$1:$1048576"),MATCH($A76,INDIRECT("'"&F$4&"'!$A:$A"),0),MATCH($A$2,INDIRECT("'"&F$4&"'!$5:$5"),0)) -> 0 | G76: =IFERROR(F76/F16, "NA") -> 0 | H76: =INDEX(INDIRECT("'"&H$4&"'!$1:$1048576"),MATCH($A76,INDIRECT("'"&H$4&"'!$A:$A"),0),MATCH($A$2,INDIRECT("'"&H$4&"'!$5:$5"),0)) -> 11.96 | I76: =IFERROR(H76/H16, "NA") -> 0.0006882764 | J76: =INDEX(INDIRECT("'"&J$4&"'!$1:$1048576"),MATCH($A76,INDIRECT("'"&J$4&"'!$A:$A"),0),MATCH($A$2,INDIRECT("'"&J$4&"'!$5:$5"),0)) -> 0 | K76: =IFERROR(J76/J16, "NA") -> 0 | L76: =+J76+H76+F76+D76+B76 -> 211.09 | M76: =IFERROR(L76/L16, "NA") -> 0.0018206387
A77: Total Salaries & Wages | B77: =INDEX(INDIRECT("'"&B$4&"'!$1:$1048576"),MATCH($A77,INDIRECT("'"&B$4&"'!$A:$A"),0),MATCH($A$2,INDIRECT("'"&B$4&"'!$5:$5"),0)) -> 5245.55 | C77: =IFERROR(B77/B16, "NA") -> 0.26182206 | D77: =INDEX(INDIRECT("'"&D$4&"'!$1:$1048576"),MATCH($A77,INDIRECT("'"&D$4&"'!$A:$A"),0),MATCH($A$2,INDIRECT("'"&D$4&"'!$5:$5"),0)) -> 8581.19 | E77: =IFERROR(D77/D16, "NA") -> 0.21615409 | F77: =INDEX(INDIRECT("'"&F$4&"'!$1:$1048576"),MATCH($A77,INDIRECT("'"&F$4&"'!$A:$A"),0),MATCH($A$2,INDIRECT("'"&F$4&"'!$5:$5"),0)) -> 4553.97 | G77: =IFERROR(F77/F16, "NA") -> 0.27818267 | H77: =INDEX(INDIRECT("'"&H$4&"'!$1:$1048576"),MATCH($A77,INDIRECT("'"&H$4&"'!$A:$A"),0),MATCH($A$2,INDIRECT("'"&H$4&"'!$5:$5"),0)) -> 4586.37 | I77: =IFERROR(H77/H16, "NA") -> 0.26393731 | J77: =INDEX(INDIRECT("'"&J$4&"'!$1:$1048576"),MATCH($A77,INDIRECT("'"&J$4&"'!$A:$A"),0),MATCH($A$2,INDIRECT("'"&J$4&"'!$5:$5"),0)) -> 5697.06 | K77: =IFERROR(J77/J16, "NA") -> 0.25363712 | L77: =+J77+H77+F77+D77+B77 -> 28664.14 | M77: =IFERROR(L77/L16, "NA") -> 0.2472265
A78: 61105 - Salaries & Wages Adjustment | B78: =INDEX(INDIRECT("'"&B$4&"'!$1:$1048576"),MATCH($A78,INDIRECT("'"&B$4&"'!$A:$A"),0),MATCH($A$2,INDIRECT("'"&B$4&"'!$5:$5"),0)) -> 0 | C78: =IFERROR(B78/B16, "NA") -> 0 | D78: =INDEX(INDIRECT("'"&D$4&"'!$1:$1048576"),MATCH($A78,INDIRECT("'"&D$4&"'!$A:$A"),0),MATCH($A$2,INDIRECT("'"&D$4&"'!$5:$5"),0)) -> 0 | E78: =IFERROR(D78/D16, "NA") -> 0 | F78: =INDEX(INDIRECT("'"&F$4&"'!$1:$1048576"),MATCH($A78,INDIRECT("'"&F$4&"'!$A:$A"),0),MATCH($A$2,INDIRECT("'"&F$4&"'!$5:$5"),0)) -> 0 | G78: =IFERROR(F78/F16, "NA") -> 0 | H78: =INDEX(INDIRECT("'"&H$4&"'!$1:$1048576"),MATCH($A78,INDIRECT("'"&H$4&"'!$A:$A"),0),MATCH($A$2,INDIRECT("'"&H$4&"'!$5:$5"),0)) -> 0 | I78: =IFERROR(H78/H16, "NA") -> 0 | J78: =INDEX(INDIRECT("'"&J$4&"'!$1:$1048576"),MATCH($A78,INDIRECT("'"&J$4&"'!$A:$A"),0),MATCH($A$2,INDIRECT("'"&J$4&"'!$5:$5"),0)) -> 0 | K78: =IFERROR(J78/J16, "NA") -> 0 | M78: =IFERROR(L78/L16, "NA") -> 0
A79: 61250 - Bonus | B79: =INDEX(INDIRECT("'"&B$4&"'!$1:$1048576"),MATCH($A79,INDIRECT("'"&B$4&"'!$A:$A"),0),MATCH($A$2,INDIRECT("'"&B$4&"'!$5:$5"),0)) -> 300 | C79: =IFERROR(B79/B16, "NA") -> 0.014973953 | D79: =INDEX(INDIRECT("'"&D$4&"'!$1:$1048576"),MATCH($A79,INDIRECT("'"&D$4&"'!$A:$A"),0),MATCH($A$2,INDIRECT("'"&D$4&"'!$5:$5"),0)) -> 1150 | E79: =IFERROR(D79/D16, "NA") -> 0.028967685 | F79: =INDEX(INDIRECT("'"&F$4&"'!$1:$1048576"),MATCH($A79,INDIRECT("'"&F$4&"'!$A:$A"),0),MATCH($A$2,INDIRECT("'"&F$4&"'!$5:$5"),0)) -> 500 | G79: =IFERROR(F79/F16, "NA") -> 0.030542875 | H79: =INDEX(INDIRECT("'"&H$4&"'!$1:$1048576"),MATCH($A79,INDIRECT("'"&H$4&"'!$A:$A"),0),MATCH($A$2,INDIRECT("'"&H$4&"'!$5:$5"),0)) -> 500 | I79: =IFERROR(H79/H16, "NA") -> 0.028774097 | J79: =INDEX(INDIRECT("'"&J$4&"'!$1:$1048576"),MATCH($A79,INDIRECT("'"&J$4&"'!$A:$A"),0),MATCH($A$2,INDIRECT("'"&J$4&"'!$5:$5"),0)) -> 500 | K79: =IFERROR(J79/J16, "NA") -> 0.022260352 | L79: =+J79+H79+F79+D79+B79 -> 2950 | M79: =IFERROR(L79/L16, "NA") -> 0.025443574
A80: Payroll Taxes
A81: 61300 - Payroll Taxes | B81: =INDEX(INDIRECT("'"&B$4&"'!$1:$1048576"),MATCH($A81,INDIRECT("'"&B$4&"'!$A:$A"),0),MATCH($A$2,INDIRECT("'"&B$4&"'!$5:$5"),0)) -> 624.46 | C81: =IFERROR(B81/B16, "NA") -> 0.031168782 | D81: =INDEX(INDIRECT("'"&D$4&"'!$1:$1048576"),MATCH($A81,INDIRECT("'"&D$4&"'!$A:$A"),0),MATCH($A$2,INDIRECT("'"&D$4&"'!$5:$5"),0)) -> 1025.61 | E81: =IFERROR(D81/D16, "NA") -> 0.025834389 | F81: =INDEX(INDIRECT("'"&F$4&"'!$1:$1048576"),MATCH($A81,INDIRECT("'"&F$4&"'!$A:$A"),0),MATCH($A$2,INDIRECT("'"&F$4&"'!$5:$5"),0)) -> 430.65 | G81: =IFERROR(F81/F16, "NA") -> 0.026306578 | H81: =INDEX(INDIRECT("'"&H$4&"'!$1:$1048576"),MATCH($A81,INDIRECT("'"&H$4&"'!$A:$A"),0),MATCH($A$2,INDIRECT("'"&H$4&"'!$5:$5"),0)) -> 423.82 | I81: =IFERROR(H81/H16, "NA") -> 0.024390075 | J81: =INDEX(INDIRECT("'"&J$4&"'!$1:$1048576"),MATCH($A81,INDIRECT("'"&J$4&"'!$A:$A"),0),MATCH($A$2,INDIRECT("'"&J$4&"'!$5:$5"),0)) -> 568.43 | K81: =IFERROR(J81/J16, "NA") -> 0.025306903 | L81: =+J81+H81+F81+D81+B81 -> 3072.97 | M81: =IFERROR(L81/L16, "NA") -> 0.026504183
A82: 61310 - FICA Tax Expense | B82: =INDEX(INDIRECT("'"&B$4&"'!$1:$1048576"),MATCH($A82,INDIRECT("'"&B$4&"'!$A:$A"),0),MATCH($A$2,INDIRECT("'"&B$4&"'!$5:$5"),0)) -> 0 | C82: =IFERROR(B82/B16, "NA") -> 0 | D82: =INDEX(INDIRECT("'"&D$4&"'!$1:$1048576"),MATCH($A82,INDIRECT("'"&D$4&"'!$A:$A"),0),MATCH($A$2,INDIRECT("'"&D$4&"'!$5:$5"),0)) -> 0 | E82: =IFERROR(D82/D16, "NA") -> 0 | F82: =INDEX(INDIRECT("'"&F$4&"'!$1:$1048576"),MATCH($A82,INDIRECT("'"&F$4&"'!$A:$A"),0),MATCH($A$2,INDIRECT("'"&F$4&"'!$5:$5"),0)) -> 0 | G82: =IFERROR(F82/F16, "NA") -> 0 | H82: =INDEX(INDIRECT("'"&H$4&"'!$1:$1048576"),MATCH($A82,INDIRECT("'"&H$4&"'!$A:$A"),0),MATCH($A$2,INDIRECT("'"&H$4&"'!$5:$5"),0)) -> 0 | I82: =IFERROR(H82/H16, "NA") -> 0 | J82: =INDEX(INDIRECT("'"&J$4&"'!$1:$1048576"),MATCH($A82,INDIRECT("'"&J$4&"'!$A:$A"),0),MATCH($A$2,INDIRECT("'"&J$4&"'!$5:$5"),0)) -> 0 | K82: =IFERROR(J82/J16, "NA") -> 0 | L82: =+J82+H82+F82+D82+B82 -> 0 | M82: =IFERROR(L82/L16, "NA") -> 0
A83: 61330 - FUTA Tax Expense | B83: =INDEX(INDIRECT("'"&B$4&"'!$1:$1048576"),MATCH($A83,INDIRECT("'"&B$4&"'!$A:$A"),0),MATCH($A$2,INDIRECT("'"&B$4&"'!$5:$5"),0)) -> 0 | C83: =IFERROR(B83/B16, "NA") -> 0 | D83: =INDEX(INDIRECT("'"&D$4&"'!$1:$1048576"),MATCH($A83,INDIRECT("'"&D$4&"'!$A:$A"),0),MATCH($A$2,INDIRECT("'"&D$4&"'!$5:$5"),0)) -> 0 | E83: =IFERROR(D83/D16, "NA") -> 0 | F83: =INDEX(INDIRECT("'"&F$4&"'!$1:$1048576"),MATCH($A83,INDIRECT("'"&F$4&"'!$A:$A"),0),MATCH($A$2,INDIRECT("'"&F$4&"'!$5:$5"),0)) -> 0 | G83: =IFERROR(F83/F16, "NA") -> 0 | H83: =INDEX(INDIRECT("'"&H$4&"'!$1:$1048576"),MATCH($A83,INDIRECT("'"&H$4&"'!$A:$A"),0),MATCH($A$2,INDIRECT("'"&H$4&"'!$5:$5"),0)) -> 0 | I83: =IFERROR(H83/H16, "NA") -> 0 | J83: =INDEX(INDIRECT("'"&J$4&"'!$1:$1048576"),MATCH($A83,INDIRECT("'"&J$4&"'!$A:$A"),0),MATCH($A$2,INDIRECT("'"&J$4&"'!$5:$5"),0)) -> 0 | K83: =IFERROR(J83/J16, "NA") -> 0 | L83: =+J83+H83+F83+D83+B83 -> 0 | M83: =IFERROR(L83/L16, "NA") -> 0
A84: 61335 - SUTA Tax Expense (VA) | B84: =INDEX(INDIRECT("'"&B$4&"'!$1:$1048576"),MATCH($A84,INDIRECT("'"&B$4&"'!$A:$A"),0),MATCH($A$2,INDIRECT("'"&B$4&"'!$5:$5"),0)) -> 0 | C84: =IFERROR(B84/B16, "NA") -> 0 | D84: =INDEX(INDIRECT("'"&D$4&"'!$1:$1048576"),MATCH($A84,INDIRECT("'"&D$4&"'!$A:$A"),0),MATCH($A$2,INDIRECT("'"&D$4&"'!$5:$5"),0)) -> 0 | E84: =IFERROR(D84/D16, "NA") -> 0 | F84: =INDEX(INDIRECT("'"&F$4&"'!$1:$1048576"),MATCH($A84,INDIRECT("'"&F$4&"'!$A:$A"),0),MATCH($A$2,INDIRECT("'"&F$4&"'!$5:$5"),0)) -> 0 | G84: =IFERROR(F84/F16, "NA") -> 0 | H84: =INDEX(INDIRECT("'"&H$4&"'!$1:$1048576"),MATCH($A84,INDIRECT("'"&H$4&"'!$A:$A"),0),MATCH($A$2,INDIRECT("'"&H$4&"'!$5:$5"),0)) -> 0 | I84: =IFERROR(H84/H16, "NA") -> 0 | J84: =INDEX(INDIRECT("'"&J$4&"'!$1:$1048576"),MATCH($A84,INDIRECT("'"&J$4&"'!$A:$A"),0),MATCH($A$2,INDIRECT("'"&J$4&"'!$5:$5"),0)) -> 0 | K84: =IFERROR(J84/J16, "NA") -> 0 | L84: =+J84+H84+F84+D84+B84 -> 0 | M84: =IFERROR(L84/L16, "NA") -> 0
A85: 61340 - SUTA Tax Expense (DC) | B85: =INDEX(INDIRECT("'"&B$4&"'!$1:$1048576"),MATCH($A85,INDIRECT("'"&B$4&"'!$A:$A"),0),MATCH($A$2,INDIRECT("'"&B$4&"'!$5:$5"),0)) -> 0 | C85: =IFERROR(B85/B16, "NA") -> 0 | D85: =INDEX(INDIRECT("'"&D$4&"'!$1:$1048576"),MATCH($A85,INDIRECT("'"&D$4&"'!$A:$A"),0),MATCH($A$2,INDIRECT("'"&D$4&"'!$5:$5"),0)) -> 0 | E85: =IFERROR(D85/D16, "NA") -> 0 | F85: =INDEX(INDIRECT("'"&F$4&"'!$1:$1048576"),MATCH($A85,INDIRECT("'"&F$4&"'!$A:$A"),0),MATCH($A$2,INDIRECT("'"&F$4&"'!$5:$5"),0)) -> 0 | G85: =IFERROR(F85/F16, "NA") -> 0 | H85: =INDEX(INDIRECT("'"&H$4&"'!$1:$1048576"),MATCH($A85,INDIRECT("'"&H$4&"'!$A:$A"),0),MATCH($A$2,INDIRECT("'"&H$4&"'!$5:$5"),0)) -> 0 | I85: =IFERROR(H85/H16, "NA") -> 0 | J85: =INDEX(INDIRECT("'"&J$4&"'!$1:$1048576"),MATCH($A85,INDIRECT("'"&J$4&"'!$A:$A"),0),MATCH($A$2,INDIRECT("'"&J$4&"'!$5:$5"),0)) -> 0 | K85: =IFERROR(J85/J16, "NA") -> 0 | L85: =+J85+H85+F85+D85+B85 -> 0 | M85: =IFERROR(L85/L16, "NA") -> 0
A86: 61360 - FL Tax Expense (DC) | B86: =INDEX(INDIRECT("'"&B$4&"'!$1:$1048576"),MATCH($A86,INDIRECT("'"&B$4&"'!$A:$A"),0),MATCH($A$2,INDIRECT("'"&B$4&"'!$5:$5"),0)) -> 0 | C86: =IFERROR(B86/B16, "NA") -> 0 | D86: =INDEX(INDIRECT("'"&D$4&"'!$1:$1048576"),MATCH($A86,INDIRECT("'"&D$4&"'!$A:$A"),0),MATCH($A$2,INDIRECT("'"&D$4&"'!$5:$5"),0)) -> 0 | E86: =IFERROR(D86/D16, "NA") -> 0 | F86: =INDEX(INDIRECT("'"&F$4&"'!$1:$1048576"),MATCH($A86,INDIRECT("'"&F$4&"'!$A:$A"),0),MATCH($A$2,INDIRECT("'"&F$4&"'!$5:$5"),0)) -> 0 | G86: =IFERROR(F86/F16, "NA") -> 0 | H86: =INDEX(INDIRECT("'"&H$4&"'!$1:$1048576"),MATCH($A86,INDIRECT("'"&H$4&"'!$A:$A"),0),MATCH($A$2,INDIRECT("'"&H$4&"'!$5:$5"),0)) -> 0 | I86: =IFERROR(H86/H16, "NA") -> 0 | J86: =INDEX(INDIRECT("'"&J$4&"'!$1:$1048576"),MATCH($A86,INDIRECT("'"&J$4&"'!$A:$A"),0),MATCH($A$2,INDIRECT("'"&J$4&"'!$5:$5"),0)) -> 0 | K86: =IFERROR(J86/J16, "NA") -> 0 | L86: =+J86+H86+F86+D86+B86 -> 0 | M86: =IFERROR(L86/L16, "NA") -> 0
A87: 61395 - Other Payroll Taxes | B87: =INDEX(INDIRECT("'"&B$4&"'!$1:$1048576"),MATCH($A87,INDIRECT("'"&B$4&"'!$A:$A"),0),MATCH($A$2,INDIRECT("'"&B$4&"'!$5:$5"),0)) -> 0 | C87: =IFERROR(B87/B16, "NA") -> 0 | D87: =INDEX(INDIRECT("'"&D$4&"'!$1:$1048576"),MATCH($A87,INDIRECT("'"&D$4&"'!$A:$A"),0),MATCH($A$2,INDIRECT("'"&D$4&"'!$5:$5"),0)) -> 0 | E87: =IFERROR(D87/D16, "NA") -> 0 | F87: =INDEX(INDIRECT("'"&F$4&"'!$1:$1048576"),MATCH($A87,INDIRECT("'"&F$4&"'!$A:$A"),0),MATCH($A$2,INDIRECT("'"&F$4&"'!$5:$5"),0)) -> 0 | G87: =IFERROR(F87/F16, "NA") -> 0 | H87: =INDEX(INDIRECT("'"&H$4&"'!$1:$1048576"),MATCH($A87,INDIRECT("'"&H$4&"'!$A:$A"),0),MATCH($A$2,INDIRECT("'"&H$4&"'!$5:$5"),0)) -> 0 | I87: =IFERROR(H87/H16, "NA") -> 0 | J87: =INDEX(INDIRECT("'"&J$4&"'!$1:$1048576"),MATCH($A87,INDIRECT("'"&J$4&"'!$A:$A"),0),MATCH($A$2,INDIRECT("'"&J$4&"'!$5:$5"),0)) -> 0 | K87: =IFERROR(J87/J16, "NA") -> 0 | L87: =+J87+H87+F87+D87+B87 -> 0 | M87: =IFERROR(L87/L16, "NA") -> 0
A88: Total Payroll Taxes | B88: =INDEX(INDIRECT("'"&B$4&"'!$1:$1048576"),MATCH($A88,INDIRECT("'"&B$4&"'!$A:$A"),0),MATCH($A$2,INDIRECT("'"&B$4&"'!$5:$5"),0)) -> 624.46 | C88: =IFERROR(B88/B16, "NA") -> 0.031168782 | D88: =INDEX(INDIRECT("'"&D$4&"'!$1:$1048576"),MATCH($A88,INDIRECT("'"&D$4&"'!$A:$A"),0),MATCH($A$2,INDIRECT("'"&D$4&"'!$5:$5"),0)) -> 1025.61 | E88: =IFERROR(D88/D16, "NA") -> 0.025834389 | F88: =INDEX(INDIRECT("'"&F$4&"'!$1:$1048576"),MATCH($A88,INDIRECT("'"&F$4&"'!$A:$A"),0),MATCH($A$2,INDIRECT("'"&F$4&"'!$5:$5"),0)) -> 430.65 | G88: =IFERROR(F88/F16, "NA") -> 0.026306578 | H88: =INDEX(INDIRECT("'"&H$4&"'!$1:$1048576"),MATCH($A88,INDIRECT("'"&H$4&"'!$A:$A"),0),MATCH($A$2,INDIRECT("'"&H$4&"'!$5:$5"),0)) -> 423.82 | I88: =IFERROR(H88/H16, "NA") -> 0.024390075 | J88: =INDEX(INDIRECT("'"&J$4&"'!$1:$1048576"),MATCH($A88,INDIRECT("'"&J$4&"'!$A:$A"),0),MATCH($A$2,INDIRECT("'"&J$4&"'!$5:$5"),0)) -> 568.43 | K88: =IFERROR(J88/J16, "NA") -> 0.025306903 | L88: =+J88+H88+F88+D88+B88 -> 3072.97 | M88: =IFERROR(L88/L16, "NA") -> 0.026504183
A89: 61400 - Payroll Processing Fee | B89: =INDEX(INDIRECT("'"&B$4&"'!$1:$1048576"),MATCH($A89,INDIRECT("'"&B$4&"'!$A:$A"),0),MATCH($A$2,INDIRECT("'"&B$4&"'!$5:$5"),0)) -> 0 | C89: =IFERROR(B89/B16, "NA") -> 0 | D89: =INDEX(INDIRECT("'"&D$4&"'!$1:$1048576"),MATCH($A89,INDIRECT("'"&D$4&"'!$A:$A"),0),MATCH($A$2,INDIRECT("'"&D$4&"'!$5:$5"),0)) -> 0 | E89: =IFERROR(D89/D16, "NA") -> 0 | F89: =INDEX(INDIRECT("'"&F$4&"'!$1:$1048576"),MATCH($A89,INDIRECT("'"&F$4&"'!$A:$A"),0),MATCH($A$2,INDIRECT("'"&F$4&"'!$5:$5"),0)) -> 0 | G89: =IFERROR(F89/F16, "NA") -> 0 | H89: =INDEX(INDIRECT("'"&H$4&"'!$1:$1048576"),MATCH($A89,INDIRECT("'"&H$4&"'!$A:$A"),0),MATCH($A$2,INDIRECT("'"&H$4&"'!$5:$5"),0)) -> 0 | I89: =IFERROR(H89/H16, "NA") -> 0 | J89: =INDEX(INDIRECT("'"&J$4&"'!$1:$1048576"),MATCH($A89,INDIRECT("'"&J$4&"'!$A:$A"),0),MATCH($A$2,INDIRECT("'"&J$4&"'!$5:$5"),0)) -> 0 | K89: =IFERROR(J89/J16, "NA") -> 0 | L89: =+J89+H89+F89+D89+B89 -> 0 | M89: =IFERROR(L89/L16, "NA") -> 0
A90: 61500 - Health Insurance | B90: =INDEX(INDIRECT("'"&B$4&"'!$1:$1048576"),MATCH($A90,INDIRECT("'"&B$4&"'!$A:$A"),0),MATCH($A$2,INDIRECT("'"&B$4&"'!$5:$5"),0)) -> -10.72 | C90: =IFERROR(B90/B16, "NA") -> -0.00053506925 | D90: =INDEX(INDIRECT("'"&D$4&"'!$1:$1048576"),MATCH($A90,INDIRECT("'"&D$4&"'!$A:$A"),0),MATCH($A$2,INDIRECT("'"&D$4&"'!$5:$5"),0)) -> -61.25 | E90: =IFERROR(D90/D16, "NA") -> -0.0015428441 | F90: =INDEX(INDIRECT("'"&F$4&"'!$1:$1048576"),MATCH($A90,INDIRECT("'"&F$4&"'!$A:$A"),0),MATCH($A$2,INDIRECT("'"&F$4&"'!$5:$5"),0)) -> 0 | G90: =IFERROR(F90/F16, "NA") -> 0 | H90: =INDEX(INDIRECT("'"&H$4&"'!$1:$1048576"),MATCH($A90,INDIRECT("'"&H$4&"'!$A:$A"),0),MATCH($A$2,INDIRECT("'"&H$4&"'!$5:$5"),0)) -> -236.49 | I90: =IFERROR(H90/H16, "NA") -> -0.013609572 | J90: =INDEX(INDIRECT("'"&J$4&"'!$1:$1048576"),MATCH($A90,INDIRECT("'"&J$4&"'!$A:$A"),0),MATCH($A$2,INDIRECT("'"&J$4&"'!$5:$5"),0)) -> 0 | K90: =IFERROR(J90/J16, "NA") -> 0 | L90: =+J90+H90+F90+D90+B90 -> -308.46 | M90: =IFERROR(L90/L16, "NA") -> -0.0026604491
A91: Total Payroll Expenses | B91: =INDEX(INDIRECT("'"&B$4&"'!$1:$1048576"),MATCH($A91,INDIRECT("'"&B$4&"'!$A:$A"),0),MATCH($A$2,INDIRECT("'"&B$4&"'!$5:$5"),0)) -> 6159.29 | C91: =IFERROR(B91/B16, "NA") -> 0.30742973 | D91: =INDEX(INDIRECT("'"&D$4&"'!$1:$1048576"),MATCH($A91,INDIRECT("'"&D$4&"'!$A:$A"),0),MATCH($A$2,INDIRECT("'"&D$4&"'!$5:$5"),0)) -> 10695.55 | E91: =IFERROR(D91/D16, "NA") -> 0.26941332 | F91: =INDEX(INDIRECT("'"&F$4&"'!$1:$1048576"),MATCH($A91,INDIRECT("'"&F$4&"'!$A:$A"),0),MATCH($A$2,INDIRECT("'"&F$4&"'!$5:$5"),0)) -> 5484.62 | G91: =IFERROR(F91/F16, "NA") -> 0.33503213 | H91: =INDEX(INDIRECT("'"&H$4&"'!$1:$1048576"),MATCH($A91,INDIRECT("'"&H$4&"'!$A:$A"),0),MATCH($A$2,INDIRECT("'"&H$4&"'!$5:$5"),0)) -> 5273.7 | I91: =IFERROR(H91/H16, "NA") -> 0.30349191 | J91: =INDEX(INDIRECT("'"&J$4&"'!$1:$1048576"),MATCH($A91,INDIRECT("'"&J$4&"'!$A:$A"),0),MATCH($A$2,INDIRECT("'"&J$4&"'!$5:$5"),0)) -> 6765.49 | K91: =IFERROR(J91/J16, "NA") -> 0.30120437 | L91: =+J91+H91+F91+D91+B91 -> 34378.65 | M91: =IFERROR(L91/L16, "NA") -> 0.29651381
A92: Total Payroll Expenses | B92: =INDEX(INDIRECT("'"&B$4&"'!$1:$1048576"),MATCH($A92,INDIRECT("'"&B$4&"'!$A:$A"),0),MATCH($A$2,INDIRECT("'"&B$4&"'!$5:$5"),0)) -> 6159.29 | C92: =IFERROR(B92/B16, "NA") -> 0.30742973 | D92: =INDEX(INDIRECT("'"&D$4&"'!$1:$1048576"),MATCH($A92,INDIRECT("'"&D$4&"'!$A:$A"),0),MATCH($A$2,INDIRECT("'"&D$4&"'!$5:$5"),0)) -> 10695.55 | E92: =IFERROR(D92/D16, "NA") -> 0.26941332 | F92: =INDEX(INDIRECT("'"&F$4&"'!$1:$1048576"),MATCH($A92,INDIRECT("'"&F$4&"'!$A:$A"),0),MATCH($A$2,INDIRECT("'"&F$4&"'!$5:$5"),0)) -> 5484.62 | G92: =IFERROR(F92/F16, "NA") -> 0.33503213 | H92: =INDEX(INDIRECT("'"&H$4&"'!$1:$1048576"),MATCH($A92,INDIRECT("'"&H$4&"'!$A:$A"),0),MATCH($A$2,INDIRECT("'"&H$4&"'!$5:$5"),0)) -> 5273.7 | I92: =IFERROR(H92/H16, "NA") -> 0.30349191 | J92: =INDEX(INDIRECT("'"&J$4&"'!$1:$1048576"),MATCH($A92,INDIRECT("'"&J$4&"'!$A:$A"),0),MATCH($A$2,INDIRECT("'"&J$4&"'!$5:$5"),0)) -> 6765.49 | K92: =IFERROR(J92/J16, "NA") -> 0.30120437 | L92: =+J92+H92+F92+D92+B92 -> 34378.65 | M92: =IFERROR(L92/L16, "NA") -> 0.29651381
A94: Prime Profit | B94: {=INDEX(INDIRECT("'"&B$4&"'!$1:$1048576"),MATCH($A94,INDIRECT("'"&B$4&"'!$A:$A"),0),MATCH($A$2,INDIRECT("'"&B$4&"'!$5:$5"),0))} -> 8348.58 | C94: =IFERROR(B94/B16, "NA") -> 0.41670414 | D94: {=INDEX(INDIRECT("'"&D$4&"'!$1:$1048576"),MATCH($A94,INDIRECT("'"&D$4&"'!$A:$A"),0),MATCH($A$2,INDIRECT("'"&D$4&"'!$5:$5"),0))} -> 19228.83 | E94: =IFERROR(D94/D16, "NA") -> 0.4843606 | F94: {=INDEX(INDIRECT("'"&F$4&"'!$1:$1048576"),MATCH($A94,INDIRECT("'"&F$4&"'!$A:$A"),0),MATCH($A$2,INDIRECT("'"&F$4&"'!$5:$5"),0))} -> 6731.05 | G94: =IFERROR(F94/F16, "NA") -> 0.41117124 | H94: {=INDEX(INDIRECT("'"&H$4&"'!$1:$1048576"),MATCH($A94,INDIRECT("'"&H$4&"'!$A:$A"),0),MATCH($A$2,INDIRECT("'"&H$4&"'!$5:$5"),0))} -> 7245.65 | I94: =IFERROR(H94/H16, "NA") -> 0.41697407 | J94: {=INDEX(INDIRECT("'"&J$4&"'!$1:$1048576"),MATCH($A94,INDIRECT("'"&J$4&"'!$A:$A"),0),MATCH($A$2,INDIRECT("'"&J$4&"'!$5:$5"),0))} -> 8680.92 | K94: =IFERROR(J94/J16, "NA") -> 0.38648067 | L94: =+J94+H94+F94+D94+B94 -> 50235.03 | M94: =IFERROR(L94/L16, "NA") -> 0.43327414

Sheet Consolidated
A1: Prime Margin - Trailing 12 Week
A2: 01/25/2026
A3: Consolidated
B5: Week Ending 11/09/2025 | D5: Week Ending 11/16/2025 | F5: Week Ending 11/23/2025 | H5: Week Ending 11/30/2025 | J5: Week Ending 12/07/2025 | L5: Week Ending 12/14/2025 | N5: Week Ending 12/21/2025 | P5: Week Ending 12/28/2025 | R5: Week Ending 01/04/2026 | T5: Week Ending 01/11/2026 | V5: Week Ending 01/18/2026 | X5: Week Ending 01/25/2026 | Z5: Period to Date | AB5: Trailing 4 Week | AD5: $ vs. 4 Week | AF5: % vs. 4 Week | AG5: Trailing 8 Week | AI5: $ vs. 8 Week | AK5: % vs. 8 Week
A6: Sales
A7: Sales | B7: 203694.32 | C7: =IFERROR(B7/B148, "NA") -> 1 | D7: 185604.19 | E7: =IFERROR(D7/D148, "NA") -> 1 | F7: 141258.89 | G7: =IFERROR(F7/F148, "NA") -> 1 | H7: 74664.32 | I7: =IFERROR(H7/H148, "NA") -> 1 | J7: 142398.2 | K7: =IFERROR(J7/J148, "NA") -> 1 | L7: 135140.37 | M7: =IFERROR(L7/L148, "NA") -> 1 | N7: 121597.41 | O7: =IFERROR(N7/N148, "NA") -> 1 | P7: 56612.63 | Q7: =IFERROR(P7/P148, "NA") -> 1 | R7: 69486.64 | S7: =IFERROR(R7/R148, "NA") -> 1 | T7: 110506.18 | U7: =IFERROR(T7/T148, "NA") -> 1 | V7: 135051.74 | W7: =IFERROR(V7/V148, "NA") -> 1 | X7: 115942.83 | Y7: =IFERROR(X7/X148, "NA") -> 1 | Z7: 430987.39 | AA7: =IFERROR(Z7/Z148, "NA") -> 1 | AB7: =IFERROR((R7+T7+V7+X7)/4, "NA") -> 107746.85 | AC7: =IFERROR(AB7/AB148, "NA") -> 1 | AD7: =IFERROR(X7-AB7, "NA") -> 8195.9825 | AE7: =IFERROR(AD7/AD148, "NA") -> 1 | AF7: =IFERROR((X7-AB7)/AB7, "NA") -> 0.076067028 | AG7: =IFERROR((J7+L7+N7+P7+R7+T7+V7+X7)/8, "NA") -> 110842 | AH7: =IFERROR(AG7/AG148, "NA") -> 1 | AI7: =IFERROR(X7-AG7, "NA") -> 5100.83 | AJ7: =IFERROR(AI7/AI148, "NA") -> 1 | AK7: =IFERROR((X7-AG7)/AG7, "NA") -> 0.046018928 | AL7: =IFERROR(AK7/AK148, "NA") -> 1
A8: 49600 - Toast Order Processing Fee Pass-Through | B8: 0 | C8: =IFERROR(B8/B148, "NA") -> 0 | D8: 0 | E8: =IFERROR(D8/D148, "NA") -> 0 | F8: 0 | G8: =IFERROR(F8/F148, "NA") -> 0 | H8: 0 | I8: =IFERROR(H8/H148, "NA") -> 0 | J8: 0 | K8: =IFERROR(J8/J148, "NA") -> 0 | L8: 0 | M8: =IFERROR(L8/L148, "NA") -> 0 | N8: 0 | O8: =IFERROR(N8/N148, "NA") -> 0 | P8: 0 | Q8: =IFERROR(P8/P148, "NA") -> 0 | R8: 0 | S8: =IFERROR(R8/R148, "NA") -> 0 | T8: 0 | U8: =IFERROR(T8/T148, "NA") -> 0 | V8: 0 | W8: =IFERROR(V8/V148, "NA") -> 0 | X8: 0 | Y8: =IFERROR(X8/X148, "NA") -> 0 | Z8: 0 | AA8: =IFERROR(Z8/Z148, "NA") -> 0 | AB8: =IFERROR((R8+T8+V8+X8)/4, "NA") -> 0 | AC8: =IFERROR(AB8/AB148, "NA") -> 0 | AD8: =IFERROR(X8-AB8, "NA") -> 0 | AE8: =IFERROR(AD8/AD148, "NA") -> 0 | AF8: =IFERROR((X8-AB8)/AB8, "NA") -> NA | AG8: =IFERROR((J8+L8+N8+P8+R8+T8+V8+X8)/8, "NA") -> 0 | AH8: =IFERROR(AG8/AG148, "NA") -> 0 | AI8: =IFERROR(X8-AG8, "NA") -> 0 | AJ8: =IFERROR(AI8/AI148, "NA") -> 0 | AK8: =IFERROR((X8-AG8)/AG8, "NA") -> NA | AL8: =IFERROR(AK8/AK148, "NA") -> NA
A9: Total Sales | B9: =IFERROR(B7+B8, "NA") -> 203694.32 | C9: =IFERROR(B9/B148, "NA") -> 1 | D9: =IFERROR(D7+D8, "NA") -> 185604.19 | E9: =IFERROR(D9/D148, "NA") -> 1 | F9: =IFERROR(F7+F8, "NA") -> 141258.89 | G9: =IFERROR(F9/F148, "NA") -> 1 | H9: =IFERROR(H7+H8, "NA") -> 74664.32 | I9: =IFERROR(H9/H148, "NA") -> 1 | J9: =IFERROR(J7+J8, "NA") -> 142398.2 | K9: =IFERROR(J9/J148, "NA") -> 1 | L9: =IFERROR(L7+L8, "NA") -> 135140.37 | M9: =IFERROR(L9/L148, "NA") -> 1 | N9: =IFERROR(N7+N8, "NA") -> 121597.41 | O9: =IFERROR(N9/N148, "NA") -> 1 | P9: =IFERROR(P7+P8, "NA") -> 56612.63 | Q9: =IFERROR(P9/P148, "NA") -> 1 | R9: =IFERROR(R7+R8, "NA") -> 69486.64 | S9: =IFERROR(R9/R148, "NA") -> 1 | T9: =IFERROR(T7+T8, "NA") -> 110506.18 | U9: =IFERROR(T9/T148, "NA") -> 1 | V9: =IFERROR(V7+V8, "NA") -> 135051.74 | W9: =IFERROR(V9/V148, "NA") -> 1 | X9: =IFERROR(X7+X8, "NA") -> 115942.83 | Y9: =IFERROR(X9/X148, "NA") -> 1 | Z9: =IFERROR(Z7+Z8, "NA") -> 430987.39 | AA9: =IFERROR(Z9/Z148, "NA") -> 1 | AB9: =IFERROR((R9+T9+V9+X9)/4, "NA") -> 107746.85 | AC9: =IFERROR(AB9/AB148, "NA") -> 1 | AD9: =IFERROR(X9-AB9, "NA") -> 8195.9825 | AE9: =IFERROR(AD9/AD148, "NA") -> 1 | AF9: =IFERROR((X9-AB9)/AB9, "NA") -> 0.076067028 | AG9: =IFERROR((J9+L9+N9+P9+R9+T9+V9+X9)/8, "NA") -> 110842 | AH9: =IFERROR(AG9/AG148, "NA") -> 1 | AI9: =IFERROR(X9-AG9, "NA") -> 5100.83 | AJ9: =IFERROR(AI9/AI148, "NA") -> 1 | AK9: =IFERROR((X9-AG9)/AG9, "NA") -> 0.046018928 | AL9: =IFERROR(AK9/AK148, "NA") -> 1
A11: Cost of Goods Sold
A12: Food & Beverage Costs
A13: 50000 - Food & Beverage Costs | B13: 0 | C13: =IFERROR(B13/B148, "NA") -> 0 | D13: 0 | E13: =IFERROR(D13/D148, "NA") -> 0 | F13: 0 | G13: =IFERROR(F13/F148, "NA") -> 0 | H13: 0 | I13: =IFERROR(H13/H148, "NA") -> 0 | J13: 0 | K13: =IFERROR(J13/J148, "NA") -> 0 | L13: 0 | M13: =IFERROR(L13/L148, "NA") -> 0 | N13: 0 | O13: =IFERROR(N13/N148, "NA") -> 0 | P13: 0 | Q13: =IFERROR(P13/P148, "NA") -> 0 | R13: 0 | S13: =IFERROR(R13/R148, "NA") -> 0 | T13: 0 | U13: =IFERROR(T13/T148, "NA") -> 0 | V13: 0 | W13: =IFERROR(V13/V148, "NA") -> 0 | X13: 0 | Y13: =IFERROR(X13/X148, "NA") -> 0 | Z13: 0 | AA13: =IFERROR(Z13/Z148, "NA") -> 0 | AB13: =IFERROR((R13+T13+V13+X13)/4, "NA") -> 0 | AC13: =IFERROR(AB13/AB148, "NA") -> 0 | AD13: =IFERROR(X13-AB13, "NA") -> 0 | AE13: =IFERROR(AD13/AD148, "NA") -> 0 | AF13: =IFERROR((X13-AB13)/AB13, "NA") -> NA | AG13: =IFERROR((J13+L13+N13+P13+R13+T13+V13+X13)/8, "NA") -> 0 | AH13: =IFERROR(AG13/AG148, "NA") -> 0 | AI13: =IFERROR(X13-AG13, "NA") -> 0 | AJ13: =IFERROR(AI13/AI148, "NA") -> 0 | AK13: =IFERROR((X13-AG13)/AG13, "NA") -> NA | AL13: =IFERROR(AK13/AK148, "NA") -> NA
A14: Food Costs
A15: 50100 - Food Costs | B15: 0 | C15: =IFERROR(B15/B148, "NA") -> 0 | D15: 0 | E15: =IFERROR(D15/D148, "NA") -> 0 | F15: 0 | G15: =IFERROR(F15/F148, "NA") -> 0 | H15: 0 | I15: =IFERROR(H15/H148, "NA") -> 0 | J15: 0 | K15: =IFERROR(J15/J148, "NA") -> 0 | L15: 0 | M15: =IFERROR(L15/L148, "NA") -> 0 | N15: 0 | O15: =IFERROR(N15/N148, "NA") -> 0 | P15: 0 | Q15: =IFERROR(P15/P148, "NA") -> 0 | R15: 0 | S15: =IFERROR(R15/R148, "NA") -> 0 | T15: 0 | U15: =IFERROR(T15/T148, "NA") -> 0 | V15: 0 | W15: =IFERROR(V15/V148, "NA") -> 0 | X15: 0 | Y15: =IFERROR(X15/X148, "NA") -> 0 | Z15: 0 | AA15: =IFERROR(Z15/Z148, "NA") -> 0 | AB15: =IFERROR((R15+T15+V15+X15)/4, "NA") -> 0 | AC15: =IFERROR(AB15/AB148, "NA") -> 0 | AD15: =IFERROR(X15-AB15, "NA") -> 0 | AE15: =IFERROR(AD15/AD148, "NA") -> 0 | AF15: =IFERROR((X15-AB15)/AB15, "NA") -> NA | AG15: =IFERROR((J15+L15+N15+P15+R15+T15+V15+X15)/8, "NA") -> 0 | AH15: =IFERROR(AG15/AG148, "NA") -> 0 | AI15: =IFERROR(X15-AG15, "NA") -> 0 | AJ15: =IFERROR(AI15/AI148, "NA") -> 0 | AK15: =IFERROR((X15-AG15)/AG15, "NA") -> NA | AL15: =IFERROR(AK15/AK148, "NA") -> NA
A16: 50110 - COGS - Produce | B16: 8746.78 | C16: =IFERROR(B16/B148, "NA") -> 0.042940716 | D16: 9248.4 | E16: =IFERROR(D16/D148, "NA") -> 0.049828616 | F16: 7029.09 | G16: =IFERROR(F16/F148, "NA") -> 0.049760337 | H16: 3865.17 | I16: =IFERROR(H16/H148, "NA") -> 0.051767297 | J16: 7809.73 | K16: =IFERROR(J16/J148, "NA") -> 0.054844303 | L16: 7124.1 | M16: =IFERROR(L16/L148, "NA") -> 0.052716298 | N16: 6096.73 | O16: =IFERROR(N16/N148, "NA") -> 0.05013865 | P16: 2764.73 | Q16: =IFERROR(P16/P148, "NA") -> 0.048835922 | R16: 3856.81 | S16: =IFERROR(R16/R148, "NA") -> 0.055504339 | T16: 6091.47 | U16: =IFERROR(T16/T148, "NA") -> 0.055123342 | V16: 5827.11 | W16: =IFERROR(V16/V148, "NA") -> 0.043147241 | X16: 5706.65 | Y16: =IFERROR(X16/X148, "NA") -> 0.049219516 | Z16: 21482.04 | AA16: =IFERROR(Z16/Z148, "NA") -> 0.049843778 | AB16: =IFERROR((R16+T16+V16+X16)/4, "NA") -> 5370.51 | AC16: =IFERROR(AB16/AB148, "NA") -> 0.049843778 | AD16: =IFERROR(X16-AB16, "NA") -> 336.14 | AE16: =IFERROR(AD16/AD148, "NA") -> 0.041012777 | AF16: =IFERROR((X16-AB16)/AB16, "NA") -> 0.062589959 | AG16: =IFERROR((J16+L16+N16+P16+R16+T16+V16+X16)/8, "NA") -> 5659.6663 | AH16: =IFERROR(AG16/AG148, "NA") -> 0.051060665 | AI16: =IFERROR(X16-AG16, "NA") -> 46.98375 | AJ16: =IFERROR(AI16/AI148, "NA") -> 0.009211001 | AK16: =IFERROR((X16-AG16)/AG16, "NA") -> 0.0083015054 | AL16: =IFERROR(AK16/AK148, "NA") -> 0.18039328
A17: 50120 - COGS - Grocery Dry & Canned | B17: 5260 | C17: =IFERROR(B17/B148, "NA") -> 0.025823008 | D17: 4969.77 | E17: =IFERROR(D17/D148, "NA") -> 0.026776174 | F17: 2276.43 | G17: =IFERROR(F17/F148, "NA") -> 0.016115304 | H17: 3133.64 | I17: =IFERROR(H17/H148, "NA") -> 0.041969712 | J17: 3897.98 | K17: =IFERROR(J17/J148, "NA") -> 0.027373801 | L17: 3504.4 | M17: =IFERROR(L17/L148, "NA") -> 0.025931555 | N17: 3716.12 | O17: =IFERROR(N17/N148, "NA") -> 0.030560848 | P17: 1701.2 | Q17: =IFERROR(P17/P148, "NA") -> 0.030049832 | R17: 2170.02 | S17: =IFERROR(R17/R148, "NA") -> 0.031229313 | T17: 3608.22 | U17: =IFERROR(T17/T148, "NA") -> 0.032651749 | V17: 3971.59 | W17: =IFERROR(V17/V148, "NA") -> 0.029407914 | X17: 3334.05 | Y17: =IFERROR(X17/X148, "NA") -> 0.028755983 | Z17: 13083.88 | AA17: =IFERROR(Z17/Z148, "NA") -> 0.030357918 | AB17: =IFERROR((R17+T17+V17+X17)/4, "NA") -> 3270.97 | AC17: =IFERROR(AB17/AB148, "NA") -> 0.030357918 | AD17: =IFERROR(X17-AB17, "NA") -> 63.08 | AE17: =IFERROR(AD17/AD148, "NA") -> 0.0076964537 | AF17: =IFERROR((X17-AB17)/AB17, "NA") -> 0.019284799 | AG17: =IFERROR((J17+L17+N17+P17+R17+T17+V17+X17)/8, "NA") -> 3237.9475 | AH17: =IFERROR(AG17/AG148, "NA") -> 0.02921228 | AI17: =IFERROR(X17-AG17, "NA") -> 96.1025 | AJ17: =IFERROR(AI17/AI148, "NA") -> 0.018840561 | AK17: =IFERROR((X17-AG17)/AG17, "NA") -> 0.029680067 | AL17: =IFERROR(AK17/AK148, "NA") -> 0.64495347
A18: 50130 - COGS - Poultry | B18: 6799.85 | C18: =IFERROR(B18/B148, "NA") -> 0.03338262 | D18: 5423.64 | E18: =IFERROR(D18/D148, "NA") -> 0.029221539 | F18: 3961.02 | G18: =IFERROR(F18/F148, "NA") -> 0.028040855 | H18: 1889.36 | I18: =IFERROR(H18/H148, "NA") -> 0.025304724 | J18: 4291.23 | K18: =IFERROR(J18/J148, "NA") -> 0.030135423 | L18: 3689.51 | M18: =IFERROR(L18/L148, "NA") -> 0.027301316 | N18: 3337.95 | O18: =IFERROR(N18/N148, "NA") -> 0.027450831 | P18: 1547.04 | Q18: =IFERROR(P18/P148, "NA") -> 0.027326764 | R18: 2060.87 | S18: =IFERROR(R18/R148, "NA") -> 0.029658507 | T18: 3255.41 | U18: =IFERROR(T18/T148, "NA") -> 0.029459076 | V18: 4374.13 | W18: =IFERROR(V18/V148, "NA") -> 0.03238855 | X18: 3243.26 | Y18: =IFERROR(X18/X148, "NA") -> 0.027972924 | Z18: 12933.67 | AA18: =IFERROR(Z18/Z148, "NA") -> 0.030009393 | AB18: =IFERROR((R18+T18+V18+X18)/4, "NA") -> 3233.4175 | AC18: =IFERROR(AB18/AB148, "NA") -> 0.030009393 | AD18: =IFERROR(X18-AB18, "NA") -> 9.8425 | AE18: =IFERROR(AD18/AD148, "NA") -> 0.0012008932 | AF18: =IFERROR((X18-AB18)/AB18, "NA") -> 0.0030439929 | AG18: =IFERROR((J18+L18+N18+P18+R18+T18+V18+X18)/8, "NA") -> 3224.925 | AH18: =IFERROR(AG18/AG148, "NA") -> 0.029094793 | AI18: =IFERROR(X18-AG18, "NA") -> 18.335 | AJ18: =IFERROR(AI18/AI148, "NA") -> 0.003594513 | AK18: =IFERROR((X18-AG18)/AG18, "NA") -> 0.0056854035 | AL18: =IFERROR(AK18/AK148, "NA") -> 0.12354489
A19: 50140 - COGS - Dairy | B19: 3772.39 | C19: =IFERROR(B19/B148, "NA") -> 0.018519859 | D19: 3067.71 | E19: =IFERROR(D19/D148, "NA") -> 0.016528237 | F19: 2734.9 | G19: =IFERROR(F19/F148, "NA") -> 0.019360905 | H19: 2794.02 | I19: =IFERROR(H19/H148, "NA") -> 0.037421087 | J19: 3139.48 | K19: =IFERROR(J19/J148, "NA") -> 0.022047189 | L19: 3497.43 | M19: =IFERROR(L19/L148, "NA") -> 0.025879979 | N19: 2933.33 | O19: =IFERROR(N19/N148, "NA") -> 0.024123293 | P19: 1267.09 | Q19: =IFERROR(P19/P148, "NA") -> 0.022381755 | R19: 1996.08 | S19: =IFERROR(R19/R148, "NA") -> 0.028726098 | T19: 2401.35 | U19: =IFERROR(T19/T148, "NA") -> 0.021730459 | V19: 3371.43 | W19: =IFERROR(V19/V148, "NA") -> 0.024963988 | X19: 2408.37 | Y19: =IFERROR(X19/X148, "NA") -> 0.020772048 | Z19: 10177.23 | AA19: =IFERROR(Z19/Z148, "NA") -> 0.023613754 | AB19: =IFERROR((R19+T19+V19+X19)/4, "NA") -> 2544.3075 | AC19: =IFERROR(AB19/AB148, "NA") -> 0.023613754 | AD19: =IFERROR(X19-AB19, "NA") -> -135.9375 | AE19: =IFERROR(AD19/AD148, "NA") -> -0.01658587 | AF19: =IFERROR((X19-AB19)/AB19, "NA") -> -0.053428094 | AG19: =IFERROR((J19+L19+N19+P19+R19+T19+V19+X19)/8, "NA") -> 2626.82 | AH19: =IFERROR(AG19/AG148, "NA") -> 0.023698778 | AI19: =IFERROR(X19-AG19, "NA") -> -218.45 | AJ19: =IFERROR(AI19/AI148, "NA") -> -0.042826364 | AK19: =IFERROR((X19-AG19)/AG19, "NA") -> -0.083161389 | AL19: =IFERROR(AK19/AK148, "NA") -> -1.8071127
A20: 50150 - COGS - Frozen | B20: 1749.18 | C20: =IFERROR(B20/B148, "NA") -> 0.0085872792 | D20: 1435.1 | E20: =IFERROR(D20/D148, "NA") -> 0.0077320453 | F20: 674.19 | G20: =IFERROR(F20/F148, "NA") -> 0.0047727262 | H20: 1763.42 | I20: =IFERROR(H20/H148, "NA") -> 0.023617974 | J20: 1748.02 | K20: =IFERROR(J20/J148, "NA") -> 0.012275577 | L20: 1792.71 | M20: =IFERROR(L20/L148, "NA") -> 0.01326554 | N20: 1431 | O20: =IFERROR(N20/N148, "NA") -> 0.011768343 | P20: 747.13 | Q20: =IFERROR(P20/P148, "NA") -> 0.013197232 | R20: 1072.79 | S20: =IFERROR(R20/R148, "NA") -> 0.015438795 | T20: 1260.74 | U20: =IFERROR(T20/T148, "NA") -> 0.011408774 | V20: 1475.29 | W20: =IFERROR(V20/V148, "NA") -> 0.010923887 | X20: 1298.26 | Y20: =IFERROR(X20/X148, "NA") -> 0.011197415 | Z20: 5107.08 | AA20: =IFERROR(Z20/Z148, "NA") -> 0.01184972 | AB20: =IFERROR((R20+T20+V20+X20)/4, "NA") -> 1276.77 | AC20: =IFERROR(AB20/AB148, "NA") -> 0.01184972 | AD20: =IFERROR(X20-AB20, "NA") -> 21.49 | AE20: =IFERROR(AD20/AD148, "NA") -> 0.0026220163 | AF20: =IFERROR((X20-AB20)/AB20, "NA") -> 0.016831536 | AG20: =IFERROR((J20+L20+N20+P20+R20+T20+V20+X20)/8, "NA") -> 1353.2425 | AH20: =IFERROR(AG20/AG148, "NA") -> 0.012208752 | AI20: =IFERROR(X20-AG20, "NA") -> -54.9825 | AJ20: =IFERROR(AI20/AI148, "NA") -> -0.010779128 | AK20: =IFERROR((X20-AG20)/AG20, "NA") -> -0.04063019 | AL20: =IFERROR(AK20/AK148, "NA") -> -0.88290171
A21: 50160 - COGS - Meat | B21: 1034.75 | C21: =IFERROR(B21/B148, "NA") -> 0.0050799158 | D21: 1148.33 | E21: =IFERROR(D21/D148, "NA") -> 0.0061869832 | F21: 1174.98 | G21: =IFERROR(F21/F148, "NA") -> 0.008317919 | H21: 572.71 | I21: =IFERROR(H21/H148, "NA") -> 0.0076704643 | J21: -557.31 | K21: =IFERROR(J21/J148, "NA") -> -0.0039137433 | L21: 3077.26 | M21: =IFERROR(L21/L148, "NA") -> 0.022770842 | N21: 896.98 | O21: =IFERROR(N21/N148, "NA") -> 0.0073766374 | P21: 434.26 | Q21: =IFERROR(P21/P148, "NA") -> 0.0076707265 | R21: 594.6 | S21: =IFERROR(R21/R148, "NA") -> 0.0085570406 | T21: 1013.54 | U21: =IFERROR(T21/T148, "NA") -> 0.0091717947 | V21: 1063.54 | W21: =IFERROR(V21/V148, "NA") -> 0.0078750559 | X21: 1168.94 | Y21: =IFERROR(X21/X148, "NA") -> 0.010082038 | Z21: 3840.62 | AA21: =IFERROR(Z21/Z148, "NA") -> 0.008911212 | AB21: =IFERROR((R21+T21+V21+X21)/4, "NA") -> 960.155 | AC21: =IFERROR(AB21/AB148, "NA") -> 0.008911212 | AD21: =IFERROR(X21-AB21, "NA") -> 208.785 | AE21: =IFERROR(AD21/AD148, "NA") -> 0.025474066 | AF21: =IFERROR((X21-AB21)/AB21, "NA") -> 0.21744927 | AG21: =IFERROR((J21+L21+N21+P21+R21+T21+V21+X21)/8, "NA") -> 961.47625 | AH21: =IFERROR(AG21/AG148, "NA") -> 0.0086742954 | AI21: =IFERROR(X21-AG21, "NA") -> 207.46375 | AJ21: =IFERROR(AI21/AI148, "NA") -> 0.040672547 | AK21: =IFERROR((X21-AG21)/AG21, "NA") -> 0.21577626 | AL21: =IFERROR(AK21/AK148, "NA") -> 4.6888589
A22: 50170 - COGS - Seafood | B22: 0 | C22: =IFERROR(B22/B148, "NA") -> 0 | D22: 0 | E22: =IFERROR(D22/D148, "NA") -> 0 | F22: 0 | G22: =IFERROR(F22/F148, "NA") -> 0 | H22: 0 | I22: =IFERROR(H22/H148, "NA") -> 0 | J22: 0 | K22: =IFERROR(J22/J148, "NA") -> 0 | L22: 0 | M22: =IFERROR(L22/L148, "NA") -> 0 | N22: 0 | O22: =IFERROR(N22/N148, "NA") -> 0 | P22: 0 | Q22: =IFERROR(P22/P148, "NA") -> 0 | R22: 0 | S22: =IFERROR(R22/R148, "NA") -> 0 | T22: 0 | U22: =IFERROR(T22/T148, "NA") -> 0 | V22: 0 | W22: =IFERROR(V22/V148, "NA") -> 0 | X22: 0 | Y22: =IFERROR(X22/X148, "NA") -> 0 | Z22: 0 | AA22: =IFERROR(Z22/Z148, "NA") -> 0 | AB22: =IFERROR((R22+T22+V22+X22)/4, "NA") -> 0 | AC22: =IFERROR(AB22/AB148, "NA") -> 0 | AD22: =IFERROR(X22-AB22, "NA") -> 0 | AE22: =IFERROR(AD22/AD148, "NA") -> 0 | AF22: =IFERROR((X22-AB22)/AB22, "NA") -> NA | AG22: =IFERROR((J22+L22+N22+P22+R22+T22+V22+X22)/8, "NA") -> 0 | AH22: =IFERROR(AG22/AG148, "NA") -> 0 | AI22: =IFERROR(X22-AG22, "NA") -> 0 | AJ22: =IFERROR(AI22/AI148, "NA") -> 0 | AK22: =IFERROR((X22-AG22)/AG22, "NA") -> NA | AL22: =IFERROR(AK22/AK148, "NA") -> NA
A23: 50180 - COGS - Spices | B23: 338.77 | C23: =IFERROR(B23/B148, "NA") -> 0.0016631293 | D23: 799.35 | E23: =IFERROR(D23/D148, "NA") -> 0.0043067454 | F23: 483.86 | G23: =IFERROR(F23/F148, "NA") -> 0.0034253419 | H23: 488.32 | I23: =IFERROR(H23/H148, "NA") -> 0.0065402055 | J23: 721.15 | K23: =IFERROR(J23/J148, "NA") -> 0.0050643196 | L23: 367.58 | M23: =IFERROR(L23/L148, "NA") -> 0.0027199866 | N23: 827.01 | O23: =IFERROR(N23/N148, "NA") -> 0.0068012139 | P23: 247.45 | Q23: =IFERROR(P23/P148, "NA") -> 0.0043709328 | R23: 627.4 | S23: =IFERROR(R23/R148, "NA") -> 0.0090290738 | T23: 462.15 | U23: =IFERROR(T23/T148, "NA") -> 0.004182119 | V23: 737.08 | W23: =IFERROR(V23/V148, "NA") -> 0.0054577601 | X23: 542.14 | Y23: =IFERROR(X23/X148, "NA") -> 0.0046759252 | Z23: 2368.77 | AA23: =IFERROR(Z23/Z148, "NA") -> 0.0054961469 | AB23: =IFERROR((R23+T23+V23+X23)/4, "NA") -> 592.1925 | AC23: =IFERROR(AB23/AB148, "NA") -> 0.0054961469 | AD23: =IFERROR(X23-AB23, "NA") -> -50.0525 | AE23: =IFERROR(AD23/AD148, "NA") -> -0.0061069554 | AF23: =IFERROR((X23-AB23)/AB23, "NA") -> -0.084520658 | AG23: =IFERROR((J23+L23+N23+P23+R23+T23+V23+X23)/8, "NA") -> 566.495 | AH23: =IFERROR(AG23/AG148, "NA") -> 0.0051108334 | AI23: =IFERROR(X23-AG23, "NA") -> -24.355 | AJ23: =IFERROR(AI23/AI148, "NA") -> -0.0047747131 | AK23: =IFERROR((X23-AG23)/AG23, "NA") -> -0.042992436 | AL23: =IFERROR(AK23/AK148, "NA") -> -0.93423376
A24: 50190 - COGS - Prepped Food | B24: 14639.08 | C24: =IFERROR(B24/B148, "NA") -> 0.071867885 | D24: 13572.96 | E24: =IFERROR(D24/D148, "NA") -> 0.073128522 | F24: 10551.28 | G24: =IFERROR(F24/F148, "NA") -> 0.074694626 | H24: 5547.31 | I24: =IFERROR(H24/H148, "NA") -> 0.074296665 | J24: 10707.26 | K24: =IFERROR(J24/J148, "NA") -> 0.075192383 | L24: 9469.51 | M24: =IFERROR(L24/L148, "NA") -> 0.07007166 | N24: 8680.64 | O24: =IFERROR(N24/N148, "NA") -> 0.071388363 | P24: 5066.18 | Q24: =IFERROR(P24/P148, "NA") -> 0.089488512 | R24: 6074.61 | S24: =IFERROR(R24/R148, "NA") -> 0.087421265 | T24: 7983.05 | U24: =IFERROR(T24/T148, "NA") -> 0.072240756 | V24: 10236.53 | W24: =IFERROR(V24/V148, "NA") -> 0.075797098 | X24: 7543.02 | Y24: =IFERROR(X24/X148, "NA") -> 0.065058098 | Z24: 31837.21 | AA24: =IFERROR(Z24/Z148, "NA") -> 0.073870398 | AB24: =IFERROR((R24+T24+V24+X24)/4, "NA") -> 7959.3025 | AC24: =IFERROR(AB24/AB148, "NA") -> 0.073870398 | AD24: =IFERROR(X24-AB24, "NA") -> -416.2825 | AE24: =IFERROR(AD24/AD148, "NA") -> -0.050791043 | AF24: =IFERROR((X24-AB24)/AB24, "NA") -> -0.052301379 | AG24: =IFERROR((J24+L24+N24+P24+R24+T24+V24+X24)/8, "NA") -> 8220.1 | AH24: =IFERROR(AG24/AG148, "NA") -> 0.074160517 | AI24: =IFERROR(X24-AG24, "NA") -> -677.08 | AJ24: =IFERROR(AI24/AI148, "NA") -> -0.13273918 | AK24: =IFERROR((X24-AG24)/AG24, "NA") -> -0.082368828 | AL24: =IFERROR(AK24/AK148, "NA") -> -1.7898902
A25: 50191 - COGS - Wow Bao | B25: 0 | C25: =IFERROR(B25/B148, "NA") -> 0 | D25: 0 | E25: =IFERROR(D25/D148, "NA") -> 0 | F25: 0 | G25: =IFERROR(F25/F148, "NA") -> 0 | H25: 0 | I25: =IFERROR(H25/H148, "NA") -> 0 | J25: 0 | K25: =IFERROR(J25/J148, "NA") -> 0 | L25: 0 | M25: =IFERROR(L25/L148, "NA") -> 0 | N25: 0 | O25: =IFERROR(N25/N148, "NA") -> 0 | P25: 0 | Q25: =IFERROR(P25/P148, "NA") -> 0 | R25: 0 | S25: =IFERROR(R25/R148, "NA") -> 0 | T25: 0 | U25: =IFERROR(T25/T148, "NA") -> 0 | V25: 0 | W25: =IFERROR(V25/V148, "NA") -> 0 | X25: 0 | Y25: =IFERROR(X25/X148, "NA") -> 0 | Z25: 0 | AA25: =IFERROR(Z25/Z148, "NA") -> 0 | AB25: =IFERROR((R25+T25+V25+X25)/4, "NA") -> 0 | AC25: =IFERROR(AB25/AB148, "NA") -> 0 | AD25: =IFERROR(X25-AB25, "NA") -> 0 | AE25: =IFERROR(AD25/AD148, "NA") -> 0 | AF25: =IFERROR((X25-AB25)/AB25, "NA") -> NA | AG25: =IFERROR((J25+L25+N25+P25+R25+T25+V25+X25)/8, "NA") -> 0 | AH25: =IFERROR(AG25/AG148, "NA") -> 0 | AI25: =IFERROR(X25-AG25, "NA") -> 0 | AJ25: =IFERROR(AI25/AI148, "NA") -> 0 | AK25: =IFERROR((X25-AG25)/AG25, "NA") -> NA | AL25: =IFERROR(AK25/AK148, "NA") -> NA
A26: 50195 - COGS - Distribution | B26: 0 | C26: =IFERROR(B26/B148, "NA") -> 0 | D26: 0 | E26: =IFERROR(D26/D148, "NA") -> 0 | F26: 0 | G26: =IFERROR(F26/F148, "NA") -> 0 | H26: 0 | I26: =IFERROR(H26/H148, "NA") -> 0 | J26: 0 | K26: =IFERROR(J26/J148, "NA") -> 0 | L26: 0 | M26: =IFERROR(L26/L148, "NA") -> 0 | N26: 0 | O26: =IFERROR(N26/N148, "NA") -> 0 | P26: 0 | Q26: =IFERROR(P26/P148, "NA") -> 0 | R26: 0 | S26: =IFERROR(R26/R148, "NA") -> 0 | T26: 0 | U26: =IFERROR(T26/T148, "NA") -> 0 | V26: 0 | W26: =IFERROR(V26/V148, "NA") -> 0 | X26: 0 | Y26: =IFERROR(X26/X148, "NA") -> 0 | Z26: 0 | AA26: =IFERROR(Z26/Z148, "NA") -> 0 | AB26: =IFERROR((R26+T26+V26+X26)/4, "NA") -> 0 | AC26: =IFERROR(AB26/AB148, "NA") -> 0 | AD26: =IFERROR(X26-AB26, "NA") -> 0 | AE26: =IFERROR(AD26/AD148, "NA") -> 0 | AF26: =IFERROR((X26-AB26)/AB26, "NA") -> NA | AG26: =IFERROR((J26+L26+N26+P26+R26+T26+V26+X26)/8, "NA") -> 0 | AH26: =IFERROR(AG26/AG148, "NA") -> 0 | AI26: =IFERROR(X26-AG26, "NA") -> 0 | AJ26: =IFERROR(AI26/AI148, "NA") -> 0 | AK26: =IFERROR((X26-AG26)/AG26, "NA") -> NA | AL26: =IFERROR(AK26/AK148, "NA") -> NA
A27: Total Food Costs | B27: =IFERROR(B15+B16+B17+B18+B19+B20+B21+B22+B23+B24+B25+B26, "NA") -> 42340.8 | C27: =IFERROR(B27/B148, "NA") -> 0.20786441 | D27: =IFERROR(D15+D16+D17+D18+D19+D20+D21+D22+D23+D24+D25+D26, "NA") -> 39665.26 | E27: =IFERROR(D27/D148, "NA") -> 0.21370886 | F27: =IFERROR(F15+F16+F17+F18+F19+F20+F21+F22+F23+F24+F25+F26, "NA") -> 28885.75 | G27: =IFERROR(F27/F148, "NA") -> 0.20448801 | H27: =IFERROR(H15+H16+H17+H18+H19+H20+H21+H22+H23+H24+H25+H26, "NA") -> 20053.95 | I27: =IFERROR(H27/H148, "NA") -> 0.26858813 | J27: =IFERROR(J15+J16+J17+J18+J19+J20+J21+J22+J23+J24+J25+J26, "NA") -> 31757.54 | K27: =IFERROR(J27/J148, "NA") -> 0.22301925 | L27: =IFERROR(L15+L16+L17+L18+L19+L20+L21+L22+L23+L24+L25+L26, "NA") -> 32522.5 | M27: =IFERROR(L27/L148, "NA") -> 0.24065718 | N27: =IFERROR(N15+N16+N17+N18+N19+N20+N21+N22+N23+N24+N25+N26, "NA") -> 27919.76 | O27: =IFERROR(N27/N148, "NA") -> 0.22960818 | P27: =IFERROR(P15+P16+P17+P18+P19+P20+P21+P22+P23+P24+P25+P26, "NA") -> 13775.08 | Q27: =IFERROR(P27/P148, "NA") -> 0.24332168 | R27: =IFERROR(R15+R16+R17+R18+R19+R20+R21+R22+R23+R24+R25+R26, "NA") -> 18453.18 | S27: =IFERROR(R27/R148, "NA") -> 0.26556443 | T27: =IFERROR(T15+T16+T17+T18+T19+T20+T21+T22+T23+T24+T25+T26, "NA") -> 26075.93 | U27: =IFERROR(T27/T148, "NA") -> 0.23596807 | V27: =IFERROR(V15+V16+V17+V18+V19+V20+V21+V22+V23+V24+V25+V26, "NA") -> 31056.7 | W27: =IFERROR(V27/V148, "NA") -> 0.22996149 | X27: =IFERROR(X15+X16+X17+X18+X19+X20+X21+X22+X23+X24+X25+X26, "NA") -> 25244.69 | Y27: =IFERROR(X27/X148, "NA") -> 0.21773395 | Z27: =IFERROR(Z15+Z16+Z17+Z18+Z19+Z20+Z21+Z22+Z23+Z24+Z25+Z26, "NA") -> 100830.5 | AA27: =IFERROR(Z27/Z148, "NA") -> 0.23395232 | AB27: =IFERROR((R27+T27+V27+X27)/4, "NA") -> 25207.625 | AC27: =IFERROR(AB27/AB148, "NA") -> 0.23395232 | AD27: =IFERROR(X27-AB27, "NA") -> 37.065 | AE27: =IFERROR(AD27/AD148, "NA") -> 0.0045223376 | AF27: =IFERROR((X27-AB27)/AB27, "NA") -> 0.0014703884 | AG27: =IFERROR((J27+L27+N27+P27+R27+T27+V27+X27)/8, "NA") -> 25850.673 | AH27: =IFERROR(AG27/AG148, "NA") -> 0.23322091 | AI27: =IFERROR(X27-AG27, "NA") -> -605.9825 | AJ27: =IFERROR(AI27/AI148, "NA") -> -0.11880076 | AK27: =IFERROR((X27-AG27)/AG27, "NA") -> -0.023441653 | AL27: =IFERROR(AK27/AK148, "NA") -> -0.50939155
A28: Beverage Costs
A29: 50101 - Beverage Costs | B29: 0 | C29: =IFERROR(B29/B148, "NA") -> 0 | D29: 0 | E29: =IFERROR(D29/D148, "NA") -> 0 | F29: 0 | G29: =IFERROR(F29/F148, "NA") -> 0 | H29: 0 | I29: =IFERROR(H29/H148, "NA") -> 0 | J29: 0 | K29: =IFERROR(J29/J148, "NA") -> 0 | L29: 0 | M29: =IFERROR(L29/L148, "NA") -> 0 | N29: 0 | O29: =IFERROR(N29/N148, "NA") -> 0 | P29: 0 | Q29: =IFERROR(P29/P148, "NA") -> 0 | R29: 0 | S29: =IFERROR(R29/R148, "NA") -> 0 | T29: 0 | U29: =IFERROR(T29/T148, "NA") -> 0 | V29: 0 | W29: =IFERROR(V29/V148, "NA") -> 0 | X29: 0 | Y29: =IFERROR(X29/X148, "NA") -> 0 | Z29: 0 | AA29: =IFERROR(Z29/Z148, "NA") -> 0 | AB29: =IFERROR((R29+T29+V29+X29)/4, "NA") -> 0 | AC29: =IFERROR(AB29/AB148, "NA") -> 0 | AD29: =IFERROR(X29-AB29, "NA") -> 0 | AE29: =IFERROR(AD29/AD148, "NA") -> 0 | AF29: =IFERROR((X29-AB29)/AB29, "NA") -> NA | AG29: =IFERROR((J29+L29+N29+P29+R29+T29+V29+X29)/8, "NA") -> 0 | AH29: =IFERROR(AG29/AG148, "NA") -> 0 | AI29: =IFERROR(X29-AG29, "NA") -> 0 | AJ29: =IFERROR(AI29/AI148, "NA") -> 0 | AK29: =IFERROR((X29-AG29)/AG29, "NA") -> NA | AL29: =IFERROR(AK29/AK148, "NA") -> NA
A30: 50200 - COGS - N/A Beverage | B30: 1879.47 | C30: =IFERROR(B30/B148, "NA") -> 0.0092269141 | D30: 1972.86 | E30: =IFERROR(D30/D148, "NA") -> 0.010629394 | F30: 1508.95 | G30: =IFERROR(F30/F148, "NA") -> 0.01068216 | H30: 1179.95 | I30: =IFERROR(H30/H148, "NA") -> 0.015803398 | J30: 1334.11 | K30: =IFERROR(J30/J148, "NA") -> 0.0093688684 | L30: 1911.05 | M30: =IFERROR(L30/L148, "NA") -> 0.014141222 | N30: 1195.14 | O30: =IFERROR(N30/N148, "NA") -> 0.0098286633 | P30: 1060.18 | Q30: =IFERROR(P30/P148, "NA") -> 0.018726917 | R30: 857.99 | S30: =IFERROR(R30/R148, "NA") -> 0.012347553 | T30: 1530.36 | U30: =IFERROR(T30/T148, "NA") -> 0.013848637 | V30: 1470.33 | W30: =IFERROR(V30/V148, "NA") -> 0.010887161 | X30: 1433.98 | Y30: =IFERROR(X30/X148, "NA") -> 0.012367992 | Z30: 5292.66 | AA30: =IFERROR(Z30/Z148, "NA") -> 0.012280313 | AB30: =IFERROR((R30+T30+V30+X30)/4, "NA") -> 1323.165 | AC30: =IFERROR(AB30/AB148, "NA") -> 0.012280313 | AD30: =IFERROR(X30-AB30, "NA") -> 110.815 | AE30: =IFERROR(AD30/AD148, "NA") -> 0.013520649 | AF30: =IFERROR((X30-AB30)/AB30, "NA") -> 0.083749948 | AG30: =IFERROR((J30+L30+N30+P30+R30+T30+V30+X30)/8, "NA") -> 1349.1425 | AH30: =IFERROR(AG30/AG148, "NA") -> 0.012171763 | AI30: =IFERROR(X30-AG30, "NA") -> 84.8375 | AJ30: =IFERROR(AI30/AI148, "NA") -> 0.016632097 | AK30: =IFERROR((X30-AG30)/AG30, "NA") -> 0.062882535 | AL30: =IFERROR(AK30/AK148, "NA") -> 1.3664494
A31: 50300 - COGS - Beer | B31: -155.27 | C31: =IFERROR(B31/B148, "NA") -> -0.00076226966 | D31: 147.08 | E31: =IFERROR(D31/D148, "NA") -> 0.00079243901 | F31: -64.88 | G31: =IFERROR(F31/F148, "NA") -> -0.00045929853 | H31: 59.03 | I31: =IFERROR(H31/H148, "NA") -> 0.0007906052 | J31: 108.66 | K31: =IFERROR(J31/J148, "NA") -> 0.00076307144 | L31: 59.2 | M31: =IFERROR(L31/L148, "NA") -> 0.00043806303 | N31: 37.65 | O31: =IFERROR(N31/N148, "NA") -> 0.00030962831 | P31: 28.78 | Q31: =IFERROR(P31/P148, "NA") -> 0.00050836713 | R31: 22.8 | S31: =IFERROR(R31/R148, "NA") -> 0.00032812063 | T31: 80.05 | U31: =IFERROR(T31/T148, "NA") -> 0.00072439388 | V31: 26.71 | W31: =IFERROR(V31/V148, "NA") -> 0.00019777605 | X31: 59.28 | Y31: =IFERROR(X31/X148, "NA") -> 0.00051128647 | Z31: 188.84 | AA31: =IFERROR(Z31/Z148, "NA") -> 0.00043815667 | AB31: =IFERROR((R31+T31+V31+X31)/4, "NA") -> 47.21 | AC31: =IFERROR(AB31/AB148, "NA") -> 0.00043815667 | AD31: =IFERROR(X31-AB31, "NA") -> 12.07 | AE31: =IFERROR(AD31/AD148, "NA") -> 0.0014726727 | AF31: =IFERROR((X31-AB31)/AB31, "NA") -> 0.25566617 | AG31: =IFERROR((J31+L31+N31+P31+R31+T31+V31+X31)/8, "NA") -> 52.89125 | AH31: =IFERROR(AG31/AG148, "NA") -> 0.00047717697 | AI31: =IFERROR(X31-AG31, "NA") -> 6.38875 | AJ31: =IFERROR(AI31/AI148, "NA") -> 0.0012524922 | AK31: =IFERROR((X31-AG31)/AG31, "NA") -> 0.1207903 | AL31: =IFERROR(AK31/AK148, "NA") -> 2.6247961
A32: 50400 - COGS - Liquor | B32: -31.57 | C32: =IFERROR(B32/B148, "NA") -> -0.00015498714 | D32: 20.29 | E32: =IFERROR(D32/D148, "NA") -> 0.00010931865 | F32: 269.66 | G32: =IFERROR(F32/F148, "NA") -> 0.0019089772 | H32: -336.03 | I32: =IFERROR(H32/H148, "NA") -> -0.0045005432 | J32: 216.71 | K32: =IFERROR(J32/J148, "NA") -> 0.0015218591 | L32: 127.34 | M32: =IFERROR(L32/L148, "NA") -> 0.0009422795 | N32: 127.02 | O32: =IFERROR(N32/N148, "NA") -> 0.0010445946 | P32: 462.72 | Q32: =IFERROR(P32/P148, "NA") -> 0.0081734412 | R32: 43.31 | S32: =IFERROR(R32/R148, "NA") -> 0.00062328528 | T32: 17.59 | U32: =IFERROR(T32/T148, "NA") -> 0.00015917662 | V32: 5.28 | W32: =IFERROR(V32/V148, "NA") -> 3.9096127e-05 | X32: 30.7 | Y32: =IFERROR(X32/X148, "NA") -> 0.00026478567 | Z32: 96.88 | AA32: =IFERROR(Z32/Z148, "NA") -> 0.00022478616 | AB32: =IFERROR((R32+T32+V32+X32)/4, "NA") -> 24.22 | AC32: =IFERROR(AB32/AB148, "NA") -> 0.00022478616 | AD32: =IFERROR(X32-AB32, "NA") -> 6.48 | AE32: =IFERROR(AD32/AD148, "NA") -> 0.00079063126 | AF32: =IFERROR((X32-AB32)/AB32, "NA") -> 0.26754748 | AG32: =IFERROR((J32+L32+N32+P32+R32+T32+V32+X32)/8, "NA") -> 128.83375 | AH32: =IFERROR(AG32/AG148, "NA") -> 0.0011623189 | AI32: =IFERROR(X32-AG32, "NA") -> -98.13375 | AJ32: =IFERROR(AI32/AI148, "NA") -> -0.019238781 | AK32: =IFERROR((X32-AG32)/AG32, "NA") -> -0.7617084 | AL32: =IFERROR(AK32/AK148, "NA") -> -16.552068
A33: 50500 - COGS - Wine | B33: 17 | C33: =IFERROR(B33/B148, "NA") -> 8.345839e-05 | D33: 23.59 | E33: =IFERROR(D33/D148, "NA") -> 0.00012709842 | F33: 12.88 | G33: =IFERROR(F33/F148, "NA") -> 9.1180102e-05 | H33: 28.38 | I33: =IFERROR(H33/H148, "NA") -> 0.00038010123 | J33: 39.4 | K33: =IFERROR(J33/J148, "NA") -> 0.00027668889 | L33: -30.46 | M33: =IFERROR(L33/L148, "NA") -> -0.00022539527 | N33: 15.02 | O33: =IFERROR(N33/N148, "NA") -> 0.00012352237 | P33: 12.7 | Q33: =IFERROR(P33/P148, "NA") -> 0.00022433157 | R33: -16.94 | S33: =IFERROR(R33/R148, "NA") -> -0.00024378787 | T33: 45.7 | U33: =IFERROR(T33/T148, "NA") -> 0.00041355153 | V33: -21.61 | W33: =IFERROR(V33/V148, "NA") -> -0.00016001275 | X33: 40.28 | Y33: =IFERROR(X33/X148, "NA") -> 0.0003474126 | Z33: 47.43 | AA33: =IFERROR(Z33/Z148, "NA") -> 0.00011004962 | AB33: =IFERROR((R33+T33+V33+X33)/4, "NA") -> 11.8575 | AC33: =IFERROR(AB33/AB148, "NA") -> 0.00011004962 | AD33: =IFERROR(X33-AB33, "NA") -> 28.4225 | AE33: =IFERROR(AD33/AD148, "NA") -> 0.0034678576 | AF33: =IFERROR((X33-AB33)/AB33, "NA") -> 2.3970061 | AG33: =IFERROR((J33+L33+N33+P33+R33+T33+V33+X33)/8, "NA") -> 10.51125 | AH33: =IFERROR(AG33/AG148, "NA") -> 9.4830931e-05 | AI33: =IFERROR(X33-AG33, "NA") -> 29.76875 | AJ33: =IFERROR(AI33/AI148, "NA") -> 0.00583606 | AK33: =IFERROR((X33-AG33)/AG33, "NA") -> 2.8320847 | AL33: =IFERROR(AK33/AK148, "NA") -> 61.541735
A34: Total Beverage Costs | B34: =IFERROR(B29+B30+B31+B32+B33, "NA") -> 1709.63 | C34: =IFERROR(B34/B148, "NA") -> 0.0083931157 | D34: =IFERROR(D29+D30+D31+D32+D33, "NA") -> 2163.82 | E34: =IFERROR(D34/D148, "NA") -> 0.01165825 | F34: =IFERROR(F29+F30+F31+F32+F33, "NA") -> 1726.61 | G34: =IFERROR(F34/F148, "NA") -> 0.012223018 | H34: =IFERROR(H29+H30+H31+H32+H33, "NA") -> 931.33 | I34: =IFERROR(H34/H148, "NA") -> 0.012473562 | J34: =IFERROR(J29+J30+J31+J32+J33, "NA") -> 1698.88 | K34: =IFERROR(J34/J148, "NA") -> 0.011930488 | L34: =IFERROR(L29+L30+L31+L32+L33, "NA") -> 2067.13 | M34: =IFERROR(L34/L148, "NA") -> 0.015296169 | N34: =IFERROR(N29+N30+N31+N32+N33, "NA") -> 1374.83 | O34: =IFERROR(N34/N148, "NA") -> 0.011306409 | P34: =IFERROR(P29+P30+P31+P32+P33, "NA") -> 1564.38 | Q34: =IFERROR(P34/P148, "NA") -> 0.027633056 | R34: =IFERROR(R29+R30+R31+R32+R33, "NA") -> 907.16 | S34: =IFERROR(R34/R148, "NA") -> 0.013055171 | T34: =IFERROR(T29+T30+T31+T32+T33, "NA") -> 1673.7 | U34: =IFERROR(T34/T148, "NA") -> 0.015145759 | V34: =IFERROR(V29+V30+V31+V32+V33, "NA") -> 1480.71 | W34: =IFERROR(V34/V148, "NA") -> 0.01096402 | X34: =IFERROR(X29+X30+X31+X32+X33, "NA") -> 1564.24 | Y34: =IFERROR(X34/X148, "NA") -> 0.013491477 | Z34: =IFERROR(Z29+Z30+Z31+Z32+Z33, "NA") -> 5625.81 | AA34: =IFERROR(Z34/Z148, "NA") -> 0.013053305 | AB34: =IFERROR((R34+T34+V34+X34)/4, "NA") -> 1406.4525 | AC34: =IFERROR(AB34/AB148, "NA") -> 0.013053305 | AD34: =IFERROR(X34-AB34, "NA") -> 157.7875 | AE34: =IFERROR(AD34/AD148, "NA") -> 0.01925181 | AF34: =IFERROR((X34-AB34)/AB34, "NA") -> 0.11218829 | AG34: =IFERROR((J34+L34+N34+P34+R34+T34+V34+X34)/8, "NA") -> 1541.3788 | AH34: =IFERROR(AG34/AG148, "NA") -> 0.013906089 | AI34: =IFERROR(X34-AG34, "NA") -> 22.86125 | AJ34: =IFERROR(AI34/AI148, "NA") -> 0.0044818686 | AK34: =IFERROR((X34-AG34)/AG34, "NA") -> 0.014831689 | AL34: =IFERROR(AK34/AK148, "NA") -> 0.3222954
A35: Total Food & Beverage Costs | B35: =IFERROR(B13+B15+B16+B17+B18+B19+B20+B21+B22+B23+B24+B25+B26+B29+B30+B31+B32+B33, "NA") -> 44050.43 | C35: =IFERROR(B35/B148, "NA") -> 0.21625753 | D35: =IFERROR(D13+D15+D16+D17+D18+D19+D20+D21+D22+D23+D24+D25+D26+D29+D30+D31+D32+D33, "NA") -> 41829.08 | E35: =IFERROR(D35/D148, "NA") -> 0.22536711 | F35: =IFERROR(F13+F15+F16+F17+F18+F19+F20+F21+F22+F23+F24+F25+F26+F29+F30+F31+F32+F33, "NA") -> 30612.36 | G35: =IFERROR(F35/F148, "NA") -> 0.21671103 | H35: =IFERROR(H13+H15+H16+H17+H18+H19+H20+H21+H22+H23+H24+H25+H26+H29+H30+H31+H32+H33, "NA") -> 20985.28 | I35: =IFERROR(H35/H148, "NA") -> 0.28106169 | J35: =IFERROR(J13+J15+J16+J17+J18+J19+J20+J21+J22+J23+J24+J25+J26+J29+J30+J31+J32+J33, "NA") -> 33456.42 | K35: =IFERROR(J35/J148, "NA") -> 0.23494974 | L35: =IFERROR(L13+L15+L16+L17+L18+L19+L20+L21+L22+L23+L24+L25+L26+L29+L30+L31+L32+L33, "NA") -> 34589.63 | M35: =IFERROR(L35/L148, "NA") -> 0.25595335 | N35: =IFERROR(N13+N15+N16+N17+N18+N19+N20+N21+N22+N23+N24+N25+N26+N29+N30+N31+N32+N33, "NA") -> 29294.59 | O35: =IFERROR(N35/N148, "NA") -> 0.24091459 | P35: =IFERROR(P13+P15+P16+P17+P18+P19+P20+P21+P22+P23+P24+P25+P26+P29+P30+P31+P32+P33, "NA") -> 15339.46 | Q35: =IFERROR(P35/P148, "NA") -> 0.27095473 | R35: =IFERROR(R13+R15+R16+R17+R18+R19+R20+R21+R22+R23+R24+R25+R26+R29+R30+R31+R32+R33, "NA") -> 19360.34 | S35: =IFERROR(R35/R148, "NA") -> 0.2786196 | T35: =IFERROR(T13+T15+T16+T17+T18+T19+T20+T21+T22+T23+T24+T25+T26+T29+T30+T31+T32+T33, "NA") -> 27749.63 | U35: =IFERROR(T35/T148, "NA") -> 0.25111383 | V35: =IFERROR(V13+V15+V16+V17+V18+V19+V20+V21+V22+V23+V24+V25+V26+V29+V30+V31+V32+V33, "NA") -> 32537.41 | W35: =IFERROR(V35/V148, "NA") -> 0.24092551 | X35: =IFERROR(X13+X15+X16+X17+X18+X19+X20+X21+X22+X23+X24+X25+X26+X29+X30+X31+X32+X33, "NA") -> 26808.93 | Y35: =IFERROR(X35/X148, "NA") -> 0.23122542 | Z35: =IFERROR(Z13+Z15+Z16+Z17+Z18+Z19+Z20+Z21+Z22+Z23+Z24+Z25+Z26+Z29+Z30+Z31+Z32+Z33, "NA") -> 106456.31 | AA35: =IFERROR(Z35/Z148, "NA") -> 0.24700563 | AB35: =IFERROR((R35+T35+V35+X35)/4, "NA") -> 26614.077 | AC35: =IFERROR(AB35/AB148, "NA") -> 0.24700563 | AD35: =IFERROR(X35-AB35, "NA") -> 194.8525 | AE35: =IFERROR(AD35/AD148, "NA") -> 0.023774148 | AF35: =IFERROR((X35-AB35)/AB35, "NA") -> 0.0073214073 | AG35: =IFERROR((J35+L35+N35+P35+R35+T35+V35+X35)/8, "NA") -> 27392.051 | AH35: =IFERROR(AG35/AG148, "NA") -> 0.247127 | AI35: =IFERROR(X35-AG35, "NA") -> -583.12125 | AJ35: =IFERROR(AI35/AI148, "NA") -> -0.1143189 | AK35: =IFERROR((X35-AG35)/AG35, "NA") -> -0.021287973 | AL35: =IFERROR(AK35/AK148, "NA") -> -0.46259168
A36: Other Costs
A37: 50550 - Other Costs | B37: 0 | C37: =IFERROR(B37/B148, "NA") -> 0 | D37: 0 | E37: =IFERROR(D37/D148, "NA") -> 0 | F37: 0 | G37: =IFERROR(F37/F148, "NA") -> 0 | H37: 0 | I37: =IFERROR(H37/H148, "NA") -> 0 | J37: 0 | K37: =IFERROR(J37/J148, "NA") -> 0 | L37: 0 | M37: =IFERROR(L37/L148, "NA") -> 0 | N37: 0 | O37: =IFERROR(N37/N148, "NA") -> 0 | P37: 0 | Q37: =IFERROR(P37/P148, "NA") -> 0 | R37: 0 | S37: =IFERROR(R37/R148, "NA") -> 0 | T37: 0 | U37: =IFERROR(T37/T148, "NA") -> 0 | V37: 0 | W37: =IFERROR(V37/V148, "NA") -> 0 | X37: 0 | Y37: =IFERROR(X37/X148, "NA") -> 0 | Z37: 0 | AA37: =IFERROR(Z37/Z148, "NA") -> 0 | AB37: =IFERROR((R37+T37+V37+X37)/4, "NA") -> 0 | AC37: =IFERROR(AB37/AB148, "NA") -> 0 | AD37: =IFERROR(X37-AB37, "NA") -> 0 | AE37: =IFERROR(AD37/AD148, "NA") -> 0 | AF37: =IFERROR((X37-AB37)/AB37, "NA") -> NA | AG37: =IFERROR((J37+L37+N37+P37+R37+T37+V37+X37)/8, "NA") -> 0 | AH37: =IFERROR(AG37/AG148, "NA") -> 0 | AI37: =IFERROR(X37-AG37, "NA") -> 0 | AJ37: =IFERROR(AI37/AI148, "NA") -> 0 | AK37: =IFERROR((X37-AG37)/AG37, "NA") -> NA | AL37: =IFERROR(AK37/AK148, "NA") -> NA
A38: Paper Costs
A39: 50600 - Paper Costs | B39: 0 | C39: =IFERROR(B39/B148, "NA") -> 0 | D39: 0 | E39: =IFERROR(D39/D148, "NA") -> 0 | F39: 0 | G39: =IFERROR(F39/F148, "NA") -> 0 | H39: 0 | I39: =IFERROR(H39/H148, "NA") -> 0 | J39: 0 | K39: =IFERROR(J39/J148, "NA") -> 0 | L39: 0 | M39: =IFERROR(L39/L148, "NA") -> 0 | N39: 0 | O39: =IFERROR(N39/N148, "NA") -> 0 | P39: 0 | Q39: =IFERROR(P39/P148, "NA") -> 0 | R39: 0 | S39: =IFERROR(R39/R148, "NA") -> 0 | T39: 0 | U39: =IFERROR(T39/T148, "NA") -> 0 | V39: 0 | W39: =IFERROR(V39/V148, "NA") -> 0 | X39: 0 | Y39: =IFERROR(X39/X148, "NA") -> 0 | Z39: 0 | AA39: =IFERROR(Z39/Z148, "NA") -> 0 | AB39: =IFERROR((R39+T39+V39+X39)/4, "NA") -> 0 | AC39: =IFERROR(AB39/AB148, "NA") -> 0 | AD39: =IFERROR(X39-AB39, "NA") -> 0 | AE39: =IFERROR(AD39/AD148, "NA") -> 0 | AF39: =IFERROR((X39-AB39)/AB39, "NA") -> NA | AG39: =IFERROR((J39+L39+N39+P39+R39+T39+V39+X39)/8, "NA") -> 0 | AH39: =IFERROR(AG39/AG148, "NA") -> 0 | AI39: =IFERROR(X39-AG39, "NA") -> 0 | AJ39: =IFERROR(AI39/AI148, "NA") -> 0 | AK39: =IFERROR((X39-AG39)/AG39, "NA") -> NA | AL39: =IFERROR(AK39/AK148, "NA") -> NA
A40: 50610 - COGS - Paper Supplies | B40: 4562.2 | C40: =IFERROR(B40/B148, "NA") -> 0.022397286 | D40: 3606.95 | E40: =IFERROR(D40/D148, "NA") -> 0.019433559 | F40: 4047.68 | G40: =IFERROR(F40/F148, "NA") -> 0.028654338 | H40: 2757.06 | I40: =IFERROR(H40/H148, "NA") -> 0.036926071 | J40: 4648.55 | K40: =IFERROR(J40/J148, "NA") -> 0.032644724 | L40: 3797.96 | M40: =IFERROR(L40/L148, "NA") -> 0.028103815 | N40: 4126.53 | O40: =IFERROR(N40/N148, "NA") -> 0.033936002 | P40: 1925.3 | Q40: =IFERROR(P40/P148, "NA") -> 0.034008312 | R40: 2508.36 | S40: =IFERROR(R40/R148, "NA") -> 0.03609845 | T40: 3680.76 | U40: =IFERROR(T40/T148, "NA") -> 0.033308182 | V40: 4252.7 | W40: =IFERROR(V40/V148, "NA") -> 0.031489413 | X40: 3496.12 | Y40: =IFERROR(X40/X148, "NA") -> 0.030153827 | Z40: 13937.94 | AA40: =IFERROR(Z40/Z148, "NA") -> 0.032339554 | AB40: =IFERROR((R40+T40+V40+X40)/4, "NA") -> 3484.485 | AC40: =IFERROR(AB40/AB148, "NA") -> 0.032339554 | AD40: =IFERROR(X40-AB40, "NA") -> 11.635 | AE40: =IFERROR(AD40/AD148, "NA") -> 0.001419598 | AF40: =IFERROR((X40-AB40)/AB40, "NA") -> 0.0033390874 | AG40: =IFERROR((J40+L40+N40+P40+R40+T40+V40+X40)/8, "NA") -> 3554.535 | AH40: =IFERROR(AG40/AG148, "NA") -> 0.032068485 | AI40: =IFERROR(X40-AG40, "NA") -> -58.415 | AJ40: =IFERROR(AI40/AI148, "NA") -> -0.011452058 | AK40: =IFERROR((X40-AG40)/AG40, "NA") -> -0.016433936 | AL40: =IFERROR(AK40/AK148, "NA") -> -0.35711253
A41: 50620 - COGS - Catering Supplies | B41: 3635.08 | C41: =IFERROR(B41/B148, "NA") -> 0.01784576 | D41: 2815.87 | E41: =IFERROR(D41/D148, "NA") -> 0.015171371 | F41: 1457.32 | G41: =IFERROR(F41/F148, "NA") -> 0.01031666 | H41: 438.41 | I41: =IFERROR(H41/H148, "NA") -> 0.005871747 | J41: 2088.51 | K41: =IFERROR(J41/J148, "NA") -> 0.014666688 | L41: 2112.72 | M41: =IFERROR(L41/L148, "NA") -> 0.015633522 | N41: 1976.47 | O41: =IFERROR(N41/N148, "NA") -> 0.016254211 | P41: 95.63 | Q41: =IFERROR(P41/P148, "NA") -> 0.001689199 | R41: 458.89 | S41: =IFERROR(R41/R148, "NA") -> 0.0066040033 | T41: 1249.34 | U41: =IFERROR(T41/T148, "NA") -> 0.011305612 | V41: 1234.84 | W41: =IFERROR(V41/V148, "NA") -> 0.0091434586 | X41: 1645.68 | Y41: =IFERROR(X41/X148, "NA") -> 0.014193892 | Z41: 4588.75 | AA41: =IFERROR(Z41/Z148, "NA") -> 0.010647063 | AB41: =IFERROR((R41+T41+V41+X41)/4, "NA") -> 1147.1875 | AC41: =IFERROR(AB41/AB148, "NA") -> 0.010647063 | AD41: =IFERROR(X41-AB41, "NA") -> 498.4925 | AE41: =IFERROR(AD41/AD148, "NA") -> 0.060821567 | AF41: =IFERROR((X41-AB41)/AB41, "NA") -> 0.43453446 | AG41: =IFERROR((J41+L41+N41+P41+R41+T41+V41+X41)/8, "NA") -> 1357.76 | AH41: =IFERROR(AG41/AG148, "NA") -> 0.012249508 | AI41: =IFERROR(X41-AG41, "NA") -> 287.92 | AJ41: =IFERROR(AI41/AI148, "NA") -> 0.056445716 | AK41: =IFERROR((X41-AG41)/AG41, "NA") -> 0.21205515 | AL41: =IFERROR(AK41/AK148, "NA") -> 4.6079985
A42: 50630 - COGS - Event Supplies | B42: 0 | C42: =IFERROR(B42/B148, "NA") -> 0 | D42: 0 | E42: =IFERROR(D42/D148, "NA") -> 0 | F42: 0 | G42: =IFERROR(F42/F148, "NA") -> 0 | H42: 0 | I42: =IFERROR(H42/H148, "NA") -> 0 | J42: 0 | K42: =IFERROR(J42/J148, "NA") -> 0 | L42: 0 | M42: =IFERROR(L42/L148, "NA") -> 0 | N42: 0 | O42: =IFERROR(N42/N148, "NA") -> 0 | P42: 0 | Q42: =IFERROR(P42/P148, "NA") -> 0 | R42: 0 | S42: =IFERROR(R42/R148, "NA") -> 0 | T42: 74.2 | U42: =IFERROR(T42/T148, "NA") -> 0.00067145566 | V42: 0 | W42: =IFERROR(V42/V148, "NA") -> 0 | X42: 0 | Y42: =IFERROR(X42/X148, "NA") -> 0 | Z42: 74.2 | AA42: =IFERROR(Z42/Z148, "NA") -> 0.00017216281 | AB42: =IFERROR((R42+T42+V42+X42)/4, "NA") -> 18.55 | AC42: =IFERROR(AB42/AB148, "NA") -> 0.00017216281 | AD42: =IFERROR(X42-AB42, "NA") -> -18.55 | AE42: =IFERROR(AD42/AD148, "NA") -> -0.002263304 | AF42: =IFERROR((X42-AB42)/AB42, "NA") -> -1 | AG42: =IFERROR((J42+L42+N42+P42+R42+T42+V42+X42)/8, "NA") -> 9.275 | AH42: =IFERROR(AG42/AG148, "NA") -> 8.3677667e-05 | AI42: =IFERROR(X42-AG42, "NA") -> -9.275 | AJ42: =IFERROR(AI42/AI148, "NA") -> -0.0018183315 | AK42: =IFERROR((X42-AG42)/AG42, "NA") -> -1 | AL42: =IFERROR(AK42/AK148, "NA") -> -21.730189
A43: 50640 - COGS - Wow Bao Supplies | B43: 0 | C43: =IFERROR(B43/B148, "NA") -> 0 | D43: 0 | E43: =IFERROR(D43/D148, "NA") -> 0 | F43: 0 | G43: =IFERROR(F43/F148, "NA") -> 0 | H43: 0 | I43: =IFERROR(H43/H148, "NA") -> 0 | J43: 0 | K43: =IFERROR(J43/J148, "NA") -> 0 | L43: 0 | M43: =IFERROR(L43/L148, "NA") -> 0 | N43: 0 | O43: =IFERROR(N43/N148, "NA") -> 0 | P43: 0 | Q43: =IFERROR(P43/P148, "NA") -> 0 | R43: 0 | S43: =IFERROR(R43/R148, "NA") -> 0 | T43: 0 | U43: =IFERROR(T43/T148, "NA") -> 0 | V43: 0 | W43: =IFERROR(V43/V148, "NA") -> 0 | X43: 0 | Y43: =IFERROR(X43/X148, "NA") -> 0 | Z43: 0 | AA43: =IFERROR(Z43/Z148, "NA") -> 0 | AB43: =IFERROR((R43+T43+V43+X43)/4, "NA") -> 0 | AC43: =IFERROR(AB43/AB148, "NA") -> 0 | AD43: =IFERROR(X43-AB43, "NA") -> 0 | AE43: =IFERROR(AD43/AD148, "NA") -> 0 | AF43: =IFERROR((X43-AB43)/AB43, "NA") -> NA | AG43: =IFERROR((J43+L43+N43+P43+R43+T43+V43+X43)/8, "NA") -> 0 | AH43: =IFERROR(AG43/AG148, "NA") -> 0 | AI43: =IFERROR(X43-AG43, "NA") -> 0 | AJ43: =IFERROR(AI43/AI148, "NA") -> 0 | AK43: =IFERROR((X43-AG43)/AG43, "NA") -> NA | AL43: =IFERROR(AK43/AK148, "NA") -> NA
A44: Total Paper Costs | B44: =IFERROR(B39+B40+B41+B42+B43, "NA") -> 8197.28 | C44: =IFERROR(B44/B148, "NA") -> 0.040243047 | D44: =IFERROR(D39+D40+D41+D42+D43, "NA") -> 6422.82 | E44: =IFERROR(D44/D148, "NA") -> 0.03460493 | F44: =IFERROR(F39+F40+F41+F42+F43, "NA") -> 5505 | G44: =IFERROR(F44/F148, "NA") -> 0.038970999 | H44: =IFERROR(H39+H40+H41+H42+H43, "NA") -> 3195.47 | I44: =IFERROR(H44/H148, "NA") -> 0.042797818 | J44: =IFERROR(J39+J40+J41+J42+J43, "NA") -> 6737.06 | K44: =IFERROR(J44/J148, "NA") -> 0.047311413 | L44: =IFERROR(L39+L40+L41+L42+L43, "NA") -> 5910.68 | M44: =IFERROR(L44/L148, "NA") -> 0.043737338 | N44: =IFERROR(N39+N40+N41+N42+N43, "NA") -> 6103 | O44: =IFERROR(N44/N148, "NA") -> 0.050190214 | P44: =IFERROR(P39+P40+P41+P42+P43, "NA") -> 2020.93 | Q44: =IFERROR(P44/P148, "NA") -> 0.035697511 | R44: =IFERROR(R39+R40+R41+R42+R43, "NA") -> 2967.25 | S44: =IFERROR(R44/R148, "NA") -> 0.042702453 | T44: =IFERROR(T39+T40+T41+T42+T43, "NA") -> 5004.3 | U44: =IFERROR(T44/T148, "NA") -> 0.04528525 | V44: =IFERROR(V39+V40+V41+V42+V43, "NA") -> 5487.54 | W44: =IFERROR(V44/V148, "NA") -> 0.040632872 | X44: =IFERROR(X39+X40+X41+X42+X43, "NA") -> 5141.8 | Y44: =IFERROR(X44/X148, "NA") -> 0.044347719 | Z44: =IFERROR(Z39+Z40+Z41+Z42+Z43, "NA") -> 18600.89 | AA44: =IFERROR(Z44/Z148, "NA") -> 0.04315878 | AB44: =IFERROR((R44+T44+V44+X44)/4, "NA") -> 4650.2225 | AC44: =IFERROR(AB44/AB148, "NA") -> 0.04315878 | AD44: =IFERROR(X44-AB44, "NA") -> 491.5775 | AE44: =IFERROR(AD44/AD148, "NA") -> 0.059977861 | AF44: =IFERROR((X44-AB44)/AB44, "NA") -> 0.10571053 | AG44: =IFERROR((J44+L44+N44+P44+R44+T44+V44+X44)/8, "NA") -> 4921.57 | AH44: =IFERROR(AG44/AG148, "NA") -> 0.044401671 | AI44: =IFERROR(X44-AG44, "NA") -> 220.23 | AJ44: =IFERROR(AI44/AI148, "NA") -> 0.043175326 | AK44: =IFERROR((X44-AG44)/AG44, "NA") -> 0.044747916 | AL44: =IFERROR(AK44/AK148, "NA") -> 0.97238067
A45: Waste Costs
A46: 50700 - Waste Costs | B46: 0 | C46: =IFERROR(B46/B148, "NA") -> 0 | D46: 0 | E46: =IFERROR(D46/D148, "NA") -> 0 | F46: 0 | G46: =IFERROR(F46/F148, "NA") -> 0 | H46: 0 | I46: =IFERROR(H46/H148, "NA") -> 0 | J46: 0 | K46: =IFERROR(J46/J148, "NA") -> 0 | L46: 0 | M46: =IFERROR(L46/L148, "NA") -> 0 | N46: 0 | O46: =IFERROR(N46/N148, "NA") -> 0 | P46: 0 | Q46: =IFERROR(P46/P148, "NA") -> 0 | R46: 0 | S46: =IFERROR(R46/R148, "NA") -> 0 | T46: 0 | U46: =IFERROR(T46/T148, "NA") -> 0 | V46: 0 | W46: =IFERROR(V46/V148, "NA") -> 0 | X46: 0 | Y46: =IFERROR(X46/X148, "NA") -> 0 | Z46: 0 | AA46: =IFERROR(Z46/Z148, "NA") -> 0 | AB46: =IFERROR((R46+T46+V46+X46)/4, "NA") -> 0 | AC46: =IFERROR(AB46/AB148, "NA") -> 0 | AD46: =IFERROR(X46-AB46, "NA") -> 0 | AE46: =IFERROR(AD46/AD148, "NA") -> 0 | AF46: =IFERROR((X46-AB46)/AB46, "NA") -> NA | AG46: =IFERROR((J46+L46+N46+P46+R46+T46+V46+X46)/8, "NA") -> 0 | AH46: =IFERROR(AG46/AG148, "NA") -> 0 | AI46: =IFERROR(X46-AG46, "NA") -> 0 | AJ46: =IFERROR(AI46/AI148, "NA") -> 0 | AK46: =IFERROR((X46-AG46)/AG46, "NA") -> NA | AL46: =IFERROR(AK46/AK148, "NA") -> NA
A47: 50710 - Waste - Food | B47: 491.54 | C47: =IFERROR(B47/B148, "NA") -> 0.0024131257 | D47: 569.87 | E47: =IFERROR(D47/D148, "NA") -> 0.0030703509 | F47: 671.05 | G47: =IFERROR(F47/F148, "NA") -> 0.0047504975 | H47: 286.82 | I47: =IFERROR(H47/H148, "NA") -> 0.00384146 | J47: 377.48 | K47: =IFERROR(J47/J148, "NA") -> 0.0026508762 | L47: 407.42 | M47: =IFERROR(L47/L148, "NA") -> 0.0030147912 | N47: 331.61 | O47: =IFERROR(N47/N148, "NA") -> 0.002727114 | P47: 249.25 | Q47: =IFERROR(P47/P148, "NA") -> 0.0044027278 | R47: 357.17 | S47: =IFERROR(R47/R148, "NA") -> 0.0051401248 | T47: 371.8 | U47: =IFERROR(T47/T148, "NA") -> 0.0033645177 | V47: 181.36 | W47: =IFERROR(V47/V148, "NA") -> 0.0013428927 | X47: 214.59 | Y47: =IFERROR(X47/X148, "NA") -> 0.001850826 | Z47: 1124.92 | AA47: =IFERROR(Z47/Z148, "NA") -> 0.0026100996 | AB47: =IFERROR((R47+T47+V47+X47)/4, "NA") -> 281.23 | AC47: =IFERROR(AB47/AB148, "NA") -> 0.0026100996 | AD47: =IFERROR(X47-AB47, "NA") -> -66.64 | AE47: =IFERROR(AD47/AD148, "NA") -> -0.0081308129 | AF47: =IFERROR((X47-AB47)/AB47, "NA") -> -0.23695907 | AG47: =IFERROR((J47+L47+N47+P47+R47+T47+V47+X47)/8, "NA") -> 311.335 | AH47: =IFERROR(AG47/AG148, "NA") -> 0.002808818 | AI47: =IFERROR(X47-AG47, "NA") -> -96.745 | AJ47: =IFERROR(AI47/AI148, "NA") -> -0.018966521 | AK47: =IFERROR((X47-AG47)/AG47, "NA") -> -0.31074245 | AL47: =IFERROR(AK47/AK148, "NA") -> -6.7524921
A48: 50720 - Waste - N/A Beverage | B48: 0 | C48: =IFERROR(B48/B148, "NA") -> 0 | D48: 0 | E48: =IFERROR(D48/D148, "NA") -> 0 | F48: 0 | G48: =IFERROR(F48/F148, "NA") -> 0 | H48: 0 | I48: =IFERROR(H48/H148, "NA") -> 0 | J48: 0 | K48: =IFERROR(J48/J148, "NA") -> 0 | L48: 5.83 | M48: =IFERROR(L48/L148, "NA") -> 4.3140329e-05 | N48: 0 | O48: =IFERROR(N48/N148, "NA") -> 0 | P48: 0 | Q48: =IFERROR(P48/P148, "NA") -> 0 | R48: 3.5 | S48: =IFERROR(R48/R148, "NA") -> 5.0369395e-05 | T48: 0 | U48: =IFERROR(T48/T148, "NA") -> 0 | V48: 0 | W48: =IFERROR(V48/V148, "NA") -> 0 | X48: 0 | Y48: =IFERROR(X48/X148, "NA") -> 0 | Z48: 3.5 | AA48: =IFERROR(Z48/Z148, "NA") -> 8.1208872e-06 | AB48: =IFERROR((R48+T48+V48+X48)/4, "NA") -> 0.875 | AC48: =IFERROR(AB48/AB148, "NA") -> 8.1208872e-06 | AD48: =IFERROR(X48-AB48, "NA") -> -0.875 | AE48: =IFERROR(AD48/AD148, "NA") -> -0.00010675962 | AF48: =IFERROR((X48-AB48)/AB48, "NA") -> -1 | AG48: =IFERROR((J48+L48+N48+P48+R48+T48+V48+X48)/8, "NA") -> 1.16625 | AH48: =IFERROR(AG48/AG148, "NA") -> 1.0521734e-05 | AI48: =IFERROR(X48-AG48, "NA") -> -1.16625 | AJ48: =IFERROR(AI48/AI148, "NA") -> -0.00022863926 | AK48: =IFERROR((X48-AG48)/AG48, "NA") -> -1 | AL48: =IFERROR(AK48/AK148, "NA") -> -21.730189
A49: 50730 - Waste - Beer | B49: 0 | C49: =IFERROR(B49/B148, "NA") -> 0 | D49: 0 | E49: =IFERROR(D49/D148, "NA") -> 0 | F49: 0 | G49: =IFERROR(F49/F148, "NA") -> 0 | H49: 0 | I49: =IFERROR(H49/H148, "NA") -> 0 | J49: 0 | K49: =IFERROR(J49/J148, "NA") -> 0 | L49: 0 | M49: =IFERROR(L49/L148, "NA") -> 0 | N49: 0 | O49: =IFERROR(N49/N148, "NA") -> 0 | P49: 1.4 | Q49: =IFERROR(P49/P148, "NA") -> 2.4729464e-05 | R49: 0 | S49: =IFERROR(R49/R148, "NA") -> 0 | T49: 0 | U49: =IFERROR(T49/T148, "NA") -> 0 | V49: 0 | W49: =IFERROR(V49/V148, "NA") -> 0 | X49: 0 | Y49: =IFERROR(X49/X148, "NA") -> 0 | Z49: 0 | AA49: =IFERROR(Z49/Z148, "NA") -> 0 | AB49: =IFERROR((R49+T49+V49+X49)/4, "NA") -> 0 | AC49: =IFERROR(AB49/AB148, "NA") -> 0 | AD49: =IFERROR(X49-AB49, "NA") -> 0 | AE49: =IFERROR(AD49/AD148, "NA") -> 0 | AF49: =IFERROR((X49-AB49)/AB49, "NA") -> NA | AG49: =IFERROR((J49+L49+N49+P49+R49+T49+V49+X49)/8, "NA") -> 0.175 | AH49: =IFERROR(AG49/AG148, "NA") -> 1.5788239e-06 | AI49: =IFERROR(X49-AG49, "NA") -> -0.175 | AJ49: =IFERROR(AI49/AI148, "NA") -> -3.4308142e-05 | AK49: =IFERROR((X49-AG49)/AG49, "NA") -> -1 | AL49: =IFERROR(AK49/AK148, "NA") -> -21.730189
A50: 50740 - Waste - Liquor | B50: 0 | C50: =IFERROR(B50/B148, "NA") -> 0 | D50: 0 | E50: =IFERROR(D50/D148, "NA") -> 0 | F50: 0 | G50: =IFERROR(F50/F148, "NA") -> 0 | H50: 0 | I50: =IFERROR(H50/H148, "NA") -> 0 | J50: 0 | K50: =IFERROR(J50/J148, "NA") -> 0 | L50: 0 | M50: =IFERROR(L50/L148, "NA") -> 0 | N50: 0 | O50: =IFERROR(N50/N148, "NA") -> 0 | P50: 0 | Q50: =IFERROR(P50/P148, "NA") -> 0 | R50: 0 | S50: =IFERROR(R50/R148, "NA") -> 0 | T50: 0 | U50: =IFERROR(T50/T148, "NA") -> 0 | V50: 0 | W50: =IFERROR(V50/V148, "NA") -> 0 | X50: 0 | Y50: =IFERROR(X50/X148, "NA") -> 0 | Z50: 0 | AA50: =IFERROR(Z50/Z148, "NA") -> 0 | AB50: =IFERROR((R50+T50+V50+X50)/4, "NA") -> 0 | AC50: =IFERROR(AB50/AB148, "NA") -> 0 | AD50: =IFERROR(X50-AB50, "NA") -> 0 | AE50: =IFERROR(AD50/AD148, "NA") -> 0 | AF50: =IFERROR((X50-AB50)/AB50, "NA") -> NA | AG50: =IFERROR((J50+L50+N50+P50+R50+T50+V50+X50)/8, "NA") -> 0 | AH50: =IFERROR(AG50/AG148, "NA") -> 0 | AI50: =IFERROR(X50-AG50, "NA") -> 0 | AJ50: =IFERROR(AI50/AI148, "NA") -> 0 | AK50: =IFERROR((X50-AG50)/AG50, "NA") -> NA | AL50: =IFERROR(AK50/AK148, "NA") -> NA
A51: 50750 - Waste - Wine | B51: 0 | C51: =IFERROR(B51/B148, "NA") -> 0 | D51: 0 | E51: =IFERROR(D51/D148, "NA") -> 0 | F51: 0 | G51: =IFERROR(F51/F148, "NA") -> 0 | H51: 0 | I51: =IFERROR(H51/H148, "NA") -> 0 | J51: 0 | K51: =IFERROR(J51/J148, "NA") -> 0 | L51: 0 | M51: =IFERROR(L51/L148, "NA") -> 0 | N51: 0 | O51: =IFERROR(N51/N148, "NA") -> 0 | P51: 0 | Q51: =IFERROR(P51/P148, "NA") -> 0 | R51: 0 | S51: =IFERROR(R51/R148, "NA") -> 0 | T51: 0 | U51: =IFERROR(T51/T148, "NA") -> 0 | V51: 0 | W51: =IFERROR(V51/V148, "NA") -> 0 | X51: 0 | Y51: =IFERROR(X51/X148, "NA") -> 0 | Z51: 0 | AA51: =IFERROR(Z51/Z148, "NA") -> 0 | AB51: =IFERROR((R51+T51+V51+X51)/4, "NA") -> 0 | AC51: =IFERROR(AB51/AB148, "NA") -> 0 | AD51: =IFERROR(X51-AB51, "NA") -> 0 | AE51: =IFERROR(AD51/AD148, "NA") -> 0 | AF51: =IFERROR((X51-AB51)/AB51, "NA") -> NA | AG51: =IFERROR((J51+L51+N51+P51+R51+T51+V51+X51)/8, "NA") -> 0 | AH51: =IFERROR(AG51/AG148, "NA") -> 0 | AI51: =IFERROR(X51-AG51, "NA") -> 0 | AJ51: =IFERROR(AI51/AI148, "NA") -> 0 | AK51: =IFERROR((X51-AG51)/AG51, "NA") -> NA | AL51: =IFERROR(AK51/AK148, "NA") -> NA
A52: Total Waste Costs | B52: =IFERROR(B46+B47+B48+B49+B50+B51, "NA") -> 491.54 | C52: =IFERROR(B52/B148, "NA") -> 0.0024131257 | D52: =IFERROR(D46+D47+D48+D49+D50+D51, "NA") -> 569.87 | E52: =IFERROR(D52/D148, "NA") -> 0.0030703509 | F52: =IFERROR(F46+F47+F48+F49+F50+F51, "NA") -> 671.05 | G52: =IFERROR(F52/F148, "NA") -> 0.0047504975 | H52: =IFERROR(H46+H47+H48+H49+H50+H51, "NA") -> 286.82 | I52: =IFERROR(H52/H148, "NA") -> 0.00384146 | J52: =IFERROR(J46+J47+J48+J49+J50+J51, "NA") -> 377.48 | K52: =IFERROR(J52/J148, "NA") -> 0.0026508762 | L52: =IFERROR(L46+L47+L48+L49+L50+L51, "NA") -> 413.25 | M52: =IFERROR(L52/L148, "NA") -> 0.0030579315 | N52: =IFERROR(N46+N47+N48+N49+N50+N51, "NA") -> 331.61 | O52: =IFERROR(N52/N148, "NA") -> 0.002727114 | P52: =IFERROR(P46+P47+P48+P49+P50+P51, "NA") -> 250.65 | Q52: =IFERROR(P52/P148, "NA") -> 0.0044274573 | R52: =IFERROR(R46+R47+R48+R49+R50+R51, "NA") -> 360.67 | S52: =IFERROR(R52/R148, "NA") -> 0.0051904942 | T52: =IFERROR(T46+T47+T48+T49+T50+T51, "NA") -> 371.8 | U52: =IFERROR(T52/T148, "NA") -> 0.0033645177 | V52: =IFERROR(V46+V47+V48+V49+V50+V51, "NA") -> 181.36 | W52: =IFERROR(V52/V148, "NA") -> 0.0013428927 | X52: =IFERROR(X46+X47+X48+X49+X50+X51, "NA") -> 214.59 | Y52: =IFERROR(X52/X148, "NA") -> 0.001850826 | Z52: =IFERROR(Z46+Z47+Z48+Z49+Z50+Z51, "NA") -> 1128.42 | AA52: =IFERROR(Z52/Z148, "NA") -> 0.0026182205 | AB52: =IFERROR((R52+T52+V52+X52)/4, "NA") -> 282.105 | AC52: =IFERROR(AB52/AB148, "NA") -> 0.0026182205 | AD52: =IFERROR(X52-AB52, "NA") -> -67.515 | AE52: =IFERROR(AD52/AD148, "NA") -> -0.0082375725 | AF52: =IFERROR((X52-AB52)/AB52, "NA") -> -0.23932578 | AG52: =IFERROR((J52+L52+N52+P52+R52+T52+V52+X52)/8, "NA") -> 312.67625 | AH52: =IFERROR(AG52/AG148, "NA") -> 0.0028209185 | AI52: =IFERROR(X52-AG52, "NA") -> -98.08625 | AJ52: =IFERROR(AI52/AI148, "NA") -> -0.019229469 | AK52: =IFERROR((X52-AG52)/AG52, "NA") -> -0.31369907 | AL52: =IFERROR(AK52/AK148, "NA") -> -6.8167402
A53: 50800 - COGS - Freight, Delivery, & Sales Tax | B53: 267.71 | C53: =IFERROR(B53/B148, "NA") -> 0.0013142733 | D53: 189.62 | E53: =IFERROR(D53/D148, "NA") -> 0.0010216364 | F53: 211.77 | G53: =IFERROR(F53/F148, "NA") -> 0.0014991623 | H53: 140.72 | I53: =IFERROR(H53/H148, "NA") -> 0.0018847021 | J53: 180.15 | K53: =IFERROR(J53/J148, "NA") -> 0.0012651143 | L53: 208.72 | M53: =IFERROR(L53/L148, "NA") -> 0.0015444682 | N53: 223.36 | O53: =IFERROR(N53/N148, "NA") -> 0.0018368812 | P53: 44.13 | Q53: =IFERROR(P53/P148, "NA") -> 0.00077950804 | R53: 163.74 | S53: =IFERROR(R53/R148, "NA") -> 0.0023564242 | T53: 183.45 | U53: =IFERROR(T53/T148, "NA") -> 0.0016600882 | V53: 234.19 | W53: =IFERROR(V53/V148, "NA") -> 0.0017340761 | X53: 143.35 | Y53: =IFERROR(X53/X148, "NA") -> 0.0012363852 | Z53: 724.73 | AA53: =IFERROR(Z53/Z148, "NA") -> 0.0016815573 | AB53: =IFERROR((R53+T53+V53+X53)/4, "NA") -> 181.1825 | AC53: =IFERROR(AB53/AB148, "NA") -> 0.0016815573 | AD53: =IFERROR(X53-AB53, "NA") -> -37.8325 | AE53: =IFERROR(AD53/AD148, "NA") -> -0.0046159811 | AF53: =IFERROR((X53-AB53)/AB53, "NA") -> -0.2088088 | AG53: =IFERROR((J53+L53+N53+P53+R53+T53+V53+X53)/8, "NA") -> 172.63625 | AH53: =IFERROR(AG53/AG148, "NA") -> 0.0015574985 | AI53: =IFERROR(X53-AG53, "NA") -> -29.28625 | AJ53: =IFERROR(AI53/AI148, "NA") -> -0.0057414676 | AK53: =IFERROR((X53-AG53)/AG53, "NA") -> -0.16964137 | AL53: =IFERROR(AK53/AK148, "NA") -> -3.686339
A54: 50850 - COGS - Fuel Surcharge | B54: 60.62 | C54: =IFERROR(B54/B148, "NA") -> 0.0002976028 | D54: 42 | E54: =IFERROR(D54/D148, "NA") -> 0.00022628799 | F54: 30.31 | G54: =IFERROR(F54/F148, "NA") -> 0.00021457057 | H54: 36.62 | I54: =IFERROR(H54/H148, "NA") -> 0.00049046184 | J54: 51.93 | K54: =IFERROR(J54/J148, "NA") -> 0.00036468158 | L54: 51 | M54: =IFERROR(L54/L148, "NA") -> 0.00037738538 | N54: 39 | O54: =IFERROR(N54/N148, "NA") -> 0.00032073052 | P54: 15 | Q54: =IFERROR(P54/P148, "NA") -> 0.00026495854 | R54: 27 | S54: =IFERROR(R54/R148, "NA") -> 0.0003885639 | T54: 33.31 | U54: =IFERROR(T54/T148, "NA") -> 0.00030143111 | V54: 42.31 | W54: =IFERROR(V54/V148, "NA") -> 0.00031328734 | X54: 48.93 | Y54: =IFERROR(X54/X148, "NA") -> 0.00042201833 | Z54: 151.55 | AA54: =IFERROR(Z54/Z148, "NA") -> 0.00035163442 | AB54: =IFERROR((R54+T54+V54+X54)/4, "NA") -> 37.8875 | AC54: =IFERROR(AB54/AB148, "NA") -> 0.00035163442 | AD54: =IFERROR(X54-AB54, "NA") -> 11.0425 | AE54: =IFERROR(AD54/AD148, "NA") -> 0.0013473064 | AF54: =IFERROR((X54-AB54)/AB54, "NA") -> 0.29145497 | AG54: =IFERROR((J54+L54+N54+P54+R54+T54+V54+X54)/8, "NA") -> 38.56 | AH54: =IFERROR(AG54/AG148, "NA") -> 0.00034788257 | AI54: =IFERROR(X54-AG54, "NA") -> 10.37 | AJ54: =IFERROR(AI54/AI148, "NA") -> 0.0020330025 | AK54: =IFERROR((X54-AG54)/AG54, "NA") -> 0.26893154 | AL54: =IFERROR(AK54/AK148, "NA") -> 5.8439331
A55: 50900 - COGS - Credit for Discounts | B55: -1518.21 | C55: =IFERROR(B55/B148, "NA") -> -0.0074533743 | D55: -1428.82 | E55: =IFERROR(D55/D148, "NA") -> -0.0076982098 | F55: -1482.31 | G55: =IFERROR(F55/F148, "NA") -> -0.01049357 | H55: -994.81 | I55: =IFERROR(H55/H148, "NA") -> -0.013323767 | J55: -2832.96 | K55: =IFERROR(J55/J148, "NA") -> -0.019894634 | L55: -2176.7 | M55: =IFERROR(L55/L148, "NA") -> -0.016106956 | N55: -1715.9 | O55: =IFERROR(N55/N148, "NA") -> -0.01411132 | P55: -904.17 | Q55: =IFERROR(P55/P148, "NA") -> -0.015971171 | R55: -1132.04 | S55: =IFERROR(R55/R148, "NA") -> -0.016291477 | T55: -1919.55 | U55: =IFERROR(T55/T148, "NA") -> -0.017370522 | V55: -1227.99 | W55: =IFERROR(V55/V148, "NA") -> -0.0090927373 | X55: -1028.45 | Y55: =IFERROR(X55/X148, "NA") -> -0.00887032 | Z55: -5308.03 | AA55: =IFERROR(Z55/Z148, "NA") -> -0.012315975 | AB55: =IFERROR((R55+T55+V55+X55)/4, "NA") -> -1327.0075 | AC55: =IFERROR(AB55/AB148, "NA") -> -0.012315975 | AD55: =IFERROR(X55-AB55, "NA") -> 298.5575 | AE55: =IFERROR(AD55/AD148, "NA") -> 0.036427298 | AF55: =IFERROR((X55-AB55)/AB55, "NA") -> -0.22498554 | AG55: =IFERROR((J55+L55+N55+P55+R55+T55+V55+X55)/8, "NA") -> -1617.22 | AH55: =IFERROR(AG55/AG148, "NA") -> -0.014590318 | AI55: =IFERROR(X55-AG55, "NA") -> 588.77 | AJ55: =IFERROR(AI55/AI148, "NA") -> 0.11542631 | AK55: =IFERROR((X55-AG55)/AG55, "NA") -> -0.36406302 | AL55: =IFERROR(AK55/AK148, "NA") -> -7.9111583
A56: Total Other Costs | B56: =IFERROR(B37+B39+B40+B41+B42+B43+B46+B47+B48+B49+B50+B51+B53+B54+B55, "NA") -> 7498.94 | C56: =IFERROR(B56/B148, "NA") -> 0.036814674 | D56: =IFERROR(D37+D39+D40+D41+D42+D43+D46+D47+D48+D49+D50+D51+D53+D54+D55, "NA") -> 5795.49 | E56: =IFERROR(D56/D148, "NA") -> 0.031224996 | F56: =IFERROR(F37+F39+F40+F41+F42+F43+F46+F47+F48+F49+F50+F51+F53+F54+F55, "NA") -> 4935.82 | G56: =IFERROR(F56/F148, "NA") -> 0.034941659 | H56: =IFERROR(H37+H39+H40+H41+H42+H43+H46+H47+H48+H49+H50+H51+H53+H54+H55, "NA") -> 2664.82 | I56: =IFERROR(H56/H148, "NA") -> 0.035690675 | J56: =IFERROR(J37+J39+J40+J41+J42+J43+J46+J47+J48+J49+J50+J51+J53+J54+J55, "NA") -> 4513.66 | K56: =IFERROR(J56/J148, "NA") -> 0.031697451 | L56: =IFERROR(L37+L39+L40+L41+L42+L43+L46+L47+L48+L49+L50+L51+L53+L54+L55, "NA") -> 4406.95 | M56: =IFERROR(L56/L148, "NA") -> 0.032610167 | N56: =IFERROR(N37+N39+N40+N41+N42+N43+N46+N47+N48+N49+N50+N51+N53+N54+N55, "NA") -> 4981.07 | O56: =IFERROR(N56/N148, "NA") -> 0.040963619 | P56: =IFERROR(P37+P39+P40+P41+P42+P43+P46+P47+P48+P49+P50+P51+P53+P54+P55, "NA") -> 1426.54 | Q56: =IFERROR(P56/P148, "NA") -> 0.025198264 | R56: =IFERROR(R37+R39+R40+R41+R42+R43+R46+R47+R48+R49+R50+R51+R53+R54+R55, "NA") -> 2386.62 | S56: =IFERROR(R56/R148, "NA") -> 0.034346459 | T56: =IFERROR(T37+T39+T40+T41+T42+T43+T46+T47+T48+T49+T50+T51+T53+T54+T55, "NA") -> 3673.31 | U56: =IFERROR(T56/T148, "NA") -> 0.033240765 | V56: =IFERROR(V37+V39+V40+V41+V42+V43+V46+V47+V48+V49+V50+V51+V53+V54+V55, "NA") -> 4717.41 | W56: =IFERROR(V56/V148, "NA") -> 0.03493039 | X56: =IFERROR(X37+X39+X40+X41+X42+X43+X46+X47+X48+X49+X50+X51+X53+X54+X55, "NA") -> 4520.22 | Y56: =IFERROR(X56/X148, "NA") -> 0.038986628 | Z56: =IFERROR(Z37+Z39+Z40+Z41+Z42+Z43+Z46+Z47+Z48+Z49+Z50+Z51+Z53+Z54+Z55, "NA") -> 15297.56 | AA56: =IFERROR(Z56/Z148, "NA") -> 0.035494217 | AB56: =IFERROR((R56+T56+V56+X56)/4, "NA") -> 3824.39 | AC56: =IFERROR(AB56/AB148, "NA") -> 0.035494217 | AD56: =IFERROR(X56-AB56, "NA") -> 695.83 | AE56: =IFERROR(AD56/AD148, "NA") -> 0.084898912 | AF56: =IFERROR((X56-AB56)/AB56, "NA") -> 0.18194536 | AG56: =IFERROR((J56+L56+N56+P56+R56+T56+V56+X56)/8, "NA") -> 3828.2225 | AH56: =IFERROR(AG56/AG148, "NA") -> 0.034537653 | AI56: =IFERROR(X56-AG56, "NA") -> 691.9975 | AJ56: =IFERROR(AI56/AI148, "NA") -> 0.13566371 | AK56: =IFERROR((X56-AG56)/AG56, "NA") -> 0.18076209 | AL56: =IFERROR(AK56/AK148, "NA") -> 3.9279944
A57: Total Cost of Goods Sold | B57: =IFERROR(B13+B15+B16+B17+B18+B19+B20+B21+B22+B23+B24+B25+B26+B29+B30+B31+B32+B33+B37+B39+B40+B41+B42+B43+B46+B47+B48+B49+B50+B51+B53+B54+B55, "NA") -> 51549.37 | C57: =IFERROR(B57/B148, "NA") -> 0.2530722 | D57: =IFERROR(D13+D15+D16+D17+D18+D19+D20+D21+D22+D23+D24+D25+D26+D29+D30+D31+D32+D33+D37+D39+D40+D41+D42+D43+D46+D47+D48+D49+D50+D51+D53+D54+D55, "NA") -> 47624.57 | E57: =IFERROR(D57/D148, "NA") -> 0.25659211 | F57: =IFERROR(F13+F15+F16+F17+F18+F19+F20+F21+F22+F23+F24+F25+F26+F29+F30+F31+F32+F33+F37+F39+F40+F41+F42+F43+F46+F47+F48+F49+F50+F51+F53+F54+F55, "NA") -> 35548.18 | G57: =IFERROR(F57/F148, "NA") -> 0.25165269 | H57: =IFERROR(H13+H15+H16+H17+H18+H19+H20+H21+H22+H23+H24+H25+H26+H29+H30+H31+H32+H33+H37+H39+H40+H41+H42+H43+H46+H47+H48+H49+H50+H51+H53+H54+H55, "NA") -> 23650.1 | I57: =IFERROR(H57/H148, "NA") -> 0.31675237 | J57: =IFERROR(J13+J15+J16+J17+J18+J19+J20+J21+J22+J23+J24+J25+J26+J29+J30+J31+J32+J33+J37+J39+J40+J41+J42+J43+J46+J47+J48+J49+J50+J51+J53+J54+J55, "NA") -> 37970.08 | K57: =IFERROR(J57/J148, "NA") -> 0.26664719 | L57: =IFERROR(L13+L15+L16+L17+L18+L19+L20+L21+L22+L23+L24+L25+L26+L29+L30+L31+L32+L33+L37+L39+L40+L41+L42+L43+L46+L47+L48+L49+L50+L51+L53+L54+L55, "NA") -> 38996.58 | M57: =IFERROR(L57/L148, "NA") -> 0.28856351 | N57: =IFERROR(N13+N15+N16+N17+N18+N19+N20+N21+N22+N23+N24+N25+N26+N29+N30+N31+N32+N33+N37+N39+N40+N41+N42+N43+N46+N47+N48+N49+N50+N51+N53+N54+N55, "NA") -> 34275.66 | O57: =IFERROR(N57/N148, "NA") -> 0.28187821 | P57: =IFERROR(P13+P15+P16+P17+P18+P19+P20+P21+P22+P23+P24+P25+P26+P29+P30+P31+P32+P33+P37+P39+P40+P41+P42+P43+P46+P47+P48+P49+P50+P51+P53+P54+P55, "NA") -> 16766 | Q57: =IFERROR(P57/P148, "NA") -> 0.296153 | R57: =IFERROR(R13+R15+R16+R17+R18+R19+R20+R21+R22+R23+R24+R25+R26+R29+R30+R31+R32+R33+R37+R39+R40+R41+R42+R43+R46+R47+R48+R49+R50+R51+R53+R54+R55, "NA") -> 21746.96 | S57: =IFERROR(R57/R148, "NA") -> 0.31296606 | T57: =IFERROR(T13+T15+T16+T17+T18+T19+T20+T21+T22+T23+T24+T25+T26+T29+T30+T31+T32+T33+T37+T39+T40+T41+T42+T43+T46+T47+T48+T49+T50+T51+T53+T54+T55, "NA") -> 31422.94 | U57: =IFERROR(T57/T148, "NA") -> 0.28435459 | V57: =IFERROR(V13+V15+V16+V17+V18+V19+V20+V21+V22+V23+V24+V25+V26+V29+V30+V31+V32+V33+V37+V39+V40+V41+V42+V43+V46+V47+V48+V49+V50+V51+V53+V54+V55, "NA") -> 37254.82 | W57: =IFERROR(V57/V148, "NA") -> 0.27585591 | X57: =IFERROR(X13+X15+X16+X17+X18+X19+X20+X21+X22+X23+X24+X25+X26+X29+X30+X31+X32+X33+X37+X39+X40+X41+X42+X43+X46+X47+X48+X49+X50+X51+X53+X54+X55, "NA") -> 31329.15 | Y57: =IFERROR(X57/X148, "NA") -> 0.27021205 | Z57: =IFERROR(Z13+Z15+Z16+Z17+Z18+Z19+Z20+Z21+Z22+Z23+Z24+Z25+Z26+Z29+Z30+Z31+Z32+Z33+Z37+Z39+Z40+Z41+Z42+Z43+Z46+Z47+Z48+Z49+Z50+Z51+Z53+Z54+Z55, "NA") -> 121753.87 | AA57: =IFERROR(Z57/Z148, "NA") -> 0.28249984 | AB57: =IFERROR((R57+T57+V57+X57)/4, "NA") -> 30438.467 | AC57: =IFERROR(AB57/AB148, "NA") -> 0.28249984 | AD57: =IFERROR(X57-AB57, "NA") -> 890.6825 | AE57: =IFERROR(AD57/AD148, "NA") -> 0.10867306 | AF57: =IFERROR((X57-AB57)/AB57, "NA") -> 0.029261739 | AG57: =IFERROR((J57+L57+N57+P57+R57+T57+V57+X57)/8, "NA") -> 31220.274 | AH57: =IFERROR(AG57/AG148, "NA") -> 0.28166466 | AI57: =IFERROR(X57-AG57, "NA") -> 108.87625 | AJ57: =IFERROR(AI57/AI148, "NA") -> 0.021344811 | AK57: =IFERROR((X57-AG57)/AG57, "NA") -> 0.0034873573 | AL57: =IFERROR(AK57/AK148, "NA") -> 0.075780934
A59: Gross Profit | B59: =IFERROR(B9-B57, "NA") -> 152144.95 | C59: =IFERROR(B59/B148, "NA") -> 0.7469278 | D59: =IFERROR(D9-D57, "NA") -> 137979.62 | E59: =IFERROR(D59/D148, "NA") -> 0.74340789 | F59: =IFERROR(F9-F57, "NA") -> 105710.71 | G59: =IFERROR(F59/F148, "NA") -> 0.74834731 | H59: =IFERROR(H9-H57, "NA") -> 51014.22 | I59: =IFERROR(H59/H148, "NA") -> 0.68324763 | J59: =IFERROR(J9-J57, "NA") -> 104428.12 | K59: =IFERROR(J59/J148, "NA") -> 0.73335281 | L59: =IFERROR(L9-L57, "NA") -> 96143.79 | M59: =IFERROR(L59/L148, "NA") -> 0.71143649 | N59: =IFERROR(N9-N57, "NA") -> 87321.75 | O59: =IFERROR(N59/N148, "NA") -> 0.71812179 | P59: =IFERROR(P9-P57, "NA") -> 39846.63 | Q59: =IFERROR(P59/P148, "NA") -> 0.703847 | R59: =IFERROR(R9-R57, "NA") -> 47739.68 | S59: =IFERROR(R59/R148, "NA") -> 0.68703394 | T59: =IFERROR(T9-T57, "NA") -> 79083.24 | U59: =IFERROR(T59/T148, "NA") -> 0.71564541 | V59: =IFERROR(V9-V57, "NA") -> 97796.92 | W59: =IFERROR(V59/V148, "NA") -> 0.72414409 | X59: =IFERROR(X9-X57, "NA") -> 84613.68 | Y59: =IFERROR(X59/X148, "NA") -> 0.72978795 | Z59: =IFERROR(Z9-Z57, "NA") -> 309233.52 | AA59: =IFERROR(Z59/Z148, "NA") -> 0.71750016 | AB59: =IFERROR((R59+T59+V59+X59)/4, "NA") -> 77308.38 | AC59: =IFERROR(AB59/AB148, "NA") -> 0.71750016 | AD59: =IFERROR(X59-AB59, "NA") -> 7305.3 | AE59: =IFERROR(AD59/AD148, "NA") -> 0.89132694 | AF59: =IFERROR((X59-AB59)/AB59, "NA") -> 0.094495577 | AG59: =IFERROR((J59+L59+N59+P59+R59+T59+V59+X59)/8, "NA") -> 79621.726 | AH59: =IFERROR(AG59/AG148, "NA") -> 0.71833534 | AI59: =IFERROR(X59-AG59, "NA") -> 4991.9537 | AJ59: =IFERROR(AI59/AI148, "NA") -> 0.97865519 | AK59: =IFERROR((X59-AG59)/AG59, "NA") -> 0.062695874 | AL59: =IFERROR(AK59/AK148, "NA") -> 1.3623932
A61: Payroll Expenses
A62: Payroll Expenses
A63: 61000 - Payroll Expenses | B63: 0 | C63: =IFERROR(B63/B148, "NA") -> 0 | D63: 0 | E63: =IFERROR(D63/D148, "NA") -> 0 | F63: 0 | G63: =IFERROR(F63/F148, "NA") -> 0 | H63: 0 | I63: =IFERROR(H63/H148, "NA") -> 0 | J63: 0 | K63: =IFERROR(J63/J148, "NA") -> 0 | L63: 0 | M63: =IFERROR(L63/L148, "NA") -> 0 | N63: 0 | O63: =IFERROR(N63/N148, "NA") -> 0 | P63: 0 | Q63: =IFERROR(P63/P148, "NA") -> 0 | R63: 0 | S63: =IFERROR(R63/R148, "NA") -> 0 | T63: 0 | U63: =IFERROR(T63/T148, "NA") -> 0 | V63: 0 | W63: =IFERROR(V63/V148, "NA") -> 0 | X63: 0 | Y63: =IFERROR(X63/X148, "NA") -> 0 | Z63: 0 | AA63: =IFERROR(Z63/Z148, "NA") -> 0 | AB63: =IFERROR((R63+T63+V63+X63)/4, "NA") -> 0 | AC63: =IFERROR(AB63/AB148, "NA") -> 0 | AD63: =IFERROR(X63-AB63, "NA") -> 0 | AE63: =IFERROR(AD63/AD148, "NA") -> 0 | AF63: =IFERROR((X63-AB63)/AB63, "NA") -> NA | AG63: =IFERROR((J63+L63+N63+P63+R63+T63+V63+X63)/8, "NA") -> 0 | AH63: =IFERROR(AG63/AG148, "NA") -> 0 | AI63: =IFERROR(X63-AG63, "NA") -> 0 | AJ63: =IFERROR(AI63/AI148, "NA") -> 0 | AK63: =IFERROR((X63-AG63)/AG63, "NA") -> NA | AL63: =IFERROR(AK63/AK148, "NA") -> NA
A64: Salaries & Wages
A65: 61100 - Salaries & Wages | B65: 0 | C65: =IFERROR(B65/B148, "NA") -> 0 | D65: 0 | E65: =IFERROR(D65/D148, "NA") -> 0 | F65: 0 | G65: =IFERROR(F65/F148, "NA") -> 0 | H65: 0 | I65: =IFERROR(H65/H148, "NA") -> 0 | J65: 0 | K65: =IFERROR(J65/J148, "NA") -> 0 | L65: 0 | M65: =IFERROR(L65/L148, "NA") -> 0 | N65: 0 | O65: =IFERROR(N65/N148, "NA") -> 0 | P65: 0 | Q65: =IFERROR(P65/P148, "NA") -> 0 | R65: 0 | S65: =IFERROR(R65/R148, "NA") -> 0 | T65: 0 | U65: =IFERROR(T65/T148, "NA") -> 0 | V65: 0 | W65: =IFERROR(V65/V148, "NA") -> 0 | X65: 0 | Y65: =IFERROR(X65/X148, "NA") -> 0 | Z65: 0 | AA65: =IFERROR(Z65/Z148, "NA") -> 0 | AB65: =IFERROR((R65+T65+V65+X65)/4, "NA") -> 0 | AC65: =IFERROR(AB65/AB148, "NA") -> 0 | AD65: =IFERROR(X65-AB65, "NA") -> 0 | AE65: =IFERROR(AD65/AD148, "NA") -> 0 | AF65: =IFERROR((X65-AB65)/AB65, "NA") -> NA | AG65: =IFERROR((J65+L65+N65+P65+R65+T65+V65+X65)/8, "NA") -> 0 | AH65: =IFERROR(AG65/AG148, "NA") -> 0 | AI65: =IFERROR(X65-AG65, "NA") -> 0 | AJ65: =IFERROR(AI65/AI148, "NA") -> 0 | AK65: =IFERROR((X65-AG65)/AG65, "NA") -> NA | AL65: =IFERROR(AK65/AK148, "NA") -> NA
A66: 61110 - Management | B66: 7958.08 | C66: =IFERROR(B66/B148, "NA") -> 0.039068738 | D66: 7958.08 | E66: =IFERROR(D66/D148, "NA") -> 0.042876618 | F66: 7958.08 | G66: =IFERROR(F66/F148, "NA") -> 0.056336844 | H66: 7958.08 | I66: =IFERROR(H66/H148, "NA") -> 0.10658478 | J66: 7958.08 | K66: =IFERROR(J66/J148, "NA") -> 0.0558861 | L66: 7958.08 | M66: =IFERROR(L66/L148, "NA") -> 0.058887511 | N66: 7958.08 | O66: =IFERROR(N66/N148, "NA") -> 0.065446131 | P66: 7958.08 | Q66: =IFERROR(P66/P148, "NA") -> 0.14057075 | R66: 7958.08 | S66: =IFERROR(R66/R148, "NA") -> 0.11452676 | T66: 7958.08 | U66: =IFERROR(T66/T148, "NA") -> 0.072014796 | V66: 7958.08 | W66: =IFERROR(V66/V148, "NA") -> 0.058926157 | X66: 7958.08 | Y66: =IFERROR(X66/X148, "NA") -> 0.068637966 | Z66: 31832.32 | AA66: =IFERROR(Z66/Z148, "NA") -> 0.073859052 | AB66: =IFERROR((R66+T66+V66+X66)/4, "NA") -> 7958.08 | AC66: =IFERROR(AB66/AB148, "NA") -> 0.073859052 | AD66: =IFERROR(X66-AB66, "NA") -> 0 | AE66: =IFERROR(AD66/AD148, "NA") -> 0 | AF66: =IFERROR((X66-AB66)/AB66, "NA") -> 0 | AG66: =IFERROR((J66+L66+N66+P66+R66+T66+V66+X66)/8, "NA") -> 7958.08 | AH66: =IFERROR(AG66/AG148, "NA") -> 0.071796611 | AI66: =IFERROR(X66-AG66, "NA") -> 0 | AJ66: =IFERROR(AI66/AI148, "NA") -> 0 | AK66: =IFERROR((X66-AG66)/AG66, "NA") -> 0 | AL66: =IFERROR(AK66/AK148, "NA") -> 0
A67: 61120 - Culinary | B67: 0 | C67: =IFERROR(B67/B148, "NA") -> 0 | D67: 0 | E67: =IFERROR(D67/D148, "NA") -> 0 | F67: 0 | G67: =IFERROR(F67/F148, "NA") -> 0 | H67: 0 | I67: =IFERROR(H67/H148, "NA") -> 0 | J67: 0 | K67: =IFERROR(J67/J148, "NA") -> 0 | L67: 0 | M67: =IFERROR(L67/L148, "NA") -> 0 | N67: 0 | O67: =IFERROR(N67/N148, "NA") -> 0 | P67: 0 | Q67: =IFERROR(P67/P148, "NA") -> 0 | R67: 0 | S67: =IFERROR(R67/R148, "NA") -> 0 | T67: 0 | U67: =IFERROR(T67/T148, "NA") -> 0 | V67: 0 | W67: =IFERROR(V67/V148, "NA") -> 0 | X67: 0 | Y67: =IFERROR(X67/X148, "NA") -> 0 | Z67: 0 | AA67: =IFERROR(Z67/Z148, "NA") -> 0 | AB67: =IFERROR((R67+T67+V67+X67)/4, "NA") -> 0 | AC67: =IFERROR(AB67/AB148, "NA") -> 0 | AD67: =IFERROR(X67-AB67, "NA") -> 0 | AE67: =IFERROR(AD67/AD148, "NA") -> 0 | AF67: =IFERROR((X67-AB67)/AB67, "NA") -> NA | AG67: =IFERROR((J67+L67+N67+P67+R67+T67+V67+X67)/8, "NA") -> 0 | AH67: =IFERROR(AG67/AG148, "NA") -> 0 | AI67: =IFERROR(X67-AG67, "NA") -> 0 | AJ67: =IFERROR(AI67/AI148, "NA") -> 0 | AK67: =IFERROR((X67-AG67)/AG67, "NA") -> NA | AL67: =IFERROR(AK67/AK148, "NA") -> NA
A68: 61150 - Hourly | B68: 29406.27 | C68: =IFERROR(B68/B148, "NA") -> 0.1443647 | D68: 28064.66 | E68: =IFERROR(D68/D148, "NA") -> 0.15120704 | F68: 26735.3 | G68: =IFERROR(F68/F148, "NA") -> 0.18926455 | H68: 16782.3 | I68: =IFERROR(H68/H148, "NA") -> 0.22477001 | J68: 26541.67 | K68: =IFERROR(J68/J148, "NA") -> 0.18639049 | L68: 25988.08 | M68: =IFERROR(L68/L148, "NA") -> 0.19230434 | N68: 24937.08 | O68: =IFERROR(N68/N148, "NA") -> 0.20507904 | P68: 14320.07 | Q68: =IFERROR(P68/P148, "NA") -> 0.25294833 | R68: 17605.45 | S68: =IFERROR(R68/R148, "NA") -> 0.25336453 | T68: 24137.86 | U68: =IFERROR(T68/T148, "NA") -> 0.21842996 | V68: 22759.54 | W68: =IFERROR(V68/V148, "NA") -> 0.1685246 | X68: 20494.97 | Y68: =IFERROR(X68/X148, "NA") -> 0.1767679 | Z68: 84997.82 | AA68: =IFERROR(Z68/Z148, "NA") -> 0.19721649 | AB68: =IFERROR((R68+T68+V68+X68)/4, "NA") -> 21249.455 | AC68: =IFERROR(AB68/AB148, "NA") -> 0.19721649 | AD68: =IFERROR(X68-AB68, "NA") -> -754.485 | AE68: =IFERROR(AD68/AD148, "NA") -> -0.092055467 | AF68: =IFERROR((X68-AB68)/AB68, "NA") -> -0.035506087 | AG68: =IFERROR((J68+L68+N68+P68+R68+T68+V68+X68)/8, "NA") -> 22098.09 | AH68: =IFERROR(AG68/AG148, "NA") -> 0.19936567 | AI68: =IFERROR(X68-AG68, "NA") -> -1603.12 | AJ68: =IFERROR(AI68/AI148, "NA") -> -0.31428611 | AK68: =IFERROR((X68-AG68)/AG68, "NA") -> -0.072545636 | AL68: =IFERROR(AK68/AK148, "NA") -> -1.5764304
A69: 61200 - Overtime | B69: 3259.94 | C69: =IFERROR(B69/B148, "NA") -> 0.016004079 | D69: 2834.35 | E69: =IFERROR(D69/D148, "NA") -> 0.015270938 | F69: 1103.4 | G69: =IFERROR(F69/F148, "NA") -> 0.0078111898 | H69: 0 | I69: =IFERROR(H69/H148, "NA") -> 0 | J69: 540.95 | K69: =IFERROR(J69/J148, "NA") -> 0.0037988542 | L69: 426.26 | M69: =IFERROR(L69/L148, "NA") -> 0.0031542018 | N69: 236.4 | O69: =IFERROR(N69/N148, "NA") -> 0.0019441204 | P69: 0 | Q69: =IFERROR(P69/P148, "NA") -> 0 | R69: 0 | S69: =IFERROR(R69/R148, "NA") -> 0 | T69: 0 | U69: =IFERROR(T69/T148, "NA") -> 0 | V69: 0 | W69: =IFERROR(V69/V148, "NA") -> 0 | X69: 211.09 | Y69: =IFERROR(X69/X148, "NA") -> 0.0018206387 | Z69: 211.09 | AA69: =IFERROR(Z69/Z148, "NA") -> 0.00048978231 | AB69: =IFERROR((R69+T69+V69+X69)/4, "NA") -> 52.7725 | AC69: =IFERROR(AB69/AB148, "NA") -> 0.00048978231 | AD69: =IFERROR(X69-AB69, "NA") -> 158.3175 | AE69: =IFERROR(AD69/AD148, "NA") -> 0.019316476 | AF69: =IFERROR((X69-AB69)/AB69, "NA") -> 3 | AG69: =IFERROR((J69+L69+N69+P69+R69+T69+V69+X69)/8, "NA") -> 176.8375 | AH69: =IFERROR(AG69/AG148, "NA") -> 0.0015954016 | AI69: =IFERROR(X69-AG69, "NA") -> 34.2525 | AJ69: =IFERROR(AI69/AI148, "NA") -> 0.0067150836 | AK69: =IFERROR((X69-AG69)/AG69, "NA") -> 0.19369478 | AL69: =IFERROR(AK69/AK148, "NA") -> 4.2090241
A70: Total Salaries & Wages | B70: =IFERROR(B65+B66+B67+B68+B69, "NA") -> 40624.29 | C70: =IFERROR(B70/B148, "NA") -> 0.19943752 | D70: =IFERROR(D65+D66+D67+D68+D69, "NA") -> 38857.09 | E70: =IFERROR(D70/D148, "NA") -> 0.20935459 | F70: =IFERROR(F65+F66+F67+F68+F69, "NA") -> 35796.78 | G70: =IFERROR(F70/F148, "NA") -> 0.25341258 | H70: =IFERROR(H65+H66+H67+H68+H69, "NA") -> 24740.38 | I70: =IFERROR(H70/H148, "NA") -> 0.33135479 | J70: =IFERROR(J65+J66+J67+J68+J69, "NA") -> 35040.7 | K70: =IFERROR(J70/J148, "NA") -> 0.24607544 | L70: =IFERROR(L65+L66+L67+L68+L69, "NA") -> 34372.42 | M70: =IFERROR(L70/L148, "NA") -> 0.25434606 | N70: =IFERROR(N65+N66+N67+N68+N69, "NA") -> 33131.56 | O70: =IFERROR(N70/N148, "NA") -> 0.27246929 | P70: =IFERROR(P65+P66+P67+P68+P69, "NA") -> 22278.15 | Q70: =IFERROR(P70/P148, "NA") -> 0.39351908 | R70: =IFERROR(R65+R66+R67+R68+R69, "NA") -> 25563.53 | S70: =IFERROR(R70/R148, "NA") -> 0.3678913 | T70: =IFERROR(T65+T66+T67+T68+T69, "NA") -> 32095.94 | U70: =IFERROR(T70/T148, "NA") -> 0.29044475 | V70: =IFERROR(V65+V66+V67+V68+V69, "NA") -> 30717.62 | W70: =IFERROR(V70/V148, "NA") -> 0.22745075 | X70: =IFERROR(X65+X66+X67+X68+X69, "NA") -> 28664.14 | Y70: =IFERROR(X70/X148, "NA") -> 0.2472265 | Z70: =IFERROR(Z65+Z66+Z67+Z68+Z69, "NA") -> 117041.23 | AA70: =IFERROR(Z70/Z148, "NA") -> 0.27156532 | AB70: =IFERROR((R70+T70+V70+X70)/4, "NA") -> 29260.307 | AC70: =IFERROR(AB70/AB148, "NA") -> 0.27156532 | AD70: =IFERROR(X70-AB70, "NA") -> -596.1675 | AE70: =IFERROR(AD70/AD148, "NA") -> -0.072738991 | AF70: =IFERROR((X70-AB70)/AB70, "NA") -> -0.020374615 | AG70: =IFERROR((J70+L70+N70+P70+R70+T70+V70+X70)/8, "NA") -> 30233.007 | AH70: =IFERROR(AG70/AG148, "NA") -> 0.27275769 | AI70: =IFERROR(X70-AG70, "NA") -> -1568.8675 | AJ70: =IFERROR(AI70/AI148, "NA") -> -0.30757102 | AK70: =IFERROR((X70-AG70)/AG70, "NA") -> -0.051892538 | AL70: =IFERROR(AK70/AK148, "NA") -> -1.1276347
A71: 61105 - Salaries & Wages Adjustment | B71: 0 | C71: =IFERROR(B71/B148, "NA") -> 0 | D71: 0 | E71: =IFERROR(D71/D148, "NA") -> 0 | F71: 0 | G71: =IFERROR(F71/F148, "NA") -> 0 | H71: 0 | I71: =IFERROR(H71/H148, "NA") -> 0 | J71: 0 | K71: =IFERROR(J71/J148, "NA") -> 0 | L71: 0 | M71: =IFERROR(L71/L148, "NA") -> 0 | N71: 0 | O71: =IFERROR(N71/N148, "NA") -> 0 | P71: 0 | Q71: =IFERROR(P71/P148, "NA") -> 0 | R71: 0 | S71: =IFERROR(R71/R148, "NA") -> 0 | T71: 0 | U71: =IFERROR(T71/T148, "NA") -> 0 | V71: 0 | W71: =IFERROR(V71/V148, "NA") -> 0 | X71: 0 | Y71: =IFERROR(X71/X148, "NA") -> 0 | Z71: 0 | AA71: =IFERROR(Z71/Z148, "NA") -> 0 | AB71: =IFERROR((R71+T71+V71+X71)/4, "NA") -> 0 | AC71: =IFERROR(AB71/AB148, "NA") -> 0 | AD71: =IFERROR(X71-AB71, "NA") -> 0 | AE71: =IFERROR(AD71/AD148, "NA") -> 0 | AF71: =IFERROR((X71-AB71)/AB71, "NA") -> NA | AG71: =IFERROR((J71+L71+N71+P71+R71+T71+V71+X71)/8, "NA") -> 0 | AH71: =IFERROR(AG71/AG148, "NA") -> 0 | AI71: =IFERROR(X71-AG71, "NA") -> 0 | AJ71: =IFERROR(AI71/AI148, "NA") -> 0 | AK71: =IFERROR((X71-AG71)/AG71, "NA") -> NA | AL71: =IFERROR(AK71/AK148, "NA") -> NA
A72: 61250 - Bonus | B72: 0 | C72: =IFERROR(B72/B148, "NA") -> 0 | D72: 0 | E72: =IFERROR(D72/D148, "NA") -> 0 | F72: -3400 | G72: =IFERROR(F72/F148, "NA") -> -0.024069282 | H72: 0 | I72: =IFERROR(H72/H148, "NA") -> 0 | J72: 0 | K72: =IFERROR(J72/J148, "NA") -> 0 | L72: 0 | M72: =IFERROR(L72/L148, "NA") -> 0 | N72: 0 | O72: =IFERROR(N72/N148, "NA") -> 0 | P72: 2950 | Q72: =IFERROR(P72/P148, "NA") -> 0.052108514 | R72: 0 | S72: =IFERROR(R72/R148, "NA") -> 0 | T72: 0 | U72: =IFERROR(T72/T148, "NA") -> 0 | V72: 0 | W72: =IFERROR(V72/V148, "NA") -> 0 | X72: 2950 | Y72: =IFERROR(X72/X148, "NA") -> 0.025443574 | Z72: 2950 | AA72: =IFERROR(Z72/Z148, "NA") -> 0.0068447478 | AB72: =IFERROR((R72+T72+V72+X72)/4, "NA") -> 737.5 | AC72: =IFERROR(AB72/AB148, "NA") -> 0.0068447478 | AD72: =IFERROR(X72-AB72, "NA") -> 2212.5 | AE72: =IFERROR(AD72/AD148, "NA") -> 0.26994933 | AF72: =IFERROR((X72-AB72)/AB72, "NA") -> 3 | AG72: =IFERROR((J72+L72+N72+P72+R72+T72+V72+X72)/8, "NA") -> 737.5 | AH72: =IFERROR(AG72/AG148, "NA") -> 0.0066536151 | AI72: =IFERROR(X72-AG72, "NA") -> 2212.5 | AJ72: =IFERROR(AI72/AI148, "NA") -> 0.43375294 | AK72: =IFERROR((X72-AG72)/AG72, "NA") -> 3 | AL72: =IFERROR(AK72/AK148, "NA") -> 65.190567
A73: Payroll Taxes
A74: 61300 - Payroll Taxes | B74: 3753.42 | C74: =IFERROR(B74/B148, "NA") -> 0.018426729 | D74: 3471.16 | E74: =IFERROR(D74/D148, "NA") -> 0.018701948 | F74: 3504.27 | G74: =IFERROR(F74/F148, "NA") -> 0.02480743 | H74: 2200.35 | I74: =IFERROR(H74/H148, "NA") -> 0.029469899 | J74: 3111.96 | K74: =IFERROR(J74/J148, "NA") -> 0.021853928 | L74: 3148.4 | M74: =IFERROR(L74/L148, "NA") -> 0.023297258 | N74: 3000.89 | O74: =IFERROR(N74/N148, "NA") -> 0.024678897 | P74: 2326.41 | Q74: =IFERROR(P74/P148, "NA") -> 0.04109348 | R74: 2626.38 | S74: =IFERROR(R74/R148, "NA") -> 0.037796906 | T74: 3409.67 | U74: =IFERROR(T74/T148, "NA") -> 0.030855016 | V74: 3335.01 | W74: =IFERROR(V74/V148, "NA") -> 0.024694313 | X74: 3072.97 | Y74: =IFERROR(X74/X148, "NA") -> 0.026504183 | Z74: 12444.03 | AA74: =IFERROR(Z74/Z148, "NA") -> 0.028873304 | AB74: =IFERROR((R74+T74+V74+X74)/4, "NA") -> 3111.0075 | AC74: =IFERROR(AB74/AB148, "NA") -> 0.028873304 | AD74: =IFERROR(X74-AB74, "NA") -> -38.0375 | AE74: =IFERROR(AD74/AD148, "NA") -> -0.0046409933 | AF74: =IFERROR((X74-AB74)/AB74, "NA") -> -0.012226746 | AG74: =IFERROR((J74+L74+N74+P74+R74+T74+V74+X74)/8, "NA") -> 3003.9612 | AH74: =IFERROR(AG74/AG148, "NA") -> 0.027101291 | AI74: =IFERROR(X74-AG74, "NA") -> 69.00875 | AJ74: =IFERROR(AI74/AI148, "NA") -> 0.013528926 | AK74: =IFERROR((X74-AG74)/AG74, "NA") -> 0.022972583 | AL74: =IFERROR(AK74/AK148, "NA") -> 0.49919858
A75: 61310 - FICA Tax Expense | B75: 0 | C75: =IFERROR(B75/B148, "NA") -> 0 | D75: 0 | E75: =IFERROR(D75/D148, "NA") -> 0 | F75: 0 | G75: =IFERROR(F75/F148, "NA") -> 0 | H75: 0 | I75: =IFERROR(H75/H148, "NA") -> 0 | J75: 0 | K75: =IFERROR(J75/J148, "NA") -> 0 | L75: 0 | M75: =IFERROR(L75/L148, "NA") -> 0 | N75: 0 | O75: =IFERROR(N75/N148, "NA") -> 0 | P75: 0 | Q75: =IFERROR(P75/P148, "NA") -> 0 | R75: 0 | S75: =IFERROR(R75/R148, "NA") -> 0 | T75: 0 | U75: =IFERROR(T75/T148, "NA") -> 0 | V75: 0 | W75: =IFERROR(V75/V148, "NA") -> 0 | X75: 0 | Y75: =IFERROR(X75/X148, "NA") -> 0 | Z75: 0 | AA75: =IFERROR(Z75/Z148, "NA") -> 0 | AB75: =IFERROR((R75+T75+V75+X75)/4, "NA") -> 0 | AC75: =IFERROR(AB75/AB148, "NA") -> 0 | AD75: =IFERROR(X75-AB75, "NA") -> 0 | AE75: =IFERROR(AD75/AD148, "NA") -> 0 | AF75: =IFERROR((X75-AB75)/AB75, "NA") -> NA | AG75: =IFERROR((J75+L75+N75+P75+R75+T75+V75+X75)/8, "NA") -> 0 | AH75: =IFERROR(AG75/AG148, "NA") -> 0 | AI75: =IFERROR(X75-AG75, "NA") -> 0 | AJ75: =IFERROR(AI75/AI148, "NA") -> 0 | AK75: =IFERROR((X75-AG75)/AG75, "NA") -> NA | AL75: =IFERROR(AK75/AK148, "NA") -> NA
A76: 61330 - FUTA Tax Expense | B76: 0 | C76: =IFERROR(B76/B148, "NA") -> 0 | D76: 0 | E76: =IFERROR(D76/D148, "NA") -> 0 | F76: 0 | G76: =IFERROR(F76/F148, "NA") -> 0 | H76: 0 | I76: =IFERROR(H76/H148, "NA") -> 0 | J76: 0 | K76: =IFERROR(J76/J148, "NA") -> 0 | L76: 0 | M76: =IFERROR(L76/L148, "NA") -> 0 | N76: 0 | O76: =IFERROR(N76/N148, "NA") -> 0 | P76: 0 | Q76: =IFERROR(P76/P148, "NA") -> 0 | R76: 0 | S76: =IFERROR(R76/R148, "NA") -> 0 | T76: 0 | U76: =IFERROR(T76/T148, "NA") -> 0 | V76: 0 | W76: =IFERROR(V76/V148, "NA") -> 0 | X76: 0 | Y76: =IFERROR(X76/X148, "NA") -> 0 | Z76: 0 | AA76: =IFERROR(Z76/Z148, "NA") -> 0 | AB76: =IFERROR((R76+T76+V76+X76)/4, "NA") -> 0 | AC76: =IFERROR(AB76/AB148, "NA") -> 0 | AD76: =IFERROR(X76-AB76, "NA") -> 0 | AE76: =IFERROR(AD76/AD148, "NA") -> 0 | AF76: =IFERROR((X76-AB76)/AB76, "NA") -> NA | AG76: =IFERROR((J76+L76+N76+P76+R76+T76+V76+X76)/8, "NA") -> 0 | AH76: =IFERROR(AG76/AG148, "NA") -> 0 | AI76: =IFERROR(X76-AG76, "NA") -> 0 | AJ76: =IFERROR(AI76/AI148, "NA") -> 0 | AK76: =IFERROR((X76-AG76)/AG76, "NA") -> NA | AL76: =IFERROR(AK76/AK148, "NA") -> NA
A77: 61335 - SUTA Tax Expense (VA) | B77: 0 | C77: =IFERROR(B77/B148, "NA") -> 0 | D77: 0 | E77: =IFERROR(D77/D148, "NA") -> 0 | F77: 0 | G77: =IFERROR(F77/F148, "NA") -> 0 | H77: 0 | I77: =IFERROR(H77/H148, "NA") -> 0 | J77: 0 | K77: =IFERROR(J77/J148, "NA") -> 0 | L77: 0 | M77: =IFERROR(L77/L148, "NA") -> 0 | N77: 0 | O77: =IFERROR(N77/N148, "NA") -> 0 | P77: 0 | Q77: =IFERROR(P77/P148, "NA") -> 0 | R77: 0 | S77: =IFERROR(R77/R148, "NA") -> 0 | T77: 0 | U77: =IFERROR(T77/T148, "NA") -> 0 | V77: 0 | W77: =IFERROR(V77/V148, "NA") -> 0 | X77: 0 | Y77: =IFERROR(X77/X148, "NA") -> 0 | Z77: 0 | AA77: =IFERROR(Z77/Z148, "NA") -> 0 | AB77: =IFERROR((R77+T77+V77+X77)/4, "NA") -> 0 | AC77: =IFERROR(AB77/AB148, "NA") -> 0 | AD77: =IFERROR(X77-AB77, "NA") -> 0 | AE77: =IFERROR(AD77/AD148, "NA") -> 0 | AF77: =IFERROR((X77-AB77)/AB77, "NA") -> NA | AG77: =IFERROR((J77+L77+N77+P77+R77+T77+V77+X77)/8, "NA") -> 0 | AH77: =IFERROR(AG77/AG148, "NA") -> 0 | AI77: =IFERROR(X77-AG77, "NA") -> 0 | AJ77: =IFERROR(AI77/AI148, "NA") -> 0 | AK77: =IFERROR((X77-AG77)/AG77, "NA") -> NA | AL77: =IFERROR(AK77/AK148, "NA") -> NA
A78: 61340 - SUTA Tax Expense (DC) | B78: 0 | C78: =IFERROR(B78/B148, "NA") -> 0 | D78: 0 | E78: =IFERROR(D78/D148, "NA") -> 0 | F78: 0 | G78: =IFERROR(F78/F148, "NA") -> 0 | H78: 0 | I78: =IFERROR(H78/H148, "NA") -> 0 | J78: 0 | K78: =IFERROR(J78/J148, "NA") -> 0 | L78: 0 | M78: =IFERROR(L78/L148, "NA") -> 0 | N78: 0 | O78: =IFERROR(N78/N148, "NA") -> 0 | P78: 0 | Q78: =IFERROR(P78/P148, "NA") -> 0 | R78: 0 | S78: =IFERROR(R78/R148, "NA") -> 0 | T78: 0 | U78: =IFERROR(T78/T148, "NA") -> 0 | V78: 0 | W78: =IFERROR(V78/V148, "NA") -> 0 | X78: 0 | Y78: =IFERROR(X78/X148, "NA") -> 0 | Z78: 0 | AA78: =IFERROR(Z78/Z148, "NA") -> 0 | AB78: =IFERROR((R78+T78+V78+X78)/4, "NA") -> 0 | AC78: =IFERROR(AB78/AB148, "NA") -> 0 | AD78: =IFERROR(X78-AB78, "NA") -> 0 | AE78: =IFERROR(AD78/AD148, "NA") -> 0 | AF78: =IFERROR((X78-AB78)/AB78, "NA") -> NA | AG78: =IFERROR((J78+L78+N78+P78+R78+T78+V78+X78)/8, "NA") -> 0 | AH78: =IFERROR(AG78/AG148, "NA") -> 0 | AI78: =IFERROR(X78-AG78, "NA") -> 0 | AJ78: =IFERROR(AI78/AI148, "NA") -> 0 | AK78: =IFERROR((X78-AG78)/AG78, "NA") -> NA | AL78: =IFERROR(AK78/AK148, "NA") -> NA
A79: 61360 - FL Tax Expense (DC) | B79: 0 | C79: =IFERROR(B79/B148, "NA") -> 0 | D79: 0 | E79: =IFERROR(D79/D148, "NA") -> 0 | F79: 0 | G79: =IFERROR(F79/F148, "NA") -> 0 | H79: 0 | I79: =IFERROR(H79/H148, "NA") -> 0 | J79: 0 | K79: =IFERROR(J79/J148, "NA") -> 0 | L79: 0 | M79: =IFERROR(L79/L148, "NA") -> 0 | N79: 0 | O79: =IFERROR(N79/N148, "NA") -> 0 | P79: 0 | Q79: =IFERROR(P79/P148, "NA") -> 0 | R79: 0 | S79: =IFERROR(R79/R148, "NA") -> 0 | T79: 0 | U79: =IFERROR(T79/T148, "NA") -> 0 | V79: 0 | W79: =IFERROR(V79/V148, "NA") -> 0 | X79: 0 | Y79: =IFERROR(X79/X148, "NA") -> 0 | Z79: 0 | AA79: =IFERROR(Z79/Z148, "NA") -> 0 | AB79: =IFERROR((R79+T79+V79+X79)/4, "NA") -> 0 | AC79: =IFERROR(AB79/AB148, "NA") -> 0 | AD79: =IFERROR(X79-AB79, "NA") -> 0 | AE79: =IFERROR(AD79/AD148, "NA") -> 0 | AF79: =IFERROR((X79-AB79)/AB79, "NA") -> NA | AG79: =IFERROR((J79+L79+N79+P79+R79+T79+V79+X79)/8, "NA") -> 0 | AH79: =IFERROR(AG79/AG148, "NA") -> 0 | AI79: =IFERROR(X79-AG79, "NA") -> 0 | AJ79: =IFERROR(AI79/AI148, "NA") -> 0 | AK79: =IFERROR((X79-AG79)/AG79, "NA") -> NA | AL79: =IFERROR(AK79/AK148, "NA") -> NA
A80: 61395 - Other Payroll Taxes | B80: 0 | C80: =IFERROR(B80/B148, "NA") -> 0 | D80: 0 | E80: =IFERROR(D80/D148, "NA") -> 0 | F80: 0 | G80: =IFERROR(F80/F148, "NA") -> 0 | H80: 0 | I80: =IFERROR(H80/H148, "NA") -> 0 | J80: 0 | K80: =IFERROR(J80/J148, "NA") -> 0 | L80: 0 | M80: =IFERROR(L80/L148, "NA") -> 0 | N80: 0 | O80: =IFERROR(N80/N148, "NA") -> 0 | P80: 0 | Q80: =IFERROR(P80/P148, "NA") -> 0 | R80: 0 | S80: =IFERROR(R80/R148, "NA") -> 0 | T80: 0 | U80: =IFERROR(T80/T148, "NA") -> 0 | V80: 0 | W80: =IFERROR(V80/V148, "NA") -> 0 | X80: 0 | Y80: =IFERROR(X80/X148, "NA") -> 0 | Z80: 0 | AA80: =IFERROR(Z80/Z148, "NA") -> 0 | AB80: =IFERROR((R80+T80+V80+X80)/4, "NA") -> 0 | AC80: =IFERROR(AB80/AB148, "NA") -> 0 | AD80: =IFERROR(X80-AB80, "NA") -> 0 | AE80: =IFERROR(AD80/AD148, "NA") -> 0 | AF80: =IFERROR((X80-AB80)/AB80, "NA") -> NA | AG80: =IFERROR((J80+L80+N80+P80+R80+T80+V80+X80)/8, "NA") -> 0 | AH80: =IFERROR(AG80/AG148, "NA") -> 0 | AI80: =IFERROR(X80-AG80, "NA") -> 0 | AJ80: =IFERROR(AI80/AI148, "NA") -> 0 | AK80: =IFERROR((X80-AG80)/AG80, "NA") -> NA | AL80: =IFERROR(AK80/AK148, "NA") -> NA
A81: Total Payroll Taxes | B81: =IFERROR(B74+B75+B76+B77+B78+B79+B80, "NA") -> 3753.42 | C81: =IFERROR(B81/B148, "NA") -> 0.018426729 | D81: =IFERROR(D74+D75+D76+D77+D78+D79+D80, "NA") -> 3471.16 | E81: =IFERROR(D81/D148, "NA") -> 0.018701948 | F81: =IFERROR(F74+F75+F76+F77+F78+F79+F80, "NA") -> 3504.27 | G81: =IFERROR(F81/F148, "NA") -> 0.02480743 | H81: =IFERROR(H74+H75+H76+H77+H78+H79+H80, "NA") -> 2200.35 | I81: =IFERROR(H81/H148, "NA") -> 0.029469899 | J81: =IFERROR(J74+J75+J76+J77+J78+J79+J80, "NA") -> 3111.96 | K81: =IFERROR(J81/J148, "NA") -> 0.021853928 | L81: =IFERROR(L74+L75+L76+L77+L78+L79+L80, "NA") -> 3148.4 | M81: =IFERROR(L81/L148, "NA") -> 0.023297258 | N81: =IFERROR(N74+N75+N76+N77+N78+N79+N80, "NA") -> 3000.89 | O81: =IFERROR(N81/N148, "NA") -> 0.024678897 | P81: =IFERROR(P74+P75+P76+P77+P78+P79+P80, "NA") -> 2326.41 | Q81: =IFERROR(P81/P148, "NA") -> 0.04109348 | R81: =IFERROR(R74+R75+R76+R77+R78+R79+R80, "NA") -> 2626.38 | S81: =IFERROR(R81/R148, "NA") -> 0.037796906 | T81: =IFERROR(T74+T75+T76+T77+T78+T79+T80, "NA") -> 3409.67 | U81: =IFERROR(T81/T148, "NA") -> 0.030855016 | V81: =IFERROR(V74+V75+V76+V77+V78+V79+V80, "NA") -> 3335.01 | W81: =IFERROR(V81/V148, "NA") -> 0.024694313 | X81: =IFERROR(X74+X75+X76+X77+X78+X79+X80, "NA") -> 3072.97 | Y81: =IFERROR(X81/X148, "NA") -> 0.026504183 | Z81: =IFERROR(Z74+Z75+Z76+Z77+Z78+Z79+Z80, "NA") -> 12444.03 | AA81: =IFERROR(Z81/Z148, "NA") -> 0.028873304 | AB81: =IFERROR((R81+T81+V81+X81)/4, "NA") -> 3111.0075 | AC81: =IFERROR(AB81/AB148, "NA") -> 0.028873304 | AD81: =IFERROR(X81-AB81, "NA") -> -38.0375 | AE81: =IFERROR(AD81/AD148, "NA") -> -0.0046409933 | AF81: =IFERROR((X81-AB81)/AB81, "NA") -> -0.012226746 | AG81: =IFERROR((J81+L81+N81+P81+R81+T81+V81+X81)/8, "NA") -> 3003.9612 | AH81: =IFERROR(AG81/AG148, "NA") -> 0.027101291 | AI81: =IFERROR(X81-AG81, "NA") -> 69.00875 | AJ81: =IFERROR(AI81/AI148, "NA") -> 0.013528926 | AK81: =IFERROR((X81-AG81)/AG81, "NA") -> 0.022972583 | AL81: =IFERROR(AK81/AK148, "NA") -> 0.49919858
A82: 61400 - Payroll Processing Fee | B82: 0 | C82: =IFERROR(B82/B148, "NA") -> 0 | D82: 0 | E82: =IFERROR(D82/D148, "NA") -> 0 | F82: 0 | G82: =IFERROR(F82/F148, "NA") -> 0 | H82: 1286.08 | I82: =IFERROR(H82/H148, "NA") -> 0.017224827 | J82: 0 | K82: =IFERROR(J82/J148, "NA") -> 0 | L82: 0 | M82: =IFERROR(L82/L148, "NA") -> 0 | N82: 0 | O82: =IFERROR(N82/N148, "NA") -> 0 | P82: 0 | Q82: =IFERROR(P82/P148, "NA") -> 0 | R82: 1286.8 | S82: =IFERROR(R82/R148, "NA") -> 0.018518668 | T82: 0 | U82: =IFERROR(T82/T148, "NA") -> 0 | V82: 0 | W82: =IFERROR(V82/V148, "NA") -> 0 | X82: 0 | Y82: =IFERROR(X82/X148, "NA") -> 0 | Z82: 1286.8 | AA82: =IFERROR(Z82/Z148, "NA") -> 0.0029857022 | AB82: =IFERROR((R82+T82+V82+X82)/4, "NA") -> 321.7 | AC82: =IFERROR(AB82/AB148, "NA") -> 0.0029857022 | AD82: =IFERROR(X82-AB82, "NA") -> -321.7 | AE82: =IFERROR(AD82/AD148, "NA") -> -0.039250938 | AF82: =IFERROR((X82-AB82)/AB82, "NA") -> -1 | AG82: =IFERROR((J82+L82+N82+P82+R82+T82+V82+X82)/8, "NA") -> 160.85 | AH82: =IFERROR(AG82/AG148, "NA") -> 0.0014511647 | AI82: =IFERROR(X82-AG82, "NA") -> -160.85 | AJ82: =IFERROR(AI82/AI148, "NA") -> -0.031534084 | AK82: =IFERROR((X82-AG82)/AG82, "NA") -> -1 | AL82: =IFERROR(AK82/AK148, "NA") -> -21.730189
A83: 61500 - Health Insurance | B83: -330.77 | C83: =IFERROR(B83/B148, "NA") -> -0.0016238548 | D83: 1000.88 | E83: =IFERROR(D83/D148, "NA") -> 0.0053925507 | F83: -330.77 | G83: =IFERROR(F83/F148, "NA") -> -0.0023415871 | H83: -330.77 | I83: =IFERROR(H83/H148, "NA") -> -0.0044300946 | J83: -346.87 | K83: =IFERROR(J83/J148, "NA") -> -0.0024359156 | L83: -337.93 | M83: =IFERROR(L83/L148, "NA") -> -0.0025005851 | N83: 3513.42 | O83: =IFERROR(N83/N148, "NA") -> 0.028893872 | P83: -308.46 | Q83: =IFERROR(P83/P148, "NA") -> -0.0054486075 | R83: -308.46 | S83: =IFERROR(R83/R148, "NA") -> -0.0044391267 | T83: -308.46 | U83: =IFERROR(T83/T148, "NA") -> -0.0027913371 | V83: 2769.95 | W83: =IFERROR(V83/V148, "NA") -> 0.020510287 | X83: -308.46 | Y83: =IFERROR(X83/X148, "NA") -> -0.0026604491 | Z83: 1844.57 | AA83: =IFERROR(Z83/Z148, "NA") -> 0.00427987 | AB83: =IFERROR((R83+T83+V83+X83)/4, "NA") -> 461.1425 | AC83: =IFERROR(AB83/AB148, "NA") -> 0.00427987 | AD83: =IFERROR(X83-AB83, "NA") -> -769.6025 | AE83: =IFERROR(AD83/AD148, "NA") -> -0.093899969 | AF83: =IFERROR((X83-AB83)/AB83, "NA") -> -1.6689039 | AG83: =IFERROR((J83+L83+N83+P83+R83+T83+V83+X83)/8, "NA") -> 545.59125 | AH83: =IFERROR(AG83/AG148, "NA") -> 0.0049222429 | AI83: =IFERROR(X83-AG83, "NA") -> -854.05125 | AJ83: =IFERROR(AI83/AI148, "NA") -> -0.16743378 | AK83: =IFERROR((X83-AG83)/AG83, "NA") -> -1.5653683 | AL83: =IFERROR(AK83/AK148, "NA") -> -34.015749
A84: Total Payroll Expenses | B84: =IFERROR(B63+B65+B66+B67+B68+B69+B71+B72+B74+B75+B76+B77+B78+B79+B80+B82+B83, "NA") -> 44046.94 | C84: =IFERROR(B84/B148, "NA") -> 0.21624039 | D84: =IFERROR(D63+D65+D66+D67+D68+D69+D71+D72+D74+D75+D76+D77+D78+D79+D80+D82+D83, "NA") -> 43329.13 | E84: =IFERROR(D84/D148, "NA") -> 0.23344909 | F84: =IFERROR(F63+F65+F66+F67+F68+F69+F71+F72+F74+F75+F76+F77+F78+F79+F80+F82+F83, "NA") -> 35570.28 | G84: =IFERROR(F84/F148, "NA") -> 0.25180914 | H84: =IFERROR(H63+H65+H66+H67+H68+H69+H71+H72+H74+H75+H76+H77+H78+H79+H80+H82+H83, "NA") -> 27896.04 | I84: =IFERROR(H84/H148, "NA") -> 0.37361942 | J84: =IFERROR(J63+J65+J66+J67+J68+J69+J71+J72+J74+J75+J76+J77+J78+J79+J80+J82+J83, "NA") -> 37805.79 | K84: =IFERROR(J84/J148, "NA") -> 0.26549345 | L84: =IFERROR(L63+L65+L66+L67+L68+L69+L71+L72+L74+L75+L76+L77+L78+L79+L80+L82+L83, "NA") -> 37182.89 | M84: =IFERROR(L84/L148, "NA") -> 0.27514273 | N84: =IFERROR(N63+N65+N66+N67+N68+N69+N71+N72+N74+N75+N76+N77+N78+N79+N80+N82+N83, "NA") -> 39645.87 | O84: =IFERROR(N84/N148, "NA") -> 0.32604206 | P84: =IFERROR(P63+P65+P66+P67+P68+P69+P71+P72+P74+P75+P76+P77+P78+P79+P80+P82+P83, "NA") -> 27246.1 | Q84: =IFERROR(P84/P148, "NA") -> 0.48127247 | R84: =IFERROR(R63+R65+R66+R67+R68+R69+R71+R72+R74+R75+R76+R77+R78+R79+R80+R82+R83, "NA") -> 29168.25 | S84: =IFERROR(R84/R148, "NA") -> 0.41976774 | T84: =IFERROR(T63+T65+T66+T67+T68+T69+T71+T72+T74+T75+T76+T77+T78+T79+T80+T82+T83, "NA") -> 35197.15 | U84: =IFERROR(T84/T148, "NA") -> 0.31850843 | V84: =IFERROR(V63+V65+V66+V67+V68+V69+V71+V72+V74+V75+V76+V77+V78+V79+V80+V82+V83, "NA") -> 36822.58 | W84: =IFERROR(V84/V148, "NA") -> 0.27265535 | X84: =IFERROR(X63+X65+X66+X67+X68+X69+X71+X72+X74+X75+X76+X77+X78+X79+X80+X82+X83, "NA") -> 34378.65 | Y84: =IFERROR(X84/X148, "NA") -> 0.29651381 | Z84: =IFERROR(Z63+Z65+Z66+Z67+Z68+Z69+Z71+Z72+Z74+Z75+Z76+Z77+Z78+Z79+Z80+Z82+Z83, "NA") -> 135566.63 | AA84: =IFERROR(Z84/Z148, "NA") -> 0.31454895 | AB84: =IFERROR((R84+T84+V84+X84)/4, "NA") -> 33891.658 | AC84: =IFERROR(AB84/AB148, "NA") -> 0.31454895 | AD84: =IFERROR(X84-AB84, "NA") -> 486.9925 | AE84: =IFERROR(AD84/AD148, "NA") -> 0.059418441 | AF84: =IFERROR((X84-AB84)/AB84, "NA") -> 0.014369097 | AG84: =IFERROR((J84+L84+N84+P84+R84+T84+V84+X84)/8, "NA") -> 34680.91 | AH84: =IFERROR(AG84/AG148, "NA") -> 0.312886 | AI84: =IFERROR(X84-AG84, "NA") -> -302.26 | AJ84: =IFERROR(AI84/AI148, "NA") -> -0.059257023 | AK84: =IFERROR((X84-AG84)/AG84, "NA") -> -0.0087154576 | AL84: =IFERROR(AK84/AK148, "NA") -> -0.18938854
A85: Total Payroll Expenses | B85: =IFERROR(B63+B65+B66+B67+B68+B69+B71+B72+B74+B75+B76+B77+B78+B79+B80+B82+B83, "NA") -> 44046.94 | C85: =IFERROR(B85/B148, "NA") -> 0.21624039 | D85: =IFERROR(D63+D65+D66+D67+D68+D69+D71+D72+D74+D75+D76+D77+D78+D79+D80+D82+D83, "NA") -> 43329.13 | E85: =IFERROR(D85/D148, "NA") -> 0.23344909 | F85: =IFERROR(F63+F65+F66+F67+F68+F69+F71+F72+F74+F75+F76+F77+F78+F79+F80+F82+F83, "NA") -> 35570.28 | G85: =IFERROR(F85/F148, "NA") -> 0.25180914 | H85: =IFERROR(H63+H65+H66+H67+H68+H69+H71+H72+H74+H75+H76+H77+H78+H79+H80+H82+H83, "NA") -> 27896.04 | I85: =IFERROR(H85/H148, "NA") -> 0.37361942 | J85: =IFERROR(J63+J65+J66+J67+J68+J69+J71+J72+J74+J75+J76+J77+J78+J79+J80+J82+J83, "NA") -> 37805.79 | K85: =IFERROR(J85/J148, "NA") -> 0.26549345 | L85: =IFERROR(L63+L65+L66+L67+L68+L69+L71+L72+L74+L75+L76+L77+L78+L79+L80+L82+L83, "NA") -> 37182.89 | M85: =IFERROR(L85/L148, "NA") -> 0.27514273 | N85: =IFERROR(N63+N65+N66+N67+N68+N69+N71+N72+N74+N75+N76+N77+N78+N79+N80+N82+N83, "NA") -> 39645.87 | O85: =IFERROR(N85/N148, "NA") -> 0.32604206 | P85: =IFERROR(P63+P65+P66+P67+P68+P69+P71+P72+P74+P75+P76+P77+P78+P79+P80+P82+P83, "NA") -> 27246.1 | Q85: =IFERROR(P85/P148, "NA") -> 0.48127247 | R85: =IFERROR(R63+R65+R66+R67+R68+R69+R71+R72+R74+R75+R76+R77+R78+R79+R80+R82+R83, "NA") -> 29168.25 | S85: =IFERROR(R85/R148, "NA") -> 0.41976774 | T85: =IFERROR(T63+T65+T66+T67+T68+T69+T71+T72+T74+T75+T76+T77+T78+T79+T80+T82+T83, "NA") -> 35197.15 | U85: =IFERROR(T85/T148, "NA") -> 0.31850843 | V85: =IFERROR(V63+V65+V66+V67+V68+V69+V71+V72+V74+V75+V76+V77+V78+V79+V80+V82+V83, "NA") -> 36822.58 | W85: =IFERROR(V85/V148, "NA") -> 0.27265535 | X85: =IFERROR(X63+X65+X66+X67+X68+X69+X71+X72+X74+X75+X76+X77+X78+X79+X80+X82+X83, "NA") -> 34378.65 | Y85: =IFERROR(X85/X148, "NA") -> 0.29651381 | Z85: =IFERROR(Z63+Z65+Z66+Z67+Z68+Z69+Z71+Z72+Z74+Z75+Z76+Z77+Z78+Z79+Z80+Z82+Z83, "NA") -> 135566.63 | AA85: =IFERROR(Z85/Z148, "NA") -> 0.31454895 | AB85: =IFERROR((R85+T85+V85+X85)/4, "NA") -> 33891.658 | AC85: =IFERROR(AB85/AB148, "NA") -> 0.31454895 | AD85: =IFERROR(X85-AB85, "NA") -> 486.9925 | AE85: =IFERROR(AD85/AD148, "NA") -> 0.059418441 | AF85: =IFERROR((X85-AB85)/AB85, "NA") -> 0.014369097 | AG85: =IFERROR((J85+L85+N85+P85+R85+T85+V85+X85)/8, "NA") -> 34680.91 | AH85: =IFERROR(AG85/AG148, "NA") -> 0.312886 | AI85: =IFERROR(X85-AG85, "NA") -> -302.26 | AJ85: =IFERROR(AI85/AI148, "NA") -> -0.059257023 | AK85: =IFERROR((X85-AG85)/AG85, "NA") -> -0.0087154576 | AL85: =IFERROR(AK85/AK148, "NA") -> -0.18938854
A87: Prime Profit | B87: =IFERROR(B59-B85, "NA") -> 108098.01 | C87: =IFERROR(B87/B148, "NA") -> 0.5306874 | D87: =IFERROR(D59-D85, "NA") -> 94650.49 | E87: =IFERROR(D87/D148, "NA") -> 0.5099588 | F87: =IFERROR(F59-F85, "NA") -> 70140.43 | G87: =IFERROR(F87/F148, "NA") -> 0.49653816 | H87: =IFERROR(H59-H85, "NA") -> 23118.18 | I87: =IFERROR(H87/H148, "NA") -> 0.30962821 | J87: =IFERROR(J59-J85, "NA") -> 66622.33 | K87: =IFERROR(J87/J148, "NA") -> 0.46785935 | L87: =IFERROR(L59-L85, "NA") -> 58960.9 | M87: =IFERROR(L87/L148, "NA") -> 0.43629376 | N87: =IFERROR(N59-N85, "NA") -> 47675.88 | O87: =IFERROR(N87/N148, "NA") -> 0.39207973 | P87: =IFERROR(P59-P85, "NA") -> 12600.53 | Q87: =IFERROR(P87/P148, "NA") -> 0.22257454 | R87: =IFERROR(R59-R85, "NA") -> 18571.43 | S87: =IFERROR(R87/R148, "NA") -> 0.2672662 | T87: =IFERROR(T59-T85, "NA") -> 43886.09 | U87: =IFERROR(T87/T148, "NA") -> 0.39713697 | V87: =IFERROR(V59-V85, "NA") -> 60974.34 | W87: =IFERROR(V87/V148, "NA") -> 0.45148874 | X87: =IFERROR(X59-X85, "NA") -> 50235.03 | Y87: =IFERROR(X87/X148, "NA") -> 0.43327414 | Z87: =IFERROR(Z59-Z85, "NA") -> 173666.89 | AA87: =IFERROR(Z87/Z148, "NA") -> 0.40295121 | AB87: =IFERROR((R87+T87+V87+X87)/4, "NA") -> 43416.723 | AC87: =IFERROR(AB87/AB148, "NA") -> 0.40295121 | AD87: =IFERROR(X87-AB87, "NA") -> 6818.3075 | AE87: =IFERROR(AD87/AD148, "NA") -> 0.8319085 | AF87: =IFERROR((X87-AB87)/AB87, "NA") -> 0.15704335 | AG87: =IFERROR((J87+L87+N87+P87+R87+T87+V87+X87)/8, "NA") -> 44940.816 | AH87: =IFERROR(AG87/AG148, "NA") -> 0.40544934 | AI87: =IFERROR(X87-AG87, "NA") -> 5294.2137 | AJ87: =IFERROR(AI87/AI148, "NA") -> 1.0379122 | AK87: =IFERROR((X87-AG87)/AG87, "NA") -> 0.11780413 | AL87: =IFERROR(AK87/AK148, "NA") -> 2.559906
A89: Operating Expense
A90: Supplies | B90: 4586.19 | C90: =IFERROR(B90/B148, "NA") -> 0.022515061 | D90: 3657.42 | E90: =IFERROR(D90/D148, "NA") -> 0.019705482 | F90: 2502.11 | G90: =IFERROR(F90/F148, "NA") -> 0.017712938 | H90: 3274.54 | I90: =IFERROR(H90/H148, "NA") -> 0.043856825 | J90: 5304.25 | K90: =IFERROR(J90/J148, "NA") -> 0.037249417 | L90: 3128.04 | M90: =IFERROR(L90/L148, "NA") -> 0.023146599 | N90: 2616.22 | O90: =IFERROR(N90/N148, "NA") -> 0.021515425 | P90: 1851.03 | Q90: =IFERROR(P90/P148, "NA") -> 0.032696414 | R90: 2105.04 | S90: =IFERROR(R90/R148, "NA") -> 0.030294169 | T90: 3137.56 | U90: =IFERROR(T90/T148, "NA") -> 0.02839262 | V90: 2920.66 | W90: =IFERROR(V90/V148, "NA") -> 0.02162623 | X90: 2008.72 | Y90: =IFERROR(X90/X148, "NA") -> 0.01732509 | Z90: 10171.98 | AA90: =IFERROR(Z90/Z148, "NA") -> 0.023601572 | AB90: =IFERROR((R90+T90+V90+X90)/4, "NA") -> 2542.995 | AC90: =IFERROR(AB90/AB148, "NA") -> 0.023601572 | AD90: =IFERROR(X90-AB90, "NA") -> -534.275 | AE90: =IFERROR(AD90/AD148, "NA") -> -0.065187426 | AF90: =IFERROR((X90-AB90)/AB90, "NA") -> -0.21009676 | AG90: =IFERROR((J90+L90+N90+P90+R90+T90+V90+X90)/8, "NA") -> 2883.94 | AH90: =IFERROR(AG90/AG148, "NA") -> 0.026018477 | AI90: =IFERROR(X90-AG90, "NA") -> -875.22 | AJ90: =IFERROR(AI90/AI148, "NA") -> -0.17158384 | AK90: =IFERROR((X90-AG90)/AG90, "NA") -> -0.30348065 | AL90: =IFERROR(AK90/AK148, "NA") -> -6.594692
A91: Marketing | B91: 5600.57 | C91: =IFERROR(B91/B148, "NA") -> 0.027494974 | D91: 4805.01 | E91: =IFERROR(D91/D148, "NA") -> 0.025888478 | F91: 5562.86 | G91: =IFERROR(F91/F148, "NA") -> 0.039380601 | H91: 4451.82 | I91: =IFERROR(H91/H148, "NA") -> 0.059624463 | J91: 6100.83 | K91: =IFERROR(J91/J148, "NA") -> 0.042843449 | L91: 5508.43 | M91: =IFERROR(L91/L148, "NA") -> 0.040760803 | N91: 4005.19 | O91: =IFERROR(N91/N148, "NA") -> 0.032938119 | P91: 1701.53 | Q91: =IFERROR(P91/P148, "NA") -> 0.030055661 | R91: 1932.35 | S91: =IFERROR(R91/R148, "NA") -> 0.027808943 | T91: 2504.09 | U91: =IFERROR(T91/T148, "NA") -> 0.022660181 | V91: 4651.05 | W91: =IFERROR(V91/V148, "NA") -> 0.034439023 | X91: 4514.64 | Y91: =IFERROR(X91/X148, "NA") -> 0.038938501 | Z91: 13602.13 | AA91: =IFERROR(Z91/Z148, "NA") -> 0.03156039 | AB91: =IFERROR((R91+T91+V91+X91)/4, "NA") -> 3400.5325 | AC91: =IFERROR(AB91/AB148, "NA") -> 0.03156039 | AD91: =IFERROR(X91-AB91, "NA") -> 1114.1075 | AE91: =IFERROR(AD91/AD148, "NA") -> 0.13593337 | AF91: =IFERROR((X91-AB91)/AB91, "NA") -> 0.32762736 | AG91: =IFERROR((J91+L91+N91+P91+R91+T91+V91+X91)/8, "NA") -> 3864.7638 | AH91: =IFERROR(AG91/AG148, "NA") -> 0.034867322 | AI91: =IFERROR(X91-AG91, "NA") -> 649.87625 | AJ91: =IFERROR(AI91/AI148, "NA") -> 0.12740598 | AK91: =IFERROR((X91-AG91)/AG91, "NA") -> 0.1681542 | AL91: =IFERROR(AK91/AK148, "NA") -> 3.6540225
A92: Delivery Fees | B92: 2603.47 | C92: =IFERROR(B92/B148, "NA") -> 0.01278126 | D92: 2254.83 | E92: =IFERROR(D92/D148, "NA") -> 0.012148594 | F92: 2135.79 | G92: =IFERROR(F92/F148, "NA") -> 0.015119686 | H92: 1542.36 | I92: =IFERROR(H92/H148, "NA") -> 0.020657256 | J92: 2173.49 | K92: =IFERROR(J92/J148, "NA") -> 0.015263465 | L92: 2442.79 | M92: =IFERROR(L92/L148, "NA") -> 0.018075946 | N92: 2434.89 | O92: =IFERROR(N92/N148, "NA") -> 0.020024193 | P92: 257.56 | Q92: =IFERROR(P92/P148, "NA") -> 0.0045495148 | R92: 1113.39 | S92: =IFERROR(R92/R148, "NA") -> 0.01602308 | T92: 1632.78 | U92: =IFERROR(T92/T148, "NA") -> 0.014775463 | V92: 2305.98 | W92: =IFERROR(V92/V148, "NA") -> 0.017074789 | X92: 2047.2 | Y92: =IFERROR(X92/X148, "NA") -> 0.017656978 | Z92: 7099.35 | AA92: =IFERROR(Z92/Z148, "NA") -> 0.016472292 | AB92: =IFERROR((R92+T92+V92+X92)/4, "NA") -> 1774.8375 | AC92: =IFERROR(AB92/AB148, "NA") -> 0.016472292 | AD92: =IFERROR(X92-AB92, "NA") -> 272.3625 | AE92: =IFERROR(AD92/AD148, "NA") -> 0.03323122 | AF92: =IFERROR((X92-AB92)/AB92, "NA") -> 0.15345771 | AG92: =IFERROR((J92+L92+N92+P92+R92+T92+V92+X92)/8, "NA") -> 1801.01 | AH92: =IFERROR(AG92/AG148, "NA") -> 0.016248444 | AI92: =IFERROR(X92-AG92, "NA") -> 246.19 | AJ92: =IFERROR(AI92/AI148, "NA") -> 0.048264694 | AK92: =IFERROR((X92-AG92)/AG92, "NA") -> 0.13669552 | AL92: =IFERROR(AK92/AK148, "NA") -> 2.9704195
A93: Third-Party Fees | B93: 10470.68 | C93: =IFERROR(B93/B148, "NA") -> 0.051403888 | D93: 9973.22 | E93: =IFERROR(D93/D148, "NA") -> 0.053733808 | F93: 11622.16 | G93: =IFERROR(F93/F148, "NA") -> 0.0822756 | H93: 5343.48 | I93: =IFERROR(H93/H148, "NA") -> 0.071566714 | J93: 12720.71 | K93: =IFERROR(J93/J148, "NA") -> 0.089331958 | L93: 11484.18 | M93: =IFERROR(L93/L148, "NA") -> 0.08497964 | N93: 9332.57 | O93: =IFERROR(N93/N148, "NA") -> 0.076749743 | P93: 3768.83 | Q93: =IFERROR(P93/P148, "NA") -> 0.066572247 | R93: 3479.81 | S93: =IFERROR(R93/R148, "NA") -> 0.050078835 | T93: 7829.64 | U93: =IFERROR(T93/T148, "NA") -> 0.070852508 | V93: 10375.89 | W93: =IFERROR(V93/V148, "NA") -> 0.076828999 | X93: 8876.44 | Y93: =IFERROR(X93/X148, "NA") -> 0.076558766 | Z93: 30561.78 | AA93: =IFERROR(Z93/Z148, "NA") -> 0.070911077 | AB93: =IFERROR((R93+T93+V93+X93)/4, "NA") -> 7640.445 | AC93: =IFERROR(AB93/AB148, "NA") -> 0.070911077 | AD93: =IFERROR(X93-AB93, "NA") -> 1235.995 | AE93: =IFERROR(AD93/AD148, "NA") -> 0.15080498 | AF93: =IFERROR((X93-AB93)/AB93, "NA") -> 0.16177003 | AG93: =IFERROR((J93+L93+N93+P93+R93+T93+V93+X93)/8, "NA") -> 8483.5088 | AH93: =IFERROR(AG93/AG148, "NA") -> 0.076536951 | AI93: =IFERROR(X93-AG93, "NA") -> 392.93125 | AJ93: =IFERROR(AI93/AI148, "NA") -> 0.077032806 | AK93: =IFERROR((X93-AG93)/AG93, "NA") -> 0.046317068 | AL93: =IFERROR(AK93/AK148, "NA") -> 1.0064786
